Workbook

Sheet Annual Cost Summary
A1: S/N | B1: Job Role | C1: Headcount | D1: Total Annual Gross | E1: Total Leave Allowance | F1: Total 13th Month | G1: Total Bonus Pot | H1: Telephone | I1: Airtime | J1: Mobile Data Plan | K1: Total Cafeteria Subsidy | L1: Total Health Insurance | M1: Employer Pension Contr. | N1: Group Life Insurance Premium Cost | O1: ITF Cost | P1: NSITF (ECS) | Q1: Employer Cost
A2: 1 | B2: Managing Director | C2: 1 | D2: ='Annual Employer Cost per Grade'!F2*C2 -> 46080000 | E2: ='Annual Employer Cost per Grade'!G2*'Annual Cost Summary'!C2 -> 3225600 | F2: ='Annual Employer Cost per Grade'!H2*'Annual Cost Summary'!C2 -> 3840000 | G2: ='Annual Employer Cost per Grade'!I2*'Annual Cost Summary'!C2 -> 13824000 | H2: ='Annual Employer Cost per Grade'!J2*'Annual Cost Summary'!C2 -> 0 | I2: ='Annual Employer Cost per Grade'!K2*'Annual Cost Summary'!C2 -> 0 | J2: ='Annual Employer Cost per Grade'!L2*'Annual Cost Summary'!C2 -> 0 | K2: ='Annual Employer Cost per Grade'!M2*'Annual Cost Summary'!C2 -> 0 | L2: ='Annual Employer Cost per Grade'!N2*'Annual Cost Summary'!C2 -> 0 | M2: ='Annual Employer Cost per Grade'!O2*'Annual Cost Summary'!C2 -> 4147200 | N2: ='Annual Employer Cost per Grade'!P2*'Annual Cost Summary'!C2 -> 746496 | O2: ='Annual Employer Cost per Grade'!Q2*'Annual Cost Summary'!C2 -> 599040 | P2: ='Annual Employer Cost per Grade'!R2*'Annual Cost Summary'!C2 -> 599040 | Q2: =SUM(D2:P2) -> 73061376
A3: =A2+1 -> 2 | B3: Director of Programs | C3: 1 | D3: ='Annual Employer Cost per Grade'!F3*C3 -> 26328000 | E3: ='Annual Employer Cost per Grade'!G3*'Annual Cost Summary'!C3 -> 1842960 | F3: ='Annual Employer Cost per Grade'!H3*'Annual Cost Summary'!C3 -> 2194000 | G3: ='Annual Employer Cost per Grade'!I3*'Annual Cost Summary'!C3 -> 5265600 | H3: ='Annual Employer Cost per Grade'!J3*'Annual Cost Summary'!C3 -> 0 | I3: ='Annual Employer Cost per Grade'!K3*'Annual Cost Summary'!C3 -> 0 | J3: ='Annual Employer Cost per Grade'!L3*'Annual Cost Summary'!C3 -> 0 | K3: ='Annual Employer Cost per Grade'!M3*'Annual Cost Summary'!C3 -> 0 | L3: ='Annual Employer Cost per Grade'!N3*'Annual Cost Summary'!C3 -> 0 | M3: ='Annual Employer Cost per Grade'!O3*'Annual Cost Summary'!C3 -> 2369520 | N3: ='Annual Employer Cost per Grade'!P3*'Annual Cost Summary'!C3 -> 426513.6 | O3: ='Annual Employer Cost per Grade'!Q3*'Annual Cost Summary'!C3 -> 315936 | P3: ='Annual Employer Cost per Grade'!R3*'Annual Cost Summary'!C3 -> 315936 | Q3: =SUM(D3:P3) -> 39058466
A4: =A3+1 -> 3 | B4: IT Manager | C4: 1 | D4: ='Annual Employer Cost per Grade'!F4*C4 -> 5664000 | E4: ='Annual Employer Cost per Grade'!G4*'Annual Cost Summary'!C4 -> 396480 | F4: ='Annual Employer Cost per Grade'!H4*'Annual Cost Summary'!C4 -> 472000 | G4: ='Annual Employer Cost per Grade'!I4*'Annual Cost Summary'!C4 -> 849600 | H4: ='Annual Employer Cost per Grade'!J4*'Annual Cost Summary'!C4 -> 0 | I4: ='Annual Employer Cost per Grade'!K4*'Annual Cost Summary'!C4 -> 0 | J4: ='Annual Employer Cost per Grade'!L4*'Annual Cost Summary'!C4 -> 0 | K4: ='Annual Employer Cost per Grade'!M4*'Annual Cost Summary'!C4 -> 0 | L4: ='Annual Employer Cost per Grade'!N4*'Annual Cost Summary'!C4 -> 0 | M4: ='Annual Employer Cost per Grade'!O4*'Annual Cost Summary'!C4 -> 509760 | N4: ='Annual Employer Cost per Grade'!P4*'Annual Cost Summary'!C4 -> 91756.8 | O4: ='Annual Employer Cost per Grade'!Q4*'Annual Cost Summary'!C4 -> 65136 | P4: ='Annual Employer Cost per Grade'!R4*'Annual Cost Summary'!C4 -> 65136 | Q4: =SUM(D4:P4) -> 8113868.8
A5: =A4+1 -> 4 | B5: Community Manager | C5: 1 | D5: ='Annual Employer Cost per Grade'!F5*C5 -> 5664000 | E5: ='Annual Employer Cost per Grade'!G5*'Annual Cost Summary'!C5 -> 396480 | F5: ='Annual Employer Cost per Grade'!H5*'Annual Cost Summary'!C5 -> 472000 | G5: ='Annual Employer Cost per Grade'!I5*'Annual Cost Summary'!C5 -> 849600 | H5: ='Annual Employer Cost per Grade'!J5*'Annual Cost Summary'!C5 -> 0 | I5: ='Annual Employer Cost per Grade'!K5*'Annual Cost Summary'!C5 -> 0 | J5: ='Annual Employer Cost per Grade'!L5*'Annual Cost Summary'!C5 -> 0 | K5: ='Annual Employer Cost per Grade'!M5*'Annual Cost Summary'!C5 -> 0 | L5: ='Annual Employer Cost per Grade'!N5*'Annual Cost Summary'!C5 -> 0 | M5: ='Annual Employer Cost per Grade'!O5*'Annual Cost Summary'!C5 -> 509760 | N5: ='Annual Employer Cost per Grade'!P5*'Annual Cost Summary'!C5 -> 91756.8 | O5: ='Annual Employer Cost per Grade'!Q5*'Annual Cost Summary'!C5 -> 65136 | P5: ='Annual Employer Cost per Grade'!R5*'Annual Cost Summary'!C5 -> 65136 | Q5: =SUM(D5:P5) -> 8113868.8
A6: =A5+1 -> 5 | B6: Facility Associate | C6: 1 | D6: ='Annual Employer Cost per Grade'!F6*C6 -> 3288000 | E6: ='Annual Employer Cost per Grade'!G6*'Annual Cost Summary'!C6 -> 230160 | F6: ='Annual Employer Cost per Grade'!H6*'Annual Cost Summary'!C6 -> 274000 | G6: ='Annual Employer Cost per Grade'!I6*'Annual Cost Summary'!C6 -> 328800 | H6: ='Annual Employer Cost per Grade'!J6*'Annual Cost Summary'!C6 -> 0 | I6: ='Annual Employer Cost per Grade'!K6*'Annual Cost Summary'!C6 -> 0 | J6: ='Annual Employer Cost per Grade'!L6*'Annual Cost Summary'!C6 -> 0 | K6: ='Annual Employer Cost per Grade'!M6*'Annual Cost Summary'!C6 -> 0 | L6: ='Annual Employer Cost per Grade'!N6*'Annual Cost Summary'!C6 -> 0 | M6: ='Annual Employer Cost per Grade'!O6*'Annual Cost Summary'!C6 -> 295920 | N6: ='Annual Employer Cost per Grade'!P6*'Annual Cost Summary'!C6 -> 53265.6 | O6: ='Annual Employer Cost per Grade'!Q6*'Annual Cost Summary'!C6 -> 36168 | P6: ='Annual Employer Cost per Grade'!R6*'Annual Cost Summary'!C6 -> 36168 | Q6: =SUM(D6:P6) -> 4542481.6
A7: =A6+1 -> 6 | B7: Front Desk Associate (x2) | C7: 2 | D7: ='Annual Employer Cost per Grade'!F7*C7 -> 6576000 | E7: ='Annual Employer Cost per Grade'!G7*'Annual Cost Summary'!C7 -> 460320 | F7: ='Annual Employer Cost per Grade'!H7*'Annual Cost Summary'!C7 -> 548000 | G7: ='Annual Employer Cost per Grade'!I7*'Annual Cost Summary'!C7 -> 657600 | H7: ='Annual Employer Cost per Grade'!J7*'Annual Cost Summary'!C7 -> 0 | I7: ='Annual Employer Cost per Grade'!K7*'Annual Cost Summary'!C7 -> 0 | J7: ='Annual Employer Cost per Grade'!L7*'Annual Cost Summary'!C7 -> 0 | K7: ='Annual Employer Cost per Grade'!M7*'Annual Cost Summary'!C7 -> 0 | L7: ='Annual Employer Cost per Grade'!N7*'Annual Cost Summary'!C7 -> 0 | M7: ='Annual Employer Cost per Grade'!O7*'Annual Cost Summary'!C7 -> 591840 | N7: ='Annual Employer Cost per Grade'!P7*'Annual Cost Summary'!C7 -> 106531.2 | O7: ='Annual Employer Cost per Grade'!Q7*'Annual Cost Summary'!C7 -> 72336 | P7: ='Annual Employer Cost per Grade'!R7*'Annual Cost Summary'!C7 -> 72336 | Q7: =SUM(D7:P7) -> 9084963.2
A8: =A7+1 -> 7 | B8: Finance Associate | C8: 1 | D8: ='Annual Employer Cost per Grade'!F8*C8 -> 3288000 | E8: ='Annual Employer Cost per Grade'!G8*'Annual Cost Summary'!C8 -> 230160 | F8: ='Annual Employer Cost per Grade'!H8*'Annual Cost Summary'!C8 -> 274000 | G8: ='Annual Employer Cost per Grade'!I8*'Annual Cost Summary'!C8 -> 328800 | H8: ='Annual Employer Cost per Grade'!J8*'Annual Cost Summary'!C8 -> 0 | I8: ='Annual Employer Cost per Grade'!K8*'Annual Cost Summary'!C8 -> 0 | J8: ='Annual Employer Cost per Grade'!L8*'Annual Cost Summary'!C8 -> 0 | K8: ='Annual Employer Cost per Grade'!M8*'Annual Cost Summary'!C8 -> 0 | L8: ='Annual Employer Cost per Grade'!N8*'Annual Cost Summary'!C8 -> 0 | M8: ='Annual Employer Cost per Grade'!O8*'Annual Cost Summary'!C8 -> 295920 | N8: ='Annual Employer Cost per Grade'!P8*'Annual Cost Summary'!C8 -> 53265.6 | O8: ='Annual Employer Cost per Grade'!Q8*'Annual Cost Summary'!C8 -> 36168 | P8: ='Annual Employer Cost per Grade'!R8*'Annual Cost Summary'!C8 -> 36168 | Q8: =SUM(D8:P8) -> 4542481.6
A9: =A8+1 -> 8 | B9: Admin & HR Associate | C9: 1 | D9: ='Annual Employer Cost per Grade'!F9*C9 -> 3288000 | E9: ='Annual Employer Cost per Grade'!G9*'Annual Cost Summary'!C9 -> 230160 | F9: ='Annual Employer Cost per Grade'!H9*'Annual Cost Summary'!C9 -> 274000 | G9: ='Annual Employer Cost per Grade'!I9*'Annual Cost Summary'!C9 -> 328800 | H9: ='Annual Employer Cost per Grade'!J9*'Annual Cost Summary'!C9 -> 0 | I9: ='Annual Employer Cost per Grade'!K9*'Annual Cost Summary'!C9 -> 0 | J9: ='Annual Employer Cost per Grade'!L9*'Annual Cost Summary'!C9 -> 0 | K9: ='Annual Employer Cost per Grade'!M9*'Annual Cost Summary'!C9 -> 0 | L9: ='Annual Employer Cost per Grade'!N9*'Annual Cost Summary'!C9 -> 0 | M9: ='Annual Employer Cost per Grade'!O9*'Annual Cost Summary'!C9 -> 295920 | N9: ='Annual Employer Cost per Grade'!P9*'Annual Cost Summary'!C9 -> 53265.6 | O9: ='Annual Employer Cost per Grade'!Q9*'Annual Cost Summary'!C9 -> 36168 | P9: ='Annual Employer Cost per Grade'!R9*'Annual Cost Summary'!C9 -> 36168 | Q9: =SUM(D9:P9) -> 4542481.6
A10: =A9+1 -> 9 | B10: IT Support Associate (x2) | C10: 2 | D10: ='Annual Employer Cost per Grade'!F10*C10 -> 6576000 | E10: ='Annual Employer Cost per Grade'!G10*'Annual Cost Summary'!C10 -> 460320 | F10: ='Annual Employer Cost per Grade'!H10*'Annual Cost Summary'!C10 -> 548000 | G10: ='Annual Employer Cost per Grade'!I10*'Annual Cost Summary'!C10 -> 657600 | H10: ='Annual Employer Cost per Grade'!J10*'Annual Cost Summary'!C10 -> 0 | I10: ='Annual Employer Cost per Grade'!K10*'Annual Cost Summary'!C10 -> 0 | J10: ='Annual Employer Cost per Grade'!L10*'Annual Cost Summary'!C10 -> 0 | K10: ='Annual Employer Cost per Grade'!M10*'Annual Cost Summary'!C10 -> 0 | L10: ='Annual Employer Cost per Grade'!N10*'Annual Cost Summary'!C10 -> 0 | M10: ='Annual Employer Cost per Grade'!O10*'Annual Cost Summary'!C10 -> 591840 | N10: ='Annual Employer Cost per Grade'!P10*'Annual Cost Summary'!C10 -> 106531.2 | O10: ='Annual Employer Cost per Grade'!Q10*'Annual Cost Summary'!C10 -> 72336 | P10: ='Annual Employer Cost per Grade'!R10*'Annual Cost Summary'!C10 -> 72336 | Q10: =SUM(D10:P10) -> 9084963.2
A11: =A10+1 -> 10 | B11: Content & Marketing Lead | C11: 1 | D11: ='Annual Employer Cost per Grade'!F11*C11 -> 3288000 | E11: ='Annual Employer Cost per Grade'!G11*'Annual Cost Summary'!C11 -> 230160 | F11: ='Annual Employer Cost per Grade'!H11*'Annual Cost Summary'!C11 -> 274000 | G11: ='Annual Employer Cost per Grade'!I11*'Annual Cost Summary'!C11 -> 328800 | H11: ='Annual Employer Cost per Grade'!J11*'Annual Cost Summary'!C11 -> 0 | I11: ='Annual Employer Cost per Grade'!K11*'Annual Cost Summary'!C11 -> 0 | J11: ='Annual Employer Cost per Grade'!L11*'Annual Cost Summary'!C11 -> 0 | K11: ='Annual Employer Cost per Grade'!M11*'Annual Cost Summary'!C11 -> 0 | L11: ='Annual Employer Cost per Grade'!N11*'Annual Cost Summary'!C11 -> 0 | M11: ='Annual Employer Cost per Grade'!O11*'Annual Cost Summary'!C11 -> 295920 | N11: ='Annual Employer Cost per Grade'!P11*'Annual Cost Summary'!C11 -> 53265.6 | O11: ='Annual Employer Cost per Grade'!Q11*'Annual Cost Summary'!C11 -> 36168 | P11: ='Annual Employer Cost per Grade'!R11*'Annual Cost Summary'!C11 -> 36168 | Q11: =SUM(D11:P11) -> 4542481.6
A12: =A11+1 -> 11 | B12: Graphic & Multimedia Associate | C12: 1 | D12: ='Annual Employer Cost per Grade'!F12*C12 -> 3288000 | E12: ='Annual Employer Cost per Grade'!G12*'Annual Cost Summary'!C12 -> 230160 | F12: ='Annual Employer Cost per Grade'!H12*'Annual Cost Summary'!C12 -> 274000 | G12: ='Annual Employer Cost per Grade'!I12*'Annual Cost Summary'!C12 -> 328800 | H12: ='Annual Employer Cost per Grade'!J12*'Annual Cost Summary'!C12 -> 0 | I12: ='Annual Employer Cost per Grade'!K12*'Annual Cost Summary'!C12 -> 0 | J12: ='Annual Employer Cost per Grade'!L12*'Annual Cost Summary'!C12 -> 0 | K12: ='Annual Employer Cost per Grade'!M12*'Annual Cost Summary'!C12 -> 0 | L12: ='Annual Employer Cost per Grade'!N12*'Annual Cost Summary'!C12 -> 0 | M12: ='Annual Employer Cost per Grade'!O12*'Annual Cost Summary'!C12 -> 295920 | N12: ='Annual Employer Cost per Grade'!P12*'Annual Cost Summary'!C12 -> 53265.6 | O12: ='Annual Employer Cost per Grade'!Q12*'Annual Cost Summary'!C12 -> 36168 | P12: ='Annual Employer Cost per Grade'!R12*'Annual Cost Summary'!C12 -> 36168 | Q12: =SUM(D12:P12) -> 4542481.6
A13: =A12+1 -> 12 | B13: Facility Technician (x3) | C13: 3 | D13: ='Annual Employer Cost per Grade'!F13*C13 -> 4932000 | E13: ='Annual Employer Cost per Grade'!G13*'Annual Cost Summary'!C13 -> 345240 | F13: ='Annual Employer Cost per Grade'!H13*'Annual Cost Summary'!C13 -> 411000 | G13: ='Annual Employer Cost per Grade'!I13*'Annual Cost Summary'!C13 -> 493200 | H13: ='Annual Employer Cost per Grade'!J13*'Annual Cost Summary'!C13 -> 0 | I13: ='Annual Employer Cost per Grade'!K13*'Annual Cost Summary'!C13 -> 0 | J13: ='Annual Employer Cost per Grade'!L13*'Annual Cost Summary'!C13 -> 0 | K13: ='Annual Employer Cost per Grade'!M13*'Annual Cost Summary'!C13 -> 0 | L13: ='Annual Employer Cost per Grade'!N13*'Annual Cost Summary'!C13 -> 0 | M13: ='Annual Employer Cost per Grade'!O13*'Annual Cost Summary'!C13 -> 443880 | N13: ='Annual Employer Cost per Grade'!P13*'Annual Cost Summary'!C13 -> 79898.4 | O13: ='Annual Employer Cost per Grade'!Q13*'Annual Cost Summary'!C13 -> 54252 | P13: ='Annual Employer Cost per Grade'!R13*'Annual Cost Summary'!C13 -> 54252 | Q13: =SUM(D13:P13) -> 6813722.4
A14: =A13+1 -> 13 | B14: Driver | C14: 1 | D14: ='Annual Employer Cost per Grade'!F14*C14 -> 1644000 | E14: ='Annual Employer Cost per Grade'!G14*'Annual Cost Summary'!C14 -> 115080 | F14: ='Annual Employer Cost per Grade'!H14*'Annual Cost Summary'!C14 -> 137000 | G14: ='Annual Employer Cost per Grade'!I14*'Annual Cost Summary'!C14 -> 164400 | H14: ='Annual Employer Cost per Grade'!J14*'Annual Cost Summary'!C14 -> 0 | I14: ='Annual Employer Cost per Grade'!K14*'Annual Cost Summary'!C14 -> 0 | J14: ='Annual Employer Cost per Grade'!L14*'Annual Cost Summary'!C14 -> 0 | K14: ='Annual Employer Cost per Grade'!M14*'Annual Cost Summary'!C14 -> 0 | L14: ='Annual Employer Cost per Grade'!N14*'Annual Cost Summary'!C14 -> 0 | M14: ='Annual Employer Cost per Grade'!O14*'Annual Cost Summary'!C14 -> 147960 | N14: ='Annual Employer Cost per Grade'!P14*'Annual Cost Summary'!C14 -> 26632.8 | O14: ='Annual Employer Cost per Grade'!Q14*'Annual Cost Summary'!C14 -> 18084 | P14: ='Annual Employer Cost per Grade'!R14*'Annual Cost Summary'!C14 -> 18084 | Q14: =SUM(D14:P14) -> 2271240.8
... A16: =A15+1 -> 15 | B16: Intern (x3) | C16: 3 | D16: ='Annual Employer Cost per Grade'!F16*C16 -> 1656000 | E16: ='Annual Employer Cost per Grade'!G16*'Annual Cost Summary'!C16 -> 115920 | F16: ='Annual Employer Cost per Grade'!H16*'Annual Cost Summary'!C16 -> 138000 | G16: ='Annual Employer Cost per Grade'!I16*'Annual Cost Summary'!C16 -> 0 | H16: ='Annual Employer Cost per Grade'!J16*'Annual Cost Summary'!C16 -> 0 | I16: ='Annual Employer Cost per Grade'!K16*'Annual Cost Summary'!C16 -> 0 | J16: ='Annual Employer Cost per Grade'!L16*'Annual Cost Summary'!C16 -> 0 | K16: ='Annual Employer Cost per Grade'!M16*'Annual Cost Summary'!C16 -> 0 | L16: ='Annual Employer Cost per Grade'!N16*'Annual Cost Summary'!C16 -> 0 | M16: ='Annual Employer Cost per Grade'!O16*'Annual Cost Summary'!C16 -> 0 | N16: ='Annual Employer Cost per Grade'!P16*'Annual Cost Summary'!C16 -> 26827.2 | O16: ='Annual Employer Cost per Grade'!Q16*'Annual Cost Summary'!C16 -> 16560 | P16: ='Annual Employer Cost per Grade'!R16*'Annual Cost Summary'!C16 -> 16560 | Q16: =SUM(D16:P16) -> 1969867.2
B17: Total | C17: =SUM(C2:C16) -> 22 | D17: =SUM(D2:D16) -> 122880000 | E17: =SUM(E2:E16) -> 8601600 | F17: =SUM(F2:F16) -> 10240000 | G17: =SUM(G2:G16) -> 24405600 | H17: =SUM(H2:H16) -> 0 | I17: =SUM(I2:I16) -> 0 | J17: =SUM(J2:J16) -> 0 | ... Q17: =SUM(Q2:Q16) -> 1.8185493e+08

Sheet Payroll breakdown per role
H1: 0.7 | I1: 0.1 | J1: 0.1 | K1: 0.0333 | L1: 0.0333 | M1: 0.0334 | O1: 8% of B+T+H | P1: Optional | W1: Tax Table | AE1: Tax Table | AF1: Monthly | AG1: =IF(AF1="Annual",1,0.0833333) -> 0.0833333
A2: S/N | B2: Job Role | C2: Description | D2: Grade | E2: Grade Name | F2: Gross Salary | H2: Basic Salary (70%) | I2: Transport Allowance (10%) | J2: Housing Allowance (10%) | K2: Meal Allowance (3.33%) | L2: Utility Allowance (3.33%) | M2: Entertainment Allowance (3.34%) | N2: Gross Pay | O2: Pension Contribution (8%) | P2: NHF Contribution (2.5%) | Q2: PAYE (Tax) - | R2: Net Pay (Monthly Take home) | T2: Employer Pension Contribution | W2: Do not touch the figures | X2: Gross Income for CRA | Y2: Consolidated Relief Allowance | Z2: Employee Pension | AA2: National Housing Fund | AB2: Total Relief / Tax Free Pay | AC2: Amount Taxable | AE2: Do not touch the figures | AG2: 0.07 | AH2: 0.11 | AI2: 0.15 | AJ2: 0.19 | AK2: 0.21 | AL2: 0.24 | AM2: Monthly Tax Payable
A3: 1 | B3: Managing Director | D3: A1 | E3: Managing Director | F3: 3840000 | H3: =F3*$H$1 -> 2688000 | I3: =F3*$I$1 -> 384000 | J3: =F3*$J$1 -> 384000 | K3: =F3*$K$1 -> 127872 | L3: =F3*$L$1 -> 127872 | M3: =F3*$M$1 -> 128256 | N3: =SUM(H3:M3) -> 3840000 | O3: =(H3+I3+J3)*8% -> 276480 | P3: =2.5%*N3 -> 96000 | Q3: =AM3 -> 640108.47 | R3: =N3-O3-P3-Q3 -> 2827411.5 | T3: =(H3+I3+J3)*10% -> 345600 | X3: =N3-O3-P3 -> 3467520 | Y3: =IF(X3*1%>200000*$AG$1,X3*1%,200000*$AG$1)+(20%*X3) -> 728179.2 | Z3: =O3 -> 276480 | AA3: =P3 -> 96000 | AB3: =SUM(Y3:AA3) -> 1100659.2 | AC3: =N3-AB3 -> 2739340.8 | AG3: =IF(300000*$AG$1<AC3,300000*$AG$1,AC3)*$AG$2 -> 1749.9993 | AH3: =(IF(300000*$AG$1>AC3,0,IF(600000*$AG$1>AC3,(AC3-(300000*$AG$1)),IF(600000*$AG$1<AC3,300000*$AG$1))))*$AH$2 -> 2749.9989 | AI3: =(IF(600000*$AG$1>AC3,0,IF(1100000*$AG$1>AC3,(AC3-(600000*$AG$1)),IF(1100000*$AG$1<AC3,500000*$AG$1))))*$AI$2 -> 6249.9975 | AJ3: =(IF(1100000*$AG$1>AC3,0,IF(1600000*$AG$1>AC3,(AC3-(1100000*$AG$1)),IF(1600000*$AG$1<AC3,500000*$AG$1))))*$AJ$2 -> 7916.6635 | AK3: =(IF(1600000*$AG$1>AC3,0,IF(3200000*$AG$1>AC3,(AC3-(1600000*$AG$1)),IF(3200000*$AG$1<AC3,1600000*$AG$1))))*$AK$2 -> 27999.989 | AL3: =(IF(3200000*$AG$1>AC3,0,IF(3200000*$AG$1<AC3,AC3-3200000*$AG$1)))*$AL$2 -> 593441.82 | AM3: =SUM(AG3:AL3) -> 640108.47
A4: =A3+1 -> 2 | B4: Director of Programs | D4: B1 | E4: Director 1 | F4: 2194000 | H4: =F4*$H$1 -> 1535800 | I4: =F4*$I$1 -> 219400 | J4: =F4*$J$1 -> 219400 | K4: =F4*$K$1 -> 73060.2 | L4: =F4*$L$1 -> 73060.2 | M4: =F4*$M$1 -> 73279.6 | N4: =SUM(H4:M4) -> 2194000 | O4: =(H4+I4+J4)*8% -> 157968 | P4: =2.5%*N4 -> 54850 | Q4: =AM4 -> 358298.78 | R4: =N4-O4-P4-Q4 -> 1622883.2 | T4: =(H4+I4+J4)*10% -> 197460 | X4: =N4-O4-P4 -> 1981182 | Y4: =IF(X4*1%>200000*$AG$1,X4*1%,200000*$AG$1)+(20%*X4) -> 416048.22 | Z4: =O4 -> 157968 | AA4: =P4 -> 54850 | AB4: =SUM(Y4:AA4) -> 628866.22 | AC4: =N4-AB4 -> 1565133.8 | AG4: =IF(300000*$AG$1<AC4,300000*$AG$1,AC4)*$AG$2 -> 1749.9993 | AH4: =(IF(300000*$AG$1>AC4,0,IF(600000*$AG$1>AC4,(AC4-(300000*$AG$1)),IF(600000*$AG$1<AC4,300000*$AG$1))))*$AH$2 -> 2749.9989 | AI4: =(IF(600000*$AG$1>AC4,0,IF(1100000*$AG$1>AC4,(AC4-(600000*$AG$1)),IF(1100000*$AG$1<AC4,500000*$AG$1))))*$AI$2 -> 6249.9975 | AJ4: =(IF(1100000*$AG$1>AC4,0,IF(1600000*$AG$1>AC4,(AC4-(1100000*$AG$1)),IF(1600000*$AG$1<AC4,500000*$AG$1))))*$AJ$2 -> 7916.6635 | AK4: =(IF(1600000*$AG$1>AC4,0,IF(3200000*$AG$1>AC4,(AC4-(1600000*$AG$1)),IF(3200000*$AG$1<AC4,1600000*$AG$1))))*$AK$2 -> 27999.989 | AL4: =(IF(3200000*$AG$1>AC4,0,IF(3200000*$AG$1<AC4,AC4-3200000*$AG$1)))*$AL$2 -> 311632.13 | AM4: =SUM(AG4:AL4) -> 358298.78
A5: =A4+1 -> 3 | B5: IT Manager | D5: G1 | E5: Senior Associate 1 | F5: 472000 | H5: =F5*$H$1 -> 330400 | I5: =F5*$I$1 -> 47200 | J5: =F5*$J$1 -> 47200 | K5: =F5*$K$1 -> 15717.6 | L5: =F5*$L$1 -> 15717.6 | M5: =F5*$M$1 -> 15764.8 | N5: =SUM(H5:M5) -> 472000 | O5: =(H5+I5+J5)*8% -> 33984 | P5: =2.5%*N5 -> 11800 | Q5: =AM5 -> 60500.147 | R5: =N5-O5-P5-Q5 -> 365715.85 | T5: =(H5+I5+J5)*10% -> 42480 | X5: =N5-O5-P5 -> 426216 | Y5: =IF(X5*1%>200000*$AG$1,X5*1%,200000*$AG$1)+(20%*X5) -> 101909.86 | Z5: =O5 -> 33984 | AA5: =P5 -> 11800 | AB5: =SUM(Y5:AA5) -> 147693.86 | AC5: =N5-AB5 -> 324306.14 | AG5: =IF(300000*$AG$1<AC5,300000*$AG$1,AC5)*$AG$2 -> 1749.9993 | AH5: =(IF(300000*$AG$1>AC5,0,IF(600000*$AG$1>AC5,(AC5-(300000*$AG$1)),IF(600000*$AG$1<AC5,300000*$AG$1))))*$AH$2 -> 2749.9989 | AI5: =(IF(600000*$AG$1>AC5,0,IF(1100000*$AG$1>AC5,(AC5-(600000*$AG$1)),IF(1100000*$AG$1<AC5,500000*$AG$1))))*$AI$2 -> 6249.9975 | AJ5: =(IF(1100000*$AG$1>AC5,0,IF(1600000*$AG$1>AC5,(AC5-(1100000*$AG$1)),IF(1600000*$AG$1<AC5,500000*$AG$1))))*$AJ$2 -> 7916.6635 | AK5: =(IF(1600000*$AG$1>AC5,0,IF(3200000*$AG$1>AC5,(AC5-(1600000*$AG$1)),IF(3200000*$AG$1<AC5,1600000*$AG$1))))*$AK$2 -> 27999.989 | AL5: =(IF(3200000*$AG$1>AC5,0,IF(3200000*$AG$1<AC5,AC5-3200000*$AG$1)))*$AL$2 -> 13833.499 | AM5: =SUM(AG5:AL5) -> 60500.147
A6: =A5+1 -> 4 | B6: Community Manager | D6: G1 | E6: Senior Associate 1 | F6: 472000 | H6: =F6*$H$1 -> 330400 | I6: =F6*$I$1 -> 47200 | J6: =F6*$J$1 -> 47200 | K6: =F6*$K$1 -> 15717.6 | L6: =F6*$L$1 -> 15717.6 | M6: =F6*$M$1 -> 15764.8 | N6: =SUM(H6:M6) -> 472000 | O6: =(H6+I6+J6)*8% -> 33984 | P6: =2.5%*N6 -> 11800 | Q6: =AM6 -> 60500.147 | R6: =N6-O6-P6-Q6 -> 365715.85 | T6: =(H6+I6+J6)*10% -> 42480 | X6: =N6-O6-P6 -> 426216 | Y6: =IF(X6*1%>200000*$AG$1,X6*1%,200000*$AG$1)+(20%*X6) -> 101909.86 | Z6: =O6 -> 33984 | AA6: =P6 -> 11800 | AB6: =SUM(Y6:AA6) -> 147693.86 | AC6: =N6-AB6 -> 324306.14 | AG6: =IF(300000*$AG$1<AC6,300000*$AG$1,AC6)*$AG$2 -> 1749.9993 | AH6: =(IF(300000*$AG$1>AC6,0,IF(600000*$AG$1>AC6,(AC6-(300000*$AG$1)),IF(600000*$AG$1<AC6,300000*$AG$1))))*$AH$2 -> 2749.9989 | AI6: =(IF(600000*$AG$1>AC6,0,IF(1100000*$AG$1>AC6,(AC6-(600000*$AG$1)),IF(1100000*$AG$1<AC6,500000*$AG$1))))*$AI$2 -> 6249.9975 | AJ6: =(IF(1100000*$AG$1>AC6,0,IF(1600000*$AG$1>AC6,(AC6-(1100000*$AG$1)),IF(1600000*$AG$1<AC6,500000*$AG$1))))*$AJ$2 -> 7916.6635 | AK6: =(IF(1600000*$AG$1>AC6,0,IF(3200000*$AG$1>AC6,(AC6-(1600000*$AG$1)),IF(3200000*$AG$1<AC6,1600000*$AG$1))))*$AK$2 -> 27999.989 | AL6: =(IF(3200000*$AG$1>AC6,0,IF(3200000*$AG$1<AC6,AC6-3200000*$AG$1)))*$AL$2 -> 13833.499 | AM6: =SUM(AG6:AL6) -> 60500.147
A7: =A6+1 -> 5 | B7: Facility Associate | D7: H1 | E7: Associate 1 | F7: 274000 | H7: =F7*$H$1 -> 191800 | I7: =F7*$I$1 -> 27400 | J7: =F7*$J$1 -> 27400 | K7: =F7*$K$1 -> 9124.2 | L7: =F7*$L$1 -> 9124.2 | M7: =F7*$M$1 -> 9151.6 | N7: =SUM(H7:M7) -> 274000 | O7: =(H7+I7+J7)*8% -> 19728 | P7: =2.5%*N7 -> 6850 | Q7: =AM7 -> 28733.568 | R7: =N7-O7-P7-Q7 -> 218688.43 | T7: =(H7+I7+J7)*10% -> 24660 | X7: =N7-O7-P7 -> 247422 | Y7: =IF(X7*1%>200000*$AG$1,X7*1%,200000*$AG$1)+(20%*X7) -> 66151.06 | Z7: =O7 -> 19728 | AA7: =P7 -> 6850 | AB7: =SUM(Y7:AA7) -> 92729.06 | AC7: =N7-AB7 -> 181270.94 | AG7: =IF(300000*$AG$1<AC7,300000*$AG$1,AC7)*$AG$2 -> 1749.9993 | AH7: =(IF(300000*$AG$1>AC7,0,IF(600000*$AG$1>AC7,(AC7-(300000*$AG$1)),IF(600000*$AG$1<AC7,300000*$AG$1))))*$AH$2 -> 2749.9989 | AI7: =(IF(600000*$AG$1>AC7,0,IF(1100000*$AG$1>AC7,(AC7-(600000*$AG$1)),IF(1100000*$AG$1<AC7,500000*$AG$1))))*$AI$2 -> 6249.9975 | AJ7: =(IF(1100000*$AG$1>AC7,0,IF(1600000*$AG$1>AC7,(AC7-(1100000*$AG$1)),IF(1600000*$AG$1<AC7,500000*$AG$1))))*$AJ$2 -> 7916.6635 | AK7: =(IF(1600000*$AG$1>AC7,0,IF(3200000*$AG$1>AC7,(AC7-(1600000*$AG$1)),IF(3200000*$AG$1<AC7,1600000*$AG$1))))*$AK$2 -> 10066.909 | AL7: =(IF(3200000*$AG$1>AC7,0,IF(3200000*$AG$1<AC7,AC7-3200000*$AG$1)))*$AL$2 -> 0 | AM7: =SUM(AG7:AL7) -> 28733.568
A8: =A7+1 -> 6 | B8: Front Desk Associate (x2) | D8: H1 | E8: Associate 1 | F8: 274000 | H8: =F8*$H$1 -> 191800 | I8: =F8*$I$1 -> 27400 | J8: =F8*$J$1 -> 27400 | K8: =F8*$K$1 -> 9124.2 | L8: =F8*$L$1 -> 9124.2 | M8: =F8*$M$1 -> 9151.6 | N8: =SUM(H8:M8) -> 274000 | O8: =(H8+I8+J8)*8% -> 19728 | P8: =2.5%*N8 -> 6850 | Q8: =AM8 -> 28733.568 | R8: =N8-O8-P8-Q8 -> 218688.43 | T8: =(H8+I8+J8)*10% -> 24660 | X8: =N8-O8-P8 -> 247422 | Y8: =IF(X8*1%>200000*$AG$1,X8*1%,200000*$AG$1)+(20%*X8) -> 66151.06 | Z8: =O8 -> 19728 | AA8: =P8 -> 6850 | AB8: =SUM(Y8:AA8) -> 92729.06 | AC8: =N8-AB8 -> 181270.94 | AG8: =IF(300000*$AG$1<AC8,300000*$AG$1,AC8)*$AG$2 -> 1749.9993 | AH8: =(IF(300000*$AG$1>AC8,0,IF(600000*$AG$1>AC8,(AC8-(300000*$AG$1)),IF(600000*$AG$1<AC8,300000*$AG$1))))*$AH$2 -> 2749.9989 | AI8: =(IF(600000*$AG$1>AC8,0,IF(1100000*$AG$1>AC8,(AC8-(600000*$AG$1)),IF(1100000*$AG$1<AC8,500000*$AG$1))))*$AI$2 -> 6249.9975 | AJ8: =(IF(1100000*$AG$1>AC8,0,IF(1600000*$AG$1>AC8,(AC8-(1100000*$AG$1)),IF(1600000*$AG$1<AC8,500000*$AG$1))))*$AJ$2 -> 7916.6635 | AK8: =(IF(1600000*$AG$1>AC8,0,IF(3200000*$AG$1>AC8,(AC8-(1600000*$AG$1)),IF(3200000*$AG$1<AC8,1600000*$AG$1))))*$AK$2 -> 10066.909 | AL8: =(IF(3200000*$AG$1>AC8,0,IF(3200000*$AG$1<AC8,AC8-3200000*$AG$1)))*$AL$2 -> 0 | AM8: =SUM(AG8:AL8) -> 28733.568
A9: =A8+1 -> 7 | B9: Finance Associate | D9: H1 | E9: Associate 1 | F9: 274000 | H9: =F9*$H$1 -> 191800 | I9: =F9*$I$1 -> 27400 | J9: =F9*$J$1 -> 27400 | K9: =F9*$K$1 -> 9124.2 | L9: =F9*$L$1 -> 9124.2 | M9: =F9*$M$1 -> 9151.6 | N9: =SUM(H9:M9) -> 274000 | O9: =(H9+I9+J9)*8% -> 19728 | P9: =2.5%*N9 -> 6850 | Q9: =AM9 -> 28733.568 | R9: =N9-O9-P9-Q9 -> 218688.43 | T9: =(H9+I9+J9)*10% -> 24660 | X9: =N9-O9-P9 -> 247422 | Y9: =IF(X9*1%>200000*$AG$1,X9*1%,200000*$AG$1)+(20%*X9) -> 66151.06 | Z9: =O9 -> 19728 | AA9: =P9 -> 6850 | AB9: =SUM(Y9:AA9) -> 92729.06 | AC9: =N9-AB9 -> 181270.94 | AG9: =IF(300000*$AG$1<AC9,300000*$AG$1,AC9)*$AG$2 -> 1749.9993 | AH9: =(IF(300000*$AG$1>AC9,0,IF(600000*$AG$1>AC9,(AC9-(300000*$AG$1)),IF(600000*$AG$1<AC9,300000*$AG$1))))*$AH$2 -> 2749.9989 | AI9: =(IF(600000*$AG$1>AC9,0,IF(1100000*$AG$1>AC9,(AC9-(600000*$AG$1)),IF(1100000*$AG$1<AC9,500000*$AG$1))))*$AI$2 -> 6249.9975 | AJ9: =(IF(1100000*$AG$1>AC9,0,IF(1600000*$AG$1>AC9,(AC9-(1100000*$AG$1)),IF(1600000*$AG$1<AC9,500000*$AG$1))))*$AJ$2 -> 7916.6635 | AK9: =(IF(1600000*$AG$1>AC9,0,IF(3200000*$AG$1>AC9,(AC9-(1600000*$AG$1)),IF(3200000*$AG$1<AC9,1600000*$AG$1))))*$AK$2 -> 10066.909 | AL9: =(IF(3200000*$AG$1>AC9,0,IF(3200000*$AG$1<AC9,AC9-3200000*$AG$1)))*$AL$2 -> 0 | AM9: =SUM(AG9:AL9) -> 28733.568
A10: =A9+1 -> 8 | B10: Admin & HR Associate | D10: H1 | E10: Associate 1 | F10: 274000 | H10: =F10*$H$1 -> 191800 | I10: =F10*$I$1 -> 27400 | J10: =F10*$J$1 -> 27400 | K10: =F10*$K$1 -> 9124.2 | L10: =F10*$L$1 -> 9124.2 | M10: =F10*$M$1 -> 9151.6 | N10: =SUM(H10:M10) -> 274000 | O10: =(H10+I10+J10)*8% -> 19728 | P10: =2.5%*N10 -> 6850 | Q10: =AM10 -> 28733.568 | R10: =N10-O10-P10-Q10 -> 218688.43 | T10: =(H10+I10+J10)*10% -> 24660 | X10: =N10-O10-P10 -> 247422 | Y10: =IF(X10*1%>200000*$AG$1,X10*1%,200000*$AG$1)+(20%*X10) -> 66151.06 | Z10: =O10 -> 19728 | AA10: =P10 -> 6850 | AB10: =SUM(Y10:AA10) -> 92729.06 | AC10: =N10-AB10 -> 181270.94 | AG10: =IF(300000*$AG$1<AC10,300000*$AG$1,AC10)*$AG$2 -> 1749.9993 | AH10: =(IF(300000*$AG$1>AC10,0,IF(600000*$AG$1>AC10,(AC10-(300000*$AG$1)),IF(600000*$AG$1<AC10,300000*$AG$1))))*$AH$2 -> 2749.9989 | AI10: =(IF(600000*$AG$1>AC10,0,IF(1100000*$AG$1>AC10,(AC10-(600000*$AG$1)),IF(1100000*$AG$1<AC10,500000*$AG$1))))*$AI$2 -> 6249.9975 | AJ10: =(IF(1100000*$AG$1>AC10,0,IF(1600000*$AG$1>AC10,(AC10-(1100000*$AG$1)),IF(1600000*$AG$1<AC10,500000*$AG$1))))*$AJ$2 -> 7916.6635 | AK10: =(IF(1600000*$AG$1>AC10,0,IF(3200000*$AG$1>AC10,(AC10-(1600000*$AG$1)),IF(3200000*$AG$1<AC10,1600000*$AG$1))))*$AK$2 -> 10066.909 | AL10: =(IF(3200000*$AG$1>AC10,0,IF(3200000*$AG$1<AC10,AC10-3200000*$AG$1)))*$AL$2 -> 0 | AM10: =SUM(AG10:AL10) -> 28733.568
A11: =A10+1 -> 9 | B11: IT Support Associate (x2) | D11: H1 | E11: Associate 1 | F11: 274000 | H11: =F11*$H$1 -> 191800 | I11: =F11*$I$1 -> 27400 | J11: =F11*$J$1 -> 27400 | K11: =F11*$K$1 -> 9124.2 | L11: =F11*$L$1 -> 9124.2 | M11: =F11*$M$1 -> 9151.6 | N11: =SUM(H11:M11) -> 274000 | O11: =(H11+I11+J11)*8% -> 19728 | P11: =2.5%*N11 -> 6850 | Q11: =AM11 -> 28733.568 | R11: =N11-O11-P11-Q11 -> 218688.43 | T11: =(H11+I11+J11)*10% -> 24660 | X11: =N11-O11-P11 -> 247422 | Y11: =IF(X11*1%>200000*$AG$1,X11*1%,200000*$AG$1)+(20%*X11) -> 66151.06 | Z11: =O11 -> 19728 | AA11: =P11 -> 6850 | AB11: =SUM(Y11:AA11) -> 92729.06 | AC11: =N11-AB11 -> 181270.94 | AG11: =IF(300000*$AG$1<AC11,300000*$AG$1,AC11)*$AG$2 -> 1749.9993 | AH11: =(IF(300000*$AG$1>AC11,0,IF(600000*$AG$1>AC11,(AC11-(300000*$AG$1)),IF(600000*$AG$1<AC11,300000*$AG$1))))*$AH$2 -> 2749.9989 | AI11: =(IF(600000*$AG$1>AC11,0,IF(1100000*$AG$1>AC11,(AC11-(600000*$AG$1)),IF(1100000*$AG$1<AC11,500000*$AG$1))))*$AI$2 -> 6249.9975 | AJ11: =(IF(1100000*$AG$1>AC11,0,IF(1600000*$AG$1>AC11,(AC11-(1100000*$AG$1)),IF(1600000*$AG$1<AC11,500000*$AG$1))))*$AJ$2 -> 7916.6635 | AK11: =(IF(1600000*$AG$1>AC11,0,IF(3200000*$AG$1>AC11,(AC11-(1600000*$AG$1)),IF(3200000*$AG$1<AC11,1600000*$AG$1))))*$AK$2 -> 10066.909 | AL11: =(IF(3200000*$AG$1>AC11,0,IF(3200000*$AG$1<AC11,AC11-3200000*$AG$1)))*$AL$2 -> 0 | AM11: =SUM(AG11:AL11) -> 28733.568
A12: =A11+1 -> 10 | B12: Content & Marketing Lead | D12: H1 | E12: Associate 1 | F12: 274000 | H12: =F12*$H$1 -> 191800 | I12: =F12*$I$1 -> 27400 | J12: =F12*$J$1 -> 27400 | K12: =F12*$K$1 -> 9124.2 | L12: =F12*$L$1 -> 9124.2 | M12: =F12*$M$1 -> 9151.6 | N12: =SUM(H12:M12) -> 274000 | O12: =(H12+I12+J12)*8% -> 19728 | P12: =2.5%*N12 -> 6850 | Q12: =AM12 -> 28733.568 | R12: =N12-O12-P12-Q12 -> 218688.43 | T12: =(H12+I12+J12)*10% -> 24660 | X12: =N12-O12-P12 -> 247422 | Y12: =IF(X12*1%>200000*$AG$1,X12*1%,200000*$AG$1)+(20%*X12) -> 66151.06 | Z12: =O12 -> 19728 | AA12: =P12 -> 6850 | AB12: =SUM(Y12:AA12) -> 92729.06 | AC12: =N12-AB12 -> 181270.94 | AG12: =IF(300000*$AG$1<AC12,300000*$AG$1,AC12)*$AG$2 -> 1749.9993 | AH12: =(IF(300000*$AG$1>AC12,0,IF(600000*$AG$1>AC12,(AC12-(300000*$AG$1)),IF(600000*$AG$1<AC12,300000*$AG$1))))*$AH$2 -> 2749.9989 | AI12: =(IF(600000*$AG$1>AC12,0,IF(1100000*$AG$1>AC12,(AC12-(600000*$AG$1)),IF(1100000*$AG$1<AC12,500000*$AG$1))))*$AI$2 -> 6249.9975 | AJ12: =(IF(1100000*$AG$1>AC12,0,IF(1600000*$AG$1>AC12,(AC12-(1100000*$AG$1)),IF(1600000*$AG$1<AC12,500000*$AG$1))))*$AJ$2 -> 7916.6635 | AK12: =(IF(1600000*$AG$1>AC12,0,IF(3200000*$AG$1>AC12,(AC12-(1600000*$AG$1)),IF(3200000*$AG$1<AC12,1600000*$AG$1))))*$AK$2 -> 10066.909 | AL12: =(IF(3200000*$AG$1>AC12,0,IF(3200000*$AG$1<AC12,AC12-3200000*$AG$1)))*$AL$2 -> 0 | AM12: =SUM(AG12:AL12) -> 28733.568
A13: =A12+1 -> 11 | B13: Graphic & Multimedia Associate | D13: H1 | E13: Associate 1 | F13: 274000 | H13: =F13*$H$1 -> 191800 | I13: =F13*$I$1 -> 27400 | J13: =F13*$J$1 -> 27400 | K13: =F13*$K$1 -> 9124.2 | L13: =F13*$L$1 -> 9124.2 | M13: =F13*$M$1 -> 9151.6 | N13: =SUM(H13:M13) -> 274000 | O13: =(H13+I13+J13)*8% -> 19728 | P13: =2.5%*N13 -> 6850 | Q13: =AM13 -> 28733.568 | R13: =N13-O13-P13-Q13 -> 218688.43 | T13: =(H13+I13+J13)*10% -> 24660 | X13: =N13-O13-P13 -> 247422 | Y13: =IF(X13*1%>200000*$AG$1,X13*1%,200000*$AG$1)+(20%*X13) -> 66151.06 | Z13: =O13 -> 19728 | AA13: =P13 -> 6850 | AB13: =SUM(Y13:AA13) -> 92729.06 | AC13: =N13-AB13 -> 181270.94 | AG13: =IF(300000*$AG$1<AC13,300000*$AG$1,AC13)*$AG$2 -> 1749.9993 | AH13: =(IF(300000*$AG$1>AC13,0,IF(600000*$AG$1>AC13,(AC13-(300000*$AG$1)),IF(600000*$AG$1<AC13,300000*$AG$1))))*$AH$2 -> 2749.9989 | AI13: =(IF(600000*$AG$1>AC13,0,IF(1100000*$AG$1>AC13,(AC13-(600000*$AG$1)),IF(1100000*$AG$1<AC13,500000*$AG$1))))*$AI$2 -> 6249.9975 | AJ13: =(IF(1100000*$AG$1>AC13,0,IF(1600000*$AG$1>AC13,(AC13-(1100000*$AG$1)),IF(1600000*$AG$1<AC13,500000*$AG$1))))*$AJ$2 -> 7916.6635 | AK13: =(IF(1600000*$AG$1>AC13,0,IF(3200000*$AG$1>AC13,(AC13-(1600000*$AG$1)),IF(3200000*$AG$1<AC13,1600000*$AG$1))))*$AK$2 -> 10066.909 | AL13: =(IF(3200000*$AG$1>AC13,0,IF(3200000*$AG$1<AC13,AC13-3200000*$AG$1)))*$AL$2 -> 0 | AM13: =SUM(AG13:AL13) -> 28733.568
A14: =A13+1 -> 12 | B14: Facility Technician (x3) | D14: I1 | E14: Support Staff 1 | F14: 137000 | H14: =F14*$H$1 -> 95900 | I14: =F14*$I$1 -> 13700 | J14: =F14*$J$1 -> 13700 | K14: =F14*$K$1 -> 4562.1 | L14: =F14*$L$1 -> 4562.1 | M14: =F14*$M$1 -> 4575.8 | N14: =SUM(H14:M14) -> 137000 | O14: =(H14+I14+J14)*8% -> 9864 | P14: =2.5%*N14 -> 3425 | Q14: =AM14 -> 9345.3222 | R14: =N14-O14-P14-Q14 -> 114365.68 | T14: =(H14+I14+J14)*10% -> 12330 | X14: =N14-O14-P14 -> 123711 | Y14: =IF(X14*1%>200000*$AG$1,X14*1%,200000*$AG$1)+(20%*X14) -> 41408.86 | Z14: =O14 -> 9864 | AA14: =P14 -> 3425 | AB14: =SUM(Y14:AA14) -> 54697.86 | AC14: =N14-AB14 -> 82302.14 | AG14: =IF(300000*$AG$1<AC14,300000*$AG$1,AC14)*$AG$2 -> 1749.9993 | AH14: =(IF(300000*$AG$1>AC14,0,IF(600000*$AG$1>AC14,(AC14-(300000*$AG$1)),IF(600000*$AG$1<AC14,300000*$AG$1))))*$AH$2 -> 2749.9989 | AI14: =(IF(600000*$AG$1>AC14,0,IF(1100000*$AG$1>AC14,(AC14-(600000*$AG$1)),IF(1100000*$AG$1<AC14,500000*$AG$1))))*$AI$2 -> 4845.324 | AJ14: =(IF(1100000*$AG$1>AC14,0,IF(1600000*$AG$1>AC14,(AC14-(1100000*$AG$1)),IF(1600000*$AG$1<AC14,500000*$AG$1))))*$AJ$2 -> 0 | AK14: =(IF(1600000*$AG$1>AC14,0,IF(3200000*$AG$1>AC14,(AC14-(1600000*$AG$1)),IF(3200000*$AG$1<AC14,1600000*$AG$1))))*$AK$2 -> 0 | AL14: =(IF(3200000*$AG$1>AC14,0,IF(3200000*$AG$1<AC14,AC14-3200000*$AG$1)))*$AL$2 -> 0 | AM14: =SUM(AG14:AL14) -> 9345.3222
A15: =A14+1 -> 13 | B15: Driver | D15: I1 | E15: Support Staff 1 | F15: 137000 | H15: =F15*$H$1 -> 95900 | I15: =F15*$I$1 -> 13700 | J15: =F15*$J$1 -> 13700 | K15: =F15*$K$1 -> 4562.1 | L15: =F15*$L$1 -> 4562.1 | M15: =F15*$M$1 -> 4575.8 | N15: =SUM(H15:M15) -> 137000 | O15: =(H15+I15+J15)*8% -> 9864 | P15: =2.5%*N15 -> 3425 | Q15: =AM15 -> 9345.3222 | R15: =N15-O15-P15-Q15 -> 114365.68 | T15: =(H15+I15+J15)*10% -> 12330 | X15: =N15-O15-P15 -> 123711 | Y15: =IF(X15*1%>200000*$AG$1,X15*1%,200000*$AG$1)+(20%*X15) -> 41408.86 | Z15: =O15 -> 9864 | AA15: =P15 -> 3425 | AB15: =SUM(Y15:AA15) -> 54697.86 | AC15: =N15-AB15 -> 82302.14 | AG15: =IF(300000*$AG$1<AC15,300000*$AG$1,AC15)*$AG$2 -> 1749.9993 | AH15: =(IF(300000*$AG$1>AC15,0,IF(600000*$AG$1>AC15,(AC15-(300000*$AG$1)),IF(600000*$AG$1<AC15,300000*$AG$1))))*$AH$2 -> 2749.9989 | AI15: =(IF(600000*$AG$1>AC15,0,IF(1100000*$AG$1>AC15,(AC15-(600000*$AG$1)),IF(1100000*$AG$1<AC15,500000*$AG$1))))*$AI$2 -> 4845.324 | AJ15: =(IF(1100000*$AG$1>AC15,0,IF(1600000*$AG$1>AC15,(AC15-(1100000*$AG$1)),IF(1600000*$AG$1<AC15,500000*$AG$1))))*$AJ$2 -> 0 | AK15: =(IF(1600000*$AG$1>AC15,0,IF(3200000*$AG$1>AC15,(AC15-(1600000*$AG$1)),IF(3200000*$AG$1<AC15,1600000*$AG$1))))*$AK$2 -> 0 | AL15: =(IF(3200000*$AG$1>AC15,0,IF(3200000*$AG$1<AC15,AC15-3200000*$AG$1)))*$AL$2 -> 0 | AM15: =SUM(AG15:AL15) -> 9345.3222
A16: =A15+1 -> 14 | B16: Intern (x2) | C16: NYSC | D16: J2 | E16: Intern 2 | F16: 55000 | H16: =F16*$H$1 -> 38500 | I16: =F16*$I$1 -> 5500 | J16: =F16*$J$1 -> 5500 | K16: =F16*$K$1 -> 1831.5 | L16: =F16*$L$1 -> 1831.5 | M16: =F16*$M$1 -> 1837 | N16: =SUM(H16:M16) -> 55000 | O16: 0 | P16: 0 | Q16: =AM16 -> 2006.6678 | R16: =N16-O16-P16-Q16 -> 52993.332 | T16: =(H16+I16+J16)*10% -> 4950 | X16: =N16-O16-P16 -> 55000 | Y16: =IF(X16*1%>200000*$AG$1,X16*1%,200000*$AG$1)+(20%*X16) -> 27666.66 | Z16: =O16 -> 0 | AA16: =P16 -> 0 | AB16: =SUM(Y16:AA16) -> 27666.66 | AC16: =N16-AB16 -> 27333.34 | AG16: =IF(300000*$AG$1<AC16,300000*$AG$1,AC16)*$AG$2 -> 1749.9993 | AH16: =(IF(300000*$AG$1>AC16,0,IF(600000*$AG$1>AC16,(AC16-(300000*$AG$1)),IF(600000*$AG$1<AC16,300000*$AG$1))))*$AH$2 -> 256.6685 | AI16: =(IF(600000*$AG$1>AC16,0,IF(1100000*$AG$1>AC16,(AC16-(600000*$AG$1)),IF(1100000*$AG$1<AC16,500000*$AG$1))))*$AI$2 -> 0 | AJ16: =(IF(1100000*$AG$1>AC16,0,IF(1600000*$AG$1>AC16,(AC16-(1100000*$AG$1)),IF(1600000*$AG$1<AC16,500000*$AG$1))))*$AJ$2 -> 0 | AK16: =(IF(1600000*$AG$1>AC16,0,IF(3200000*$AG$1>AC16,(AC16-(1600000*$AG$1)),IF(3200000*$AG$1<AC16,1600000*$AG$1))))*$AK$2 -> 0 | AL16: =(IF(3200000*$AG$1>AC16,0,IF(3200000*$AG$1<AC16,AC16-3200000*$AG$1)))*$AL$2 -> 0 | AM16: =SUM(AG16:AL16) -> 2006.6678
A17: =A16+1 -> 15 | B17: Intern (x3) | C17: SIWES | D17: J1 | E17: Intern 1 | F17: 46000 | H17: =F17*$H$1 -> 32200 | I17: =F17*$I$1 -> 4600 | J17: =F17*$J$1 -> 4600 | K17: =F17*$K$1 -> 1531.8 | L17: =F17*$L$1 -> 1531.8 | M17: =F17*$M$1 -> 1536.4 | N17: =SUM(H17:M17) -> 46000 | O17: 0 | P17: 0 | Q17: =AM17 -> 1409.3338 | R17: =N17-O17-P17-Q17 -> 44590.666 | T17: =(H17+I17+J17)*10% -> 4140 | X17: =N17-O17-P17 -> 46000 | Y17: =IF(X17*1%>200000*$AG$1,X17*1%,200000*$AG$1)+(20%*X17) -> 25866.66 | Z17: =O17 -> 0 | AA17: =P17 -> 0 | AB17: =SUM(Y17:AA17) -> 25866.66 | AC17: =N17-AB17 -> 20133.34 | AG17: =IF(300000*$AG$1<AC17,300000*$AG$1,AC17)*$AG$2 -> 1409.3338 | AH17: =(IF(300000*$AG$1>AC17,0,IF(600000*$AG$1>AC17,(AC17-(300000*$AG$1)),IF(600000*$AG$1<AC17,300000*$AG$1))))*$AH$2 -> 0 | AI17: =(IF(600000*$AG$1>AC17,0,IF(1100000*$AG$1>AC17,(AC17-(600000*$AG$1)),IF(1100000*$AG$1<AC17,500000*$AG$1))))*$AI$2 -> 0 | AJ17: =(IF(1100000*$AG$1>AC17,0,IF(1600000*$AG$1>AC17,(AC17-(1100000*$AG$1)),IF(1600000*$AG$1<AC17,500000*$AG$1))))*$AJ$2 -> 0 | AK17: =(IF(1600000*$AG$1>AC17,0,IF(3200000*$AG$1>AC17,(AC17-(1600000*$AG$1)),IF(3200000*$AG$1<AC17,1600000*$AG$1))))*$AK$2 -> 0 | AL17: =(IF(3200000*$AG$1>AC17,0,IF(3200000*$AG$1<AC17,AC17-3200000*$AG$1)))*$AL$2 -> 0 | AM17: =SUM(AG17:AL17) -> 1409.3338
E18: Total | F18: =SUM(F3:F17) -> 9271000 | H18: =SUM(H3:H17) -> 6489700 | I18: =SUM(I3:I17) -> 927100 | J18: =SUM(J3:J17) -> 927100 | K18: =SUM(K3:K17) -> 308724.3 | L18: =SUM(L3:L17) -> 308724.3 | M18: =SUM(M3:M17) -> 309651.4 | N18: =SUM(N3:N17) -> 9271000 | O18: =SUM(O3:O17) -> 660240 | ... R18: =SUM(R3:R17) -> 7038860.8 | T18: =SUM(T3:T17) -> 834390

Sheet Annual Employer Cost per Grade
A1: S/N | B1: Grade | C1: Role | D1: Monthly Gross Salary | F1: Annual Gross Salary | G1: Annual Leave Allowance | H1: 13th Month | I1: Annual Bonus (Tentative) | J1: Telephone Cost One off | K1: Airtime | L1: Mobile Data Plan | M1: Total Cafeteria Subsidy | N1: HMO (Health Insurance) | O1: Employer Pension Contribution | P1: Group Life Insurance Premium Cost | Q1: ITF Cost | R1: NSITF (ECS) | S1: Employer Cost
A2: 1 | B2: ='Payroll breakdown per role'!D3 -> A1 | C2: ='Payroll breakdown per role'!B3 -> Managing Director | D2: ='Payroll breakdown per role'!F3 -> 3840000 | F2: =D2*12 -> 46080000 | G2: =(F2*70%)*10% -> 3225600 | H2: =F2/12 -> 3840000 | I2: =IF(_xlfn.XLOOKUP(B2, 'Bonus suggestion table'!$B$3:$B$7, 'Bonus suggestion table'!$D$3:$D$7, 0, 0) * F2 = 0, 0, _xlfn.XLOOKUP(B2, 'Bonus suggestion table'!$B$3:$B$7, 'Bonus suggestion table'!$D$3:$D$7, 0, 0) * F2) -> 13824000 | O2: =(90%*F2)*(10%) -> 4147200 | P2: =(6/1000)*((F2*90%)*3) -> 746496 | Q2: =1%*(I2+F2) -> 599040 | R2: =1%*(I2+F2) -> 599040 | S2: =SUM(F2:R2) -> 73061376
A3: =A2+1 -> 2 | B3: ='Payroll breakdown per role'!D4 -> B1 | C3: ='Payroll breakdown per role'!B4 -> Director of Programs | D3: ='Payroll breakdown per role'!F4 -> 2194000 | F3: =D3*12 -> 26328000 | G3: =(F3*70%)*10% -> 1842960 | H3: =F3/12 -> 2194000 | I3: =IF(_xlfn.XLOOKUP(B3, 'Bonus suggestion table'!$B$3:$B$7, 'Bonus suggestion table'!$D$3:$D$7, 0, 0) * F3 = 0, 0, _xlfn.XLOOKUP(B3, 'Bonus suggestion table'!$B$3:$B$7, 'Bonus suggestion table'!$D$3:$D$7, 0, 0) * F3) -> 5265600 | O3: =(90%*F3)*(10%) -> 2369520 | P3: =(6/1000)*((F3*90%)*3) -> 426513.6 | Q3: =1%*(I3+F3) -> 315936 | R3: =1%*(I3+F3) -> 315936 | S3: =SUM(F3:R3) -> 39058466
A4: =A3+1 -> 3 | B4: ='Payroll breakdown per role'!D5 -> G1 | C4: ='Payroll breakdown per role'!B5 -> IT Manager | D4: ='Payroll breakdown per role'!F5 -> 472000 | F4: =D4*12 -> 5664000 | G4: =(F4*70%)*10% -> 396480 | H4: =F4/12 -> 472000 | I4: =IF(_xlfn.XLOOKUP(B4, 'Bonus suggestion table'!$B$3:$B$7, 'Bonus suggestion table'!$D$3:$D$7, 0, 0) * F4 = 0, 0, _xlfn.XLOOKUP(B4, 'Bonus suggestion table'!$B$3:$B$7, 'Bonus suggestion table'!$D$3:$D$7, 0, 0) * F4) -> 849600 | O4: =(90%*F4)*(10%) -> 509760 | P4: =(6/1000)*((F4*90%)*3) -> 91756.8 | Q4: =1%*(I4+F4) -> 65136 | R4: =1%*(I4+F4) -> 65136 | S4: =SUM(F4:R4) -> 8113868.8
A5: =A4+1 -> 4 | B5: ='Payroll breakdown per role'!D6 -> G1 | C5: ='Payroll breakdown per role'!B6 -> Community Manager | D5: ='Payroll breakdown per role'!F6 -> 472000 | F5: =D5*12 -> 5664000 | G5: =(F5*70%)*10% -> 396480 | H5: =F5/12 -> 472000 | I5: =IF(_xlfn.XLOOKUP(B5, 'Bonus suggestion table'!$B$3:$B$7, 'Bonus suggestion table'!$D$3:$D$7, 0, 0) * F5 = 0, 0, _xlfn.XLOOKUP(B5, 'Bonus suggestion table'!$B$3:$B$7, 'Bonus suggestion table'!$D$3:$D$7, 0, 0) * F5) -> 849600 | O5: =(90%*F5)*(10%) -> 509760 | P5: =(6/1000)*((F5*90%)*3) -> 91756.8 | Q5: =1%*(I5+F5) -> 65136 | R5: =1%*(I5+F5) -> 65136 | S5: =SUM(F5:R5) -> 8113868.8
A6: =A5+1 -> 5 | B6: ='Payroll breakdown per role'!D7 -> H1 | C6: ='Payroll breakdown per role'!B7 -> Facility Associate | D6: ='Payroll breakdown per role'!F7 -> 274000 | F6: =D6*12 -> 3288000 | G6: =(F6*70%)*10% -> 230160 | H6: =F6/12 -> 274000 | I6: =IF(_xlfn.XLOOKUP(B6, 'Bonus suggestion table'!$B$3:$B$7, 'Bonus suggestion table'!$D$3:$D$7, 0, 0) * F6 = 0, 0, _xlfn.XLOOKUP(B6, 'Bonus suggestion table'!$B$3:$B$7, 'Bonus suggestion table'!$D$3:$D$7, 0, 0) * F6) -> 328800 | O6: =(90%*F6)*(10%) -> 295920 | P6: =(6/1000)*((F6*90%)*3) -> 53265.6 | Q6: =1%*(I6+F6) -> 36168 | R6: =1%*(I6+F6) -> 36168 | S6: =SUM(F6:R6) -> 4542481.6
A7: =A6+1 -> 6 | B7: ='Payroll breakdown per role'!D8 -> H1 | C7: ='Payroll breakdown per role'!B8 -> Front Desk Associate (x2) | D7: ='Payroll breakdown per role'!F8 -> 274000 | F7: =D7*12 -> 3288000 | G7: =(F7*70%)*10% -> 230160 | H7: =F7/12 -> 274000 | I7: =IF(_xlfn.XLOOKUP(B7, 'Bonus suggestion table'!$B$3:$B$7, 'Bonus suggestion table'!$D$3:$D$7, 0, 0) * F7 = 0, 0, _xlfn.XLOOKUP(B7, 'Bonus suggestion table'!$B$3:$B$7, 'Bonus suggestion table'!$D$3:$D$7, 0, 0) * F7) -> 328800 | O7: =(90%*F7)*(10%) -> 295920 | P7: =(6/1000)*((F7*90%)*3) -> 53265.6 | Q7: =1%*(I7+F7) -> 36168 | R7: =1%*(I7+F7) -> 36168 | S7: =SUM(F7:R7) -> 4542481.6
A8: =A7+1 -> 7 | B8: ='Payroll breakdown per role'!D9 -> H1 | C8: ='Payroll breakdown per role'!B9 -> Finance Associate | D8: ='Payroll breakdown per role'!F9 -> 274000 | F8: =D8*12 -> 3288000 | G8: =(F8*70%)*10% -> 230160 | H8: =F8/12 -> 274000 | I8: =IF(_xlfn.XLOOKUP(B8, 'Bonus suggestion table'!$B$3:$B$7, 'Bonus suggestion table'!$D$3:$D$7, 0, 0) * F8 = 0, 0, _xlfn.XLOOKUP(B8, 'Bonus suggestion table'!$B$3:$B$7, 'Bonus suggestion table'!$D$3:$D$7, 0, 0) * F8) -> 328800 | O8: =(90%*F8)*(10%) -> 295920 | P8: =(6/1000)*((F8*90%)*3) -> 53265.6 | Q8: =1%*(I8+F8) -> 36168 | R8: =1%*(I8+F8) -> 36168 | S8: =SUM(F8:R8) -> 4542481.6
A9: =A8+1 -> 8 | B9: ='Payroll breakdown per role'!D10 -> H1 | C9: ='Payroll breakdown per role'!B10 -> Admin & HR Associate | D9: ='Payroll breakdown per role'!F10 -> 274000 | F9: =D9*12 -> 3288000 | G9: =(F9*70%)*10% -> 230160 | H9: =F9/12 -> 274000 | I9: =IF(_xlfn.XLOOKUP(B9, 'Bonus suggestion table'!$B$3:$B$7, 'Bonus suggestion table'!$D$3:$D$7, 0, 0) * F9 = 0, 0, _xlfn.XLOOKUP(B9, 'Bonus suggestion table'!$B$3:$B$7, 'Bonus suggestion table'!$D$3:$D$7, 0, 0) * F9) -> 328800 | O9: =(90%*F9)*(10%) -> 295920 | P9: =(6/1000)*((F9*90%)*3) -> 53265.6 | Q9: =1%*(I9+F9) -> 36168 | R9: =1%*(I9+F9) -> 36168 | S9: =SUM(F9:R9) -> 4542481.6
A10: =A9+1 -> 9 | B10: ='Payroll breakdown per role'!D11 -> H1 | C10: ='Payroll breakdown per role'!B11 -> IT Support Associate (x2) | D10: ='Payroll breakdown per role'!F11 -> 274000 | F10: =D10*12 -> 3288000 | G10: =(F10*70%)*10% -> 230160 | H10: =F10/12 -> 274000 | I10: =IF(_xlfn.XLOOKUP(B10, 'Bonus suggestion table'!$B$3:$B$7, 'Bonus suggestion table'!$D$3:$D$7, 0, 0) * F10 = 0, 0, _xlfn.XLOOKUP(B10, 'Bonus suggestion table'!$B$3:$B$7, 'Bonus suggestion table'!$D$3:$D$7, 0, 0) * F10) -> 328800 | O10: =(90%*F10)*(10%) -> 295920 | P10: =(6/1000)*((F10*90%)*3) -> 53265.6 | Q10: =1%*(I10+F10) -> 36168 | R10: =1%*(I10+F10) -> 36168 | S10: =SUM(F10:R10) -> 4542481.6
A11: =A10+1 -> 10 | B11: ='Payroll breakdown per role'!D12 -> H1 | C11: ='Payroll breakdown per role'!B12 -> Content & Marketing Lead | D11: ='Payroll breakdown per role'!F12 -> 274000 | F11: =D11*12 -> 3288000 | G11: =(F11*70%)*10% -> 230160 | H11: =F11/12 -> 274000 | I11: =IF(_xlfn.XLOOKUP(B11, 'Bonus suggestion table'!$B$3:$B$7, 'Bonus suggestion table'!$D$3:$D$7, 0, 0) * F11 = 0, 0, _xlfn.XLOOKUP(B11, 'Bonus suggestion table'!$B$3:$B$7, 'Bonus suggestion table'!$D$3:$D$7, 0, 0) * F11) -> 328800 | O11: =(90%*F11)*(10%) -> 295920 | P11: =(6/1000)*((F11*90%)*3) -> 53265.6 | Q11: =1%*(I11+F11) -> 36168 | R11: =1%*(I11+F11) -> 36168 | S11: =SUM(F11:R11) -> 4542481.6
A12: =A11+1 -> 11 | B12: ='Payroll breakdown per role'!D13 -> H1 | C12: ='Payroll breakdown per role'!B13 -> Graphic & Multimedia Associate | D12: ='Payroll breakdown per role'!F13 -> 274000 | F12: =D12*12 -> 3288000 | G12: =(F12*70%)*10% -> 230160 | H12: =F12/12 -> 274000 | I12: =IF(_xlfn.XLOOKUP(B12, 'Bonus suggestion table'!$B$3:$B$7, 'Bonus suggestion table'!$D$3:$D$7, 0, 0) * F12 = 0, 0, _xlfn.XLOOKUP(B12, 'Bonus suggestion table'!$B$3:$B$7, 'Bonus suggestion table'!$D$3:$D$7, 0, 0) * F12) -> 328800 | O12: =(90%*F12)*(10%) -> 295920 | P12: =(6/1000)*((F12*90%)*3) -> 53265.6 | Q12: =1%*(I12+F12) -> 36168 | R12: =1%*(I12+F12) -> 36168 | S12: =SUM(F12:R12) -> 4542481.6
A13: =A12+1 -> 12 | B13: ='Payroll breakdown per role'!D14 -> I1 | C13: ='Payroll breakdown per role'!B14 -> Facility Technician (x3) | D13: ='Payroll breakdown per role'!F14 -> 137000 | F13: =D13*12 -> 1644000 | G13: =(F13*70%)*10% -> 115080 | H13: =F13/12 -> 137000 | I13: =IF(_xlfn.XLOOKUP(B13, 'Bonus suggestion table'!$B$3:$B$7, 'Bonus suggestion table'!$D$3:$D$7, 0, 0) * F13 = 0, 0, _xlfn.XLOOKUP(B13, 'Bonus suggestion table'!$B$3:$B$7, 'Bonus suggestion table'!$D$3:$D$7, 0, 0) * F13) -> 164400 | O13: =(90%*F13)*(10%) -> 147960 | P13: =(6/1000)*((F13*90%)*3) -> 26632.8 | Q13: =1%*(I13+F13) -> 18084 | R13: =1%*(I13+F13) -> 18084 | S13: =SUM(F13:R13) -> 2271240.8
A14: =A13+1 -> 13 | B14: ='Payroll breakdown per role'!D15 -> I1 | C14: ='Payroll breakdown per role'!B15 -> Driver | D14: ='Payroll breakdown per role'!F15 -> 137000 | F14: =D14*12 -> 1644000 | G14: =(F14*70%)*10% -> 115080 | H14: =F14/12 -> 137000 | I14: =IF(_xlfn.XLOOKUP(B14, 'Bonus suggestion table'!$B$3:$B$7, 'Bonus suggestion table'!$D$3:$D$7, 0, 0) * F14 = 0, 0, _xlfn.XLOOKUP(B14, 'Bonus suggestion table'!$B$3:$B$7, 'Bonus suggestion table'!$D$3:$D$7, 0, 0) * F14) -> 164400 | O14: =(90%*F14)*(10%) -> 147960 | P14: =(6/1000)*((F14*90%)*3) -> 26632.8 | Q14: =1%*(I14+F14) -> 18084 | R14: =1%*(I14+F14) -> 18084 | S14: =SUM(F14:R14) -> 2271240.8
A15: =A14+1 -> 14 | B15: ='Payroll breakdown per role'!D16 -> J2 | C15: ='Payroll breakdown per role'!B16 -> Intern (x2) | D15: ='Payroll breakdown per role'!F16 -> 55000 | F15: =D15*12 -> 660000 | G15: =(F15*70%)*10% -> 46200 | H15: =F15/12 -> 55000 | I15: =IF(_xlfn.XLOOKUP(B15, 'Bonus suggestion table'!$B$3:$B$7, 'Bonus suggestion table'!$D$3:$D$7, 0, 0) * F15 = 0, 0, _xlfn.XLOOKUP(B15, 'Bonus suggestion table'!$B$3:$B$7, 'Bonus suggestion table'!$D$3:$D$7, 0, 0) * F15) -> 0 | O15: 0 | P15: =(6/1000)*((F15*90%)*3) -> 10692 | Q15: =1%*(I15+F15) -> 6600 | R15: =1%*(I15+F15) -> 6600 | S15: =SUM(F15:R15) -> 785092
A16: =A15+1 -> 15 | B16: ='Payroll breakdown per role'!D17 -> J1 | C16: ='Payroll breakdown per role'!B17 -> Intern (x3) | D16: ='Payroll breakdown per role'!F17 -> 46000 | F16: =D16*12 -> 552000 | G16: =(F16*70%)*10% -> 38640 | H16: =F16/12 -> 46000 | I16: =IF(_xlfn.XLOOKUP(B16, 'Bonus suggestion table'!$B$3:$B$7, 'Bonus suggestion table'!$D$3:$D$7, 0, 0) * F16 = 0, 0, _xlfn.XLOOKUP(B16, 'Bonus suggestion table'!$B$3:$B$7, 'Bonus suggestion table'!$D$3:$D$7, 0, 0) * F16) -> 0 | O16: 0 | P16: =(6/1000)*((F16*90%)*3) -> 8942.4 | Q16: =1%*(I16+F16) -> 5520 | R16: =1%*(I16+F16) -> 5520 | S16: =SUM(F16:R16) -> 656622.4
S17: =SUM(S2:S16) -> 1.6612915e+08

Sheet Bonus suggestion table
B2: Grade | C2: Role | D2: % of Bonus on Base Pay (Gross)
B3: A1 | C3: Managing Director | D3: 0.3
B4: B1 | C4: Director of Programs | D4: 0.2
B5: G1 | C5: Manager | D5: 0.15
B6: H1 | C6: Associate | D6: 0.1
B7: I1 | C7: Technician & Driver | D7: 0.1
