Workbook

Sheet Summary
A1: IIH STAFF SUMMARY
A3: Population Counts
A4: Metric | B4: Count
A5: Total Core Staff | B5: =SUMPRODUCT(--(Revised!G2:G999<>""),--ISERROR(SEARCH("intern",LOWER(Revised!A2:A999&" "&Revised!C2:C999))),--ISERROR(SEARCH("corper",LOWER(Revised!A2:A999&" "&Revised!C2:C999))),--ISERROR(SEARCH("corp",LOWER(Revised!A2:A999&" "&Revised!C2:C999)))) -> 26
A6: Total Interns | B6: =SUMPRODUCT(--(Revised!G2:G999<>""),--ISNUMBER(SEARCH("intern",LOWER(Revised!A2:A999&" "&Revised!C2:C999))))+2 -> 2
A7: Total Corpers | B7: =SUMPRODUCT(--(Revised!G2:G999<>""),--(ISNUMBER(SEARCH("corper",LOWER(Revised!A2:A999&" "&Revised!C2:C999)))+ISNUMBER(SEARCH("corp",LOWER(Revised!A2:A999&" "&Revised!C2:C999)))>0),--ISERROR(SEARCH("intern",LOWER(Revised!A2:A999&" "&Revised!C2:C999))))+6 -> 6
A8: Total People (All) | B8: =B5+B6+B7 -> 34
A10: Gender Distribution
A11: Group | B11: Male | C11: Female | D11: Unknown
A12: Core Staff | B12: =SUMPRODUCT(--(Revised!G2:G999<>""),--(LEFT(UPPER(Revised!H2:H999),1)="M"),--ISERROR(SEARCH("intern",LOWER(Revised!A2:A999&" "&Revised!C2:C999))),--ISERROR(SEARCH("corper",LOWER(Revised!A2:A999&" "&Revised!C2:C999))),--ISERROR(SEARCH("corp",LOWER(Revised!A2:A999&" "&Revised!C2:C999)))) -> 12 | C12: =SUMPRODUCT(--(Revised!G2:G999<>""),--(LEFT(UPPER(Revised!H2:H999),1)="F"),--ISERROR(SEARCH("intern",LOWER(Revised!A2:A999&" "&Revised!C2:C999))),--ISERROR(SEARCH("corper",LOWER(Revised!A2:A999&" "&Revised!C2:C999))),--ISERROR(SEARCH("corp",LOWER(Revised!A2:A999&" "&Revised!C2:C999)))) -> 8 | D12: =B5-B12-C12 -> 6
A13: All (Core+Interns+Corpers) | B13: =SUMPRODUCT(--(Revised!G2:G999<>""),--(LEFT(UPPER(Revised!H2:H999),1)="M")) -> 12 | C13: =SUMPRODUCT(--(Revised!G2:G999<>""),--(LEFT(UPPER(Revised!H2:H999),1)="F")) -> 8 | D13: =B8-B13-C13 -> 14
A16: Origin Distribution (Kwara vs Non-Kwara)
A17: Group | B17: Kwara | C17: Non-Kwara | D17: Unknown | E17: Kwara % | F17: Non-Kwara %
A18: Core Staff | B18: =SUMPRODUCT(--(Revised!G2:G999<>""),--ISNUMBER(SEARCH("kwara",LOWER(Revised!I2:I999))),--ISERROR(SEARCH("non",LOWER(Revised!I2:I999))),--ISERROR(SEARCH("intern",LOWER(Revised!A2:A999&" "&Revised!C2:C999))),--ISERROR(SEARCH("corper",LOWER(Revised!A2:A999&" "&Revised!C2:C999))),--ISERROR(SEARCH("corp",LOWER(Revised!A2:A999&" "&Revised!C2:C999)))) -> 15 | C18: =SUMPRODUCT(--(Revised!G2:G999<>""),--ISNUMBER(SEARCH("non",LOWER(Revised!I2:I999))),--ISNUMBER(SEARCH("kwara",LOWER(Revised!I2:I999))),--ISERROR(SEARCH("intern",LOWER(Revised!A2:A999&" "&Revised!C2:C999))),--ISERROR(SEARCH("corper",LOWER(Revised!A2:A999&" "&Revised!C2:C999))),--ISERROR(SEARCH("corp",LOWER(Revised!A2:A999&" "&Revised!C2:C999)))) -> 3 | D18: =B5-B18-C18 -> 8 | E18: =IF((B18+C18)=0,0,B18/(B18+C18)*100) -> 83.333333 | F18: =IF((B18+C18)=0,0,C18/(B18+C18)*100) -> 16.666667
A19: All (Core+Interns+Corpers) | B19: =SUMPRODUCT(--(Revised!G2:G999<>""),--ISNUMBER(SEARCH("kwara",LOWER(Revised!I2:I999))),--ISERROR(SEARCH("non",LOWER(Revised!I2:I999)))) -> 15 | C19: =SUMPRODUCT(--(Revised!G2:G999<>""),--ISNUMBER(SEARCH("non",LOWER(Revised!I2:I999))),--ISNUMBER(SEARCH("kwara",LOWER(Revised!I2:I999)))) -> 3 | D19: =B8-B19-C19 -> 16 | E19: =IF((B19+C19)=0,0,B19/(B19+C19)*100) -> 83.333333 | F19: =IF((B19+C19)=0,0,C19/(B19+C19)*100) -> 16.666667
A22: Notes
A23: 1) Kwara/Non-Kwara percentages requested are shown for Core Staff and for All population.
A24: Quota Planning (70% Kwara target)
A25: Core vacancies (to be filled) | B25: =SUMPRODUCT(--(LOWER(Revised!E2:E999)="yes"),--ISERROR(SEARCH("intern",LOWER(Revised!A2:A999&" "&Revised!C2:C999))),--ISERROR(SEARCH("corper",LOWER(Revised!A2:A999&" "&Revised!C2:C999))),--ISERROR(SEARCH("corp",LOWER(Revised!A2:A999&" "&Revised!C2:C999)))) -> 5
A26: Core staff with unknown origin (TBD) | B26: =D18 -> 8
A27: Total unresolved origin slots (vacancies + TBD) | B27: =B25+B26 -> 13
A28: Minimum additional Kwara needed across unresolved slots | B28: =MAX(0,ROUNDUP(0.7*(B5+B25),0)-B18) -> 7
A29: Proposed origin spread for unresolved slots (Kwara / Non-Kwara) | B29: =B28 -> 7 | C29: =MAX(0,B27-B28) -> 6 | D29: (Target: >=70% Kwara)
A30: Quota status after proposed spread | B30: =IF((B5+B25)=0,0,(B18+B29)/(B5+B25)*100) -> 70.967742

Sheet Revised
A1: IIH Role | B1: Proposed Role | C1: Proposed Grade | D1: Important to have | E1: Vacant | F1: Function | G1: Name | H1: Gender | I1: Origin | J1: LGA | K1: Why this Grade is Appropriate (Justification) | L1: Key “Descriptor Fit” Keywords | M1: Required Experience (Extracted from JD)
A2: Managing Director | B2: Hub Director | C2: 1b | D2: Yes | E2: No | G2: Temi Kolawole | H2: M | I2: Kwara | J2: Irepodun | K2: Overall accountable head of IIH with enterprise-level leadership, strategic direction, results ownership and external influence. | L2: Enterprise accountability; strategic influence; resource ownership; executive leadership | M2: Minimum 10 years senior leadership experience in innovation/tech/development sector.
A3: Director of Programs | B3: Head of Programs | C3: 3B | D3: Yes | E3: No | F3: Programs | G3: Zumah Yahaya | H3: F | I3: Kwara | K3: Functional lead accountable for programme delivery outcomes, planning, governance and performance results across the portfolio. | L3: Functional accountability; operational planning; delivery leadership; stakeholder influence | M3: Minimum 8 years program management experience (innovation/education preferred).
A4: Director of Operations | B4: Assistant Director of Operations | C4: 3B | D4: Yes | E4: Yes | F4: Operations | G4: To be filled | K4: Functional lead accountable for operational execution, service outcomes, controls, and process efficiency across IIH operations. | L4: Cross-functional execution; operational excellence; performance accountability | M4: Minimum 8 years operations management experience; multi-function oversight.
A5: Project Manager | B5: Project Manager | C5: 4A | D5: Yes | E5: Yes | F5: MD's Office | G5: To be filled | K5: High autonomy role that drives planning/execution of strategic priorities, coordinates multi-stakeholder workstreams and supports exec delivery. | L5: Independent execution; project ownership; influence without authority; complexity handling | M5: Minimum 5 years executive support + project management experience.
A6: IT Manager | C6: 4B | D6: Yes | E6: No | F6: Operations | G6: Nasiru Muhammed | H6: M | I6: Kwara | K6: Owns IT service delivery, manages support and vendors, ensures uptime/service performance and improvement of IT processes. | L6: Operational ownership; process improvement; team/vendor oversight | M6: 5–7 years IT management experience.
A7: Program Manager | B7: Program Delivery Manager | C7: 4B | D7: Yes | E7: No | F7: Programs | G7: Adebola Oladipo | H7: M | I7: Kwara | K7: Owns execution of programmes, timelines, partners and deliverables; manages resources and delivery risks. | L7: Delivery accountability; planning; cross-stakeholder coordination | M7: Minimum 5 years program management experience.
A8: Community Manager | B8: Community Officer | C8: 5C | D8: No | E8: Yes | F8: Programs | G8: To be filled | K8: Responsible for community activation strategy execution, engagement performance, and consistent delivery of community experience. | L8: Execution leadership; outcome accountability; operational influence | M8: Minimum 5 years community management/coworking experience.
A9: Content Lead | B9: Content & Communications Specialist | C9: 5B | D9: Yes | E9: No | F9: Programs | G9: Abdulraman Yusuf | H9: M | I9: Kwara | K9: Specialist lead role responsible for content strategy execution, quality assurance and brand consistency; guides execution without being a full manager. | L9: Specialist leadership; independent delivery; influencing others | M9: Minimum 5 years content creation & content management experience.
A10: Social Media Manager | B10: Digital Engagement Specialist | C10: 6A | D10: Yes | E10: No | F10: Programs | G10: Amidat Olalere | H10: F | I10: Kwara | K10: Owns social engagement performance, content execution, campaigns and analytics; operates as a specialist with high accountability. | L10: Independent specialist; performance outputs; brand impact | M10: 3–5 years social media management experience.
A11: Finance Associate | B11: Finance & Compliance Officer | C11: 5C | D11: Yes | E11: No | F11: Adminstration | G11: Khadijat Bello | H11: F | I11: Kwara | K11: Executes defined finance processes, reporting and reconciliations under supervision; applies professional knowledge to routine objectives. | L11: Professional execution; supervised; standard procedures | M11: Minimum 5 years accounting/finance experience.
A12: Program Associate | B12: Program Officer | C12: 5C | D12: Yes | E12: Yes | F12: Programs | G12: To be filled | K12: Supports programme delivery administration, documentation and tracking; defined scope and supervised work. | L12: Execution support; routine complexity; process-based delivery | M12: 2–3 years program support/coordination experience.
A13: Admin Associate | B13: Admin Officer | C13: 5C | D13: Yes | E13: No | F13: Adminstration | G13: Maureen Okey | H13: F | I13: Non-Kwara | K13: Coordinates admin processes, documentation, scheduling, and support services under set procedures and guidance. | L13: Administrative/professional support; predictable scope | M13: 3–5 years administrative experience.
A14: HR Associate | B14: HR Officer | C14: 5C | D14: Yes | E14: No | F14: Adminstration | G14: Sinachi Onuchukwu | H14: F | I14: Non-Kwara | K14: Supports HR operations and processes; manages defined tasks with guidance and structured procedures. | L14: HR process delivery; functional support role | M14: 3–5 years HR experience.
A15: Facility Associate | B15: Facilities Officer | C15: 5C | D15: Yes | E15: No | F15: Operations | G15: Kamil Ahmed | H15: M | I15: Kwara | K15: Supports facility coordination, vendors, and service tickets; applies standard procedures with supervised decision-making. | L15: Operational support; procedure-driven work | M15: 3–5 years facility management experience.
A16: Graphic & Multimedia Designer | B16: Graphic & Multimedia Specialist | C16: 5B | D16: Yes | E16: No | F16: Programs | G16: Damilare Oloyede | H16: M | I16: Kwara | K16: Produces design outputs to briefs and standards, delivering professional work products with defined requirements and supervision. | L16: Professional specialist output; defined briefs; quality execution | M16: 3–5 years graphic design experience.
A17: IT Associate | B17: IT Support Analyst | C17: 5B | D17: Yes | E17: No | F17: Operations | G17: Henry Mgbechi | H17: M | I17: Non-Kwara | K17: Support role with technical troubleshooting responsibilities; higher technical depth and complexity than general support service roles. | L17: Technical troubleshooting; service delivery; defined standards | M17: 1–2 years customer service/hospitality experience.
A18: IT Associate | B18: IT Support Analyst | C18: 5B | D18: Yes | E18: No | F18: Operations | G18: Temilola Akande | H18: F | I18: Kwara | K18: Support role with technical troubleshooting responsibilities; higher technical depth and complexity than general support service roles. | L18: Technical troubleshooting; service delivery; defined standards | M18: 1–2 years customer service/hospitality experience.
A19: IT Support | B19: IT Assistant | C19: 6B | D19: Yes | E19: Yes | G19: To be filled
A20: Facility Support | B20: Facilities Assistant | C20: 6B | D20: Yes | E20: No | F20: Operations | G20: Sulyman Yusuf Alao | H20: M | I20: Kwara | K20: Provides day-to-day facility services support; executes practical support tasks under supervision. | L20: Support services; routine delivery; supervision required | M20: 1–2 years facility/maintenance experience.
A21: Facility Assistant | B21: Facility Assistant | C21: 6B | D21: Yes | E21: No | F21: Operations | G21: Benjamin Okolie | I21: Delta | J21: Additional facility assistant absorbed from existing corper pool; no incremental payroll planned. | K21: Provides day-to-day facility services support; executes practical support tasks under supervision. | L21: Support services; routine delivery; supervision required
A22: Facility Support | B22: Facility Assistant | C22: 6B | D22: Yes | E22: No | F22: Operations | G22: Ahmed Habeeb | H22: M | I22: Kwara | K22: Provides day-to-day facility services support; executes practical support tasks under supervision. | L22: Support services; routine delivery; supervision required | M22: 1–2 years facility/maintenance experience.
A23: Facility Support | B23: Facility Assistant | C23: 6B | D23: Yes | E23: No | F23: Operations | G23: Jimoh Faruq | H23: M | I23: Kwara | K23: Provides day-to-day facility services support; executes practical support tasks under supervision. | L23: Support services; routine delivery; supervision required | M23: 1–2 years facility/maintenance experience.
A24: Front Desk Support | B24: Front Desk Officer | C24: 6B | D24: Yes | E24: No | F24: Adminstration | G24: Muinat Bello | H24: F | I24: Kwara | K24: Customer-facing support role with structured service delivery and routine coordination responsibilities. | L24: Front-of-house support; routine service tasks | M24: 1–2 years reception/customer service experience.
A25: Hospitality Assistant | B25: Hospitality Assistant | C25: 6B | D25: Yes | E25: No | F25: Adminstration | G25: Joan Oware | H25: F | I25: Edo | J25: Absorbed from existing corper pool; supports hospitality and event execution. | K25: Provides hospitality and workplace support, event/basic service execution under supervision and standard procedures. | L25: Service delivery; routine tasks; supervised | M25: 1–2 years hospitality/service experience.
A26: Driver | C26: 6C | D26: Yes | E26: No | F26: Adminstration | G26: Kayode Olaleye | H26: M | I26: Kwara | K26: Explicitly aligned to entry-level technical/support roles such as drivers within the IHS career framework. | L26: Entry support; service delivery role (driver track) | M26: 3–5 years professional driving experience.
A27: Driver | C27: 6C | D27: Yes | E27: No | F27: Adminstration | G27: Emmanuel Farayade | H27: M | I27: Oyo | K27: Explicitly aligned to entry-level technical/support roles such as drivers within the IHS career framework. | L27: Entry support; service delivery role (driver track) | M27: 3–5 years professional driving experience.
Q36: Grade 6
Q38: IT Support → 6B
Q39: Community Support → 6B
Q40: Facility Support → 6B
Q41: Front Desk → 6B
Q42: Hospitality Support → 6C
Q43: Driver → 6B

Sheet Managing Director
B1: Managing Director
B2: Dimension | C2: Objective | D2: Key Result Areas (KRAs)
B3: Enterprise Goals (Common) | C3: Deliver IIH mission outcomes and institutional credibility | D3: KR-E1, KR-E2, KR-E3 (common)
B4: Financial | C4: Ensure financial sustainability through diversified revenue and partnerships | D4: (1) Secure ₦X in grants/sponsorship/revenue (2) Maintain annual budget adherence within ±X% (3) Establish at least 2 sustainable revenue lines
B5: Operational Efficiency | C5: Strengthen governance rhythm and enterprise execution quality | D5: (1) Monthly leadership dashboard published on time (2) At least 95% strategic milestone delivery rate (3) Reduce critical escalations by X%
B6: Innovation & Learning | C6: Expand IIH relevance through new innovation programs | D6: (1) Launch at least 2 flagship initiatives in 2026 (2) Run quarterly improvement reviews and implement actions
B7: Customer Service | C7: Improve stakeholder confidence and user experience | D7: (1) Achieve target user satisfaction/NPS (2) Increase positive PR/stakeholder feedback by X%

Sheet Director of Programs
B1: Director of Programs
B2: Dimension | C2: Objective | D2: Key Result Areas (KRAs)
B3: Enterprise Goals (Common) | C3: Drive measurable ecosystem and program outcomes | D3: KR-E1, KR-E2, KR-E3 (common)
B4: Financial | C4: Improve program financial sustainability | D4: (1) Secure support/sponsorship for at least X programs (2) Reduce cost per participant/startup by X% without quality loss
B5: Operational Efficiency | C5: Deliver programs consistently and on schedule | D5: (1) At least 95% adherence to annual program calendar (2) 100% quarterly M&E reporting compliance
B6: Innovation & Learning | C6: Keep offerings relevant and future-facing | D6: (1) Refresh program design/curriculum at least 2 times yearly (2) Pilot at least 1 new high-impact program
B7: Customer Service | C7: Improve participant and partner experience | D7: (1) Participant satisfaction at or above X% (2) Program completion/retention rate at or above X%

Sheet Director of Operations
B1: Director of Operations
B2: Dimension | C2: Objective | D2: Key Result Areas (KRAs)
B3: Enterprise Goals (Common) | C3: Enable mission delivery through reliable operations | D3: KR-E1, KR-E2, KR-E3 (common)
B4: Financial | C4: Deliver cost discipline and value-for-money operations | D4: (1) Keep controllable opex within approved threshold (2) Achieve measurable procurement savings of X%
B5: Operational Efficiency | C5: Improve reliability and service quality | D5: (1) Achieve at least 95% SLA performance across core services (2) Facility uptime at or above X% (3) Vendor scorecard at or above X%
B6: Innovation & Learning | C6: Digitize and standardize operations | D6: (1) Implement at least 3 operations automation/process improvements (2) Reduce key process cycle times by X%
B7: Customer Service | C7: Improve internal and external service experience | D7: (1) Improve service satisfaction score to at least X% (2) Reduce complaint resolution time by X%

Sheet Project Manager
B1: Project Manager
B2: Dimension | C2: Objective | D2: Key Result Areas (KRAs)
B3: Enterprise Goals | C3: Drive governance and reporting discipline | D3: (1) QBR pack produced monthly with 100% timeliness (2) ≥95% action closure rate on MD/leadership actions
B4: Financial | C4: Improve project execution efficiency | D4: (1) Track project spend variance monthly (2) Reduce avoidable execution delays/cost overruns by X%
B5: Operational Efficiency | C5: Strengthen cross-functional coordination cadence | D5: (1) Meeting notes and action logs issued within 24 hours (2) Cross-team dependencies resolved within agreed SLAs
B6: Innovation & Learning | C6: Improve delivery systems and reporting quality | D6: (1) Implement at least 2 project governance/process upgrades (2) Standardize reporting templates across workstreams
B7: Customer Service | C7: Improve leadership and team service responsiveness | D7: (1) Executive stakeholder satisfaction at or above X% (2) Reduce turnaround time for critical requests by X%

Sheet IT Manager
B1: IT Manager
B2: Dimension | C2: Objective | D2: Key Result Areas (KRAs)
B3: Enterprise Goals | C3: Provide stable tech backbone for hub success | D3: (1) Maintain ≥99% uptime for core systems (2) Zero critical tech outages impacting programs
B4: Financial | C4: Optimize IT spend and vendor value | D4: (1) Keep IT spend within approved budget (2) Deliver X% savings through license/vendor optimization
B5: Operational Efficiency | C5: Improve IT support reliability and speed | D5: (1) Ticket SLA compliance at or above X% (2) Mean resolution time at or below target
B6: Innovation & Learning | C6: Modernize digital systems and controls | D6: (1) Deliver at least 2 priority IT improvements (2) Complete periodic security/compliance checks
B7: Customer Service | C7: Improve user technology experience | D7: (1) User satisfaction score at or above X% (2) Reduce repeat support issues by X%

Sheet Program Manager
B1: Program Manager
B2: Dimension | C2: Objective | D2: Key Result Areas (KRAs)
B3: Enterprise Goals | C3: Deliver high-performing cohorts & measurable outcomes | D3: (1) Achieve cohort outcomes targets (2) Produce monthly impact report
B4: Financial | C4: Manage program budgets efficiently | D4: (1) Keep program budget variance within ±X% (2) Improve cost effectiveness per cohort by X%
B5: Operational Efficiency | C5: Deliver programs on time and to standard | D5: (1) At least 95% activity-level schedule adherence (2) Timely issue/risk escalation and closure
B6: Innovation & Learning | C6: Improve program design through evidence | D6: (1) Implement at least 2 improvements based on participant/partner feedback
B7: Customer Service | C7: Improve participant and partner experience | D7: (1) Participant satisfaction at or above X% (2) Partner feedback score at or above X%

Sheet Community Manager
B1: Community Manager
B2: Dimension | C2: Objective | D2: Key Result Areas (KRAs)
B3: Enterprise Goals (Common) | C3: Grow and activate IIH community ecosystem | D3: (1) Increase active community participation by X% year-on-year
B4: Financial | C4: Support revenue and retention through community value | D4: (1) Improve paying member retention by X% (2) Support conversion pipeline from community activities
B5: Operational Efficiency | C5: Deliver consistent community operations | D5: (1) Execute planned community calendar at or above 95% adherence (2) Maintain accurate engagement reporting monthly
B6: Innovation & Learning | C6: Experiment with new engagement formats | D6: (1) Pilot at least 2 new engagement formats with documented outcomes
B7: Customer Service | C7: Improve member/community satisfaction | D7: (1) Achieve target community satisfaction score (2) Reduce response time to member queries by X%

Sheet Content Lead
B1: Content Lead
B2: Dimension | C2: Objective | D2: Key Result Areas (KRAs)
B3: Enterprise Goals | C3: Elevate IIH visibility and strategic messaging | D3: (1) Publish quarterly impact storytelling reports (2) Improve media/PR outcomes by X%
B4: Financial | C4: Support business development with content assets | D4: (1) Produce at least X sponsor/investor-ready content packs per quarter
B5: Operational Efficiency | C5: Improve content production consistency | D5: (1) Maintain content calendar adherence at or above 95% (2) Reduce turnaround time by X%
B6: Innovation & Learning | C6: Expand formats and quality standards | D6: (1) Introduce at least 2 new storytelling formats (2) Maintain quality review process compliance
B7: Customer Service | C7: Improve stakeholder communication quality | D7: (1) Stakeholder communication quality score at or above X%

Sheet Social Media Manager
B1: Social Media Manager
B2: Dimension | C2: Objective | D2: Key Result Areas (KRAs)
B3: Enterprise Goals | C3: Grow IIH digital footprint and brand relevance | D3: (1) Reach growth +X% (2) Engagement rate ≥X%
B4: Financial | C4: Support sponsorship visibility and campaign outcomes | D4: (1) Deliver campaign visibility commitments for at least X partners
B5: Operational Efficiency | C5: Ensure disciplined digital publishing operations | D5: (1) Weekly analytics reports delivered 100% on time (2) Posting cadence adherence at or above 95%
B6: Innovation & Learning | C6: Test and optimize channel performance | D6: (1) Run at least 2 structured experiments per quarter and apply learnings
B7: Customer Service | C7: Improve responsiveness and audience trust | D7: (1) Community response-time SLA met at or above X%

Sheet Finance Associate
B1: Finance Associate
B2: Dimension | C2: Objective | D2: Key Result Areas (KRAs)
B3: Enterprise Goals | C3: Ensure financial integrity supporting mission | D3: (1) 100% accurate monthly reports submitted on time
B4: Financial | C4: Strengthen controls and compliance | D4: (1) Zero preventable reconciliation breaks (2) Budget variance tracking completed monthly
B5: Operational Efficiency | C5: Improve finance process turnaround | D5: (1) Payment processing within agreed SLA (2) Payroll/input accuracy at 100%
B6: Innovation & Learning | C6: Improve tooling and reporting workflows | D6: (1) Implement at least 2 finance process improvements/automations
B7: Customer Service | C7: Improve service quality to staff/vendors | D7: (1) Internal finance service satisfaction at or above X%

Sheet Program Associate
B1: Program Associate
B2: Dimension | C2: Objective | D2: Key Result Areas (KRAs)
B3: Enterprise Goals (Common) | C3: Support smooth delivery of program operations | D3: (1) Program documentation and trackers maintained at 100% completeness
B4: Financial | C4: Support efficient use of program resources | D4: (1) Timely and accurate support for budget/input documentation
B5: Operational Efficiency | C5: Improve administrative reliability | D5: (1) Logistics/readiness checklist compliance at or above 95%
B6: Innovation & Learning | C6: Improve execution support methods | D6: (1) Implement at least 1 improvement to coordination workflow each quarter
B7: Customer Service | C7: Support positive participant experience | D7: (1) Resolve participant/admin requests within agreed SLA

Sheet Admin Associate
B1: Admin Associate
B2: Dimension | C2: Objective | D2: Key Result Areas (KRAs)
B3: Enterprise Goals | C3: Ensure hub admin stability | D3: (1) 95% SLA achievement for admin requests
B4: Financial | C4: Support administrative cost control | D4: (1) Track and report admin cost efficiency opportunities monthly
B5: Operational Efficiency | C5: Improve records, scheduling and coordination | D5: (1) Administrative cycle time reduced by X% (2) Documentation accuracy maintained at high standard
B6: Innovation & Learning | C6: Digitize and standardize admin operations | D6: (1) Maintain up-to-date digital registers/logs for key admin processes
B7: Customer Service | C7: Improve internal service satisfaction | D7: (1) Internal admin service satisfaction at or above X%

Sheet HR Associate
B1: HR Associate
B2: Dimension | C2: Objective | D2: Key Result Areas (KRAs)
B3: Enterprise Goals | C3: Enable people stability and culture | D3: (1) Hiring cycle delivery within X days
B4: Financial | C4: Improve HR process efficiency | D4: (1) Track recruitment/process cost efficiency and reduce avoidable delays
B5: Operational Efficiency | C5: Improve HR process compliance | D5: (1) Employee records completeness at 100% (2) Hiring/admin process SLA adherence at or above X%
B6: Innovation & Learning | C6: Strengthen HR systems and templates | D6: (1) Implement at least 2 HR process/document improvements
B7: Customer Service | C7: Improve employee HR service experience | D7: (1) Employee HR service satisfaction at or above X%

Sheet Facility Associate
B1: Facility Associate
B2: Dimension | C2: Objective | D2: Key Result Areas (KRAs)
B3: Enterprise Goals (Common) | C3: Support reliable facility operations and safety | D3: (1) Maintain safe, functional environment for staff/users
B4: Financial | C4: Improve facility cost efficiency | D4: (1) Track maintenance spend and reduce avoidable costs by X%
B5: Operational Efficiency | C5: Improve maintenance and service responsiveness | D5: (1) Work-order closure within SLA at or above X% (2) Preventive maintenance adherence at or above X%
B6: Innovation & Learning | C6: Improve maintenance planning and vendor coordination | D6: (1) Introduce and maintain preventive maintenance tracker and scorecards
B7: Customer Service | C7: Improve facility service experience | D7: (1) User complaints related to facilities reduced by X%

Sheet IT Associate
B1: IT Associate
B2: Dimension | C2: Objective | D2: Key Result Areas (KRAs)
B3: Enterprise Goals (Common) | C3: Provide dependable first-line technical support | D3: (1) Support continuity of digital operations with timely issue handling
B4: Financial | C4: Support efficient use of IT resources | D4: (1) Assist in inventory/license tracking with minimal losses/waste
B5: Operational Efficiency | C5: Improve support performance | D5: (1) Ticket handling SLA at or above X% (2) First-contact resolution improved by X%
B6: Innovation & Learning | C6: Build technical troubleshooting capability | D6: (1) Complete agreed technical upskilling milestones and apply to support tasks
B7: Customer Service | C7: Improve end-user support experience | D7: (1) End-user support satisfaction at or above X%

Sheet Graphic & Multimedia Designer
B1: Graphic & Multimedia Designer
B2: Dimension | C2: Objective | D2: Key Result Areas (KRAs)
B3: Enterprise Goals (Common) | C3: Produce high-quality visual outputs for IIH priorities | D3: (1) Deliver priority design assets aligned to program and brand goals
B4: Financial | C4: Improve value from media/design outputs | D4: (1) Reduce external design dependency cost by X% via in-house delivery
B5: Operational Efficiency | C5: Improve production workflow and predictability | D5: (1) Deliver approved briefs within agreed timelines at or above X%
B6: Innovation & Learning | C6: Expand design and multimedia capabilities | D6: (1) Introduce at least 2 improved visual formats/styles with measurable engagement lift
B7: Customer Service | C7: Improve stakeholder experience with design support | D7: (1) Internal stakeholder satisfaction with design support at or above X%

Sheet IT Support
B1: IT Support
B2: Dimension | C2: Objective | D2: Key Result Areas (KRAs)
B3: Enterprise Goals (Common) | C3: Maintain day-to-day IT service continuity | D3: (1) Ensure stable support coverage for core user needs
B4: Financial | C4: Support cost-conscious operations | D4: (1) Minimize repeat issues and avoidable replacement costs by X%
B5: Operational Efficiency | C5: Deliver responsive support service | D5: (1) Ticket response and resolution SLAs achieved at or above X%
B6: Innovation & Learning | C6: Improve troubleshooting and documentation quality | D6: (1) Maintain updated knowledge base for recurring issues
B7: Customer Service | C7: Improve user confidence in support services | D7: (1) User support satisfaction at or above X%

Sheet Facility Support
B1: Facility Support
B2: Dimension | C2: Objective | D2: Key Result Areas (KRAs)
B3: Enterprise Goals (Common) | C3: Support day-to-day facility readiness and hygiene | D3: (1) Maintain operational readiness of assigned facility areas
B4: Financial | C4: Support efficient consumables and service usage | D4: (1) Reduce avoidable wastage in consumables/utilities by X%
B5: Operational Efficiency | C5: Deliver routine support tasks consistently | D5: (1) Assigned task completion rate at or above 95%
B6: Innovation & Learning | C6: Improve practical work methods and safety practice | D6: (1) Follow and improve standard operating procedures with supervisor guidance
B7: Customer Service | C7: Improve facility user experience | D7: (1) Facility-related complaints in assigned areas reduced by X%

Sheet Front Desk Support
B1: Front Desk Support
B2: Dimension | C2: Objective | D2: Key Result Areas (KRAs)
B3: Enterprise Goals (Common) | C3: Provide professional first-point engagement for IIH | D3: (1) Maintain high-quality reception and visitor handling standards
B4: Financial | C4: Support accurate records for service utilization | D4: (1) Maintain complete and accurate front-desk logs/reporting
B5: Operational Efficiency | C5: Improve front-desk process consistency | D5: (1) Visitor check-in/check-out SLA at or above X%
B6: Innovation & Learning | C6: Improve service and communication practices | D6: (1) Implement agreed service-improvement actions each quarter
B7: Customer Service | C7: Improve visitor and stakeholder experience | D7: (1) Front-desk satisfaction score at or above X%

Sheet Hospitality Support
B1: Hospitality Support
B2: Dimension | C2: Objective | D2: Key Result Areas (KRAs)
B3: Enterprise Goals (Common) | C3: Deliver consistent hospitality support for events and daily operations | D3: (1) Ensure readiness and service standards for all assigned sessions/events
B4: Financial | C4: Support cost-effective hospitality operations | D4: (1) Minimize avoidable hospitality waste by X%
B5: Operational Efficiency | C5: Improve service execution consistency | D5: (1) Task completion and setup readiness at or above 95%
B6: Innovation & Learning | C6: Improve service quality practices | D6: (1) Adopt and maintain service SOP/checklist standards
B7: Customer Service | C7: Improve participant/guest service experience | D7: (1) Hospitality service satisfaction at or above X%

Sheet Driver
B1: Driver
B2: Dimension | C2: Objective | D2: Key Result Areas (KRAs)
B3: Enterprise Goals (Common) | C3: Provide safe and reliable transport support | D3: (1) Maintain punctual and incident-free transport operations
B4: Financial | C4: Support transport cost discipline | D4: (1) Improve route/fuel efficiency by X% while maintaining service quality
B5: Operational Efficiency | C5: Improve transport planning and compliance | D5: (1) On-time trip completion at or above X% (2) Vehicle logbook and maintenance compliance at 100%
B6: Innovation & Learning | C6: Improve safety and service professionalism | D6: (1) Complete required safety/compliance refreshers and apply standards consistently
B7: Customer Service | C7: Improve transport service experience | D7: (1) Internal customer transport satisfaction at or above X%

Sheet Sheet1
D2: Excellent. We’ll do this properly and build a complete, board-ready grading architecture for IIH using:
D4: Grades 1–6
D6: Sub-bands A / B / C
D8: Promotion logic
D10: Salary band logic (no figures)
D12: Mapping current roles
D14: Governance guardrails
D16: This will be clean, scalable, and defensible.
D20: PART 1 — FINAL IIH GRADING ARCHITECTURE
D22: Direction of Scale
D24: Grade 1A = Most senior
D26: Grade 6C = Entry level
... D292: Tell me which direction you want next.
