Workbook

Sheet Notes on Changes
B2: S/N | C2: Item | D2: Previously | E2: Updated | F2: Adjustment | G2: Notes/Remarks | I2: Rational
B3: 1 | C3: 13th Month | D3: 12263000 | E3: 9396240 | F3: =E3/D3-1 -> -0.23377314 | G3: Now 10% of Annual Basic Salary vs. 1 month Gross Pay. | I3: We benchmarked practices among similar-sized startups and assessed what could be sustain financially.
B4: =B3+1 -> 2 | C4: Annual Bonus | D4: 30270000 | E4: 0 | F4: -100% | G4: Removed, given the startup phase of the organization. | I4: Given the startup phase, the organization needs to conserve funds and ensure financial stability first. We felt it was prudent to suspend the bonus until the IIH is more established.
B5: =B4+1 -> 3 | C5: Airtime | D5: 840000 | E5: 1866000 | F5: =E5/D5-1 -> 1.2214286 | G5: Combined Airtime & Data into one line item. | I5: Adopted IHS approach
B6: =B5+1 -> 4 | C6: Mobile Data Plan | D6: 2040000 | E6: 0 | F6: -100% | G6: Eliminated; merged into Airtime above.
B7: =B6+1 -> 5 | C7: Total Cafeteria Subsidy | D7: 5760000 | E7: 4680000 | F7: =E7/D7-1 -> -0.1875 | G7: Standardized to 1,200/day per employee. | I7: This figure ensures that all employees still receive a reasonable meal subsidy.
B8: =B7+1 -> 6 | C8: ITF Cost | D8: 1785420 | E8: 1530244.8 | F8: =E8/D8-1 -> -0.14292167 | G8: Adjusted to reflect 1% of payroll cost. | I8: Yes, the revised figures reflect 1% of the current payroll costs, which aligns with statutory obligations
B9: =B8+1 -> 7 | C9: NSITF (ECS) | D9: 1785420 | E9: 1530244.8 | F9: =E9/D9-1 -> -0.14292167 | G9: Adjusted to reflect 1% of payroll cost.
B10: =B9+1 -> 8 | C10: Employer Cost | D10: 2.3501734e+08 | E10: ='Month on Month HC Cost'!O19 -> 1.462322e+08 | F10: =E10/D10-1 -> -0.37778122 | G10: Headcount phased in over 12 months rather than all at once. | I10: The largest driver is that we’re no longer budgeting for all employees from the start of the year. We phased in new hires throughout the year, which reduces the total annual payroll and associated costs.

Sheet Month on Month HC Cost
E1: Employer Cost - aligned with the Headcount Phasing
A2: S/N | B2: Grade | C2: Jan | D2: Feb | E2: Mar | F2: Apr | G2: May | H2: Jun | I2: Jul | J2: Aug | K2: Sep | L2: Oct | M2: Nov | N2: Dec | O2: Total Cost for the year 2025
A3: 1 | B3: Managing Director | C3: =(_xlfn.XLOOKUP(B3,'Annual Employer Cost per Grade'!$C$2:$C$17,'Annual Employer Cost per Grade'!$U$2:$U$17,0,0))*(INDEX('Headcount Phasing'!$B$3:$M$18,MATCH(B3,'Headcount Phasing'!$A$3:$A$18,0),MATCH($C$2,'Headcount Phasing'!$B$2:$M$2,0))) -> 0 | D3: =(_xlfn.XLOOKUP(B3,'Annual Employer Cost per Grade'!$C$2:$C$17,'Annual Employer Cost per Grade'!$U$2:$U$17,0,0))*(INDEX('Headcount Phasing'!$B$3:$M$18,MATCH(B3,'Headcount Phasing'!$A$3:$A$18,0),MATCH($D$2,'Headcount Phasing'!$B$2:$M$2,0))) -> 0 | E3: =(_xlfn.XLOOKUP(B3,'Annual Employer Cost per Grade'!$C$2:$C$17,'Annual Employer Cost per Grade'!$U$2:$U$17,0,0))*(INDEX('Headcount Phasing'!$B$3:$M$18,MATCH(B3,'Headcount Phasing'!$A$3:$A$18,0),MATCH($E$2,'Headcount Phasing'!$B$2:$M$2,0))) -> 6187666.7 | F3: =(_xlfn.XLOOKUP(B3,'Annual Employer Cost per Grade'!$C$2:$C$17,'Annual Employer Cost per Grade'!$U$2:$U$17,0,0))*(INDEX('Headcount Phasing'!$B$3:$M$18,MATCH(B3,'Headcount Phasing'!$A$3:$A$18,0),MATCH($F$2,'Headcount Phasing'!$B$2:$M$2,0))) -> 6187666.7 | G3: =(_xlfn.XLOOKUP(B3,'Annual Employer Cost per Grade'!$C$2:$C$17,'Annual Employer Cost per Grade'!$U$2:$U$17,0,0))*(INDEX('Headcount Phasing'!$B$3:$M$18,MATCH(B3,'Headcount Phasing'!$A$3:$A$18,0),MATCH($G$2,'Headcount Phasing'!$B$2:$M$2,0))) -> 6187666.7 | H3: =(_xlfn.XLOOKUP(B3,'Annual Employer Cost per Grade'!$C$2:$C$17,'Annual Employer Cost per Grade'!$U$2:$U$17,0,0))*(INDEX('Headcount Phasing'!$B$3:$M$18,MATCH(B3,'Headcount Phasing'!$A$3:$A$18,0),MATCH($H$2,'Headcount Phasing'!$B$2:$M$2,0))) -> 6187666.7 | I3: =(_xlfn.XLOOKUP(B3,'Annual Employer Cost per Grade'!$C$2:$C$17,'Annual Employer Cost per Grade'!$U$2:$U$17,0,0))*(INDEX('Headcount Phasing'!$B$3:$M$18,MATCH(B3,'Headcount Phasing'!$A$3:$A$18,0),MATCH($I$2,'Headcount Phasing'!$B$2:$M$2,0))) -> 6187666.7 | J3: =(_xlfn.XLOOKUP(B3,'Annual Employer Cost per Grade'!$C$2:$C$17,'Annual Employer Cost per Grade'!$U$2:$U$17,0,0))*(INDEX('Headcount Phasing'!$B$3:$M$18,MATCH(B3,'Headcount Phasing'!$A$3:$A$18,0),MATCH($J$2,'Headcount Phasing'!$B$2:$M$2,0))) -> 6187666.7 | K3: =(_xlfn.XLOOKUP(B3,'Annual Employer Cost per Grade'!$C$2:$C$17,'Annual Employer Cost per Grade'!$U$2:$U$17,0,0))*(INDEX('Headcount Phasing'!$B$3:$M$18,MATCH(B3,'Headcount Phasing'!$A$3:$A$18,0),MATCH($K$2,'Headcount Phasing'!$B$2:$M$2,0))) -> 6187666.7 | L3: =(_xlfn.XLOOKUP(B3,'Annual Employer Cost per Grade'!$C$2:$C$17,'Annual Employer Cost per Grade'!$U$2:$U$17,0,0))*(INDEX('Headcount Phasing'!$B$3:$M$18,MATCH(B3,'Headcount Phasing'!$A$3:$A$18,0),MATCH($L$2,'Headcount Phasing'!$B$2:$M$2,0))) -> 6187666.7 | M3: =(_xlfn.XLOOKUP(B3,'Annual Employer Cost per Grade'!$C$2:$C$17,'Annual Employer Cost per Grade'!$U$2:$U$17,0,0))*(INDEX('Headcount Phasing'!$B$3:$M$18,MATCH(B3,'Headcount Phasing'!$A$3:$A$18,0),MATCH($M$2,'Headcount Phasing'!$B$2:$M$2,0))) -> 6187666.7 | N3: =(_xlfn.XLOOKUP(B3,'Annual Employer Cost per Grade'!$C$2:$C$17,'Annual Employer Cost per Grade'!$U$2:$U$17,0,0))*(INDEX('Headcount Phasing'!$B$3:$M$18,MATCH(B3,'Headcount Phasing'!$A$3:$A$18,0),MATCH($N$2,'Headcount Phasing'!$B$2:$M$2,0))) -> 6187666.7 | O3: =SUM(C3:N3) -> 61876667
A4: =A3+1 -> 2 | B4: Director of Programs | C4: =(_xlfn.XLOOKUP(B4,'Annual Employer Cost per Grade'!$C$2:$C$17,'Annual Employer Cost per Grade'!$U$2:$U$17,0,0))*(INDEX('Headcount Phasing'!$B$3:$M$18,MATCH(B4,'Headcount Phasing'!$A$3:$A$18,0),MATCH($C$2,'Headcount Phasing'!$B$2:$M$2,0))) -> 0 | D4: =(_xlfn.XLOOKUP(B4,'Annual Employer Cost per Grade'!$C$2:$C$17,'Annual Employer Cost per Grade'!$U$2:$U$17,0,0))*(INDEX('Headcount Phasing'!$B$3:$M$18,MATCH(B4,'Headcount Phasing'!$A$3:$A$18,0),MATCH($D$2,'Headcount Phasing'!$B$2:$M$2,0))) -> 0 | E4: =(_xlfn.XLOOKUP(B4,'Annual Employer Cost per Grade'!$C$2:$C$17,'Annual Employer Cost per Grade'!$U$2:$U$17,0,0))*(INDEX('Headcount Phasing'!$B$3:$M$18,MATCH(B4,'Headcount Phasing'!$A$3:$A$18,0),MATCH($E$2,'Headcount Phasing'!$B$2:$M$2,0))) -> 0 | F4: =(_xlfn.XLOOKUP(B4,'Annual Employer Cost per Grade'!$C$2:$C$17,'Annual Employer Cost per Grade'!$U$2:$U$17,0,0))*(INDEX('Headcount Phasing'!$B$3:$M$18,MATCH(B4,'Headcount Phasing'!$A$3:$A$18,0),MATCH($F$2,'Headcount Phasing'!$B$2:$M$2,0))) -> 3555487.9 | G4: =(_xlfn.XLOOKUP(B4,'Annual Employer Cost per Grade'!$C$2:$C$17,'Annual Employer Cost per Grade'!$U$2:$U$17,0,0))*(INDEX('Headcount Phasing'!$B$3:$M$18,MATCH(B4,'Headcount Phasing'!$A$3:$A$18,0),MATCH($G$2,'Headcount Phasing'!$B$2:$M$2,0))) -> 3555487.9 | H4: =(_xlfn.XLOOKUP(B4,'Annual Employer Cost per Grade'!$C$2:$C$17,'Annual Employer Cost per Grade'!$U$2:$U$17,0,0))*(INDEX('Headcount Phasing'!$B$3:$M$18,MATCH(B4,'Headcount Phasing'!$A$3:$A$18,0),MATCH($H$2,'Headcount Phasing'!$B$2:$M$2,0))) -> 3555487.9 | I4: =(_xlfn.XLOOKUP(B4,'Annual Employer Cost per Grade'!$C$2:$C$17,'Annual Employer Cost per Grade'!$U$2:$U$17,0,0))*(INDEX('Headcount Phasing'!$B$3:$M$18,MATCH(B4,'Headcount Phasing'!$A$3:$A$18,0),MATCH($I$2,'Headcount Phasing'!$B$2:$M$2,0))) -> 3555487.9 | J4: =(_xlfn.XLOOKUP(B4,'Annual Employer Cost per Grade'!$C$2:$C$17,'Annual Employer Cost per Grade'!$U$2:$U$17,0,0))*(INDEX('Headcount Phasing'!$B$3:$M$18,MATCH(B4,'Headcount Phasing'!$A$3:$A$18,0),MATCH($J$2,'Headcount Phasing'!$B$2:$M$2,0))) -> 3555487.9 | K4: =(_xlfn.XLOOKUP(B4,'Annual Employer Cost per Grade'!$C$2:$C$17,'Annual Employer Cost per Grade'!$U$2:$U$17,0,0))*(INDEX('Headcount Phasing'!$B$3:$M$18,MATCH(B4,'Headcount Phasing'!$A$3:$A$18,0),MATCH($K$2,'Headcount Phasing'!$B$2:$M$2,0))) -> 3555487.9 | L4: =(_xlfn.XLOOKUP(B4,'Annual Employer Cost per Grade'!$C$2:$C$17,'Annual Employer Cost per Grade'!$U$2:$U$17,0,0))*(INDEX('Headcount Phasing'!$B$3:$M$18,MATCH(B4,'Headcount Phasing'!$A$3:$A$18,0),MATCH($L$2,'Headcount Phasing'!$B$2:$M$2,0))) -> 3555487.9 | M4: =(_xlfn.XLOOKUP(B4,'Annual Employer Cost per Grade'!$C$2:$C$17,'Annual Employer Cost per Grade'!$U$2:$U$17,0,0))*(INDEX('Headcount Phasing'!$B$3:$M$18,MATCH(B4,'Headcount Phasing'!$A$3:$A$18,0),MATCH($M$2,'Headcount Phasing'!$B$2:$M$2,0))) -> 3555487.9 | N4: =(_xlfn.XLOOKUP(B4,'Annual Employer Cost per Grade'!$C$2:$C$17,'Annual Employer Cost per Grade'!$U$2:$U$17,0,0))*(INDEX('Headcount Phasing'!$B$3:$M$18,MATCH(B4,'Headcount Phasing'!$A$3:$A$18,0),MATCH($N$2,'Headcount Phasing'!$B$2:$M$2,0))) -> 3555487.9 | O4: =SUM(C4:N4) -> 31999391
A5: =A4+1 -> 3 | B5: IT Manager | C5: =(_xlfn.XLOOKUP(B5,'Annual Employer Cost per Grade'!$C$2:$C$17,'Annual Employer Cost per Grade'!$U$2:$U$17,0,0))*(INDEX('Headcount Phasing'!$B$3:$M$18,MATCH(B5,'Headcount Phasing'!$A$3:$A$18,0),MATCH($C$2,'Headcount Phasing'!$B$2:$M$2,0))) -> 0 | D5: =(_xlfn.XLOOKUP(B5,'Annual Employer Cost per Grade'!$C$2:$C$17,'Annual Employer Cost per Grade'!$U$2:$U$17,0,0))*(INDEX('Headcount Phasing'!$B$3:$M$18,MATCH(B5,'Headcount Phasing'!$A$3:$A$18,0),MATCH($D$2,'Headcount Phasing'!$B$2:$M$2,0))) -> 0 | E5: =(_xlfn.XLOOKUP(B5,'Annual Employer Cost per Grade'!$C$2:$C$17,'Annual Employer Cost per Grade'!$U$2:$U$17,0,0))*(INDEX('Headcount Phasing'!$B$3:$M$18,MATCH(B5,'Headcount Phasing'!$A$3:$A$18,0),MATCH($E$2,'Headcount Phasing'!$B$2:$M$2,0))) -> 0 | F5: =(_xlfn.XLOOKUP(B5,'Annual Employer Cost per Grade'!$C$2:$C$17,'Annual Employer Cost per Grade'!$U$2:$U$17,0,0))*(INDEX('Headcount Phasing'!$B$3:$M$18,MATCH(B5,'Headcount Phasing'!$A$3:$A$18,0),MATCH($F$2,'Headcount Phasing'!$B$2:$M$2,0))) -> 779030.5 | G5: =(_xlfn.XLOOKUP(B5,'Annual Employer Cost per Grade'!$C$2:$C$17,'Annual Employer Cost per Grade'!$U$2:$U$17,0,0))*(INDEX('Headcount Phasing'!$B$3:$M$18,MATCH(B5,'Headcount Phasing'!$A$3:$A$18,0),MATCH($G$2,'Headcount Phasing'!$B$2:$M$2,0))) -> 779030.5 | H5: =(_xlfn.XLOOKUP(B5,'Annual Employer Cost per Grade'!$C$2:$C$17,'Annual Employer Cost per Grade'!$U$2:$U$17,0,0))*(INDEX('Headcount Phasing'!$B$3:$M$18,MATCH(B5,'Headcount Phasing'!$A$3:$A$18,0),MATCH($H$2,'Headcount Phasing'!$B$2:$M$2,0))) -> 779030.5 | I5: =(_xlfn.XLOOKUP(B5,'Annual Employer Cost per Grade'!$C$2:$C$17,'Annual Employer Cost per Grade'!$U$2:$U$17,0,0))*(INDEX('Headcount Phasing'!$B$3:$M$18,MATCH(B5,'Headcount Phasing'!$A$3:$A$18,0),MATCH($I$2,'Headcount Phasing'!$B$2:$M$2,0))) -> 779030.5 | J5: =(_xlfn.XLOOKUP(B5,'Annual Employer Cost per Grade'!$C$2:$C$17,'Annual Employer Cost per Grade'!$U$2:$U$17,0,0))*(INDEX('Headcount Phasing'!$B$3:$M$18,MATCH(B5,'Headcount Phasing'!$A$3:$A$18,0),MATCH($J$2,'Headcount Phasing'!$B$2:$M$2,0))) -> 779030.5 | K5: =(_xlfn.XLOOKUP(B5,'Annual Employer Cost per Grade'!$C$2:$C$17,'Annual Employer Cost per Grade'!$U$2:$U$17,0,0))*(INDEX('Headcount Phasing'!$B$3:$M$18,MATCH(B5,'Headcount Phasing'!$A$3:$A$18,0),MATCH($K$2,'Headcount Phasing'!$B$2:$M$2,0))) -> 779030.5 | L5: =(_xlfn.XLOOKUP(B5,'Annual Employer Cost per Grade'!$C$2:$C$17,'Annual Employer Cost per Grade'!$U$2:$U$17,0,0))*(INDEX('Headcount Phasing'!$B$3:$M$18,MATCH(B5,'Headcount Phasing'!$A$3:$A$18,0),MATCH($L$2,'Headcount Phasing'!$B$2:$M$2,0))) -> 779030.5 | M5: =(_xlfn.XLOOKUP(B5,'Annual Employer Cost per Grade'!$C$2:$C$17,'Annual Employer Cost per Grade'!$U$2:$U$17,0,0))*(INDEX('Headcount Phasing'!$B$3:$M$18,MATCH(B5,'Headcount Phasing'!$A$3:$A$18,0),MATCH($M$2,'Headcount Phasing'!$B$2:$M$2,0))) -> 779030.5 | N5: =(_xlfn.XLOOKUP(B5,'Annual Employer Cost per Grade'!$C$2:$C$17,'Annual Employer Cost per Grade'!$U$2:$U$17,0,0))*(INDEX('Headcount Phasing'!$B$3:$M$18,MATCH(B5,'Headcount Phasing'!$A$3:$A$18,0),MATCH($N$2,'Headcount Phasing'!$B$2:$M$2,0))) -> 779030.5 | O5: =SUM(C5:N5) -> 7011274.5
A6: =A5+1 -> 4 | B6: Community Manager | C6: =(_xlfn.XLOOKUP(B6,'Annual Employer Cost per Grade'!$C$2:$C$17,'Annual Employer Cost per Grade'!$U$2:$U$17,0,0))*(INDEX('Headcount Phasing'!$B$3:$M$18,MATCH(B6,'Headcount Phasing'!$A$3:$A$18,0),MATCH($C$2,'Headcount Phasing'!$B$2:$M$2,0))) -> 0 | D6: =(_xlfn.XLOOKUP(B6,'Annual Employer Cost per Grade'!$C$2:$C$17,'Annual Employer Cost per Grade'!$U$2:$U$17,0,0))*(INDEX('Headcount Phasing'!$B$3:$M$18,MATCH(B6,'Headcount Phasing'!$A$3:$A$18,0),MATCH($D$2,'Headcount Phasing'!$B$2:$M$2,0))) -> 0 | E6: =(_xlfn.XLOOKUP(B6,'Annual Employer Cost per Grade'!$C$2:$C$17,'Annual Employer Cost per Grade'!$U$2:$U$17,0,0))*(INDEX('Headcount Phasing'!$B$3:$M$18,MATCH(B6,'Headcount Phasing'!$A$3:$A$18,0),MATCH($E$2,'Headcount Phasing'!$B$2:$M$2,0))) -> 0 | F6: =(_xlfn.XLOOKUP(B6,'Annual Employer Cost per Grade'!$C$2:$C$17,'Annual Employer Cost per Grade'!$U$2:$U$17,0,0))*(INDEX('Headcount Phasing'!$B$3:$M$18,MATCH(B6,'Headcount Phasing'!$A$3:$A$18,0),MATCH($F$2,'Headcount Phasing'!$B$2:$M$2,0))) -> 474470.5 | G6: =(_xlfn.XLOOKUP(B6,'Annual Employer Cost per Grade'!$C$2:$C$17,'Annual Employer Cost per Grade'!$U$2:$U$17,0,0))*(INDEX('Headcount Phasing'!$B$3:$M$18,MATCH(B6,'Headcount Phasing'!$A$3:$A$18,0),MATCH($G$2,'Headcount Phasing'!$B$2:$M$2,0))) -> 474470.5 | H6: =(_xlfn.XLOOKUP(B6,'Annual Employer Cost per Grade'!$C$2:$C$17,'Annual Employer Cost per Grade'!$U$2:$U$17,0,0))*(INDEX('Headcount Phasing'!$B$3:$M$18,MATCH(B6,'Headcount Phasing'!$A$3:$A$18,0),MATCH($H$2,'Headcount Phasing'!$B$2:$M$2,0))) -> 474470.5 | I6: =(_xlfn.XLOOKUP(B6,'Annual Employer Cost per Grade'!$C$2:$C$17,'Annual Employer Cost per Grade'!$U$2:$U$17,0,0))*(INDEX('Headcount Phasing'!$B$3:$M$18,MATCH(B6,'Headcount Phasing'!$A$3:$A$18,0),MATCH($I$2,'Headcount Phasing'!$B$2:$M$2,0))) -> 474470.5 | J6: =(_xlfn.XLOOKUP(B6,'Annual Employer Cost per Grade'!$C$2:$C$17,'Annual Employer Cost per Grade'!$U$2:$U$17,0,0))*(INDEX('Headcount Phasing'!$B$3:$M$18,MATCH(B6,'Headcount Phasing'!$A$3:$A$18,0),MATCH($J$2,'Headcount Phasing'!$B$2:$M$2,0))) -> 474470.5 | K6: =(_xlfn.XLOOKUP(B6,'Annual Employer Cost per Grade'!$C$2:$C$17,'Annual Employer Cost per Grade'!$U$2:$U$17,0,0))*(INDEX('Headcount Phasing'!$B$3:$M$18,MATCH(B6,'Headcount Phasing'!$A$3:$A$18,0),MATCH($K$2,'Headcount Phasing'!$B$2:$M$2,0))) -> 474470.5 | L6: =(_xlfn.XLOOKUP(B6,'Annual Employer Cost per Grade'!$C$2:$C$17,'Annual Employer Cost per Grade'!$U$2:$U$17,0,0))*(INDEX('Headcount Phasing'!$B$3:$M$18,MATCH(B6,'Headcount Phasing'!$A$3:$A$18,0),MATCH($L$2,'Headcount Phasing'!$B$2:$M$2,0))) -> 474470.5 | M6: =(_xlfn.XLOOKUP(B6,'Annual Employer Cost per Grade'!$C$2:$C$17,'Annual Employer Cost per Grade'!$U$2:$U$17,0,0))*(INDEX('Headcount Phasing'!$B$3:$M$18,MATCH(B6,'Headcount Phasing'!$A$3:$A$18,0),MATCH($M$2,'Headcount Phasing'!$B$2:$M$2,0))) -> 474470.5 | N6: =(_xlfn.XLOOKUP(B6,'Annual Employer Cost per Grade'!$C$2:$C$17,'Annual Employer Cost per Grade'!$U$2:$U$17,0,0))*(INDEX('Headcount Phasing'!$B$3:$M$18,MATCH(B6,'Headcount Phasing'!$A$3:$A$18,0),MATCH($N$2,'Headcount Phasing'!$B$2:$M$2,0))) -> 474470.5 | O6: =SUM(C6:N6) -> 4270234.5
A7: =A6+1 -> 5 | B7: Facility Associate | C7: =(_xlfn.XLOOKUP(B7,'Annual Employer Cost per Grade'!$C$2:$C$17,'Annual Employer Cost per Grade'!$U$2:$U$17,0,0))*(INDEX('Headcount Phasing'!$B$3:$M$18,MATCH(B7,'Headcount Phasing'!$A$3:$A$18,0),MATCH($C$2,'Headcount Phasing'!$B$2:$M$2,0))) -> 0 | D7: =(_xlfn.XLOOKUP(B7,'Annual Employer Cost per Grade'!$C$2:$C$17,'Annual Employer Cost per Grade'!$U$2:$U$17,0,0))*(INDEX('Headcount Phasing'!$B$3:$M$18,MATCH(B7,'Headcount Phasing'!$A$3:$A$18,0),MATCH($D$2,'Headcount Phasing'!$B$2:$M$2,0))) -> 0 | E7: =(_xlfn.XLOOKUP(B7,'Annual Employer Cost per Grade'!$C$2:$C$17,'Annual Employer Cost per Grade'!$U$2:$U$17,0,0))*(INDEX('Headcount Phasing'!$B$3:$M$18,MATCH(B7,'Headcount Phasing'!$A$3:$A$18,0),MATCH($E$2,'Headcount Phasing'!$B$2:$M$2,0))) -> 0 | F7: =(_xlfn.XLOOKUP(B7,'Annual Employer Cost per Grade'!$C$2:$C$17,'Annual Employer Cost per Grade'!$U$2:$U$17,0,0))*(INDEX('Headcount Phasing'!$B$3:$M$18,MATCH(B7,'Headcount Phasing'!$A$3:$A$18,0),MATCH($F$2,'Headcount Phasing'!$B$2:$M$2,0))) -> 458050.88 | G7: =(_xlfn.XLOOKUP(B7,'Annual Employer Cost per Grade'!$C$2:$C$17,'Annual Employer Cost per Grade'!$U$2:$U$17,0,0))*(INDEX('Headcount Phasing'!$B$3:$M$18,MATCH(B7,'Headcount Phasing'!$A$3:$A$18,0),MATCH($G$2,'Headcount Phasing'!$B$2:$M$2,0))) -> 458050.88 | H7: =(_xlfn.XLOOKUP(B7,'Annual Employer Cost per Grade'!$C$2:$C$17,'Annual Employer Cost per Grade'!$U$2:$U$17,0,0))*(INDEX('Headcount Phasing'!$B$3:$M$18,MATCH(B7,'Headcount Phasing'!$A$3:$A$18,0),MATCH($H$2,'Headcount Phasing'!$B$2:$M$2,0))) -> 458050.88 | I7: =(_xlfn.XLOOKUP(B7,'Annual Employer Cost per Grade'!$C$2:$C$17,'Annual Employer Cost per Grade'!$U$2:$U$17,0,0))*(INDEX('Headcount Phasing'!$B$3:$M$18,MATCH(B7,'Headcount Phasing'!$A$3:$A$18,0),MATCH($I$2,'Headcount Phasing'!$B$2:$M$2,0))) -> 458050.88 | J7: =(_xlfn.XLOOKUP(B7,'Annual Employer Cost per Grade'!$C$2:$C$17,'Annual Employer Cost per Grade'!$U$2:$U$17,0,0))*(INDEX('Headcount Phasing'!$B$3:$M$18,MATCH(B7,'Headcount Phasing'!$A$3:$A$18,0),MATCH($J$2,'Headcount Phasing'!$B$2:$M$2,0))) -> 458050.88 | K7: =(_xlfn.XLOOKUP(B7,'Annual Employer Cost per Grade'!$C$2:$C$17,'Annual Employer Cost per Grade'!$U$2:$U$17,0,0))*(INDEX('Headcount Phasing'!$B$3:$M$18,MATCH(B7,'Headcount Phasing'!$A$3:$A$18,0),MATCH($K$2,'Headcount Phasing'!$B$2:$M$2,0))) -> 458050.88 | L7: =(_xlfn.XLOOKUP(B7,'Annual Employer Cost per Grade'!$C$2:$C$17,'Annual Employer Cost per Grade'!$U$2:$U$17,0,0))*(INDEX('Headcount Phasing'!$B$3:$M$18,MATCH(B7,'Headcount Phasing'!$A$3:$A$18,0),MATCH($L$2,'Headcount Phasing'!$B$2:$M$2,0))) -> 458050.88 | M7: =(_xlfn.XLOOKUP(B7,'Annual Employer Cost per Grade'!$C$2:$C$17,'Annual Employer Cost per Grade'!$U$2:$U$17,0,0))*(INDEX('Headcount Phasing'!$B$3:$M$18,MATCH(B7,'Headcount Phasing'!$A$3:$A$18,0),MATCH($M$2,'Headcount Phasing'!$B$2:$M$2,0))) -> 458050.88 | N7: =(_xlfn.XLOOKUP(B7,'Annual Employer Cost per Grade'!$C$2:$C$17,'Annual Employer Cost per Grade'!$U$2:$U$17,0,0))*(INDEX('Headcount Phasing'!$B$3:$M$18,MATCH(B7,'Headcount Phasing'!$A$3:$A$18,0),MATCH($N$2,'Headcount Phasing'!$B$2:$M$2,0))) -> 458050.88 | O7: =SUM(C7:N7) -> 4122457.9
A8: =A7+1 -> 6 | B8: Front Desk Associate (x1) | C8: =(_xlfn.XLOOKUP(B8,'Annual Employer Cost per Grade'!$C$2:$C$17,'Annual Employer Cost per Grade'!$U$2:$U$17,0,0))*(INDEX('Headcount Phasing'!$B$3:$M$18,MATCH(B8,'Headcount Phasing'!$A$3:$A$18,0),MATCH($C$2,'Headcount Phasing'!$B$2:$M$2,0))) -> 0 | D8: =(_xlfn.XLOOKUP(B8,'Annual Employer Cost per Grade'!$C$2:$C$17,'Annual Employer Cost per Grade'!$U$2:$U$17,0,0))*(INDEX('Headcount Phasing'!$B$3:$M$18,MATCH(B8,'Headcount Phasing'!$A$3:$A$18,0),MATCH($D$2,'Headcount Phasing'!$B$2:$M$2,0))) -> 0 | E8: =(_xlfn.XLOOKUP(B8,'Annual Employer Cost per Grade'!$C$2:$C$17,'Annual Employer Cost per Grade'!$U$2:$U$17,0,0))*(INDEX('Headcount Phasing'!$B$3:$M$18,MATCH(B8,'Headcount Phasing'!$A$3:$A$18,0),MATCH($E$2,'Headcount Phasing'!$B$2:$M$2,0))) -> 0 | F8: =(_xlfn.XLOOKUP(B8,'Annual Employer Cost per Grade'!$C$2:$C$17,'Annual Employer Cost per Grade'!$U$2:$U$17,0,0))*(INDEX('Headcount Phasing'!$B$3:$M$18,MATCH(B8,'Headcount Phasing'!$A$3:$A$18,0),MATCH($F$2,'Headcount Phasing'!$B$2:$M$2,0))) -> 458050.88 | G8: =(_xlfn.XLOOKUP(B8,'Annual Employer Cost per Grade'!$C$2:$C$17,'Annual Employer Cost per Grade'!$U$2:$U$17,0,0))*(INDEX('Headcount Phasing'!$B$3:$M$18,MATCH(B8,'Headcount Phasing'!$A$3:$A$18,0),MATCH($G$2,'Headcount Phasing'!$B$2:$M$2,0))) -> 458050.88 | H8: =(_xlfn.XLOOKUP(B8,'Annual Employer Cost per Grade'!$C$2:$C$17,'Annual Employer Cost per Grade'!$U$2:$U$17,0,0))*(INDEX('Headcount Phasing'!$B$3:$M$18,MATCH(B8,'Headcount Phasing'!$A$3:$A$18,0),MATCH($H$2,'Headcount Phasing'!$B$2:$M$2,0))) -> 458050.88 | I8: =(_xlfn.XLOOKUP(B8,'Annual Employer Cost per Grade'!$C$2:$C$17,'Annual Employer Cost per Grade'!$U$2:$U$17,0,0))*(INDEX('Headcount Phasing'!$B$3:$M$18,MATCH(B8,'Headcount Phasing'!$A$3:$A$18,0),MATCH($I$2,'Headcount Phasing'!$B$2:$M$2,0))) -> 458050.88 | J8: =(_xlfn.XLOOKUP(B8,'Annual Employer Cost per Grade'!$C$2:$C$17,'Annual Employer Cost per Grade'!$U$2:$U$17,0,0))*(INDEX('Headcount Phasing'!$B$3:$M$18,MATCH(B8,'Headcount Phasing'!$A$3:$A$18,0),MATCH($J$2,'Headcount Phasing'!$B$2:$M$2,0))) -> 458050.88 | K8: =(_xlfn.XLOOKUP(B8,'Annual Employer Cost per Grade'!$C$2:$C$17,'Annual Employer Cost per Grade'!$U$2:$U$17,0,0))*(INDEX('Headcount Phasing'!$B$3:$M$18,MATCH(B8,'Headcount Phasing'!$A$3:$A$18,0),MATCH($K$2,'Headcount Phasing'!$B$2:$M$2,0))) -> 458050.88 | L8: =(_xlfn.XLOOKUP(B8,'Annual Employer Cost per Grade'!$C$2:$C$17,'Annual Employer Cost per Grade'!$U$2:$U$17,0,0))*(INDEX('Headcount Phasing'!$B$3:$M$18,MATCH(B8,'Headcount Phasing'!$A$3:$A$18,0),MATCH($L$2,'Headcount Phasing'!$B$2:$M$2,0))) -> 458050.88 | M8: =(_xlfn.XLOOKUP(B8,'Annual Employer Cost per Grade'!$C$2:$C$17,'Annual Employer Cost per Grade'!$U$2:$U$17,0,0))*(INDEX('Headcount Phasing'!$B$3:$M$18,MATCH(B8,'Headcount Phasing'!$A$3:$A$18,0),MATCH($M$2,'Headcount Phasing'!$B$2:$M$2,0))) -> 458050.88 | N8: =(_xlfn.XLOOKUP(B8,'Annual Employer Cost per Grade'!$C$2:$C$17,'Annual Employer Cost per Grade'!$U$2:$U$17,0,0))*(INDEX('Headcount Phasing'!$B$3:$M$18,MATCH(B8,'Headcount Phasing'!$A$3:$A$18,0),MATCH($N$2,'Headcount Phasing'!$B$2:$M$2,0))) -> 458050.88 | O8: =SUM(C8:N8) -> 4122457.9
A9: =A8+1 -> 7 | B9: Front Desk Support (Tech Grade 1) | F9: =(_xlfn.XLOOKUP(B9,'Annual Employer Cost per Grade'!$C$2:$C$17,'Annual Employer Cost per Grade'!$U$2:$U$17,0,0))*(INDEX('Headcount Phasing'!$B$3:$M$18,MATCH(B9,'Headcount Phasing'!$A$3:$A$18,0),MATCH($F$2,'Headcount Phasing'!$B$2:$M$2,0))) -> 231183.15 | G9: =(_xlfn.XLOOKUP(B9,'Annual Employer Cost per Grade'!$C$2:$C$17,'Annual Employer Cost per Grade'!$U$2:$U$17,0,0))*(INDEX('Headcount Phasing'!$B$3:$M$18,MATCH(B9,'Headcount Phasing'!$A$3:$A$18,0),MATCH($G$2,'Headcount Phasing'!$B$2:$M$2,0))) -> 231183.15 | H9: =(_xlfn.XLOOKUP(B9,'Annual Employer Cost per Grade'!$C$2:$C$17,'Annual Employer Cost per Grade'!$U$2:$U$17,0,0))*(INDEX('Headcount Phasing'!$B$3:$M$18,MATCH(B9,'Headcount Phasing'!$A$3:$A$18,0),MATCH($H$2,'Headcount Phasing'!$B$2:$M$2,0))) -> 231183.15 | I9: =(_xlfn.XLOOKUP(B9,'Annual Employer Cost per Grade'!$C$2:$C$17,'Annual Employer Cost per Grade'!$U$2:$U$17,0,0))*(INDEX('Headcount Phasing'!$B$3:$M$18,MATCH(B9,'Headcount Phasing'!$A$3:$A$18,0),MATCH($I$2,'Headcount Phasing'!$B$2:$M$2,0))) -> 231183.15 | J9: =(_xlfn.XLOOKUP(B9,'Annual Employer Cost per Grade'!$C$2:$C$17,'Annual Employer Cost per Grade'!$U$2:$U$17,0,0))*(INDEX('Headcount Phasing'!$B$3:$M$18,MATCH(B9,'Headcount Phasing'!$A$3:$A$18,0),MATCH($J$2,'Headcount Phasing'!$B$2:$M$2,0))) -> 231183.15 | K9: =(_xlfn.XLOOKUP(B9,'Annual Employer Cost per Grade'!$C$2:$C$17,'Annual Employer Cost per Grade'!$U$2:$U$17,0,0))*(INDEX('Headcount Phasing'!$B$3:$M$18,MATCH(B9,'Headcount Phasing'!$A$3:$A$18,0),MATCH($K$2,'Headcount Phasing'!$B$2:$M$2,0))) -> 231183.15 | L9: =(_xlfn.XLOOKUP(B9,'Annual Employer Cost per Grade'!$C$2:$C$17,'Annual Employer Cost per Grade'!$U$2:$U$17,0,0))*(INDEX('Headcount Phasing'!$B$3:$M$18,MATCH(B9,'Headcount Phasing'!$A$3:$A$18,0),MATCH($L$2,'Headcount Phasing'!$B$2:$M$2,0))) -> 231183.15 | M9: =(_xlfn.XLOOKUP(B9,'Annual Employer Cost per Grade'!$C$2:$C$17,'Annual Employer Cost per Grade'!$U$2:$U$17,0,0))*(INDEX('Headcount Phasing'!$B$3:$M$18,MATCH(B9,'Headcount Phasing'!$A$3:$A$18,0),MATCH($M$2,'Headcount Phasing'!$B$2:$M$2,0))) -> 231183.15 | N9: =(_xlfn.XLOOKUP(B9,'Annual Employer Cost per Grade'!$C$2:$C$17,'Annual Employer Cost per Grade'!$U$2:$U$17,0,0))*(INDEX('Headcount Phasing'!$B$3:$M$18,MATCH(B9,'Headcount Phasing'!$A$3:$A$18,0),MATCH($N$2,'Headcount Phasing'!$B$2:$M$2,0))) -> 231183.15 | O9: =SUM(C9:N9) -> 2080648.3
A10: =A9+1 -> 8 | B10: Finance Associate | C10: =(_xlfn.XLOOKUP(B10,'Annual Employer Cost per Grade'!$C$2:$C$17,'Annual Employer Cost per Grade'!$U$2:$U$17,0,0))*(INDEX('Headcount Phasing'!$B$3:$M$18,MATCH(B10,'Headcount Phasing'!$A$3:$A$18,0),MATCH($C$2,'Headcount Phasing'!$B$2:$M$2,0))) -> 0 | D10: =(_xlfn.XLOOKUP(B10,'Annual Employer Cost per Grade'!$C$2:$C$17,'Annual Employer Cost per Grade'!$U$2:$U$17,0,0))*(INDEX('Headcount Phasing'!$B$3:$M$18,MATCH(B10,'Headcount Phasing'!$A$3:$A$18,0),MATCH($D$2,'Headcount Phasing'!$B$2:$M$2,0))) -> 0 | E10: =(_xlfn.XLOOKUP(B10,'Annual Employer Cost per Grade'!$C$2:$C$17,'Annual Employer Cost per Grade'!$U$2:$U$17,0,0))*(INDEX('Headcount Phasing'!$B$3:$M$18,MATCH(B10,'Headcount Phasing'!$A$3:$A$18,0),MATCH($E$2,'Headcount Phasing'!$B$2:$M$2,0))) -> 0 | F10: =(_xlfn.XLOOKUP(B10,'Annual Employer Cost per Grade'!$C$2:$C$17,'Annual Employer Cost per Grade'!$U$2:$U$17,0,0))*(INDEX('Headcount Phasing'!$B$3:$M$18,MATCH(B10,'Headcount Phasing'!$A$3:$A$18,0),MATCH($F$2,'Headcount Phasing'!$B$2:$M$2,0))) -> 458050.88 | G10: =(_xlfn.XLOOKUP(B10,'Annual Employer Cost per Grade'!$C$2:$C$17,'Annual Employer Cost per Grade'!$U$2:$U$17,0,0))*(INDEX('Headcount Phasing'!$B$3:$M$18,MATCH(B10,'Headcount Phasing'!$A$3:$A$18,0),MATCH($G$2,'Headcount Phasing'!$B$2:$M$2,0))) -> 458050.88 | H10: =(_xlfn.XLOOKUP(B10,'Annual Employer Cost per Grade'!$C$2:$C$17,'Annual Employer Cost per Grade'!$U$2:$U$17,0,0))*(INDEX('Headcount Phasing'!$B$3:$M$18,MATCH(B10,'Headcount Phasing'!$A$3:$A$18,0),MATCH($H$2,'Headcount Phasing'!$B$2:$M$2,0))) -> 458050.88 | I10: =(_xlfn.XLOOKUP(B10,'Annual Employer Cost per Grade'!$C$2:$C$17,'Annual Employer Cost per Grade'!$U$2:$U$17,0,0))*(INDEX('Headcount Phasing'!$B$3:$M$18,MATCH(B10,'Headcount Phasing'!$A$3:$A$18,0),MATCH($I$2,'Headcount Phasing'!$B$2:$M$2,0))) -> 458050.88 | J10: =(_xlfn.XLOOKUP(B10,'Annual Employer Cost per Grade'!$C$2:$C$17,'Annual Employer Cost per Grade'!$U$2:$U$17,0,0))*(INDEX('Headcount Phasing'!$B$3:$M$18,MATCH(B10,'Headcount Phasing'!$A$3:$A$18,0),MATCH($J$2,'Headcount Phasing'!$B$2:$M$2,0))) -> 458050.88 | K10: =(_xlfn.XLOOKUP(B10,'Annual Employer Cost per Grade'!$C$2:$C$17,'Annual Employer Cost per Grade'!$U$2:$U$17,0,0))*(INDEX('Headcount Phasing'!$B$3:$M$18,MATCH(B10,'Headcount Phasing'!$A$3:$A$18,0),MATCH($K$2,'Headcount Phasing'!$B$2:$M$2,0))) -> 458050.88 | L10: =(_xlfn.XLOOKUP(B10,'Annual Employer Cost per Grade'!$C$2:$C$17,'Annual Employer Cost per Grade'!$U$2:$U$17,0,0))*(INDEX('Headcount Phasing'!$B$3:$M$18,MATCH(B10,'Headcount Phasing'!$A$3:$A$18,0),MATCH($L$2,'Headcount Phasing'!$B$2:$M$2,0))) -> 458050.88 | M10: =(_xlfn.XLOOKUP(B10,'Annual Employer Cost per Grade'!$C$2:$C$17,'Annual Employer Cost per Grade'!$U$2:$U$17,0,0))*(INDEX('Headcount Phasing'!$B$3:$M$18,MATCH(B10,'Headcount Phasing'!$A$3:$A$18,0),MATCH($M$2,'Headcount Phasing'!$B$2:$M$2,0))) -> 458050.88 | N10: =(_xlfn.XLOOKUP(B10,'Annual Employer Cost per Grade'!$C$2:$C$17,'Annual Employer Cost per Grade'!$U$2:$U$17,0,0))*(INDEX('Headcount Phasing'!$B$3:$M$18,MATCH(B10,'Headcount Phasing'!$A$3:$A$18,0),MATCH($N$2,'Headcount Phasing'!$B$2:$M$2,0))) -> 458050.88 | O10: =SUM(C10:N10) -> 4122457.9
A11: =A10+1 -> 9 | B11: Admin & HR Associate | C11: =(_xlfn.XLOOKUP(B11,'Annual Employer Cost per Grade'!$C$2:$C$17,'Annual Employer Cost per Grade'!$U$2:$U$17,0,0))*(INDEX('Headcount Phasing'!$B$3:$M$18,MATCH(B11,'Headcount Phasing'!$A$3:$A$18,0),MATCH($C$2,'Headcount Phasing'!$B$2:$M$2,0))) -> 0 | D11: =(_xlfn.XLOOKUP(B11,'Annual Employer Cost per Grade'!$C$2:$C$17,'Annual Employer Cost per Grade'!$U$2:$U$17,0,0))*(INDEX('Headcount Phasing'!$B$3:$M$18,MATCH(B11,'Headcount Phasing'!$A$3:$A$18,0),MATCH($D$2,'Headcount Phasing'!$B$2:$M$2,0))) -> 0 | E11: =(_xlfn.XLOOKUP(B11,'Annual Employer Cost per Grade'!$C$2:$C$17,'Annual Employer Cost per Grade'!$U$2:$U$17,0,0))*(INDEX('Headcount Phasing'!$B$3:$M$18,MATCH(B11,'Headcount Phasing'!$A$3:$A$18,0),MATCH($E$2,'Headcount Phasing'!$B$2:$M$2,0))) -> 0 | F11: =(_xlfn.XLOOKUP(B11,'Annual Employer Cost per Grade'!$C$2:$C$17,'Annual Employer Cost per Grade'!$U$2:$U$17,0,0))*(INDEX('Headcount Phasing'!$B$3:$M$18,MATCH(B11,'Headcount Phasing'!$A$3:$A$18,0),MATCH($F$2,'Headcount Phasing'!$B$2:$M$2,0))) -> 458050.88 | G11: =(_xlfn.XLOOKUP(B11,'Annual Employer Cost per Grade'!$C$2:$C$17,'Annual Employer Cost per Grade'!$U$2:$U$17,0,0))*(INDEX('Headcount Phasing'!$B$3:$M$18,MATCH(B11,'Headcount Phasing'!$A$3:$A$18,0),MATCH($G$2,'Headcount Phasing'!$B$2:$M$2,0))) -> 458050.88 | H11: =(_xlfn.XLOOKUP(B11,'Annual Employer Cost per Grade'!$C$2:$C$17,'Annual Employer Cost per Grade'!$U$2:$U$17,0,0))*(INDEX('Headcount Phasing'!$B$3:$M$18,MATCH(B11,'Headcount Phasing'!$A$3:$A$18,0),MATCH($H$2,'Headcount Phasing'!$B$2:$M$2,0))) -> 458050.88 | I11: =(_xlfn.XLOOKUP(B11,'Annual Employer Cost per Grade'!$C$2:$C$17,'Annual Employer Cost per Grade'!$U$2:$U$17,0,0))*(INDEX('Headcount Phasing'!$B$3:$M$18,MATCH(B11,'Headcount Phasing'!$A$3:$A$18,0),MATCH($I$2,'Headcount Phasing'!$B$2:$M$2,0))) -> 458050.88 | J11: =(_xlfn.XLOOKUP(B11,'Annual Employer Cost per Grade'!$C$2:$C$17,'Annual Employer Cost per Grade'!$U$2:$U$17,0,0))*(INDEX('Headcount Phasing'!$B$3:$M$18,MATCH(B11,'Headcount Phasing'!$A$3:$A$18,0),MATCH($J$2,'Headcount Phasing'!$B$2:$M$2,0))) -> 458050.88 | K11: =(_xlfn.XLOOKUP(B11,'Annual Employer Cost per Grade'!$C$2:$C$17,'Annual Employer Cost per Grade'!$U$2:$U$17,0,0))*(INDEX('Headcount Phasing'!$B$3:$M$18,MATCH(B11,'Headcount Phasing'!$A$3:$A$18,0),MATCH($K$2,'Headcount Phasing'!$B$2:$M$2,0))) -> 458050.88 | L11: =(_xlfn.XLOOKUP(B11,'Annual Employer Cost per Grade'!$C$2:$C$17,'Annual Employer Cost per Grade'!$U$2:$U$17,0,0))*(INDEX('Headcount Phasing'!$B$3:$M$18,MATCH(B11,'Headcount Phasing'!$A$3:$A$18,0),MATCH($L$2,'Headcount Phasing'!$B$2:$M$2,0))) -> 458050.88 | M11: =(_xlfn.XLOOKUP(B11,'Annual Employer Cost per Grade'!$C$2:$C$17,'Annual Employer Cost per Grade'!$U$2:$U$17,0,0))*(INDEX('Headcount Phasing'!$B$3:$M$18,MATCH(B11,'Headcount Phasing'!$A$3:$A$18,0),MATCH($M$2,'Headcount Phasing'!$B$2:$M$2,0))) -> 458050.88 | N11: =(_xlfn.XLOOKUP(B11,'Annual Employer Cost per Grade'!$C$2:$C$17,'Annual Employer Cost per Grade'!$U$2:$U$17,0,0))*(INDEX('Headcount Phasing'!$B$3:$M$18,MATCH(B11,'Headcount Phasing'!$A$3:$A$18,0),MATCH($N$2,'Headcount Phasing'!$B$2:$M$2,0))) -> 458050.88 | O11: =SUM(C11:N11) -> 4122457.9
A12: =A11+1 -> 10 | B12: IT Support Associate (x2) | C12: =(_xlfn.XLOOKUP(B12,'Annual Employer Cost per Grade'!$C$2:$C$17,'Annual Employer Cost per Grade'!$U$2:$U$17,0,0))*(INDEX('Headcount Phasing'!$B$3:$M$18,MATCH(B12,'Headcount Phasing'!$A$3:$A$18,0),MATCH($C$2,'Headcount Phasing'!$B$2:$M$2,0))) -> 0 | D12: =(_xlfn.XLOOKUP(B12,'Annual Employer Cost per Grade'!$C$2:$C$17,'Annual Employer Cost per Grade'!$U$2:$U$17,0,0))*(INDEX('Headcount Phasing'!$B$3:$M$18,MATCH(B12,'Headcount Phasing'!$A$3:$A$18,0),MATCH($D$2,'Headcount Phasing'!$B$2:$M$2,0))) -> 0 | E12: =(_xlfn.XLOOKUP(B12,'Annual Employer Cost per Grade'!$C$2:$C$17,'Annual Employer Cost per Grade'!$U$2:$U$17,0,0))*(INDEX('Headcount Phasing'!$B$3:$M$18,MATCH(B12,'Headcount Phasing'!$A$3:$A$18,0),MATCH($E$2,'Headcount Phasing'!$B$2:$M$2,0))) -> 0 | F12: =(_xlfn.XLOOKUP(B12,'Annual Employer Cost per Grade'!$C$2:$C$17,'Annual Employer Cost per Grade'!$U$2:$U$17,0,0))*(INDEX('Headcount Phasing'!$B$3:$M$18,MATCH(B12,'Headcount Phasing'!$A$3:$A$18,0),MATCH($F$2,'Headcount Phasing'!$B$2:$M$2,0))) -> 458050.88 | G12: =(_xlfn.XLOOKUP(B12,'Annual Employer Cost per Grade'!$C$2:$C$17,'Annual Employer Cost per Grade'!$U$2:$U$17,0,0))*(INDEX('Headcount Phasing'!$B$3:$M$18,MATCH(B12,'Headcount Phasing'!$A$3:$A$18,0),MATCH($G$2,'Headcount Phasing'!$B$2:$M$2,0))) -> 458050.88 | H12: =(_xlfn.XLOOKUP(B12,'Annual Employer Cost per Grade'!$C$2:$C$17,'Annual Employer Cost per Grade'!$U$2:$U$17,0,0))*(INDEX('Headcount Phasing'!$B$3:$M$18,MATCH(B12,'Headcount Phasing'!$A$3:$A$18,0),MATCH($H$2,'Headcount Phasing'!$B$2:$M$2,0))) -> 458050.88 | I12: =(_xlfn.XLOOKUP(B12,'Annual Employer Cost per Grade'!$C$2:$C$17,'Annual Employer Cost per Grade'!$U$2:$U$17,0,0))*(INDEX('Headcount Phasing'!$B$3:$M$18,MATCH(B12,'Headcount Phasing'!$A$3:$A$18,0),MATCH($I$2,'Headcount Phasing'!$B$2:$M$2,0))) -> 458050.88 | J12: =(_xlfn.XLOOKUP(B12,'Annual Employer Cost per Grade'!$C$2:$C$17,'Annual Employer Cost per Grade'!$U$2:$U$17,0,0))*(INDEX('Headcount Phasing'!$B$3:$M$18,MATCH(B12,'Headcount Phasing'!$A$3:$A$18,0),MATCH($J$2,'Headcount Phasing'!$B$2:$M$2,0))) -> 458050.88 | K12: =(_xlfn.XLOOKUP(B12,'Annual Employer Cost per Grade'!$C$2:$C$17,'Annual Employer Cost per Grade'!$U$2:$U$17,0,0))*(INDEX('Headcount Phasing'!$B$3:$M$18,MATCH(B12,'Headcount Phasing'!$A$3:$A$18,0),MATCH($K$2,'Headcount Phasing'!$B$2:$M$2,0))) -> 458050.88 | L12: =(_xlfn.XLOOKUP(B12,'Annual Employer Cost per Grade'!$C$2:$C$17,'Annual Employer Cost per Grade'!$U$2:$U$17,0,0))*(INDEX('Headcount Phasing'!$B$3:$M$18,MATCH(B12,'Headcount Phasing'!$A$3:$A$18,0),MATCH($L$2,'Headcount Phasing'!$B$2:$M$2,0))) -> 458050.88 | M12: =(_xlfn.XLOOKUP(B12,'Annual Employer Cost per Grade'!$C$2:$C$17,'Annual Employer Cost per Grade'!$U$2:$U$17,0,0))*(INDEX('Headcount Phasing'!$B$3:$M$18,MATCH(B12,'Headcount Phasing'!$A$3:$A$18,0),MATCH($M$2,'Headcount Phasing'!$B$2:$M$2,0))) -> 458050.88 | N12: =(_xlfn.XLOOKUP(B12,'Annual Employer Cost per Grade'!$C$2:$C$17,'Annual Employer Cost per Grade'!$U$2:$U$17,0,0))*(INDEX('Headcount Phasing'!$B$3:$M$18,MATCH(B12,'Headcount Phasing'!$A$3:$A$18,0),MATCH($N$2,'Headcount Phasing'!$B$2:$M$2,0))) -> 458050.88 | O12: =SUM(C12:N12) -> 4122457.9
A13: =A12+1 -> 11 | B13: Content & Digital Marketing Lead | C13: =(_xlfn.XLOOKUP(B13,'Annual Employer Cost per Grade'!$C$2:$C$17,'Annual Employer Cost per Grade'!$U$2:$U$17,0,0))*(INDEX('Headcount Phasing'!$B$3:$M$18,MATCH(B13,'Headcount Phasing'!$A$3:$A$18,0),MATCH($C$2,'Headcount Phasing'!$B$2:$M$2,0))) -> 0 | D13: =(_xlfn.XLOOKUP(B13,'Annual Employer Cost per Grade'!$C$2:$C$17,'Annual Employer Cost per Grade'!$U$2:$U$17,0,0))*(INDEX('Headcount Phasing'!$B$3:$M$18,MATCH(B13,'Headcount Phasing'!$A$3:$A$18,0),MATCH($D$2,'Headcount Phasing'!$B$2:$M$2,0))) -> 0 | E13: =(_xlfn.XLOOKUP(B13,'Annual Employer Cost per Grade'!$C$2:$C$17,'Annual Employer Cost per Grade'!$U$2:$U$17,0,0))*(INDEX('Headcount Phasing'!$B$3:$M$18,MATCH(B13,'Headcount Phasing'!$A$3:$A$18,0),MATCH($E$2,'Headcount Phasing'!$B$2:$M$2,0))) -> 0 | F13: =(_xlfn.XLOOKUP(B13,'Annual Employer Cost per Grade'!$C$2:$C$17,'Annual Employer Cost per Grade'!$U$2:$U$17,0,0))*(INDEX('Headcount Phasing'!$B$3:$M$18,MATCH(B13,'Headcount Phasing'!$A$3:$A$18,0),MATCH($F$2,'Headcount Phasing'!$B$2:$M$2,0))) -> 465550.88 | G13: =(_xlfn.XLOOKUP(B13,'Annual Employer Cost per Grade'!$C$2:$C$17,'Annual Employer Cost per Grade'!$U$2:$U$17,0,0))*(INDEX('Headcount Phasing'!$B$3:$M$18,MATCH(B13,'Headcount Phasing'!$A$3:$A$18,0),MATCH($G$2,'Headcount Phasing'!$B$2:$M$2,0))) -> 465550.88 | H13: =(_xlfn.XLOOKUP(B13,'Annual Employer Cost per Grade'!$C$2:$C$17,'Annual Employer Cost per Grade'!$U$2:$U$17,0,0))*(INDEX('Headcount Phasing'!$B$3:$M$18,MATCH(B13,'Headcount Phasing'!$A$3:$A$18,0),MATCH($H$2,'Headcount Phasing'!$B$2:$M$2,0))) -> 465550.88 | I13: =(_xlfn.XLOOKUP(B13,'Annual Employer Cost per Grade'!$C$2:$C$17,'Annual Employer Cost per Grade'!$U$2:$U$17,0,0))*(INDEX('Headcount Phasing'!$B$3:$M$18,MATCH(B13,'Headcount Phasing'!$A$3:$A$18,0),MATCH($I$2,'Headcount Phasing'!$B$2:$M$2,0))) -> 465550.88 | J13: =(_xlfn.XLOOKUP(B13,'Annual Employer Cost per Grade'!$C$2:$C$17,'Annual Employer Cost per Grade'!$U$2:$U$17,0,0))*(INDEX('Headcount Phasing'!$B$3:$M$18,MATCH(B13,'Headcount Phasing'!$A$3:$A$18,0),MATCH($J$2,'Headcount Phasing'!$B$2:$M$2,0))) -> 465550.88 | K13: =(_xlfn.XLOOKUP(B13,'Annual Employer Cost per Grade'!$C$2:$C$17,'Annual Employer Cost per Grade'!$U$2:$U$17,0,0))*(INDEX('Headcount Phasing'!$B$3:$M$18,MATCH(B13,'Headcount Phasing'!$A$3:$A$18,0),MATCH($K$2,'Headcount Phasing'!$B$2:$M$2,0))) -> 465550.88 | L13: =(_xlfn.XLOOKUP(B13,'Annual Employer Cost per Grade'!$C$2:$C$17,'Annual Employer Cost per Grade'!$U$2:$U$17,0,0))*(INDEX('Headcount Phasing'!$B$3:$M$18,MATCH(B13,'Headcount Phasing'!$A$3:$A$18,0),MATCH($L$2,'Headcount Phasing'!$B$2:$M$2,0))) -> 465550.88 | M13: =(_xlfn.XLOOKUP(B13,'Annual Employer Cost per Grade'!$C$2:$C$17,'Annual Employer Cost per Grade'!$U$2:$U$17,0,0))*(INDEX('Headcount Phasing'!$B$3:$M$18,MATCH(B13,'Headcount Phasing'!$A$3:$A$18,0),MATCH($M$2,'Headcount Phasing'!$B$2:$M$2,0))) -> 465550.88 | N13: =(_xlfn.XLOOKUP(B13,'Annual Employer Cost per Grade'!$C$2:$C$17,'Annual Employer Cost per Grade'!$U$2:$U$17,0,0))*(INDEX('Headcount Phasing'!$B$3:$M$18,MATCH(B13,'Headcount Phasing'!$A$3:$A$18,0),MATCH($N$2,'Headcount Phasing'!$B$2:$M$2,0))) -> 465550.88 | O13: =SUM(C13:N13) -> 4189957.9
A14: =A13+1 -> 12 | B14: Graphic & Multimedia Associate | C14: =(_xlfn.XLOOKUP(B14,'Annual Employer Cost per Grade'!$C$2:$C$17,'Annual Employer Cost per Grade'!$U$2:$U$17,0,0))*(INDEX('Headcount Phasing'!$B$3:$M$18,MATCH(B14,'Headcount Phasing'!$A$3:$A$18,0),MATCH($C$2,'Headcount Phasing'!$B$2:$M$2,0))) -> 0 | D14: =(_xlfn.XLOOKUP(B14,'Annual Employer Cost per Grade'!$C$2:$C$17,'Annual Employer Cost per Grade'!$U$2:$U$17,0,0))*(INDEX('Headcount Phasing'!$B$3:$M$18,MATCH(B14,'Headcount Phasing'!$A$3:$A$18,0),MATCH($D$2,'Headcount Phasing'!$B$2:$M$2,0))) -> 0 | E14: =(_xlfn.XLOOKUP(B14,'Annual Employer Cost per Grade'!$C$2:$C$17,'Annual Employer Cost per Grade'!$U$2:$U$17,0,0))*(INDEX('Headcount Phasing'!$B$3:$M$18,MATCH(B14,'Headcount Phasing'!$A$3:$A$18,0),MATCH($E$2,'Headcount Phasing'!$B$2:$M$2,0))) -> 0 | F14: =(_xlfn.XLOOKUP(B14,'Annual Employer Cost per Grade'!$C$2:$C$17,'Annual Employer Cost per Grade'!$U$2:$U$17,0,0))*(INDEX('Headcount Phasing'!$B$3:$M$18,MATCH(B14,'Headcount Phasing'!$A$3:$A$18,0),MATCH($F$2,'Headcount Phasing'!$B$2:$M$2,0))) -> 465550.88 | G14: =(_xlfn.XLOOKUP(B14,'Annual Employer Cost per Grade'!$C$2:$C$17,'Annual Employer Cost per Grade'!$U$2:$U$17,0,0))*(INDEX('Headcount Phasing'!$B$3:$M$18,MATCH(B14,'Headcount Phasing'!$A$3:$A$18,0),MATCH($G$2,'Headcount Phasing'!$B$2:$M$2,0))) -> 465550.88 | H14: =(_xlfn.XLOOKUP(B14,'Annual Employer Cost per Grade'!$C$2:$C$17,'Annual Employer Cost per Grade'!$U$2:$U$17,0,0))*(INDEX('Headcount Phasing'!$B$3:$M$18,MATCH(B14,'Headcount Phasing'!$A$3:$A$18,0),MATCH($H$2,'Headcount Phasing'!$B$2:$M$2,0))) -> 465550.88 | I14: =(_xlfn.XLOOKUP(B14,'Annual Employer Cost per Grade'!$C$2:$C$17,'Annual Employer Cost per Grade'!$U$2:$U$17,0,0))*(INDEX('Headcount Phasing'!$B$3:$M$18,MATCH(B14,'Headcount Phasing'!$A$3:$A$18,0),MATCH($I$2,'Headcount Phasing'!$B$2:$M$2,0))) -> 465550.88 | J14: =(_xlfn.XLOOKUP(B14,'Annual Employer Cost per Grade'!$C$2:$C$17,'Annual Employer Cost per Grade'!$U$2:$U$17,0,0))*(INDEX('Headcount Phasing'!$B$3:$M$18,MATCH(B14,'Headcount Phasing'!$A$3:$A$18,0),MATCH($J$2,'Headcount Phasing'!$B$2:$M$2,0))) -> 465550.88 | K14: =(_xlfn.XLOOKUP(B14,'Annual Employer Cost per Grade'!$C$2:$C$17,'Annual Employer Cost per Grade'!$U$2:$U$17,0,0))*(INDEX('Headcount Phasing'!$B$3:$M$18,MATCH(B14,'Headcount Phasing'!$A$3:$A$18,0),MATCH($K$2,'Headcount Phasing'!$B$2:$M$2,0))) -> 465550.88 | L14: =(_xlfn.XLOOKUP(B14,'Annual Employer Cost per Grade'!$C$2:$C$17,'Annual Employer Cost per Grade'!$U$2:$U$17,0,0))*(INDEX('Headcount Phasing'!$B$3:$M$18,MATCH(B14,'Headcount Phasing'!$A$3:$A$18,0),MATCH($L$2,'Headcount Phasing'!$B$2:$M$2,0))) -> 465550.88 | M14: =(_xlfn.XLOOKUP(B14,'Annual Employer Cost per Grade'!$C$2:$C$17,'Annual Employer Cost per Grade'!$U$2:$U$17,0,0))*(INDEX('Headcount Phasing'!$B$3:$M$18,MATCH(B14,'Headcount Phasing'!$A$3:$A$18,0),MATCH($M$2,'Headcount Phasing'!$B$2:$M$2,0))) -> 465550.88 | N14: =(_xlfn.XLOOKUP(B14,'Annual Employer Cost per Grade'!$C$2:$C$17,'Annual Employer Cost per Grade'!$U$2:$U$17,0,0))*(INDEX('Headcount Phasing'!$B$3:$M$18,MATCH(B14,'Headcount Phasing'!$A$3:$A$18,0),MATCH($N$2,'Headcount Phasing'!$B$2:$M$2,0))) -> 465550.88 | O14: =SUM(C14:N14) -> 4189957.9
A15: =A14+1 -> 13 | B15: Facility Technician (x3) | C15: =(_xlfn.XLOOKUP(B15,'Annual Employer Cost per Grade'!$C$2:$C$17,'Annual Employer Cost per Grade'!$U$2:$U$17,0,0))*(INDEX('Headcount Phasing'!$B$3:$M$18,MATCH(B15,'Headcount Phasing'!$A$3:$A$18,0),MATCH($C$2,'Headcount Phasing'!$B$2:$M$2,0))) -> 0 | D15: =(_xlfn.XLOOKUP(B15,'Annual Employer Cost per Grade'!$C$2:$C$17,'Annual Employer Cost per Grade'!$U$2:$U$17,0,0))*(INDEX('Headcount Phasing'!$B$3:$M$18,MATCH(B15,'Headcount Phasing'!$A$3:$A$18,0),MATCH($D$2,'Headcount Phasing'!$B$2:$M$2,0))) -> 0 | E15: =(_xlfn.XLOOKUP(B15,'Annual Employer Cost per Grade'!$C$2:$C$17,'Annual Employer Cost per Grade'!$U$2:$U$17,0,0))*(INDEX('Headcount Phasing'!$B$3:$M$18,MATCH(B15,'Headcount Phasing'!$A$3:$A$18,0),MATCH($E$2,'Headcount Phasing'!$B$2:$M$2,0))) -> 0 | F15: =(_xlfn.XLOOKUP(B15,'Annual Employer Cost per Grade'!$C$2:$C$17,'Annual Employer Cost per Grade'!$U$2:$U$17,0,0))*(INDEX('Headcount Phasing'!$B$3:$M$18,MATCH(B15,'Headcount Phasing'!$A$3:$A$18,0),MATCH($F$2,'Headcount Phasing'!$B$2:$M$2,0))) -> 231183.15 | G15: =(_xlfn.XLOOKUP(B15,'Annual Employer Cost per Grade'!$C$2:$C$17,'Annual Employer Cost per Grade'!$U$2:$U$17,0,0))*(INDEX('Headcount Phasing'!$B$3:$M$18,MATCH(B15,'Headcount Phasing'!$A$3:$A$18,0),MATCH($G$2,'Headcount Phasing'!$B$2:$M$2,0))) -> 231183.15 | H15: =(_xlfn.XLOOKUP(B15,'Annual Employer Cost per Grade'!$C$2:$C$17,'Annual Employer Cost per Grade'!$U$2:$U$17,0,0))*(INDEX('Headcount Phasing'!$B$3:$M$18,MATCH(B15,'Headcount Phasing'!$A$3:$A$18,0),MATCH($H$2,'Headcount Phasing'!$B$2:$M$2,0))) -> 231183.15 | I15: =(_xlfn.XLOOKUP(B15,'Annual Employer Cost per Grade'!$C$2:$C$17,'Annual Employer Cost per Grade'!$U$2:$U$17,0,0))*(INDEX('Headcount Phasing'!$B$3:$M$18,MATCH(B15,'Headcount Phasing'!$A$3:$A$18,0),MATCH($I$2,'Headcount Phasing'!$B$2:$M$2,0))) -> 231183.15 | J15: =(_xlfn.XLOOKUP(B15,'Annual Employer Cost per Grade'!$C$2:$C$17,'Annual Employer Cost per Grade'!$U$2:$U$17,0,0))*(INDEX('Headcount Phasing'!$B$3:$M$18,MATCH(B15,'Headcount Phasing'!$A$3:$A$18,0),MATCH($J$2,'Headcount Phasing'!$B$2:$M$2,0))) -> 231183.15 | K15: =(_xlfn.XLOOKUP(B15,'Annual Employer Cost per Grade'!$C$2:$C$17,'Annual Employer Cost per Grade'!$U$2:$U$17,0,0))*(INDEX('Headcount Phasing'!$B$3:$M$18,MATCH(B15,'Headcount Phasing'!$A$3:$A$18,0),MATCH($K$2,'Headcount Phasing'!$B$2:$M$2,0))) -> 231183.15 | L15: =(_xlfn.XLOOKUP(B15,'Annual Employer Cost per Grade'!$C$2:$C$17,'Annual Employer Cost per Grade'!$U$2:$U$17,0,0))*(INDEX('Headcount Phasing'!$B$3:$M$18,MATCH(B15,'Headcount Phasing'!$A$3:$A$18,0),MATCH($L$2,'Headcount Phasing'!$B$2:$M$2,0))) -> 231183.15 | M15: =(_xlfn.XLOOKUP(B15,'Annual Employer Cost per Grade'!$C$2:$C$17,'Annual Employer Cost per Grade'!$U$2:$U$17,0,0))*(INDEX('Headcount Phasing'!$B$3:$M$18,MATCH(B15,'Headcount Phasing'!$A$3:$A$18,0),MATCH($M$2,'Headcount Phasing'!$B$2:$M$2,0))) -> 231183.15 | N15: =(_xlfn.XLOOKUP(B15,'Annual Employer Cost per Grade'!$C$2:$C$17,'Annual Employer Cost per Grade'!$U$2:$U$17,0,0))*(INDEX('Headcount Phasing'!$B$3:$M$18,MATCH(B15,'Headcount Phasing'!$A$3:$A$18,0),MATCH($N$2,'Headcount Phasing'!$B$2:$M$2,0))) -> 231183.15 | O15: =SUM(C15:N15) -> 2080648.3
A16: =A15+1 -> 14 | B16: Driver | C16: =(_xlfn.XLOOKUP(B16,'Annual Employer Cost per Grade'!$C$2:$C$17,'Annual Employer Cost per Grade'!$U$2:$U$17,0,0))*(INDEX('Headcount Phasing'!$B$3:$M$18,MATCH(B16,'Headcount Phasing'!$A$3:$A$18,0),MATCH($C$2,'Headcount Phasing'!$B$2:$M$2,0))) -> 0 | D16: =(_xlfn.XLOOKUP(B16,'Annual Employer Cost per Grade'!$C$2:$C$17,'Annual Employer Cost per Grade'!$U$2:$U$17,0,0))*(INDEX('Headcount Phasing'!$B$3:$M$18,MATCH(B16,'Headcount Phasing'!$A$3:$A$18,0),MATCH($D$2,'Headcount Phasing'!$B$2:$M$2,0))) -> 0 | E16: =(_xlfn.XLOOKUP(B16,'Annual Employer Cost per Grade'!$C$2:$C$17,'Annual Employer Cost per Grade'!$U$2:$U$17,0,0))*(INDEX('Headcount Phasing'!$B$3:$M$18,MATCH(B16,'Headcount Phasing'!$A$3:$A$18,0),MATCH($E$2,'Headcount Phasing'!$B$2:$M$2,0))) -> 231183.15 | F16: =(_xlfn.XLOOKUP(B16,'Annual Employer Cost per Grade'!$C$2:$C$17,'Annual Employer Cost per Grade'!$U$2:$U$17,0,0))*(INDEX('Headcount Phasing'!$B$3:$M$18,MATCH(B16,'Headcount Phasing'!$A$3:$A$18,0),MATCH($F$2,'Headcount Phasing'!$B$2:$M$2,0))) -> 231183.15 | G16: =(_xlfn.XLOOKUP(B16,'Annual Employer Cost per Grade'!$C$2:$C$17,'Annual Employer Cost per Grade'!$U$2:$U$17,0,0))*(INDEX('Headcount Phasing'!$B$3:$M$18,MATCH(B16,'Headcount Phasing'!$A$3:$A$18,0),MATCH($G$2,'Headcount Phasing'!$B$2:$M$2,0))) -> 462366.29 | H16: =(_xlfn.XLOOKUP(B16,'Annual Employer Cost per Grade'!$C$2:$C$17,'Annual Employer Cost per Grade'!$U$2:$U$17,0,0))*(INDEX('Headcount Phasing'!$B$3:$M$18,MATCH(B16,'Headcount Phasing'!$A$3:$A$18,0),MATCH($H$2,'Headcount Phasing'!$B$2:$M$2,0))) -> 462366.29 | I16: =(_xlfn.XLOOKUP(B16,'Annual Employer Cost per Grade'!$C$2:$C$17,'Annual Employer Cost per Grade'!$U$2:$U$17,0,0))*(INDEX('Headcount Phasing'!$B$3:$M$18,MATCH(B16,'Headcount Phasing'!$A$3:$A$18,0),MATCH($I$2,'Headcount Phasing'!$B$2:$M$2,0))) -> 462366.29 | J16: =(_xlfn.XLOOKUP(B16,'Annual Employer Cost per Grade'!$C$2:$C$17,'Annual Employer Cost per Grade'!$U$2:$U$17,0,0))*(INDEX('Headcount Phasing'!$B$3:$M$18,MATCH(B16,'Headcount Phasing'!$A$3:$A$18,0),MATCH($J$2,'Headcount Phasing'!$B$2:$M$2,0))) -> 462366.29 | K16: =(_xlfn.XLOOKUP(B16,'Annual Employer Cost per Grade'!$C$2:$C$17,'Annual Employer Cost per Grade'!$U$2:$U$17,0,0))*(INDEX('Headcount Phasing'!$B$3:$M$18,MATCH(B16,'Headcount Phasing'!$A$3:$A$18,0),MATCH($K$2,'Headcount Phasing'!$B$2:$M$2,0))) -> 462366.29 | L16: =(_xlfn.XLOOKUP(B16,'Annual Employer Cost per Grade'!$C$2:$C$17,'Annual Employer Cost per Grade'!$U$2:$U$17,0,0))*(INDEX('Headcount Phasing'!$B$3:$M$18,MATCH(B16,'Headcount Phasing'!$A$3:$A$18,0),MATCH($L$2,'Headcount Phasing'!$B$2:$M$2,0))) -> 462366.29 | M16: =(_xlfn.XLOOKUP(B16,'Annual Employer Cost per Grade'!$C$2:$C$17,'Annual Employer Cost per Grade'!$U$2:$U$17,0,0))*(INDEX('Headcount Phasing'!$B$3:$M$18,MATCH(B16,'Headcount Phasing'!$A$3:$A$18,0),MATCH($M$2,'Headcount Phasing'!$B$2:$M$2,0))) -> 462366.29 | N16: =(_xlfn.XLOOKUP(B16,'Annual Employer Cost per Grade'!$C$2:$C$17,'Annual Employer Cost per Grade'!$U$2:$U$17,0,0))*(INDEX('Headcount Phasing'!$B$3:$M$18,MATCH(B16,'Headcount Phasing'!$A$3:$A$18,0),MATCH($N$2,'Headcount Phasing'!$B$2:$M$2,0))) -> 462366.29 | O16: =SUM(C16:N16) -> 4161296.6
A17: =A16+1 -> 15 | B17: NYSC Intern (x3) | C17: =(_xlfn.XLOOKUP(B17,'Annual Employer Cost per Grade'!$C$2:$C$17,'Annual Employer Cost per Grade'!$U$2:$U$17,0,0))*(INDEX('Headcount Phasing'!$B$3:$M$18,MATCH(B17,'Headcount Phasing'!$A$3:$A$18,0),MATCH($C$2,'Headcount Phasing'!$B$2:$M$2,0))) -> 0 | D17: =(_xlfn.XLOOKUP(B17,'Annual Employer Cost per Grade'!$C$2:$C$17,'Annual Employer Cost per Grade'!$U$2:$U$17,0,0))*(INDEX('Headcount Phasing'!$B$3:$M$18,MATCH(B17,'Headcount Phasing'!$A$3:$A$18,0),MATCH($D$2,'Headcount Phasing'!$B$2:$M$2,0))) -> 0 | E17: =(_xlfn.XLOOKUP(B17,'Annual Employer Cost per Grade'!$C$2:$C$17,'Annual Employer Cost per Grade'!$U$2:$U$17,0,0))*(INDEX('Headcount Phasing'!$B$3:$M$18,MATCH(B17,'Headcount Phasing'!$A$3:$A$18,0),MATCH($E$2,'Headcount Phasing'!$B$2:$M$2,0))) -> 0 | F17: =(_xlfn.XLOOKUP(B17,'Annual Employer Cost per Grade'!$C$2:$C$17,'Annual Employer Cost per Grade'!$U$2:$U$17,0,0))*(INDEX('Headcount Phasing'!$B$3:$M$18,MATCH(B17,'Headcount Phasing'!$A$3:$A$18,0),MATCH($F$2,'Headcount Phasing'!$B$2:$M$2,0))) -> 0 | G17: =(_xlfn.XLOOKUP(B17,'Annual Employer Cost per Grade'!$C$2:$C$17,'Annual Employer Cost per Grade'!$U$2:$U$17,0,0))*(INDEX('Headcount Phasing'!$B$3:$M$18,MATCH(B17,'Headcount Phasing'!$A$3:$A$18,0),MATCH($G$2,'Headcount Phasing'!$B$2:$M$2,0))) -> 199189.62 | H17: =(_xlfn.XLOOKUP(B17,'Annual Employer Cost per Grade'!$C$2:$C$17,'Annual Employer Cost per Grade'!$U$2:$U$17,0,0))*(INDEX('Headcount Phasing'!$B$3:$M$18,MATCH(B17,'Headcount Phasing'!$A$3:$A$18,0),MATCH($H$2,'Headcount Phasing'!$B$2:$M$2,0))) -> 199189.62 | I17: =(_xlfn.XLOOKUP(B17,'Annual Employer Cost per Grade'!$C$2:$C$17,'Annual Employer Cost per Grade'!$U$2:$U$17,0,0))*(INDEX('Headcount Phasing'!$B$3:$M$18,MATCH(B17,'Headcount Phasing'!$A$3:$A$18,0),MATCH($I$2,'Headcount Phasing'!$B$2:$M$2,0))) -> 199189.62 | J17: =(_xlfn.XLOOKUP(B17,'Annual Employer Cost per Grade'!$C$2:$C$17,'Annual Employer Cost per Grade'!$U$2:$U$17,0,0))*(INDEX('Headcount Phasing'!$B$3:$M$18,MATCH(B17,'Headcount Phasing'!$A$3:$A$18,0),MATCH($J$2,'Headcount Phasing'!$B$2:$M$2,0))) -> 199189.62 | K17: =(_xlfn.XLOOKUP(B17,'Annual Employer Cost per Grade'!$C$2:$C$17,'Annual Employer Cost per Grade'!$U$2:$U$17,0,0))*(INDEX('Headcount Phasing'!$B$3:$M$18,MATCH(B17,'Headcount Phasing'!$A$3:$A$18,0),MATCH($K$2,'Headcount Phasing'!$B$2:$M$2,0))) -> 199189.62 | L17: =(_xlfn.XLOOKUP(B17,'Annual Employer Cost per Grade'!$C$2:$C$17,'Annual Employer Cost per Grade'!$U$2:$U$17,0,0))*(INDEX('Headcount Phasing'!$B$3:$M$18,MATCH(B17,'Headcount Phasing'!$A$3:$A$18,0),MATCH($L$2,'Headcount Phasing'!$B$2:$M$2,0))) -> 199189.62 | M17: =(_xlfn.XLOOKUP(B17,'Annual Employer Cost per Grade'!$C$2:$C$17,'Annual Employer Cost per Grade'!$U$2:$U$17,0,0))*(INDEX('Headcount Phasing'!$B$3:$M$18,MATCH(B17,'Headcount Phasing'!$A$3:$A$18,0),MATCH($M$2,'Headcount Phasing'!$B$2:$M$2,0))) -> 199189.62 | N17: =(_xlfn.XLOOKUP(B17,'Annual Employer Cost per Grade'!$C$2:$C$17,'Annual Employer Cost per Grade'!$U$2:$U$17,0,0))*(INDEX('Headcount Phasing'!$B$3:$M$18,MATCH(B17,'Headcount Phasing'!$A$3:$A$18,0),MATCH($N$2,'Headcount Phasing'!$B$2:$M$2,0))) -> 199189.62 | O17: =SUM(C17:N17) -> 1593517
A18: =A17+1 -> 16 | B18: Student Intern (x3) | C18: =(_xlfn.XLOOKUP(B18,'Annual Employer Cost per Grade'!$C$2:$C$17,'Annual Employer Cost per Grade'!$U$2:$U$17,0,0))*(INDEX('Headcount Phasing'!$B$3:$M$18,MATCH(B18,'Headcount Phasing'!$A$3:$A$18,0),MATCH($C$2,'Headcount Phasing'!$B$2:$M$2,0))) -> 0 | D18: =(_xlfn.XLOOKUP(B18,'Annual Employer Cost per Grade'!$C$2:$C$17,'Annual Employer Cost per Grade'!$U$2:$U$17,0,0))*(INDEX('Headcount Phasing'!$B$3:$M$18,MATCH(B18,'Headcount Phasing'!$A$3:$A$18,0),MATCH($D$2,'Headcount Phasing'!$B$2:$M$2,0))) -> 0 | E18: =(_xlfn.XLOOKUP(B18,'Annual Employer Cost per Grade'!$C$2:$C$17,'Annual Employer Cost per Grade'!$U$2:$U$17,0,0))*(INDEX('Headcount Phasing'!$B$3:$M$18,MATCH(B18,'Headcount Phasing'!$A$3:$A$18,0),MATCH($E$2,'Headcount Phasing'!$B$2:$M$2,0))) -> 0 | F18: =(_xlfn.XLOOKUP(B18,'Annual Employer Cost per Grade'!$C$2:$C$17,'Annual Employer Cost per Grade'!$U$2:$U$17,0,0))*(INDEX('Headcount Phasing'!$B$3:$M$18,MATCH(B18,'Headcount Phasing'!$A$3:$A$18,0),MATCH($F$2,'Headcount Phasing'!$B$2:$M$2,0))) -> 240702 | G18: =(_xlfn.XLOOKUP(B18,'Annual Employer Cost per Grade'!$C$2:$C$17,'Annual Employer Cost per Grade'!$U$2:$U$17,0,0))*(INDEX('Headcount Phasing'!$B$3:$M$18,MATCH(B18,'Headcount Phasing'!$A$3:$A$18,0),MATCH($G$2,'Headcount Phasing'!$B$2:$M$2,0))) -> 240702 | H18: =(_xlfn.XLOOKUP(B18,'Annual Employer Cost per Grade'!$C$2:$C$17,'Annual Employer Cost per Grade'!$U$2:$U$17,0,0))*(INDEX('Headcount Phasing'!$B$3:$M$18,MATCH(B18,'Headcount Phasing'!$A$3:$A$18,0),MATCH($H$2,'Headcount Phasing'!$B$2:$M$2,0))) -> 240702 | I18: =(_xlfn.XLOOKUP(B18,'Annual Employer Cost per Grade'!$C$2:$C$17,'Annual Employer Cost per Grade'!$U$2:$U$17,0,0))*(INDEX('Headcount Phasing'!$B$3:$M$18,MATCH(B18,'Headcount Phasing'!$A$3:$A$18,0),MATCH($I$2,'Headcount Phasing'!$B$2:$M$2,0))) -> 240702 | J18: =(_xlfn.XLOOKUP(B18,'Annual Employer Cost per Grade'!$C$2:$C$17,'Annual Employer Cost per Grade'!$U$2:$U$17,0,0))*(INDEX('Headcount Phasing'!$B$3:$M$18,MATCH(B18,'Headcount Phasing'!$A$3:$A$18,0),MATCH($J$2,'Headcount Phasing'!$B$2:$M$2,0))) -> 240702 | K18: =(_xlfn.XLOOKUP(B18,'Annual Employer Cost per Grade'!$C$2:$C$17,'Annual Employer Cost per Grade'!$U$2:$U$17,0,0))*(INDEX('Headcount Phasing'!$B$3:$M$18,MATCH(B18,'Headcount Phasing'!$A$3:$A$18,0),MATCH($K$2,'Headcount Phasing'!$B$2:$M$2,0))) -> 240702 | L18: =(_xlfn.XLOOKUP(B18,'Annual Employer Cost per Grade'!$C$2:$C$17,'Annual Employer Cost per Grade'!$U$2:$U$17,0,0))*(INDEX('Headcount Phasing'!$B$3:$M$18,MATCH(B18,'Headcount Phasing'!$A$3:$A$18,0),MATCH($L$2,'Headcount Phasing'!$B$2:$M$2,0))) -> 240702 | M18: =(_xlfn.XLOOKUP(B18,'Annual Employer Cost per Grade'!$C$2:$C$17,'Annual Employer Cost per Grade'!$U$2:$U$17,0,0))*(INDEX('Headcount Phasing'!$B$3:$M$18,MATCH(B18,'Headcount Phasing'!$A$3:$A$18,0),MATCH($M$2,'Headcount Phasing'!$B$2:$M$2,0))) -> 240702 | N18: =(_xlfn.XLOOKUP(B18,'Annual Employer Cost per Grade'!$C$2:$C$17,'Annual Employer Cost per Grade'!$U$2:$U$17,0,0))*(INDEX('Headcount Phasing'!$B$3:$M$18,MATCH(B18,'Headcount Phasing'!$A$3:$A$18,0),MATCH($N$2,'Headcount Phasing'!$B$2:$M$2,0))) -> 240702 | O18: =SUM(C18:N18) -> 2166318
B19: Total | C19: =SUM(C3:C18) -> 0 | D19: =SUM(D3:D18) -> 0 | E19: =SUM(E3:E18) -> 6418849.8 | F19: =SUM(F3:F18) -> 15152263 | G19: =SUM(G3:G18) -> 15582636 | H19: =SUM(H3:H18) -> 15582636 | I19: =SUM(I3:I18) -> 15582636 | J19: =SUM(J3:J18) -> 15582636 | ... O19: =SUM(O3:O18) -> 1.462322e+08
M29: reduction
L30: 2.3501734e+08 | M30: =L30-O19 -> 88785135
M31: =(L30-O19)/L30 -> 0.37778122

Sheet Headcount Phasing
A2: Grade | B2: Jan | C2: Feb | D2: Mar | E2: Apr | F2: May | G2: Jun | H2: Jul | I2: Aug | J2: Sep | K2: Oct | L2: Nov | M2: Dec | N2: Total Number of Months
A3: Managing Director | B3: 0 | C3: 0 | D3: 1 | E3: 1 | F3: 1 | G3: 1 | H3: 1 | I3: 1 | J3: 1 | K3: 1 | L3: 1 | M3: 1 | N3: 10
A4: Director of Programs | B4: 0 | C4: 0 | D4: 0 | E4: 1 | F4: 1 | G4: 1 | H4: 1 | I4: 1 | J4: 1 | K4: 1 | L4: 1 | M4: 1 | N4: 9
A5: IT Manager | B5: 0 | C5: 0 | D5: 0 | E5: 1 | F5: 1 | G5: 1 | H5: 1 | I5: 1 | J5: 1 | K5: 1 | L5: 1 | M5: 1 | N5: 9
A6: Community Manager | B6: 0 | C6: 0 | D6: 0 | E6: 1 | F6: 1 | G6: 1 | H6: 1 | I6: 1 | J6: 1 | K6: 1 | L6: 1 | M6: 1 | N6: 9
A7: Facility Associate | B7: 0 | C7: 0 | D7: 0 | E7: 1 | F7: 1 | G7: 1 | H7: 1 | I7: 1 | J7: 1 | K7: 1 | L7: 1 | M7: 1 | N7: 9
A8: Front Desk Associate (x1) | B8: 0 | C8: 0 | D8: 0 | E8: 1 | F8: 1 | G8: 1 | H8: 1 | I8: 1 | J8: 1 | K8: 1 | L8: 1 | M8: 1 | N8: 9
A9: Front Desk Support (Tech Grade 1) | B9: 0 | C9: 0 | D9: 0 | E9: 1 | F9: 1 | G9: 1 | H9: 1 | I9: 1 | J9: 1 | K9: 1 | L9: 1 | M9: 1 | N9: 9
A10: Finance Associate | B10: 0 | C10: 0 | D10: 0 | E10: 1 | F10: 1 | G10: 1 | H10: 1 | I10: 1 | J10: 1 | K10: 1 | L10: 1 | M10: 1 | N10: 9
A11: Admin & HR Associate | B11: 0 | C11: 0 | D11: 0 | E11: 1 | F11: 1 | G11: 1 | H11: 1 | I11: 1 | J11: 1 | K11: 1 | L11: 1 | M11: 1 | N11: 9
A12: IT Support Associate (x2) | B12: 0 | C12: 0 | D12: 0 | E12: 1 | F12: 1 | G12: 1 | H12: 1 | I12: 1 | J12: 1 | K12: 1 | L12: 1 | M12: 1 | N12: 9
A13: Content & Digital Marketing Lead | B13: 0 | C13: 0 | D13: 0 | E13: 1 | F13: 1 | G13: 1 | H13: 1 | I13: 1 | J13: 1 | K13: 1 | L13: 1 | M13: 1 | N13: 9
A14: Graphic & Multimedia Associate | B14: 0 | C14: 0 | D14: 0 | E14: 1 | F14: 1 | G14: 1 | H14: 1 | I14: 1 | J14: 1 | K14: 1 | L14: 1 | M14: 1 | N14: 9
... A18: Student Intern (x3) | B18: 0 | C18: 0 | D18: 0 | E18: 3 | F18: 3 | G18: 3 | H18: 3 | I18: 3 | J18: 3 | K18: 3 | L18: 3 | M18: 3 | N18: 10

Sheet Annual Cost Summary
A1: S/N | B1: Job Role | C1: Headcount | D1: Unit HC | E1: Total Annual Gross | F1: Total Leave Allowance | G1: Total 13th Month | H1: Total Bonus Pot | I1: Telephone | J1: Airtime | K1: Mobile Data Plan | L1: Total Cafeteria Subsidy | M1: Total Health Insurance | N1: Employer Pension Contr. | O1: Group Life Insurance Premium Cost | P1: ITF Cost | Q1: NSITF (ECS) | R1: Annual Employer Cost | T1: Monthly Employer Cost | U1: Total Nos. of Months | V1: Total Cost For 2025 | Z1: Range
A2: 1 | B2: Managing Director | C2: 1 | D2: 1 | E2: ='Annual Employer Cost per Grade'!F2*D2 -> 57120000 | F2: ='Annual Employer Cost per Grade'!G2*'Annual Cost Summary'!D2 -> 3998400 | G2: ='Annual Employer Cost per Grade'!H2*'Annual Cost Summary'!D2 -> 3998400 | H2: ='Annual Employer Cost per Grade'!I2*'Annual Cost Summary'!D2 -> 0 | I2: ='Annual Employer Cost per Grade'!J2*'Annual Cost Summary'!D2 -> 200000 | J2: ='Annual Employer Cost per Grade'!K2*'Annual Cost Summary'!D2 -> 300000 | K2: ='Annual Employer Cost per Grade'!L2*'Annual Cost Summary'!D2 -> 0 | L2: ='Annual Employer Cost per Grade'!M2*'Annual Cost Summary'!D2 -> 312000 | M2: ='Annual Employer Cost per Grade'!N2*'Annual Cost Summary'!D2 -> 954720 | N2: ='Annual Employer Cost per Grade'!O2*'Annual Cost Summary'!D2 -> 5140800 | O2: ='Annual Employer Cost per Grade'!P2*'Annual Cost Summary'!D2 -> 925344 | P2: ='Annual Employer Cost per Grade'!Q2*'Annual Cost Summary'!D2 -> 651168 | Q2: ='Annual Employer Cost per Grade'!R2*'Annual Cost Summary'!D2 -> 651168 | R2: =SUM(E2:Q2) -> 74252000 | T2: =R2/12 -> 6187666.7 | U2: =VLOOKUP(B2,'Headcount Phasing'!$A$3:$N$18,14,FALSE) -> 10 | V2: =U2*T2 -> 61876667 | Z2: G4
A3: =A2+1 -> 2 | B3: Director of Programs | C3: 1 | D3: 1 | E3: ='Annual Employer Cost per Grade'!F3*D3 -> 32520000 | F3: ='Annual Employer Cost per Grade'!G3*'Annual Cost Summary'!D3 -> 2276400 | G3: ='Annual Employer Cost per Grade'!H3*'Annual Cost Summary'!D3 -> 2276400 | H3: ='Annual Employer Cost per Grade'!I3*'Annual Cost Summary'!D3 -> 0 | I3: ='Annual Employer Cost per Grade'!J3*'Annual Cost Summary'!D3 -> 200000 | J3: ='Annual Employer Cost per Grade'!K3*'Annual Cost Summary'!D3 -> 300000 | K3: ='Annual Employer Cost per Grade'!L3*'Annual Cost Summary'!D3 -> 0 | L3: ='Annual Employer Cost per Grade'!M3*'Annual Cost Summary'!D3 -> 312000 | M3: ='Annual Employer Cost per Grade'!N3*'Annual Cost Summary'!D3 -> 585975 | N3: ='Annual Employer Cost per Grade'!O3*'Annual Cost Summary'!D3 -> 2926800 | O3: ='Annual Employer Cost per Grade'!P3*'Annual Cost Summary'!D3 -> 526824 | P3: ='Annual Employer Cost per Grade'!Q3*'Annual Cost Summary'!D3 -> 370728 | Q3: ='Annual Employer Cost per Grade'!R3*'Annual Cost Summary'!D3 -> 370728 | R3: =SUM(E3:Q3) -> 42665855 | T3: =R3/12 -> 3555487.9 | U3: =VLOOKUP(B3,'Headcount Phasing'!$A$3:$N$18,14,FALSE) -> 9 | V3: =U3*T3 -> 31999391 | Z3: G5
A4: =A3+1 -> 3 | B4: IT Manager | C4: 1 | D4: 1 | E4: ='Annual Employer Cost per Grade'!F4*D4 -> 6660000 | F4: ='Annual Employer Cost per Grade'!G4*'Annual Cost Summary'!D4 -> 466200 | G4: ='Annual Employer Cost per Grade'!H4*'Annual Cost Summary'!D4 -> 466200 | H4: ='Annual Employer Cost per Grade'!I4*'Annual Cost Summary'!D4 -> 0 | I4: ='Annual Employer Cost per Grade'!J4*'Annual Cost Summary'!D4 -> 150000 | J4: ='Annual Employer Cost per Grade'!K4*'Annual Cost Summary'!D4 -> 180000 | K4: ='Annual Employer Cost per Grade'!L4*'Annual Cost Summary'!D4 -> 0 | L4: ='Annual Employer Cost per Grade'!M4*'Annual Cost Summary'!D4 -> 312000 | M4: ='Annual Employer Cost per Grade'!N4*'Annual Cost Summary'!D4 -> 254826 | N4: ='Annual Employer Cost per Grade'!O4*'Annual Cost Summary'!D4 -> 599400 | O4: ='Annual Employer Cost per Grade'!P4*'Annual Cost Summary'!D4 -> 107892 | P4: ='Annual Employer Cost per Grade'!Q4*'Annual Cost Summary'!D4 -> 75924 | Q4: ='Annual Employer Cost per Grade'!R4*'Annual Cost Summary'!D4 -> 75924 | R4: =SUM(E4:Q4) -> 9348366 | T4: =R4/12 -> 779030.5 | U4: =VLOOKUP(B4,'Headcount Phasing'!$A$3:$N$18,14,FALSE) -> 9 | V4: =U4*T4 -> 7011274.5 | Z4: G6
A5: =A4+1 -> 4 | B5: Community Manager | C5: 1 | D5: 1 | E5: ='Annual Employer Cost per Grade'!F5*D5 -> 3780000 | F5: ='Annual Employer Cost per Grade'!G5*'Annual Cost Summary'!D5 -> 264600 | G5: ='Annual Employer Cost per Grade'!H5*'Annual Cost Summary'!D5 -> 264600 | H5: ='Annual Employer Cost per Grade'!I5*'Annual Cost Summary'!D5 -> 0 | I5: ='Annual Employer Cost per Grade'!J5*'Annual Cost Summary'!D5 -> 150000 | J5: ='Annual Employer Cost per Grade'!K5*'Annual Cost Summary'!D5 -> 180000 | K5: ='Annual Employer Cost per Grade'!L5*'Annual Cost Summary'!D5 -> 0 | L5: ='Annual Employer Cost per Grade'!M5*'Annual Cost Summary'!D5 -> 312000 | M5: ='Annual Employer Cost per Grade'!N5*'Annual Cost Summary'!D5 -> 254826 | N5: ='Annual Employer Cost per Grade'!O5*'Annual Cost Summary'!D5 -> 340200 | O5: ='Annual Employer Cost per Grade'!P5*'Annual Cost Summary'!D5 -> 61236 | P5: ='Annual Employer Cost per Grade'!Q5*'Annual Cost Summary'!D5 -> 43092 | Q5: ='Annual Employer Cost per Grade'!R5*'Annual Cost Summary'!D5 -> 43092 | R5: =SUM(E5:Q5) -> 5693646 | T5: =R5/12 -> 474470.5 | U5: =VLOOKUP(B5,'Headcount Phasing'!$A$3:$N$18,14,FALSE) -> 9 | V5: =U5*T5 -> 4270234.5 | Z5: G7
A6: =A5+1 -> 5 | B6: Facility Associate | C6: 1 | D6: 1 | E6: ='Annual Employer Cost per Grade'!F6*D6 -> 3780000 | F6: ='Annual Employer Cost per Grade'!G6*'Annual Cost Summary'!D6 -> 264600 | G6: ='Annual Employer Cost per Grade'!H6*'Annual Cost Summary'!D6 -> 264600 | H6: ='Annual Employer Cost per Grade'!I6*'Annual Cost Summary'!D6 -> 0 | I6: ='Annual Employer Cost per Grade'!J6*'Annual Cost Summary'!D6 -> 150000 | J6: ='Annual Employer Cost per Grade'!K6*'Annual Cost Summary'!D6 -> 90000 | K6: ='Annual Employer Cost per Grade'!L6*'Annual Cost Summary'!D6 -> 0 | L6: ='Annual Employer Cost per Grade'!M6*'Annual Cost Summary'!D6 -> 312000 | M6: ='Annual Employer Cost per Grade'!N6*'Annual Cost Summary'!D6 -> 147790.5 | N6: ='Annual Employer Cost per Grade'!O6*'Annual Cost Summary'!D6 -> 340200 | O6: ='Annual Employer Cost per Grade'!P6*'Annual Cost Summary'!D6 -> 61236 | P6: ='Annual Employer Cost per Grade'!Q6*'Annual Cost Summary'!D6 -> 43092 | Q6: ='Annual Employer Cost per Grade'!R6*'Annual Cost Summary'!D6 -> 43092 | R6: =SUM(E6:Q6) -> 5496610.5 | T6: =R6/12 -> 458050.88 | U6: =VLOOKUP(B6,'Headcount Phasing'!$A$3:$N$18,14,FALSE) -> 9 | V6: =U6*T6 -> 4122457.9 | Z6: G8
A7: =A6+1 -> 6 | B7: Front Desk Associate (x2) | C7: 2 | D7: 1 | E7: ='Annual Employer Cost per Grade'!F7*D7 -> 3780000 | F7: ='Annual Employer Cost per Grade'!G7*'Annual Cost Summary'!D7 -> 264600 | G7: ='Annual Employer Cost per Grade'!H7*'Annual Cost Summary'!D7 -> 264600 | H7: ='Annual Employer Cost per Grade'!I7*'Annual Cost Summary'!D7 -> 0 | I7: ='Annual Employer Cost per Grade'!J7*'Annual Cost Summary'!D7 -> 150000 | J7: ='Annual Employer Cost per Grade'!K7*'Annual Cost Summary'!D7 -> 90000 | K7: ='Annual Employer Cost per Grade'!L7*'Annual Cost Summary'!D7 -> 0 | L7: ='Annual Employer Cost per Grade'!M7*'Annual Cost Summary'!D7 -> 312000 | M7: ='Annual Employer Cost per Grade'!N7*'Annual Cost Summary'!D7 -> 147790.5 | N7: ='Annual Employer Cost per Grade'!O7*'Annual Cost Summary'!D7 -> 340200 | O7: ='Annual Employer Cost per Grade'!P7*'Annual Cost Summary'!D7 -> 61236 | P7: ='Annual Employer Cost per Grade'!Q7*'Annual Cost Summary'!D7 -> 43092 | Q7: ='Annual Employer Cost per Grade'!R7*'Annual Cost Summary'!D7 -> 43092 | R7: =SUM(E7:Q7) -> 5496610.5 | T7: =R7/12 -> 458050.88 | V7: =((T7*7))+((T7*9)) -> 7328814 | Y7: =T7*7 -> 3206356.1 | Z7: G7
A8: =A7+1 -> 7 | B8: Finance Associate | C8: 1 | D8: 1 | E8: ='Annual Employer Cost per Grade'!F9*D8 -> 3780000 | F8: ='Annual Employer Cost per Grade'!G9*'Annual Cost Summary'!D8 -> 264600 | G8: ='Annual Employer Cost per Grade'!H9*'Annual Cost Summary'!D8 -> 264600 | H8: ='Annual Employer Cost per Grade'!I9*'Annual Cost Summary'!D8 -> 0 | I8: ='Annual Employer Cost per Grade'!J9*'Annual Cost Summary'!D8 -> 150000 | J8: ='Annual Employer Cost per Grade'!K9*'Annual Cost Summary'!D8 -> 90000 | K8: ='Annual Employer Cost per Grade'!L9*'Annual Cost Summary'!D8 -> 0 | L8: ='Annual Employer Cost per Grade'!M9*'Annual Cost Summary'!D8 -> 312000 | M8: ='Annual Employer Cost per Grade'!N9*'Annual Cost Summary'!D8 -> 147790.5 | N8: ='Annual Employer Cost per Grade'!O9*'Annual Cost Summary'!D8 -> 340200 | O8: ='Annual Employer Cost per Grade'!P9*'Annual Cost Summary'!D8 -> 61236 | P8: ='Annual Employer Cost per Grade'!Q9*'Annual Cost Summary'!D8 -> 43092 | Q8: ='Annual Employer Cost per Grade'!R9*'Annual Cost Summary'!D8 -> 43092 | R8: =SUM(E8:Q8) -> 5496610.5 | T8: =R8/12 -> 458050.88 | U8: =VLOOKUP(B8,'Headcount Phasing'!$A$3:$N$18,14,FALSE) -> 9 | V8: =U8*T8 -> 4122457.9 | Z8: G8
A9: =A8+1 -> 8 | B9: Admin & HR Associate | C9: 1 | D9: 1 | E9: ='Annual Employer Cost per Grade'!F10*D9 -> 3780000 | F9: ='Annual Employer Cost per Grade'!G10*'Annual Cost Summary'!D9 -> 264600 | G9: ='Annual Employer Cost per Grade'!H10*'Annual Cost Summary'!D9 -> 264600 | H9: ='Annual Employer Cost per Grade'!I10*'Annual Cost Summary'!D9 -> 0 | I9: ='Annual Employer Cost per Grade'!J10*'Annual Cost Summary'!D9 -> 150000 | J9: ='Annual Employer Cost per Grade'!K10*'Annual Cost Summary'!D9 -> 90000 | K9: ='Annual Employer Cost per Grade'!L10*'Annual Cost Summary'!D9 -> 0 | L9: ='Annual Employer Cost per Grade'!M10*'Annual Cost Summary'!D9 -> 312000 | M9: ='Annual Employer Cost per Grade'!N10*'Annual Cost Summary'!D9 -> 147790.5 | N9: ='Annual Employer Cost per Grade'!O10*'Annual Cost Summary'!D9 -> 340200 | O9: ='Annual Employer Cost per Grade'!P10*'Annual Cost Summary'!D9 -> 61236 | P9: ='Annual Employer Cost per Grade'!Q10*'Annual Cost Summary'!D9 -> 43092 | Q9: ='Annual Employer Cost per Grade'!R10*'Annual Cost Summary'!D9 -> 43092 | R9: =SUM(E9:Q9) -> 5496610.5 | T9: =R9/12 -> 458050.88 | U9: =VLOOKUP(B9,'Headcount Phasing'!$A$3:$N$18,14,FALSE) -> 9 | V9: =U9*T9 -> 4122457.9 | Z9: G8
A10: =A9+1 -> 9 | B10: IT Support Associate (x2) | C10: 1 | D10: 1 | E10: ='Annual Employer Cost per Grade'!F11*D10 -> 3780000 | F10: ='Annual Employer Cost per Grade'!G11*'Annual Cost Summary'!D10 -> 264600 | G10: ='Annual Employer Cost per Grade'!H11*'Annual Cost Summary'!D10 -> 264600 | H10: ='Annual Employer Cost per Grade'!I11*'Annual Cost Summary'!D10 -> 0 | I10: ='Annual Employer Cost per Grade'!J11*'Annual Cost Summary'!D10 -> 150000 | J10: ='Annual Employer Cost per Grade'!K11*'Annual Cost Summary'!D10 -> 90000 | K10: ='Annual Employer Cost per Grade'!L11*'Annual Cost Summary'!D10 -> 0 | L10: ='Annual Employer Cost per Grade'!M11*'Annual Cost Summary'!D10 -> 312000 | M10: ='Annual Employer Cost per Grade'!N11*'Annual Cost Summary'!D10 -> 147790.5 | N10: ='Annual Employer Cost per Grade'!O11*'Annual Cost Summary'!D10 -> 340200 | O10: ='Annual Employer Cost per Grade'!P11*'Annual Cost Summary'!D10 -> 61236 | P10: ='Annual Employer Cost per Grade'!Q11*'Annual Cost Summary'!D10 -> 43092 | Q10: ='Annual Employer Cost per Grade'!R11*'Annual Cost Summary'!D10 -> 43092 | R10: =SUM(E10:Q10) -> 5496610.5 | T10: =R10/12 -> 458050.88 | U10: =VLOOKUP(B10,'Headcount Phasing'!$A$3:$N$18,14,FALSE) -> 9 | V10: =U10*T10 -> 4122457.9 | Z10: G7
A11: =A10+1 -> 10 | B11: Content & Digital Marketing Lead | C11: 1 | D11: 1 | E11: ='Annual Employer Cost per Grade'!F12*D11 -> 3780000 | F11: ='Annual Employer Cost per Grade'!G12*'Annual Cost Summary'!D11 -> 264600 | G11: ='Annual Employer Cost per Grade'!H12*'Annual Cost Summary'!D11 -> 264600 | H11: ='Annual Employer Cost per Grade'!I12*'Annual Cost Summary'!D11 -> 0 | I11: ='Annual Employer Cost per Grade'!J12*'Annual Cost Summary'!D11 -> 150000 | J11: ='Annual Employer Cost per Grade'!K12*'Annual Cost Summary'!D11 -> 180000 | K11: ='Annual Employer Cost per Grade'!L12*'Annual Cost Summary'!D11 -> 0 | L11: ='Annual Employer Cost per Grade'!M12*'Annual Cost Summary'!D11 -> 312000 | M11: ='Annual Employer Cost per Grade'!N12*'Annual Cost Summary'!D11 -> 147790.5 | N11: ='Annual Employer Cost per Grade'!O12*'Annual Cost Summary'!D11 -> 340200 | O11: ='Annual Employer Cost per Grade'!P12*'Annual Cost Summary'!D11 -> 61236 | P11: ='Annual Employer Cost per Grade'!Q12*'Annual Cost Summary'!D11 -> 43092 | Q11: ='Annual Employer Cost per Grade'!R12*'Annual Cost Summary'!D11 -> 43092 | R11: =SUM(E11:Q11) -> 5586610.5 | T11: =R11/12 -> 465550.88 | U11: =VLOOKUP(B11,'Headcount Phasing'!$A$3:$N$18,14,FALSE) -> 9 | V11: =U11*T11 -> 4189957.9 | Z11: G7
A12: =A11+1 -> 11 | B12: Graphic & Multimedia Associate | C12: 1 | D12: 1 | E12: ='Annual Employer Cost per Grade'!F13*D12 -> 3780000 | F12: ='Annual Employer Cost per Grade'!G13*'Annual Cost Summary'!D12 -> 264600 | G12: ='Annual Employer Cost per Grade'!H13*'Annual Cost Summary'!D12 -> 264600 | H12: ='Annual Employer Cost per Grade'!I13*'Annual Cost Summary'!D12 -> 0 | I12: ='Annual Employer Cost per Grade'!J13*'Annual Cost Summary'!D12 -> 150000 | J12: ='Annual Employer Cost per Grade'!K13*'Annual Cost Summary'!D12 -> 180000 | K12: ='Annual Employer Cost per Grade'!L13*'Annual Cost Summary'!D12 -> 0 | L12: ='Annual Employer Cost per Grade'!M13*'Annual Cost Summary'!D12 -> 312000 | M12: ='Annual Employer Cost per Grade'!N13*'Annual Cost Summary'!D12 -> 147790.5 | N12: ='Annual Employer Cost per Grade'!O13*'Annual Cost Summary'!D12 -> 340200 | O12: ='Annual Employer Cost per Grade'!P13*'Annual Cost Summary'!D12 -> 61236 | P12: ='Annual Employer Cost per Grade'!Q13*'Annual Cost Summary'!D12 -> 43092 | Q12: ='Annual Employer Cost per Grade'!R13*'Annual Cost Summary'!D12 -> 43092 | R12: =SUM(E12:Q12) -> 5586610.5 | T12: =R12/12 -> 465550.88 | U12: =VLOOKUP(B12,'Headcount Phasing'!$A$3:$N$18,14,FALSE) -> 9 | V12: =U12*T12 -> 4189957.9 | Z12: G7
A13: =A12+1 -> 12 | B13: Facility Technician (x3) | C13: 1 | D13: 1 | E13: ='Annual Employer Cost per Grade'!F14*D13 -> 1800000 | F13: ='Annual Employer Cost per Grade'!G14*'Annual Cost Summary'!D13 -> 126000 | G13: ='Annual Employer Cost per Grade'!H14*'Annual Cost Summary'!D13 -> 126000 | H13: ='Annual Employer Cost per Grade'!I14*'Annual Cost Summary'!D13 -> 0 | I13: ='Annual Employer Cost per Grade'!J14*'Annual Cost Summary'!D13 -> 25000 | J13: ='Annual Employer Cost per Grade'!K14*'Annual Cost Summary'!D13 -> 48000 | K13: ='Annual Employer Cost per Grade'!L14*'Annual Cost Summary'!D13 -> 0 | L13: ='Annual Employer Cost per Grade'!M14*'Annual Cost Summary'!D13 -> 312000 | M13: ='Annual Employer Cost per Grade'!N14*'Annual Cost Summary'!D13 -> 104997.75 | N13: ='Annual Employer Cost per Grade'!O14*'Annual Cost Summary'!D13 -> 162000 | O13: ='Annual Employer Cost per Grade'!P14*'Annual Cost Summary'!D13 -> 29160 | P13: ='Annual Employer Cost per Grade'!Q14*'Annual Cost Summary'!D13 -> 20520 | Q13: ='Annual Employer Cost per Grade'!R14*'Annual Cost Summary'!D13 -> 20520 | R13: =SUM(E13:Q13) -> 2774197.8 | T13: =R13/12 -> 231183.15 | V13: =((T13*10)+((T13)*(1))) -> 2543014.6 | Z13: G9
A14: =A13+1 -> 13 | B14: Driver | C14: 1 | D14: 1 | E14: ='Annual Employer Cost per Grade'!F15*D14 -> 1800000 | F14: ='Annual Employer Cost per Grade'!G15*'Annual Cost Summary'!D14 -> 126000 | G14: ='Annual Employer Cost per Grade'!H15*'Annual Cost Summary'!D14 -> 126000 | H14: ='Annual Employer Cost per Grade'!I15*'Annual Cost Summary'!D14 -> 0 | I14: ='Annual Employer Cost per Grade'!J15*'Annual Cost Summary'!D14 -> 25000 | J14: ='Annual Employer Cost per Grade'!K15*'Annual Cost Summary'!D14 -> 48000 | K14: ='Annual Employer Cost per Grade'!L15*'Annual Cost Summary'!D14 -> 0 | L14: ='Annual Employer Cost per Grade'!M15*'Annual Cost Summary'!D14 -> 312000 | M14: ='Annual Employer Cost per Grade'!N15*'Annual Cost Summary'!D14 -> 104997.75 | N14: ='Annual Employer Cost per Grade'!O15*'Annual Cost Summary'!D14 -> 162000 | O14: ='Annual Employer Cost per Grade'!P15*'Annual Cost Summary'!D14 -> 29160 | P14: ='Annual Employer Cost per Grade'!Q15*'Annual Cost Summary'!D14 -> 20520 | Q14: ='Annual Employer Cost per Grade'!R15*'Annual Cost Summary'!D14 -> 20520 | R14: =SUM(E14:Q14) -> 2774197.8 | T14: =R14/12 -> 231183.15 | U14: =VLOOKUP(B14,'Headcount Phasing'!$A$3:$N$18,14,FALSE) -> 10 | V14: =((T14)*10)+((T14)*(8)) -> 4161296.6 | Z14: G7
A15: =A14+1 -> 14 | B15: Intern (x2) | C15: 2 | D15: 1 | E15: ='Annual Employer Cost per Grade'!F16*D15 -> 660000 | F15: ='Annual Employer Cost per Grade'!G16*'Annual Cost Summary'!D15 -> 46200 | G15: ='Annual Employer Cost per Grade'!H16*'Annual Cost Summary'!D15 -> 46200 | H15: ='Annual Employer Cost per Grade'!I16*'Annual Cost Summary'!D15 -> 0 | I15: ='Annual Employer Cost per Grade'!J16*'Annual Cost Summary'!D15 -> 0 | J15: ='Annual Employer Cost per Grade'!K16*'Annual Cost Summary'!D15 -> 0 | K15: ='Annual Employer Cost per Grade'!L16*'Annual Cost Summary'!D15 -> 0 | L15: ='Annual Employer Cost per Grade'!M16*'Annual Cost Summary'!D15 -> 312000 | M15: ='Annual Employer Cost per Grade'!N16*'Annual Cost Summary'!D15 -> 104997.75 | N15: ='Annual Employer Cost per Grade'!O16*'Annual Cost Summary'!D15 -> 0 | O15: ='Annual Employer Cost per Grade'!P16*'Annual Cost Summary'!D15 -> 10692 | P15: ='Annual Employer Cost per Grade'!Q16*'Annual Cost Summary'!D15 -> 7524 | Q15: ='Annual Employer Cost per Grade'!R16*'Annual Cost Summary'!D15 -> 7524 | R15: =SUM(E15:Q15) -> 1195137.8 | T15: =R15/12 -> 99594.812 | U15: =VLOOKUP(B15,'Headcount Phasing'!$A$3:$N$18,14,FALSE) -> #N/A | V15: =((T15)*(10))+((T15)*(9)) -> 1892301.4 | Z15: G7
A16: =A15+1 -> 15 | B16: Intern (x3) | C16: 3 | D16: 1 | E16: ='Annual Employer Cost per Grade'!F17*D16 -> 552000 | F16: ='Annual Employer Cost per Grade'!G17*'Annual Cost Summary'!D16 -> 38640 | G16: ='Annual Employer Cost per Grade'!H17*'Annual Cost Summary'!D16 -> 38640 | H16: ='Annual Employer Cost per Grade'!I17*'Annual Cost Summary'!D16 -> 0 | I16: ='Annual Employer Cost per Grade'!J17*'Annual Cost Summary'!D16 -> 0 | J16: ='Annual Employer Cost per Grade'!K17*'Annual Cost Summary'!D16 -> 0 | K16: ='Annual Employer Cost per Grade'!L17*'Annual Cost Summary'!D16 -> 0 | L16: ='Annual Employer Cost per Grade'!M17*'Annual Cost Summary'!D16 -> 312000 | M16: ='Annual Employer Cost per Grade'!N17*'Annual Cost Summary'!D16 -> 0 | N16: ='Annual Employer Cost per Grade'!O17*'Annual Cost Summary'!D16 -> 0 | O16: ='Annual Employer Cost per Grade'!P17*'Annual Cost Summary'!D16 -> 8942.4 | P16: ='Annual Employer Cost per Grade'!Q17*'Annual Cost Summary'!D16 -> 6292.8 | Q16: ='Annual Employer Cost per Grade'!R17*'Annual Cost Summary'!D16 -> 6292.8 | R16: =SUM(E16:Q16) -> 962808 | T16: =R16/12 -> 80234 | V16: =((T16*10))+(((T16)*(18))) -> 2246552 | Z16: G7
B17: Total | D17: =SUM(D2:D16) -> 15 | E17: =SUM(E2:E16) -> 131352000 | F17: =SUM(F2:F16) -> 9194640 | G17: =SUM(G2:G16) -> 9194640 | H17: =SUM(H2:H16) -> 0 | I17: =SUM(I2:I16) -> 1800000 | J17: =SUM(J2:J16) -> 1866000 | K17: =SUM(K2:K16) -> 0 | ... R17: =SUM(R2:R16) -> 1.7832248e+08 | T17: =SUM(T2:T16) -> 14860207 | V17: =SUM(V2:V16) -> 1.4819929e+08

Sheet Annual Employer Cost per Grade
A1: S/N | B1: Grade | C1: Role | D1: Monthly Gross Salary | F1: Annual Gross Salary | G1: Annual Leave Allowance | H1: 13th Month | I1: Annual Bonus (Tentative) | J1: Telephone Cost One off | K1: Airtime | L1: Mobile Data Plan | M1: Total Cafeteria Subsidy | N1: HMO (Health Insurance) | O1: Employer Pension Contribution | P1: Group Life Insurance Premium Cost | Q1: ITF Cost | R1: NSITF (ECS) | S1: Annual Employer Cost | U1: Monthly Employer Cost | Y1: Range @100% | Z1: Range @75%
A2: 1 | B2: ='Payroll breakdown per role'!D3 -> A1 | C2: ='Payroll breakdown per role'!B3 -> Managing Director | D2: ='Payroll breakdown per role'!F3 -> 4760000 | F2: =D2*12 -> 57120000 | G2: =(F2*70%)*10% -> 3998400 | H2: =(F2*70%)*10% -> 3998400 | J2: 200000 | K2: =25000*12 -> 300000 | L2: 0 | M2: =1200*260 -> 312000 | N2: 954720 | O2: =(90%*F2)*(10%) -> 5140800 | P2: =(6/1000)*((F2*90%)*3) -> 925344 | Q2: =1%*(I2+F2+G2+H2) -> 651168 | R2: =1%*(I2+F2+G2+H2) -> 651168 | S2: =SUM(F2:R2) -> 74252000 | U2: =S2/12 -> 6187666.7 | X2: G4 | Y2: 70m | Z2: 53m
A3: =A2+1 -> 2 | B3: ='Payroll breakdown per role'!D4 -> B1 | C3: ='Payroll breakdown per role'!B4 -> Director of Programs | D3: ='Payroll breakdown per role'!F4 -> 2710000 | F3: =D3*12 -> 32520000 | G3: =(F3*70%)*10% -> 2276400 | H3: =(F3*70%)*10% -> 2276400 | J3: 200000 | K3: =25000*12 -> 300000 | L3: 0 | M3: =1200*260 -> 312000 | N3: 585975 | O3: =(90%*F3)*(10%) -> 2926800 | P3: =(6/1000)*((F3*90%)*3) -> 526824 | Q3: =1%*(I3+F3+G3+H3) -> 370728 | R3: =1%*(I3+F3+G3+H3) -> 370728 | S3: =SUM(F3:R3) -> 42665855 | U3: =S3/12 -> 3555487.9 | X3: G5 | Y3: 47m | Z3: 35m
A4: =A3+1 -> 3 | B4: ='Payroll breakdown per role'!D5 -> G1 | C4: ='Payroll breakdown per role'!B5 -> IT Manager | D4: ='Payroll breakdown per role'!F5 -> 555000 | F4: =D4*12 -> 6660000 | G4: =(F4*70%)*10% -> 466200 | H4: =(F4*70%)*10% -> 466200 | J4: 150000 | K4: =15000*12 -> 180000 | L4: 0 | M4: =1200*260 -> 312000 | N4: 254826 | O4: =(90%*F4)*(10%) -> 599400 | P4: =(6/1000)*((F4*90%)*3) -> 107892 | Q4: =1%*(I4+F4+G4+H4) -> 75924 | R4: =1%*(I4+F4+G4+H4) -> 75924 | S4: =SUM(F4:R4) -> 9348366 | U4: =S4/12 -> 779030.5 | X4: G8 | Y4: 13m | Z4: 10.6m
A5: =A4+1 -> 4 | B5: ='Payroll breakdown per role'!D6 -> H1 | C5: ='Payroll breakdown per role'!B6 -> Community Manager | D5: ='Payroll breakdown per role'!F6 -> 315000 | F5: =D5*12 -> 3780000 | G5: =(F5*70%)*10% -> 264600 | H5: =(F5*70%)*10% -> 264600 | J5: 150000 | K5: =15000*12 -> 180000 | L5: 0 | M5: =1200*260 -> 312000 | N5: 254826 | O5: =(90%*F5)*(10%) -> 340200 | P5: =(6/1000)*((F5*90%)*3) -> 61236 | Q5: =1%*(I5+F5+G5+H5) -> 43092 | R5: =1%*(I5+F5+G5+H5) -> 43092 | S5: =SUM(F5:R5) -> 5693646 | U5: =S5/12 -> 474470.5 | X5: G8 | Y5: 13m | Z5: 10.6m
A6: =A5+1 -> 5 | B6: ='Payroll breakdown per role'!D7 -> H1 | C6: ='Payroll breakdown per role'!B7 -> Facility Associate | D6: ='Payroll breakdown per role'!F7 -> 315000 | F6: =D6*12 -> 3780000 | G6: =(F6*70%)*10% -> 264600 | H6: =(F6*70%)*10% -> 264600 | J6: 150000 | K6: =7500*12 -> 90000 | L6: 0 | M6: =1200*260 -> 312000 | N6: 147790.5 | O6: =(90%*F6)*(10%) -> 340200 | P6: =(6/1000)*((F6*90%)*3) -> 61236 | Q6: =1%*(I6+F6+G6+H6) -> 43092 | R6: =1%*(I6+F6+G6+H6) -> 43092 | S6: =SUM(F6:R6) -> 5496610.5 | U6: =S6/12 -> 458050.88 | X6: G9 | Y6: 7.8m | Z6: 6.5m
A7: =A6+1 -> 6 | B7: ='Payroll breakdown per role'!D8 -> H1 | C7: ='Payroll breakdown per role'!B8 -> Front Desk Associate (x1) | D7: ='Payroll breakdown per role'!F8 -> 315000 | F7: =D7*12 -> 3780000 | G7: =(F7*70%)*10% -> 264600 | H7: =(F7*70%)*10% -> 264600 | J7: 150000 | K7: =7500*12 -> 90000 | L7: 0 | M7: =1200*260 -> 312000 | N7: 147790.5 | O7: =(90%*F7)*(10%) -> 340200 | P7: =(6/1000)*((F7*90%)*3) -> 61236 | Q7: =1%*(I7+F7+G7+H7) -> 43092 | R7: =1%*(I7+F7+G7+H7) -> 43092 | S7: =SUM(F7:R7) -> 5496610.5 | U7: =S7/12 -> 458050.88 | X7: G9 | Y7: 7.8m | Z7: 6.5m
B8: I1 | C8: Front Desk Support (Tech Grade 1) | D8: ='Payroll breakdown per role'!F9 -> 150000 | F8: =D8*12 -> 1800000 | G8: =(F8*70%)*10% -> 126000 | H8: =(F8*70%)*10% -> 126000 | J8: 25000 | K8: =4000*12 -> 48000 | L8: 0 | M8: =1200*260 -> 312000 | N8: 104997.75 | O8: =(90%*F8)*(10%) -> 162000 | P8: =(6/1000)*((F8*90%)*3) -> 29160 | Q8: =1%*(I8+F8+G8+H8) -> 20520 | R8: =1%*(I8+F8+G8+H8) -> 20520 | S8: =SUM(F8:R8) -> 2774197.8 | U8: =S8/12 -> 231183.15
A9: =A7+1 -> 7 | B9: ='Payroll breakdown per role'!D10 -> H1 | C9: ='Payroll breakdown per role'!B10 -> Finance Associate | D9: ='Payroll breakdown per role'!F10 -> 315000 | F9: =D9*12 -> 3780000 | G9: =(F9*70%)*10% -> 264600 | H9: =(F9*70%)*10% -> 264600 | J9: 150000 | K9: =7500*12 -> 90000 | L9: 0 | M9: =1200*260 -> 312000 | N9: 147790.5 | O9: =(90%*F9)*(10%) -> 340200 | P9: =(6/1000)*((F9*90%)*3) -> 61236 | Q9: =1%*(I9+F9+G9+H9) -> 43092 | R9: =1%*(I9+F9+G9+H9) -> 43092 | S9: =SUM(F9:R9) -> 5496610.5 | U9: =S9/12 -> 458050.88 | X9: G9 | Y9: 7.8m | Z9: 6.5m
A10: =A9+1 -> 8 | B10: ='Payroll breakdown per role'!D11 -> H1 | C10: ='Payroll breakdown per role'!B11 -> Admin & HR Associate | D10: ='Payroll breakdown per role'!F11 -> 315000 | F10: =D10*12 -> 3780000 | G10: =(F10*70%)*10% -> 264600 | H10: =(F10*70%)*10% -> 264600 | J10: 150000 | K10: =7500*12 -> 90000 | L10: 0 | M10: =1200*260 -> 312000 | N10: 147790.5 | O10: =(90%*F10)*(10%) -> 340200 | P10: =(6/1000)*((F10*90%)*3) -> 61236 | Q10: =1%*(I10+F10+G10+H10) -> 43092 | R10: =1%*(I10+F10+G10+H10) -> 43092 | S10: =SUM(F10:R10) -> 5496610.5 | U10: =S10/12 -> 458050.88 | X10: G9 | Y10: 7.8m | Z10: 6.5m
A11: =A10+1 -> 9 | B11: ='Payroll breakdown per role'!D12 -> H1 | C11: ='Payroll breakdown per role'!B12 -> IT Support Associate (x2) | D11: ='Payroll breakdown per role'!F12 -> 315000 | F11: =D11*12 -> 3780000 | G11: =(F11*70%)*10% -> 264600 | H11: =(F11*70%)*10% -> 264600 | J11: 150000 | K11: =7500*12 -> 90000 | L11: 0 | M11: =1200*260 -> 312000 | N11: 147790.5 | O11: =(90%*F11)*(10%) -> 340200 | P11: =(6/1000)*((F11*90%)*3) -> 61236 | Q11: =1%*(I11+F11+G11+H11) -> 43092 | R11: =1%*(I11+F11+G11+H11) -> 43092 | S11: =SUM(F11:R11) -> 5496610.5 | U11: =S11/12 -> 458050.88 | X11: G9 | Y11: 7.8m | Z11: 6.5m
A12: =A11+1 -> 10 | B12: ='Payroll breakdown per role'!D13 -> H1 | C12: ='Payroll breakdown per role'!B13 -> Content & Digital Marketing Lead | D12: ='Payroll breakdown per role'!F13 -> 315000 | F12: =D12*12 -> 3780000 | G12: =(F12*70%)*10% -> 264600 | H12: =(F12*70%)*10% -> 264600 | J12: 150000 | K12: =15000*12 -> 180000 | L12: 0 | M12: =1200*260 -> 312000 | N12: 147790.5 | O12: =(90%*F12)*(10%) -> 340200 | P12: =(6/1000)*((F12*90%)*3) -> 61236 | Q12: =1%*(I12+F12+G12+H12) -> 43092 | R12: =1%*(I12+F12+G12+H12) -> 43092 | S12: =SUM(F12:R12) -> 5586610.5 | U12: =S12/12 -> 465550.88 | X12: G9 | Y12: 7.8m | Z12: 6.5m
A13: =A12+1 -> 11 | B13: ='Payroll breakdown per role'!D14 -> H1 | C13: ='Payroll breakdown per role'!B14 -> Graphic & Multimedia Associate | D13: ='Payroll breakdown per role'!F14 -> 315000 | F13: =D13*12 -> 3780000 | G13: =(F13*70%)*10% -> 264600 | H13: =(F13*70%)*10% -> 264600 | J13: 150000 | K13: =15000*12 -> 180000 | L13: 0 | M13: =1200*260 -> 312000 | N13: 147790.5 | O13: =(90%*F13)*(10%) -> 340200 | P13: =(6/1000)*((F13*90%)*3) -> 61236 | Q13: =1%*(I13+F13+G13+H13) -> 43092 | R13: =1%*(I13+F13+G13+H13) -> 43092 | S13: =SUM(F13:R13) -> 5586610.5 | U13: =S13/12 -> 465550.88 | X13: G8 | Y13: 7.8m | Z13: 6.5m
A14: =A13+1 -> 12 | B14: ='Payroll breakdown per role'!D15 -> I1 | C14: ='Payroll breakdown per role'!B15 -> Facility Technician (x3) | D14: ='Payroll breakdown per role'!F15 -> 150000 | F14: =D14*12 -> 1800000 | G14: =(F14*70%)*10% -> 126000 | H14: =(F14*70%)*10% -> 126000 | J14: 25000 | K14: =4000*12 -> 48000 | L14: 0 | M14: =1200*260 -> 312000 | N14: 104997.75 | O14: =(90%*F14)*(10%) -> 162000 | P14: =(6/1000)*((F14*90%)*3) -> 29160 | Q14: =1%*(I14+F14+G14+H14) -> 20520 | R14: =1%*(I14+F14+G14+H14) -> 20520 | S14: =SUM(F14:R14) -> 2774197.8 | U14: =S14/12 -> 231183.15 | X14: G10 | Y14: 5.2m | Z14: 4.5m
A15: =A14+1 -> 13 | B15: ='Payroll breakdown per role'!D16 -> I1 | C15: ='Payroll breakdown per role'!B16 -> Driver | D15: ='Payroll breakdown per role'!F16 -> 150000 | F15: =D15*12 -> 1800000 | G15: =(F15*70%)*10% -> 126000 | H15: =(F15*70%)*10% -> 126000 | J15: 25000 | K15: =4000*12 -> 48000 | L15: 0 | M15: =1200*260 -> 312000 | N15: 104997.75 | O15: =(90%*F15)*(10%) -> 162000 | P15: =(6/1000)*((F15*90%)*3) -> 29160 | Q15: =1%*(I15+F15+G15+H15) -> 20520 | R15: =1%*(I15+F15+G15+H15) -> 20520 | S15: =SUM(F15:R15) -> 2774197.8 | U15: =S15/12 -> 231183.15 | X15: G10 | Y15: 5.2m | Z15: 4.5m
A16: =A15+1 -> 14 | B16: ='Payroll breakdown per role'!D17 -> J2 | C16: NYSC Intern (x3) | D16: ='Payroll breakdown per role'!F17 -> 55000 | F16: =D16*12 -> 660000 | G16: =(F16*70%)*10% -> 46200 | H16: =(F16*70%)*10% -> 46200 | M16: =1200*260 -> 312000 | N16: 104997.75 | O16: 0 | P16: =(6/1000)*((F16*90%)*3) -> 10692 | Q16: =1%*(I16+F16+G16+H16) -> 7524 | R16: =1%*(I16+F16+G16+H16) -> 7524 | S16: =SUM(F16:R16) -> 1195137.8 | U16: =S16/12 -> 99594.812 | X16: N/A
A17: =A16+1 -> 15 | B17: ='Payroll breakdown per role'!D18 -> J1 | C17: Student Intern (x3) | D17: ='Payroll breakdown per role'!F18 -> 46000 | F17: =D17*12 -> 552000 | G17: =(F17*70%)*10% -> 38640 | H17: =(F17*70%)*10% -> 38640 | M17: =1200*260 -> 312000 | N17: 0 | O17: 0 | P17: =(6/1000)*((F17*90%)*3) -> 8942.4 | Q17: =1%*(I17+F17+G17+H17) -> 6292.8 | R17: =1%*(I17+F17+G17+H17) -> 6292.8 | S17: =SUM(F17:R17) -> 962808 | U17: =S17/12 -> 80234 | X17: N/A
F18: =SUM(F2:F17) -> 133152000 | G18: =SUM(G2:G17) -> 9320640 | H18: =SUM(H2:H17) -> 9320640 | K18: =SUM(K2:K17) -> 1914000 | L18: =SUM(L2:L17) -> 0 | M18: =SUM(M2:M17) -> 4992000 | N18: =SUM(N2:N17) -> 3504871.5 | O18: =SUM(O2:O17) -> 11874600 | P18: =SUM(P2:P17) -> 2157062.4 | Q18: =SUM(Q2:Q17) -> 1517932.8 | R18: =SUM(R2:R17) -> 1517932.8 | S18: =SUM(S2:S17) -> 1.8109668e+08 | U18: =SUM(U2:U17) -> 15091390
K20: ='[1]Annual Employer Cost per Grade'!$K$17 -> 840000
K21: =K20/K18 -> 0.43887147

Sheet Payroll breakdown per role
H1: 0.7 | I1: 0.1 | J1: 0.1 | K1: 0.0333 | L1: 0.0333 | M1: 0.0334 | O1: 8% of B+T+H | P1: Optional | W1: Tax Table | AE1: Tax Table | AF1: Monthly | AG1: =IF(AF1="Annual",1,0.0833333) -> 0.0833333
A2: S/N | B2: Job Role | C2: Description | D2: Grade | E2: Grade Name | F2: Gross Salary | H2: Basic Salary (70%) | I2: Transport Allowance (10%) | J2: Housing Allowance (10%) | K2: Meal Allowance (3.33%) | L2: Utility Allowance (3.33%) | M2: Entertainment Allowance (3.34%) | N2: Gross Pay | O2: Pension Contribution (8%) | P2: NHF Contribution (2.5%) | Q2: PAYE (Tax) - | R2: Net Pay (Monthly Take home) | T2: Employer Pension Contribution | W2: Do not touch the figures | X2: Gross Income for CRA | Y2: Consolidated Relief Allowance | Z2: Employee Pension | AA2: National Housing Fund | AB2: Total Relief / Tax Free Pay | AC2: Amount Taxable | AE2: Do not touch the figures | AG2: 0.07 | AH2: 0.11 | AI2: 0.15 | AJ2: 0.19 | AK2: 0.21 | AL2: 0.24 | AM2: Monthly Tax Payable
A3: 1 | B3: Managing Director | D3: A1 | E3: Managing Director | F3: 4760000 | H3: =F3*$H$1 -> 3332000 | I3: =F3*$I$1 -> 476000 | J3: =F3*$J$1 -> 476000 | K3: =F3*$K$1 -> 158508 | L3: =F3*$L$1 -> 158508 | M3: =F3*$M$1 -> 158984 | N3: =SUM(H3:M3) -> 4760000 | O3: =(H3+I3+J3)*8% -> 342720 | P3: =2.5%*N3 -> 119000 | Q3: =AM3 -> 797620.56 | R3: =N3-O3-P3-Q3 -> 3500659.4 | T3: =(H3+I3+J3)*10% -> 428400 | X3: =N3-O3-P3 -> 4298280 | Y3: =IF(X3*1%>200000*$AG$1,X3*1%,200000*$AG$1)+(20%*X3) -> 902638.8 | Z3: =O3 -> 342720 | AA3: =P3 -> 119000 | AB3: =SUM(Y3:AA3) -> 1364358.8 | AC3: =N3-AB3 -> 3395641.2 | AG3: =IF(300000*$AG$1<AC3,300000*$AG$1,AC3)*$AG$2 -> 1749.9993 | AH3: =(IF(300000*$AG$1>AC3,0,IF(600000*$AG$1>AC3,(AC3-(300000*$AG$1)),IF(600000*$AG$1<AC3,300000*$AG$1))))*$AH$2 -> 2749.9989 | AI3: =(IF(600000*$AG$1>AC3,0,IF(1100000*$AG$1>AC3,(AC3-(600000*$AG$1)),IF(1100000*$AG$1<AC3,500000*$AG$1))))*$AI$2 -> 6249.9975 | AJ3: =(IF(1100000*$AG$1>AC3,0,IF(1600000*$AG$1>AC3,(AC3-(1100000*$AG$1)),IF(1600000*$AG$1<AC3,500000*$AG$1))))*$AJ$2 -> 7916.6635 | AK3: =(IF(1600000*$AG$1>AC3,0,IF(3200000*$AG$1>AC3,(AC3-(1600000*$AG$1)),IF(3200000*$AG$1<AC3,1600000*$AG$1))))*$AK$2 -> 27999.989 | AL3: =(IF(3200000*$AG$1>AC3,0,IF(3200000*$AG$1<AC3,AC3-3200000*$AG$1)))*$AL$2 -> 750953.91 | AM3: =SUM(AG3:AL3) -> 797620.56
A4: =A3+1 -> 2 | B4: Director of Programs | D4: B1 | E4: Director 1 | F4: 2710000 | H4: =F4*$H$1 -> 1897000 | I4: =F4*$I$1 -> 271000 | J4: =F4*$J$1 -> 271000 | K4: =F4*$K$1 -> 90243 | L4: =F4*$L$1 -> 90243 | M4: =F4*$M$1 -> 90514 | N4: =SUM(H4:M4) -> 2710000 | O4: =(H4+I4+J4)*8% -> 195120 | P4: =2.5%*N4 -> 67750 | Q4: =AM4 -> 446642.52 | R4: =N4-O4-P4-Q4 -> 2000487.5 | T4: =(H4+I4+J4)*10% -> 243900 | X4: =N4-O4-P4 -> 2447130 | Y4: =IF(X4*1%>200000*$AG$1,X4*1%,200000*$AG$1)+(20%*X4) -> 513897.3 | Z4: =O4 -> 195120 | AA4: =P4 -> 67750 | AB4: =SUM(Y4:AA4) -> 776767.3 | AC4: =N4-AB4 -> 1933232.7 | AG4: =IF(300000*$AG$1<AC4,300000*$AG$1,AC4)*$AG$2 -> 1749.9993 | AH4: =(IF(300000*$AG$1>AC4,0,IF(600000*$AG$1>AC4,(AC4-(300000*$AG$1)),IF(600000*$AG$1<AC4,300000*$AG$1))))*$AH$2 -> 2749.9989 | AI4: =(IF(600000*$AG$1>AC4,0,IF(1100000*$AG$1>AC4,(AC4-(600000*$AG$1)),IF(1100000*$AG$1<AC4,500000*$AG$1))))*$AI$2 -> 6249.9975 | AJ4: =(IF(1100000*$AG$1>AC4,0,IF(1600000*$AG$1>AC4,(AC4-(1100000*$AG$1)),IF(1600000*$AG$1<AC4,500000*$AG$1))))*$AJ$2 -> 7916.6635 | AK4: =(IF(1600000*$AG$1>AC4,0,IF(3200000*$AG$1>AC4,(AC4-(1600000*$AG$1)),IF(3200000*$AG$1<AC4,1600000*$AG$1))))*$AK$2 -> 27999.989 | AL4: =(IF(3200000*$AG$1>AC4,0,IF(3200000*$AG$1<AC4,AC4-3200000*$AG$1)))*$AL$2 -> 399975.87 | AM4: =SUM(AG4:AL4) -> 446642.52
A5: =A4+1 -> 3 | B5: IT Manager | D5: G1 | E5: Senior Associate 1 | F5: 555000 | H5: =F5*$H$1 -> 388500 | I5: =F5*$I$1 -> 55500 | J5: =F5*$J$1 -> 55500 | K5: =F5*$K$1 -> 18481.5 | L5: =F5*$L$1 -> 18481.5 | M5: =F5*$M$1 -> 18537 | N5: =SUM(H5:M5) -> 555000 | O5: =(H5+I5+J5)*8% -> 39960 | P5: =2.5%*N5 -> 13875 | Q5: =AM5 -> 74890.355 | R5: =N5-O5-P5-Q5 -> 426274.64 | T5: =(H5+I5+J5)*10% -> 49950 | X5: =N5-O5-P5 -> 501165 | Y5: =IF(X5*1%>200000*$AG$1,X5*1%,200000*$AG$1)+(20%*X5) -> 116899.66 | Z5: =O5 -> 39960 | AA5: =P5 -> 13875 | AB5: =SUM(Y5:AA5) -> 170734.66 | AC5: =N5-AB5 -> 384265.34 | AG5: =IF(300000*$AG$1<AC5,300000*$AG$1,AC5)*$AG$2 -> 1749.9993 | AH5: =(IF(300000*$AG$1>AC5,0,IF(600000*$AG$1>AC5,(AC5-(300000*$AG$1)),IF(600000*$AG$1<AC5,300000*$AG$1))))*$AH$2 -> 2749.9989 | AI5: =(IF(600000*$AG$1>AC5,0,IF(1100000*$AG$1>AC5,(AC5-(600000*$AG$1)),IF(1100000*$AG$1<AC5,500000*$AG$1))))*$AI$2 -> 6249.9975 | AJ5: =(IF(1100000*$AG$1>AC5,0,IF(1600000*$AG$1>AC5,(AC5-(1100000*$AG$1)),IF(1600000*$AG$1<AC5,500000*$AG$1))))*$AJ$2 -> 7916.6635 | AK5: =(IF(1600000*$AG$1>AC5,0,IF(3200000*$AG$1>AC5,(AC5-(1600000*$AG$1)),IF(3200000*$AG$1<AC5,1600000*$AG$1))))*$AK$2 -> 27999.989 | AL5: =(IF(3200000*$AG$1>AC5,0,IF(3200000*$AG$1<AC5,AC5-3200000*$AG$1)))*$AL$2 -> 28223.707 | AM5: =SUM(AG5:AL5) -> 74890.355
A6: =A5+1 -> 4 | B6: Community Manager | D6: H1 | E6: Associate 1 | F6: 315000 | H6: =F6*$H$1 -> 220500 | I6: =F6*$I$1 -> 31500 | J6: =F6*$J$1 -> 31500 | K6: =F6*$K$1 -> 10489.5 | L6: =F6*$L$1 -> 10489.5 | M6: =F6*$M$1 -> 10521 | N6: =SUM(H6:M6) -> 315000 | O6: =(H6+I6+J6)*8% -> 22680 | P6: =2.5%*N6 -> 7875 | Q6: =AM6 -> 34953.432 | R6: =N6-O6-P6-Q6 -> 249491.57 | T6: =(H6+I6+J6)*10% -> 28350 | X6: =N6-O6-P6 -> 284445 | Y6: =IF(X6*1%>200000*$AG$1,X6*1%,200000*$AG$1)+(20%*X6) -> 73555.66 | Z6: =O6 -> 22680 | AA6: =P6 -> 7875 | AB6: =SUM(Y6:AA6) -> 104110.66 | AC6: =N6-AB6 -> 210889.34 | AG6: =IF(300000*$AG$1<AC6,300000*$AG$1,AC6)*$AG$2 -> 1749.9993 | AH6: =(IF(300000*$AG$1>AC6,0,IF(600000*$AG$1>AC6,(AC6-(300000*$AG$1)),IF(600000*$AG$1<AC6,300000*$AG$1))))*$AH$2 -> 2749.9989 | AI6: =(IF(600000*$AG$1>AC6,0,IF(1100000*$AG$1>AC6,(AC6-(600000*$AG$1)),IF(1100000*$AG$1<AC6,500000*$AG$1))))*$AI$2 -> 6249.9975 | AJ6: =(IF(1100000*$AG$1>AC6,0,IF(1600000*$AG$1>AC6,(AC6-(1100000*$AG$1)),IF(1600000*$AG$1<AC6,500000*$AG$1))))*$AJ$2 -> 7916.6635 | AK6: =(IF(1600000*$AG$1>AC6,0,IF(3200000*$AG$1>AC6,(AC6-(1600000*$AG$1)),IF(3200000*$AG$1<AC6,1600000*$AG$1))))*$AK$2 -> 16286.773 | AL6: =(IF(3200000*$AG$1>AC6,0,IF(3200000*$AG$1<AC6,AC6-3200000*$AG$1)))*$AL$2 -> 0 | AM6: =SUM(AG6:AL6) -> 34953.432
A7: =A6+1 -> 5 | B7: Facility Associate | D7: H1 | E7: Associate 1 | F7: 315000 | H7: =F7*$H$1 -> 220500 | I7: =F7*$I$1 -> 31500 | J7: =F7*$J$1 -> 31500 | K7: =F7*$K$1 -> 10489.5 | L7: =F7*$L$1 -> 10489.5 | M7: =F7*$M$1 -> 10521 | N7: =SUM(H7:M7) -> 315000 | O7: =(H7+I7+J7)*8% -> 22680 | P7: =2.5%*N7 -> 7875 | Q7: =AM7 -> 34953.432 | R7: =N7-O7-P7-Q7 -> 249491.57 | T7: =(H7+I7+J7)*10% -> 28350 | X7: =N7-O7-P7 -> 284445 | Y7: =IF(X7*1%>200000*$AG$1,X7*1%,200000*$AG$1)+(20%*X7) -> 73555.66 | Z7: =O7 -> 22680 | AA7: =P7 -> 7875 | AB7: =SUM(Y7:AA7) -> 104110.66 | AC7: =N7-AB7 -> 210889.34 | AG7: =IF(300000*$AG$1<AC7,300000*$AG$1,AC7)*$AG$2 -> 1749.9993 | AH7: =(IF(300000*$AG$1>AC7,0,IF(600000*$AG$1>AC7,(AC7-(300000*$AG$1)),IF(600000*$AG$1<AC7,300000*$AG$1))))*$AH$2 -> 2749.9989 | AI7: =(IF(600000*$AG$1>AC7,0,IF(1100000*$AG$1>AC7,(AC7-(600000*$AG$1)),IF(1100000*$AG$1<AC7,500000*$AG$1))))*$AI$2 -> 6249.9975 | AJ7: =(IF(1100000*$AG$1>AC7,0,IF(1600000*$AG$1>AC7,(AC7-(1100000*$AG$1)),IF(1600000*$AG$1<AC7,500000*$AG$1))))*$AJ$2 -> 7916.6635 | AK7: =(IF(1600000*$AG$1>AC7,0,IF(3200000*$AG$1>AC7,(AC7-(1600000*$AG$1)),IF(3200000*$AG$1<AC7,1600000*$AG$1))))*$AK$2 -> 16286.773 | AL7: =(IF(3200000*$AG$1>AC7,0,IF(3200000*$AG$1<AC7,AC7-3200000*$AG$1)))*$AL$2 -> 0 | AM7: =SUM(AG7:AL7) -> 34953.432
A8: =A7+1 -> 6 | B8: Front Desk Associate (x1) | D8: H1 | E8: Associate 1 | F8: 315000 | H8: =F8*$H$1 -> 220500 | I8: =F8*$I$1 -> 31500 | J8: =F8*$J$1 -> 31500 | K8: =F8*$K$1 -> 10489.5 | L8: =F8*$L$1 -> 10489.5 | M8: =F8*$M$1 -> 10521 | N8: =SUM(H8:M8) -> 315000 | O8: =(H8+I8+J8)*8% -> 22680 | P8: =2.5%*N8 -> 7875 | Q8: =AM8 -> 34953.432 | R8: =N8-O8-P8-Q8 -> 249491.57 | T8: =(H8+I8+J8)*10% -> 28350 | X8: =N8-O8-P8 -> 284445 | Y8: =IF(X8*1%>200000*$AG$1,X8*1%,200000*$AG$1)+(20%*X8) -> 73555.66 | Z8: =O8 -> 22680 | AA8: =P8 -> 7875 | AB8: =SUM(Y8:AA8) -> 104110.66 | AC8: =N8-AB8 -> 210889.34 | AG8: =IF(300000*$AG$1<AC8,300000*$AG$1,AC8)*$AG$2 -> 1749.9993 | AH8: =(IF(300000*$AG$1>AC8,0,IF(600000*$AG$1>AC8,(AC8-(300000*$AG$1)),IF(600000*$AG$1<AC8,300000*$AG$1))))*$AH$2 -> 2749.9989 | AI8: =(IF(600000*$AG$1>AC8,0,IF(1100000*$AG$1>AC8,(AC8-(600000*$AG$1)),IF(1100000*$AG$1<AC8,500000*$AG$1))))*$AI$2 -> 6249.9975 | AJ8: =(IF(1100000*$AG$1>AC8,0,IF(1600000*$AG$1>AC8,(AC8-(1100000*$AG$1)),IF(1600000*$AG$1<AC8,500000*$AG$1))))*$AJ$2 -> 7916.6635 | AK8: =(IF(1600000*$AG$1>AC8,0,IF(3200000*$AG$1>AC8,(AC8-(1600000*$AG$1)),IF(3200000*$AG$1<AC8,1600000*$AG$1))))*$AK$2 -> 16286.773 | AL8: =(IF(3200000*$AG$1>AC8,0,IF(3200000*$AG$1<AC8,AC8-3200000*$AG$1)))*$AL$2 -> 0 | AM8: =SUM(AG8:AL8) -> 34953.432
A9: =A8+1 -> 7 | B9: Front Desk Support (Tech Grade 1) | D9: I1 | E9: Support Staff 1 | F9: 150000 | H9: =F9*$H$1 -> 105000 | I9: =F9*$I$1 -> 15000 | J9: =F9*$J$1 -> 15000 | K9: =F9*$K$1 -> 4995 | L9: =F9*$L$1 -> 4995 | M9: =F9*$M$1 -> 5010 | N9: =SUM(H9:M9) -> 150000 | O9: =(H9+I9+J9)*8% -> 10800 | P9: =2.5%*N9 -> 3750 | Q9: =AM9 -> 10755.071 | R9: =N9-O9-P9-Q9 -> 124694.93 | T9: =(H9+I9+J9)*10% -> 13500 | X9: =N9-O9-P9 -> 135450 | Y9: =IF(X9*1%>200000*$AG$1,X9*1%,200000*$AG$1)+(20%*X9) -> 43756.66 | Z9: =O9 -> 10800 | AA9: =P9 -> 3750 | AB9: =SUM(Y9:AA9) -> 58306.66 | AC9: =N9-AB9 -> 91693.34 | AG9: =IF(300000*$AG$1<AC9,300000*$AG$1,AC9)*$AG$2 -> 1749.9993 | AH9: =(IF(300000*$AG$1>AC9,0,IF(600000*$AG$1>AC9,(AC9-(300000*$AG$1)),IF(600000*$AG$1<AC9,300000*$AG$1))))*$AH$2 -> 2749.9989 | AI9: =(IF(600000*$AG$1>AC9,0,IF(1100000*$AG$1>AC9,(AC9-(600000*$AG$1)),IF(1100000*$AG$1<AC9,500000*$AG$1))))*$AI$2 -> 6249.9975 | AJ9: =(IF(1100000*$AG$1>AC9,0,IF(1600000*$AG$1>AC9,(AC9-(1100000*$AG$1)),IF(1600000*$AG$1<AC9,500000*$AG$1))))*$AJ$2 -> 5.0749 | AK9: =(IF(1600000*$AG$1>AC9,0,IF(3200000*$AG$1>AC9,(AC9-(1600000*$AG$1)),IF(3200000*$AG$1<AC9,1600000*$AG$1))))*$AK$2 -> 0 | AL9: =(IF(3200000*$AG$1>AC9,0,IF(3200000*$AG$1<AC9,AC9-3200000*$AG$1)))*$AL$2 -> 0 | AM9: =SUM(AG9:AL9) -> 10755.071
A10: =A9+1 -> 8 | B10: Finance Associate | D10: H1 | E10: Associate 1 | F10: 315000 | H10: =F10*$H$1 -> 220500 | I10: =F10*$I$1 -> 31500 | J10: =F10*$J$1 -> 31500 | K10: =F10*$K$1 -> 10489.5 | L10: =F10*$L$1 -> 10489.5 | M10: =F10*$M$1 -> 10521 | N10: =SUM(H10:M10) -> 315000 | O10: =(H10+I10+J10)*8% -> 22680 | P10: =2.5%*N10 -> 7875 | Q10: =AM10 -> 34953.432 | R10: =N10-O10-P10-Q10 -> 249491.57 | T10: =(H10+I10+J10)*10% -> 28350 | X10: =N10-O10-P10 -> 284445 | Y10: =IF(X10*1%>200000*$AG$1,X10*1%,200000*$AG$1)+(20%*X10) -> 73555.66 | Z10: =O10 -> 22680 | AA10: =P10 -> 7875 | AB10: =SUM(Y10:AA10) -> 104110.66 | AC10: =N10-AB10 -> 210889.34 | AG10: =IF(300000*$AG$1<AC10,300000*$AG$1,AC10)*$AG$2 -> 1749.9993 | AH10: =(IF(300000*$AG$1>AC10,0,IF(600000*$AG$1>AC10,(AC10-(300000*$AG$1)),IF(600000*$AG$1<AC10,300000*$AG$1))))*$AH$2 -> 2749.9989 | AI10: =(IF(600000*$AG$1>AC10,0,IF(1100000*$AG$1>AC10,(AC10-(600000*$AG$1)),IF(1100000*$AG$1<AC10,500000*$AG$1))))*$AI$2 -> 6249.9975 | AJ10: =(IF(1100000*$AG$1>AC10,0,IF(1600000*$AG$1>AC10,(AC10-(1100000*$AG$1)),IF(1600000*$AG$1<AC10,500000*$AG$1))))*$AJ$2 -> 7916.6635 | AK10: =(IF(1600000*$AG$1>AC10,0,IF(3200000*$AG$1>AC10,(AC10-(1600000*$AG$1)),IF(3200000*$AG$1<AC10,1600000*$AG$1))))*$AK$2 -> 16286.773 | AL10: =(IF(3200000*$AG$1>AC10,0,IF(3200000*$AG$1<AC10,AC10-3200000*$AG$1)))*$AL$2 -> 0 | AM10: =SUM(AG10:AL10) -> 34953.432
A11: =A10+1 -> 9 | B11: Admin & HR Associate | D11: H1 | E11: Associate 1 | F11: 315000 | H11: =F11*$H$1 -> 220500 | I11: =F11*$I$1 -> 31500 | J11: =F11*$J$1 -> 31500 | K11: =F11*$K$1 -> 10489.5 | L11: =F11*$L$1 -> 10489.5 | M11: =F11*$M$1 -> 10521 | N11: =SUM(H11:M11) -> 315000 | O11: =(H11+I11+J11)*8% -> 22680 | P11: =2.5%*N11 -> 7875 | Q11: =AM11 -> 34953.432 | R11: =N11-O11-P11-Q11 -> 249491.57 | T11: =(H11+I11+J11)*10% -> 28350 | X11: =N11-O11-P11 -> 284445 | Y11: =IF(X11*1%>200000*$AG$1,X11*1%,200000*$AG$1)+(20%*X11) -> 73555.66 | Z11: =O11 -> 22680 | AA11: =P11 -> 7875 | AB11: =SUM(Y11:AA11) -> 104110.66 | AC11: =N11-AB11 -> 210889.34 | AG11: =IF(300000*$AG$1<AC11,300000*$AG$1,AC11)*$AG$2 -> 1749.9993 | AH11: =(IF(300000*$AG$1>AC11,0,IF(600000*$AG$1>AC11,(AC11-(300000*$AG$1)),IF(600000*$AG$1<AC11,300000*$AG$1))))*$AH$2 -> 2749.9989 | AI11: =(IF(600000*$AG$1>AC11,0,IF(1100000*$AG$1>AC11,(AC11-(600000*$AG$1)),IF(1100000*$AG$1<AC11,500000*$AG$1))))*$AI$2 -> 6249.9975 | AJ11: =(IF(1100000*$AG$1>AC11,0,IF(1600000*$AG$1>AC11,(AC11-(1100000*$AG$1)),IF(1600000*$AG$1<AC11,500000*$AG$1))))*$AJ$2 -> 7916.6635 | AK11: =(IF(1600000*$AG$1>AC11,0,IF(3200000*$AG$1>AC11,(AC11-(1600000*$AG$1)),IF(3200000*$AG$1<AC11,1600000*$AG$1))))*$AK$2 -> 16286.773 | AL11: =(IF(3200000*$AG$1>AC11,0,IF(3200000*$AG$1<AC11,AC11-3200000*$AG$1)))*$AL$2 -> 0 | AM11: =SUM(AG11:AL11) -> 34953.432
A12: =A11+1 -> 10 | B12: IT Support Associate (x2) | D12: H1 | E12: Associate 1 | F12: 315000 | H12: =F12*$H$1 -> 220500 | I12: =F12*$I$1 -> 31500 | J12: =F12*$J$1 -> 31500 | K12: =F12*$K$1 -> 10489.5 | L12: =F12*$L$1 -> 10489.5 | M12: =F12*$M$1 -> 10521 | N12: =SUM(H12:M12) -> 315000 | O12: =(H12+I12+J12)*8% -> 22680 | P12: =2.5%*N12 -> 7875 | Q12: =AM12 -> 34953.432 | R12: =N12-O12-P12-Q12 -> 249491.57 | T12: =(H12+I12+J12)*10% -> 28350 | X12: =N12-O12-P12 -> 284445 | Y12: =IF(X12*1%>200000*$AG$1,X12*1%,200000*$AG$1)+(20%*X12) -> 73555.66 | Z12: =O12 -> 22680 | AA12: =P12 -> 7875 | AB12: =SUM(Y12:AA12) -> 104110.66 | AC12: =N12-AB12 -> 210889.34 | AG12: =IF(300000*$AG$1<AC12,300000*$AG$1,AC12)*$AG$2 -> 1749.9993 | AH12: =(IF(300000*$AG$1>AC12,0,IF(600000*$AG$1>AC12,(AC12-(300000*$AG$1)),IF(600000*$AG$1<AC12,300000*$AG$1))))*$AH$2 -> 2749.9989 | AI12: =(IF(600000*$AG$1>AC12,0,IF(1100000*$AG$1>AC12,(AC12-(600000*$AG$1)),IF(1100000*$AG$1<AC12,500000*$AG$1))))*$AI$2 -> 6249.9975 | AJ12: =(IF(1100000*$AG$1>AC12,0,IF(1600000*$AG$1>AC12,(AC12-(1100000*$AG$1)),IF(1600000*$AG$1<AC12,500000*$AG$1))))*$AJ$2 -> 7916.6635 | AK12: =(IF(1600000*$AG$1>AC12,0,IF(3200000*$AG$1>AC12,(AC12-(1600000*$AG$1)),IF(3200000*$AG$1<AC12,1600000*$AG$1))))*$AK$2 -> 16286.773 | AL12: =(IF(3200000*$AG$1>AC12,0,IF(3200000*$AG$1<AC12,AC12-3200000*$AG$1)))*$AL$2 -> 0 | AM12: =SUM(AG12:AL12) -> 34953.432
A13: =A12+1 -> 11 | B13: Content & Digital Marketing Lead | D13: H1 | E13: Associate 1 | F13: 315000 | H13: =F13*$H$1 -> 220500 | I13: =F13*$I$1 -> 31500 | J13: =F13*$J$1 -> 31500 | K13: =F13*$K$1 -> 10489.5 | L13: =F13*$L$1 -> 10489.5 | M13: =F13*$M$1 -> 10521 | N13: =SUM(H13:M13) -> 315000 | O13: =(H13+I13+J13)*8% -> 22680 | P13: =2.5%*N13 -> 7875 | Q13: =AM13 -> 34953.432 | R13: =N13-O13-P13-Q13 -> 249491.57 | T13: =(H13+I13+J13)*10% -> 28350 | X13: =N13-O13-P13 -> 284445 | Y13: =IF(X13*1%>200000*$AG$1,X13*1%,200000*$AG$1)+(20%*X13) -> 73555.66 | Z13: =O13 -> 22680 | AA13: =P13 -> 7875 | AB13: =SUM(Y13:AA13) -> 104110.66 | AC13: =N13-AB13 -> 210889.34 | AG13: =IF(300000*$AG$1<AC13,300000*$AG$1,AC13)*$AG$2 -> 1749.9993 | AH13: =(IF(300000*$AG$1>AC13,0,IF(600000*$AG$1>AC13,(AC13-(300000*$AG$1)),IF(600000*$AG$1<AC13,300000*$AG$1))))*$AH$2 -> 2749.9989 | AI13: =(IF(600000*$AG$1>AC13,0,IF(1100000*$AG$1>AC13,(AC13-(600000*$AG$1)),IF(1100000*$AG$1<AC13,500000*$AG$1))))*$AI$2 -> 6249.9975 | AJ13: =(IF(1100000*$AG$1>AC13,0,IF(1600000*$AG$1>AC13,(AC13-(1100000*$AG$1)),IF(1600000*$AG$1<AC13,500000*$AG$1))))*$AJ$2 -> 7916.6635 | AK13: =(IF(1600000*$AG$1>AC13,0,IF(3200000*$AG$1>AC13,(AC13-(1600000*$AG$1)),IF(3200000*$AG$1<AC13,1600000*$AG$1))))*$AK$2 -> 16286.773 | AL13: =(IF(3200000*$AG$1>AC13,0,IF(3200000*$AG$1<AC13,AC13-3200000*$AG$1)))*$AL$2 -> 0 | AM13: =SUM(AG13:AL13) -> 34953.432
A14: =A13+1 -> 12 | B14: Graphic & Multimedia Associate | D14: H1 | E14: Associate 1 | F14: 315000 | H14: =F14*$H$1 -> 220500 | I14: =F14*$I$1 -> 31500 | J14: =F14*$J$1 -> 31500 | K14: =F14*$K$1 -> 10489.5 | L14: =F14*$L$1 -> 10489.5 | M14: =F14*$M$1 -> 10521 | N14: =SUM(H14:M14) -> 315000 | O14: =(H14+I14+J14)*8% -> 22680 | P14: =2.5%*N14 -> 7875 | Q14: =AM14 -> 34953.432 | R14: =N14-O14-P14-Q14 -> 249491.57 | T14: =(H14+I14+J14)*10% -> 28350 | X14: =N14-O14-P14 -> 284445 | Y14: =IF(X14*1%>200000*$AG$1,X14*1%,200000*$AG$1)+(20%*X14) -> 73555.66 | Z14: =O14 -> 22680 | AA14: =P14 -> 7875 | AB14: =SUM(Y14:AA14) -> 104110.66 | AC14: =N14-AB14 -> 210889.34 | AG14: =IF(300000*$AG$1<AC14,300000*$AG$1,AC14)*$AG$2 -> 1749.9993 | AH14: =(IF(300000*$AG$1>AC14,0,IF(600000*$AG$1>AC14,(AC14-(300000*$AG$1)),IF(600000*$AG$1<AC14,300000*$AG$1))))*$AH$2 -> 2749.9989 | AI14: =(IF(600000*$AG$1>AC14,0,IF(1100000*$AG$1>AC14,(AC14-(600000*$AG$1)),IF(1100000*$AG$1<AC14,500000*$AG$1))))*$AI$2 -> 6249.9975 | AJ14: =(IF(1100000*$AG$1>AC14,0,IF(1600000*$AG$1>AC14,(AC14-(1100000*$AG$1)),IF(1600000*$AG$1<AC14,500000*$AG$1))))*$AJ$2 -> 7916.6635 | AK14: =(IF(1600000*$AG$1>AC14,0,IF(3200000*$AG$1>AC14,(AC14-(1600000*$AG$1)),IF(3200000*$AG$1<AC14,1600000*$AG$1))))*$AK$2 -> 16286.773 | AL14: =(IF(3200000*$AG$1>AC14,0,IF(3200000*$AG$1<AC14,AC14-3200000*$AG$1)))*$AL$2 -> 0 | AM14: =SUM(AG14:AL14) -> 34953.432
A15: =A14+1 -> 13 | B15: Facility Technician (x3) | D15: I1 | E15: Support Staff 1 | F15: 150000 | H15: =F15*$H$1 -> 105000 | I15: =F15*$I$1 -> 15000 | J15: =F15*$J$1 -> 15000 | K15: =F15*$K$1 -> 4995 | L15: =F15*$L$1 -> 4995 | M15: =F15*$M$1 -> 5010 | N15: =SUM(H15:M15) -> 150000 | O15: =(H15+I15+J15)*8% -> 10800 | P15: =2.5%*N15 -> 3750 | Q15: =AM15 -> 10755.071 | R15: =N15-O15-P15-Q15 -> 124694.93 | T15: =(H15+I15+J15)*10% -> 13500 | X15: =N15-O15-P15 -> 135450 | Y15: =IF(X15*1%>200000*$AG$1,X15*1%,200000*$AG$1)+(20%*X15) -> 43756.66 | Z15: =O15 -> 10800 | AA15: =P15 -> 3750 | AB15: =SUM(Y15:AA15) -> 58306.66 | AC15: =N15-AB15 -> 91693.34 | AG15: =IF(300000*$AG$1<AC15,300000*$AG$1,AC15)*$AG$2 -> 1749.9993 | AH15: =(IF(300000*$AG$1>AC15,0,IF(600000*$AG$1>AC15,(AC15-(300000*$AG$1)),IF(600000*$AG$1<AC15,300000*$AG$1))))*$AH$2 -> 2749.9989 | AI15: =(IF(600000*$AG$1>AC15,0,IF(1100000*$AG$1>AC15,(AC15-(600000*$AG$1)),IF(1100000*$AG$1<AC15,500000*$AG$1))))*$AI$2 -> 6249.9975 | AJ15: =(IF(1100000*$AG$1>AC15,0,IF(1600000*$AG$1>AC15,(AC15-(1100000*$AG$1)),IF(1600000*$AG$1<AC15,500000*$AG$1))))*$AJ$2 -> 5.0749 | AK15: =(IF(1600000*$AG$1>AC15,0,IF(3200000*$AG$1>AC15,(AC15-(1600000*$AG$1)),IF(3200000*$AG$1<AC15,1600000*$AG$1))))*$AK$2 -> 0 | AL15: =(IF(3200000*$AG$1>AC15,0,IF(3200000*$AG$1<AC15,AC15-3200000*$AG$1)))*$AL$2 -> 0 | AM15: =SUM(AG15:AL15) -> 10755.071
A16: =A15+1 -> 14 | B16: Driver | D16: I1 | E16: Support Staff 1 | F16: 150000 | H16: =F16*$H$1 -> 105000 | I16: =F16*$I$1 -> 15000 | J16: =F16*$J$1 -> 15000 | K16: =F16*$K$1 -> 4995 | L16: =F16*$L$1 -> 4995 | M16: =F16*$M$1 -> 5010 | N16: =SUM(H16:M16) -> 150000 | O16: =(H16+I16+J16)*8% -> 10800 | P16: =2.5%*N16 -> 3750 | Q16: =AM16 -> 10755.071 | R16: =N16-O16-P16-Q16 -> 124694.93 | T16: =(H16+I16+J16)*10% -> 13500 | X16: =N16-O16-P16 -> 135450 | Y16: =IF(X16*1%>200000*$AG$1,X16*1%,200000*$AG$1)+(20%*X16) -> 43756.66 | Z16: =O16 -> 10800 | AA16: =P16 -> 3750 | AB16: =SUM(Y16:AA16) -> 58306.66 | AC16: =N16-AB16 -> 91693.34 | AG16: =IF(300000*$AG$1<AC16,300000*$AG$1,AC16)*$AG$2 -> 1749.9993 | AH16: =(IF(300000*$AG$1>AC16,0,IF(600000*$AG$1>AC16,(AC16-(300000*$AG$1)),IF(600000*$AG$1<AC16,300000*$AG$1))))*$AH$2 -> 2749.9989 | AI16: =(IF(600000*$AG$1>AC16,0,IF(1100000*$AG$1>AC16,(AC16-(600000*$AG$1)),IF(1100000*$AG$1<AC16,500000*$AG$1))))*$AI$2 -> 6249.9975 | AJ16: =(IF(1100000*$AG$1>AC16,0,IF(1600000*$AG$1>AC16,(AC16-(1100000*$AG$1)),IF(1600000*$AG$1<AC16,500000*$AG$1))))*$AJ$2 -> 5.0749 | AK16: =(IF(1600000*$AG$1>AC16,0,IF(3200000*$AG$1>AC16,(AC16-(1600000*$AG$1)),IF(3200000*$AG$1<AC16,1600000*$AG$1))))*$AK$2 -> 0 | AL16: =(IF(3200000*$AG$1>AC16,0,IF(3200000*$AG$1<AC16,AC16-3200000*$AG$1)))*$AL$2 -> 0 | AM16: =SUM(AG16:AL16) -> 10755.071
A17: =A16+1 -> 15 | B17: NYSC Intern (x3) | C17: NYSC | D17: J2 | E17: Intern 2 | F17: 55000 | H17: =F17*$H$1 -> 38500 | I17: =F17*$I$1 -> 5500 | J17: =F17*$J$1 -> 5500 | K17: =F17*$K$1 -> 1831.5 | L17: =F17*$L$1 -> 1831.5 | M17: =F17*$M$1 -> 1837 | N17: =SUM(H17:M17) -> 55000 | O17: 0 | P17: 0 | Q17: =AM17 -> 2006.6678 | R17: =N17-O17-P17-Q17 -> 52993.332 | T17: 0 | X17: =N17-O17-P17 -> 55000 | Y17: =IF(X17*1%>200000*$AG$1,X17*1%,200000*$AG$1)+(20%*X17) -> 27666.66 | Z17: =O17 -> 0 | AA17: =P17 -> 0 | AB17: =SUM(Y17:AA17) -> 27666.66 | AC17: =N17-AB17 -> 27333.34 | AG17: =IF(300000*$AG$1<AC17,300000*$AG$1,AC17)*$AG$2 -> 1749.9993 | AH17: =(IF(300000*$AG$1>AC17,0,IF(600000*$AG$1>AC17,(AC17-(300000*$AG$1)),IF(600000*$AG$1<AC17,300000*$AG$1))))*$AH$2 -> 256.6685 | AI17: =(IF(600000*$AG$1>AC17,0,IF(1100000*$AG$1>AC17,(AC17-(600000*$AG$1)),IF(1100000*$AG$1<AC17,500000*$AG$1))))*$AI$2 -> 0 | AJ17: =(IF(1100000*$AG$1>AC17,0,IF(1600000*$AG$1>AC17,(AC17-(1100000*$AG$1)),IF(1600000*$AG$1<AC17,500000*$AG$1))))*$AJ$2 -> 0 | AK17: =(IF(1600000*$AG$1>AC17,0,IF(3200000*$AG$1>AC17,(AC17-(1600000*$AG$1)),IF(3200000*$AG$1<AC17,1600000*$AG$1))))*$AK$2 -> 0 | AL17: =(IF(3200000*$AG$1>AC17,0,IF(3200000*$AG$1<AC17,AC17-3200000*$AG$1)))*$AL$2 -> 0 | AM17: =SUM(AG17:AL17) -> 2006.6678
A18: =A17+1 -> 16 | B18: Student Intern (x3) | C18: SIWES | D18: J1 | E18: Intern 1 | F18: 46000 | H18: =F18*$H$1 -> 32200 | I18: =F18*$I$1 -> 4600 | J18: =F18*$J$1 -> 4600 | K18: =F18*$K$1 -> 1531.8 | L18: =F18*$L$1 -> 1531.8 | M18: =F18*$M$1 -> 1536.4 | N18: =SUM(H18:M18) -> 46000 | O18: 0 | P18: 0 | Q18: =AM18 -> 1409.3338 | R18: =N18-O18-P18-Q18 -> 44590.666 | T18: 0 | X18: =N18-O18-P18 -> 46000 | Y18: =IF(X18*1%>200000*$AG$1,X18*1%,200000*$AG$1)+(20%*X18) -> 25866.66 | Z18: =O18 -> 0 | AA18: =P18 -> 0 | AB18: =SUM(Y18:AA18) -> 25866.66 | AC18: =N18-AB18 -> 20133.34 | AG18: =IF(300000*$AG$1<AC18,300000*$AG$1,AC18)*$AG$2 -> 1409.3338 | AH18: =(IF(300000*$AG$1>AC18,0,IF(600000*$AG$1>AC18,(AC18-(300000*$AG$1)),IF(600000*$AG$1<AC18,300000*$AG$1))))*$AH$2 -> 0 | AI18: =(IF(600000*$AG$1>AC18,0,IF(1100000*$AG$1>AC18,(AC18-(600000*$AG$1)),IF(1100000*$AG$1<AC18,500000*$AG$1))))*$AI$2 -> 0 | AJ18: =(IF(1100000*$AG$1>AC18,0,IF(1600000*$AG$1>AC18,(AC18-(1100000*$AG$1)),IF(1600000*$AG$1<AC18,500000*$AG$1))))*$AJ$2 -> 0 | AK18: =(IF(1600000*$AG$1>AC18,0,IF(3200000*$AG$1>AC18,(AC18-(1600000*$AG$1)),IF(3200000*$AG$1<AC18,1600000*$AG$1))))*$AK$2 -> 0 | AL18: =(IF(3200000*$AG$1>AC18,0,IF(3200000*$AG$1<AC18,AC18-3200000*$AG$1)))*$AL$2 -> 0 | AM18: =SUM(AG18:AL18) -> 1409.3338
E19: Total | F19: =SUM(F3:F18) -> 11096000 | H19: =SUM(H3:H18) -> 7767200 | I19: =SUM(I3:I18) -> 1109600 | J19: =SUM(J3:J18) -> 1109600 | K19: =SUM(K3:K18) -> 369496.8 | L19: =SUM(L3:L18) -> 369496.8 | M19: =SUM(M3:M18) -> 370606.4 | N19: =SUM(N3:N18) -> 11096000 | O19: =SUM(O3:O18) -> 791640 | ... R19: =SUM(R3:R18) -> 8395022.9 | T19: =SUM(T3:T18) -> 989550

Sheet Bonus suggestion table
B2: Grade | C2: Role | D2: % of Bonus on Base Pay (Gross)
B3: A1 | C3: Managing Director | D3: 0
B4: B1 | C4: Director of Programs | D4: 0
B5: G1 | C5: Manager | D5: 0
B6: H1 | C6: Associate | D6: 0
B7: I1 | C7: Technician & Driver | D7: 0
