Workbook

Sheet Sheet2 (2)
A1: Trans Date | B1: Value Date | C1: Transaction Details | D1: Category | E1: Transactions | F1: Bank
A2: 45798 | B2: 21-MAY- 2025 | C2: 016NIPT251410435 NIP TRSF FROM AYOBAMI JOEL ATOLAGBE IIH HALL BOOKING by | D2: Facility rentals | E2: -444000 | F2: Bank01
A3: 45798 | B3: 21-MAY- 2025 | C3: 016EMTL251410057 ELECTRONIC MONEY TRANSFER LEVY | D3: Bank charges | E3: 50 | F3: Bank01
A4: 45807 | B4: 30-MAY- 2025 | C4: 000MOBT25150A0VX Payment for 4 flags US EU UNDP NG NIP Transfer from ILORIN INNOVATION HUB LTD to LET S BR | D4: Stationery and Office Supplies | E4: 40000 | F4: Bank01
A5: 45807 | B5: 30-MAY- 2025 | C5: 000MOBT25150A0VX Payment for 4 flags US EU UNDP NG NIP Transfer from ILORIN INNOVATION HUB LTD to LET S BR | D5: Bank charges | E5: 25 | F5: Bank01
A6: 45807 | B6: 30-MAY- 2025 | C6: 000MOBT25150A0VX Payment for 4 flags US EU UNDP NG NIP Transfer from ILORIN INNOVATION HUB LTD to LET S BR | D6: Bank charges | E6: 1.88 | F6: Bank01
A7: 45807 | B7: 30-MAY- 2025 | C7: 0168840251500001 BNG LEGAL SEARCH FEE FOR ILORIN INNOVATION HUB LTD0040117676 | D7: Other Expenses | E7: 10750 | F7: Bank01
A8: 45807 | B8: 30-MAY- 2025 | C8: 000MOBT25150A5H9 Purchase of cleaning supplies NIP Transfer from ILORIN INNOVATION HUB LTD to MAUREEN DANIE | D8: Cleaning expenses | E8: 12000 | F8: Bank01
A9: 45807 | B9: 30-MAY- 2025 | C9: 000MOBT25150A5H9 Purchase of cleaning supplies NIP Transfer from ILORIN INNOVATION HUB LTD to MAUREEN DANIE | D9: Bank charges | E9: 25 | F9: Bank01
A10: 45807 | B10: 30-MAY- 2025 | C10: 000MOBT25150A5H9 Purchase of cleaning supplies NIP Transfer from ILORIN INNOVATION HUB LTD to MAUREEN DANIE | D10: Bank charges | E10: 1.88 | F10: Bank01
A11: 45807 | B11: 30-MAY- 2025 | C11: 000MOBT25150AA0U NIP Transfer from ILORIN INNOVATION HUB LTD to MAUREEN DANIEL OKEY | D11: Other Expenses | E11: 15300 | F11: Bank01
A12: 45807 | B12: 30-MAY- 2025 | C12: 000MOBT25150AA0U NIP Transfer from ILORIN INNOVATION HUB LTD to MAUREEN DANIEL OKEY | D12: Bank charges | E12: 25 | F12: Bank01
A13: 45807 | B13: 30-MAY- 2025 | C13: 000MOBT25150AA0U NIP Transfer from ILORIN INNOVATION HUB LTD to MAUREEN DANIEL OKEY | D13: Bank charges | E13: 1.88 | F13: Bank01
... A353: 45838 | B353: 30-JUN- 2025 | C353: 016AMFC25181003N ACCOUNT MAINTENANCE FEE | D353: Bank charges | E353: 45154.25 | F353: Bank01
A354: 45838 | B354: 30-JUN- 2025 | C354: 016AMFV25181003E VAT ON TRANSACTION CHARGES | D354: Bank charges | E354: 3386.68 | F354: Bank01 | G354: Expense
A355: 45838 | B355: 30-JUN- 2025 | C355: Bank transactions in June | D355: Bank balance | E355: =-SUM(E17:E354) -> 1.0133034e+08 | F355: Bank01 | G355: Bank
A356: 45839 | B356: 01-JUL- 2025 | C356: 000MOBT25182AT02 MONTHLY CLEANING BALANCE NIP Transfer from ILORIN INNOVATION HUB LTD to SIII MULTIPURPOSE | D356: Cleaning expenses | E356: 650000 | F356: Bank01
A357: 45839 | B357: 01-JUL- 2025 | C357: 000MOBT25182AT02 MONTHLY CLEANING BALANCE NIP Transfer from ILORIN INNOVATION HUB LTD to SIII MULTIPURPOSE | D357: Bank charges | E357: 50 | F357: Bank01
A358: 45839 | B358: 01-JUL- 2025 | C358: 000MOBT25182AT02 MONTHLY CLEANING BALANCE NIP Transfer from ILORIN INNOVATION HUB LTD to SIII MULTIPURPOSE | D358: Bank charges | E358: 3.75 | F358: Bank01
A359: 45840 | B359: 02-JUL- 2025 | C359: 000MOBT251834063 EODB LUNCH NIP Transfer from ILORIN INNOVATION HUB LTD to BOA FOODS RESTAURANT LTD 1 | D359: Guest and entertainment | E359: 190200 | F359: Bank01
A360: 45840 | B360: 02-JUL- 2025 | C360: 000MOBT251834063 EODB LUNCH NIP Transfer from ILORIN INNOVATION HUB LTD to BOA FOODS RESTAURANT LTD 1 | D360: Bank charges | E360: 50 | F360: Bank01
A361: 45840 | B361: 02-JUL- 2025 | C361: 000MOBT251834063 EODB LUNCH NIP Transfer from ILORIN INNOVATION HUB LTD to BOA FOODS RESTAURANT LTD 1 | D361: Bank charges | E361: 3.75 | F361: Bank01
A362: 45841 | B362: 03-JUL- 2025 | C362: 000MOBT251841910 EODB BREAKFAST NIP Transfer from ILORIN INNOVATION HUB LTD to Infinitus Innovations Limite | D362: Guest and entertainment | E362: 37500 | F362: Bank01
A363: 45841 | B363: 03-JUL- 2025 | C363: 000MOBT251841910 EODB BREAKFAST NIP Transfer from ILORIN INNOVATION HUB LTD to Infinitus Innovations Limite | D363: Bank charges | E363: 25 | F363: Bank01
A364: 45841 | B364: 03-JUL- 2025 | C364: 000MOBT251841910 EODB BREAKFAST NIP Transfer from ILORIN INNOVATION HUB LTD to Infinitus Innovations Limite | D364: Bank charges | E364: 1.88 | F364: Bank01
A365: 45841 | B365: 03-JUL- 2025 | C365: 000MOBT251846895 EODB Lunch NIP Transfer from ILORIN INNOVATION HUB LTD to BOA FOODS RESTAURANT LTD 1 | D365: Guest and entertainment | E365: 100200 | F365: Bank01
A366: 45841 | B366: 03-JUL- 2025 | C366: 000MOBT251846895 EODB Lunch NIP Transfer from ILORIN INNOVATION HUB LTD to BOA FOODS RESTAURANT LTD 1 | D366: Bank charges | E366: 50 | F366: Bank01
A367: 45841 | B367: 03-JUL- 2025 | C367: 000MOBT251846895 EODB Lunch NIP Transfer from ILORIN INNOVATION HUB LTD to BOA FOODS RESTAURANT LTD 1 | D367: Bank charges | E367: 3.75 | F367: Bank01
... A1025: 45908 | B1025: 08-SEP- 2025 | C1025: 000MOBT25251AIU6 PAYMENT FOR ACCOMODATION BALANCE FOR IIH STAFF ZOHO LAGOS TRIP NIP Transfer from ILORIN | D1025: Bank charges | E1025: 3.75 | F1025: Bank01

Sheet Cover
F15: Ilorin Innovation Hub
F16: Financial Report
F17: for the 6month period ended 31st August 2025

Sheet SCI
B2: IIH Financial 2025 Report
B3: Statement of comprehensive income
B4: For the 6month period ended 31 August 2025
D6: 45900 | E6: 30 xxx 2024
C7: Notes | D7: ₦’000 | E7: N'000
B8: Income | C8: =Notes!A6 -> 1 | D8: =Notes!D11 -> 156653.44
B9: Cost of sales | D9: 0
B10: Gross Surplus/(Deficit) | D10: =SUM(D8:D9) -> 156653.44 | E10: =SUM(E8:E9) -> 0
B11: Administrative expenses | C11: =Notes!A14 -> 2 | D11: =-Notes!D31 -> -121690.25
B12: Other income | C12: =Notes!A33 -> 3 | D12: =Notes!D37 -> 0
B13: Operating Surplus/(Deficit) | D13: =SUM(D10:D12) -> 34963.196 | E13: =SUM(E10:E12) -> 0
B14: Finance income | D14: 0
B15: Finance cost | D15: 0
B16: Surplus/(Deficit) before taxation | D16: =SUM(D13:D15) -> 34963.196 | E16: =SUM(E13:E15) -> 0
B17: Taxation charge | D17: 0
B18: Surplus/(Deficit) for the period | D18: =SUM(D16:D17) -> 34963.196 | E18: =SUM(E16:E17) -> 0

Sheet SFP
B2: IIH Financial 2025 Report
B3: Statement of financial position
B4: =SCI!B4 -> For the 6month period ended 31 August 2025
D6: =SCI!D6 -> 45900 | E6: 30 xxx 2024
C7: Notes | D7: ₦’000 | E7: N'000
B8: ASSETS
B9: Non-current assets
B10: Property, plant and equipment | C10: =Notes!A40 -> 4 | D10: =Notes!D55 -> 1367
B11: Intangible assets
B12: Investments
D13: =SUM(D10:D12) -> 1367 | E13: =SUM(E10:E12) -> 0
B15: Current assets
B16: Trade and other receivables | C16: =Notes!A59 -> 5 | D16: =Notes!D65 -> 0
B17: Inventories | C17: =Notes!A67 -> 6 | D17: =Notes!D72 -> 0
B18: Bank and cash balances | C18: =Notes!A74 -> 7 | D18: =Notes!D78 -> 95219.76
D19: =SUM(D16:D18) -> 95219.76 | E19: =SUM(E16:E18) -> 0
B21: Total assets | D21: =D19+D13 -> 96586.76 | E21: =E19+E13 -> 0
B23: LIABILITIES
B24: Current liabilities
B25: Trade and other payables | C25: =Notes!A80 -> 8 | D25: =Notes!D86 -> -780
B26: Borrowings
B27: Provision for liabilities and charges
B28: Income tax liabilities
D29: =SUM(D25:D28) -> -780 | E29: =SUM(E25:E28) -> 0
B31: Non-current liabilities
B32: Borrowings
B33: Provision for liabilities and charges
D34: =SUM(D32:D33) -> 0 | E34: =SUM(E32:E33) -> 0
B36: Total liabilities | D36: =D34+D29 -> -780 | E36: =E34+E29 -> 0
B38: Net Asset/(liabilities) | D38: =D21-D36 -> 97366.76 | E38: =E21-E36 -> 0
B40: FUNDS/RESERVES
B41: Surplus/Deficit | C41: =Notes!A88 -> 9 | D41: =Notes!C93 -> 34963.196
B42: Reserves | D42: 0
B43: Total Accumulated Funds | D43: =SUM(D41:D42) -> 34963.196 | E43: =SUM(E41:E42) -> 0
B45: Total liabilities and funds | D45: =D43+D36 -> 34183.196 | E45: =E43+E36 -> 0
B46: Check | D46: =D45-D21 -> -62403.563

Sheet SCF
B2: IIH Financial 2025 Report
B3: Statement of cashflows
B4: =SFP!B4 -> For the 6month period ended 31 August 2025
C6: =SFP!D6 -> 45900 | D6: 30 xxx 2024
B7: Cash flows from operating activities | C7: ₦’000 | D7: N'000
B8: Surplus/(Deficit) for the period | C8: =SCI!D18 -> 34963.196
B10: Add non-cash items:
B11: Depreciation expense | C11: =Notes!D50 -> 0
B12: Interest received | C12: =-Notes!D35 -> 0
C13: =SUM(C8:C11) -> 34963.196
B14: Changes in working capital:
B15: (Increase)/Decrease in receivables | C15: =SFP!E16-SFP!D16 -> 0
B16: Increase/(Decrease) in payables | C16: =SFP!D25-SFP!E25 -> -780
B17: (Increase)/Decrease in inventories | C17: =SFP!E17-SFP!D17 -> 0
C18: =SUM(C15:C17) -> -780 | D18: =SUM(D15:D16) -> 0
B20: Cash generated from operations | C20: =C18+C13 -> 34183.196
B21: Income taxes paid
B22: Net cash flows generated from operating activities | C22: =SUM(C20:C21) -> 34183.196
B24: Cash flows from investing activities
B25: Purchase of property, plant and equipment | C25: =-Notes!C44 -> -1367
B26: Purchase of software and licences
B27: Proceeds from sale of property, plant and equipment
B28: Proceeds from sale of investment
B29: Interest received | C29: =Notes!D35 -> 0
B30: Short term deposits
B31: Net cash used in investing activities | C31: =SUM(C25:C30) -> -1367
B33: Cash flows from financing activities
B34: Interest paid to third parties | C34: 0
B35: Interest paid to related parties | C35: 0
B36: Loan receipts from third parties | C36: 0
B37: Loan receipts from related parties | C37: 0
B38: Principal repayment to third parties | C38: 0
B39: Principal repayment to related parties | C39: 0
B40: Net cash used in financing activities | C40: =SUM(C34:C39) -> 0
B42: Increase/(decrease) in cash and cash equivalents | C42: =C40+C31+C22 -> 32816.196
B43: Cash and cash equivalents at beginning of the period | C43: 0
B44: Cash and cash equivalent at period end | C44: =SUM(C42:C43) -> 32816.196
B45: Check | C45: =C44-SFP!D18 -> -62403.563

Sheet Notes
B2: IIH Financial 2025 Report
B3: Notes to financial report
B4: =SCF!B4 -> For the 6month period ended 31 August 2025
A6: 1 | B6: Income | D6: =SCF!C6 -> 45900 | E6: 30 xxx 2024
D7: =SCF!C7 -> ₦’000 | E7: N'000
B8: Donations | D8: =-SUMIF('Trial Balance'!E:E,B8,'Trial Balance'!C:C)/1000 -> 146127.94
B9: Facility rentals | D9: =-SUMIF('Trial Balance'!E:E,B9,'Trial Balance'!C:C)/1000 -> 10525.5
B10: Others | D10: =-SUMIF('Trial Balance'!E:E,B10,'Trial Balance'!C:C)/1000 -> 0
D11: =SUM(D8:D10) -> 156653.44 | E11: =SUM(E8:E10) -> 0
A14: =A6+1 -> 2 | B14: Administrative expenses | D14: =D6 -> 45900 | E14: 30 xxx 2024
D15: =D7 -> ₦’000 | E15: N'000
B16: Staff salaries and allowance | D16: =SUMIF('Trial Balance'!E:E,B16,'Trial Balance'!C:C)/1000 -> 58552.327
B17: Repairs and Maintenance | D17: =SUMIF('Trial Balance'!E:E,B17,'Trial Balance'!C:C)/1000 -> 8458.025
B18: Guest entertainment | D18: =SUMIF('Trial Balance'!E:E,B18,'Trial Balance'!C:C)/1000 -> 3000.0912
B19: Travel expense - Local | D19: =SUMIF('Trial Balance'!E:E,B19,'Trial Balance'!C:C)/1000 -> 6035.458
B20: Travel expense - International | D20: =SUMIF('Trial Balance'!E:E,B20,'Trial Balance'!C:C)/1000 -> 7442.5598
B21: Cleaning expense | D21: =SUMIF('Trial Balance'!E:E,B21,'Trial Balance'!C:C)/1000 -> 6292
B22: Telephone and Data expense | D22: =SUMIF('Trial Balance'!E:E,B22,'Trial Balance'!C:C)/1000 -> 6354.1758
B23: Office Supplies | D23: =SUMIF('Trial Balance'!E:E,B23,'Trial Balance'!C:C)/1000 -> 6573.9248
B24: Advertising And Marketing | D24: =SUMIF('Trial Balance'!E:E,B24,'Trial Balance'!C:C)/1000 -> 4020
B25: Bank Fees and Charges | D25: =SUMIF('Trial Balance'!E:E,B25,'Trial Balance'!C:C)/1000 -> 236.41482
B26: Security expense | D26: =SUMIF('Trial Balance'!E:E,B26,'Trial Balance'!C:C)/1000 -> 4412.3
B27: Fuel/Diesel Expenses | D27: =SUMIF('Trial Balance'!E:E,B27,'Trial Balance'!C:C)/1000 -> 507.71
... B30: Other Expenses | D30: =SUMIF('Trial Balance'!E:E,B30,'Trial Balance'!C:C)/1000 -> 2449.5165
D31: =SUM(D16:D30) -> 121690.25
A33: =A14+1 -> 3 | B33: Other income | D33: =D14 -> 45900 | E33: 30 xxx 2024
D34: =D15 -> ₦’000 | E34: N'000
B35: Interest Income | D35: =SUMIF('Trial Balance'!E:E,B35,'Trial Balance'!C:C)/1000 -> 0
D37: =SUM(D35:D36) -> 0
A40: =A33+1 -> 4 | B40: Property, plant and equipment
C41: Furniture & Equipment | D41: Total
B42: Cost | C42: =D34 -> ₦’000 | D42: =C42 -> ₦’000
B43: At beginning of year | C43: 0 | D43: =SUM(C43) -> 0
B44: Additions | C44: ='Trial Balance'!C51/1000 -> 1367 | D44: =SUM(C44) -> 1367
B45: Disposals
B46: At end of year | C46: =SUM(C44:C45) -> 1367 | D46: =SUM(D44:D45) -> 1367
B48: Depreciation and impairment
B49: At beginning of year | C49: 0 | D49: =SUM(C49) -> 0
B50: Charge for the year | C50: ='Trial Balance'!C52/1000 -> 0 | D50: =SUM(C50) -> 0
B51: Disposals
B52: At end of year | C52: =SUM(C50:C51) -> 0 | D52: =SUM(D50:D51) -> 0
B54: Carrying amount
B55: As at 30 xxx 2025 | C55: =C46-C52 -> 1367 | D55: =D46-D52 -> 1367
B56: As at 30 xxx 2024 | C56: =C43-C49 -> 0 | D56: =D43-D49 -> 0
A59: =A40+1 -> 5 | B59: Trade and other receivables | D59: =D33 -> 45900 | E59: 30 xxx 2024
D60: =D34 -> ₦’000 | E60: N'000
B61: Trade receivables | D61: =SUMIF('Trial Balance'!E:E,B61,'Trial Balance'!C:C)/1000 -> 0
B62: Other receivables | D62: =SUMIF('Trial Balance'!E:E,B62,'Trial Balance'!C:C)/1000 -> 0
B63: Prepaid expenses | D63: =SUMIF('Trial Balance'!E:E,B63,'Trial Balance'!C:C)/1000 -> 0
D65: =SUM(D61:D64) -> 0
A67: =A59+1 -> 6 | B67: Inventories | D67: =D59 -> 45900 | E67: 30 xxx 2024
D68: =D60 -> ₦’000 | E68: N'000
B69: Balance at beginning | D69: 0
B70: Additions
B71: Transfered to cost of goods sold
D72: =SUM(D69:D71) -> 0
A74: =A67+1 -> 7 | B74: Bank and cash balances | D74: =D67 -> 45900 | E74: 30 xxx 2024
D75: =D68 -> ₦’000 | E75: N'000
B76: Bank | D76: =SUMIF('Trial Balance'!E:E,B76,'Trial Balance'!C:C)/1000 -> 95219.76
B77: Cash | D77: =SUMIF('Trial Balance'!E:E,B77,'Trial Balance'!C:C)/1000 -> 0
D78: =SUM(D76:D77) -> 95219.76
A80: =A74+1 -> 8 | B80: Trade and other payables | D80: =D74 -> 45900 | E80: 30 xxx 2024
D81: =D75 -> ₦’000 | E81: N'000
B82: Accounts Payable | D82: =-SUMIF('Trial Balance'!E:E,B82,'Trial Balance'!C:C)/1000 -> -780
B83: Tax Payable | D83: =-SUMIF('Trial Balance'!E:E,B83,'Trial Balance'!C:C)/1000 -> 0
B84: Unearned Revenue | D84: =-SUMIF('Trial Balance'!E:E,B84,'Trial Balance'!C:C)/1000 -> 0
B85: Other Liabilities | D85: =-SUMIF('Trial Balance'!E:E,B85,'Trial Balance'!C:C)/1000 -> 0
D86: =SUM(D82:D85) -> -780
A88: =A80+1 -> 9 | B88: Accumulated funds | C88: Surplus/Deficit for the year | D88: Total
C89: =D81 -> ₦’000 | D89: =C89 -> ₦’000
B90: Balance at beginning | D90: =SUM(C90:C90) -> 0
B91: Surplus/(Deficit) for the year | C91: =SCI!D18 -> 34963.196 | D91: =SUM(C91:C91) -> 34963.196
B92: Reserves | C92: =-SUMIF('Trial Balance'!E:E,B92,'Trial Balance'!C:C)/1000 -> 0
C93: =SUM(C90:C92) -> 34963.196 | D93: =SUM(D90:D92) -> 34963.196

Sheet >>>>

Sheet Trial Balance
C1: =SUBTOTAL(9,C3:C78) -> 62403563
A2: Account Code | B2: Account Name | C2: Amount | D2: Account Type | E2: Category | F2: FSLI
B3: Donations | C3: =SUMIF(GL_Transactions!E:E,'Trial Balance'!B3,GL_Transactions!F:F) -> -1.4612794e+08 | D3: =VLOOKUP(B3,'Chart of Accounts'!B:F,4,0) -> Income | E3: Donations | F3: =VLOOKUP(B3,'Chart of Accounts'!B:F,5,0) -> Income
B4: Facility rentals | C4: =SUMIF(GL_Transactions!E:E,'Trial Balance'!B4,GL_Transactions!F:F) -> -8392950 | D4: =VLOOKUP(B4,'Chart of Accounts'!B:F,4,0) -> Income | E4: Facility rentals | F4: =VLOOKUP(B4,'Chart of Accounts'!B:F,5,0) -> Income
B5: Guest entertainment (Income) | C5: =SUMIF(GL_Transactions!E:E,'Trial Balance'!B5,GL_Transactions!F:F) -> -2132550 | D5: =VLOOKUP(B5,'Chart of Accounts'!B:F,4,0) -> Income | E5: Facility rentals | F5: =VLOOKUP(B5,'Chart of Accounts'!B:F,5,0) -> Income
B6: Discount | C6: =SUMIF(GL_Transactions!E:E,'Trial Balance'!B6,GL_Transactions!F:F) -> 0 | D6: =VLOOKUP(B6,'Chart of Accounts'!B:F,4,0) -> Income | E6: Facility rentals | F6: =VLOOKUP(B6,'Chart of Accounts'!B:F,5,0) -> Income
B7: Other Charges | C7: =SUMIF(GL_Transactions!E:E,'Trial Balance'!B7,GL_Transactions!F:F) -> 0 | D7: =VLOOKUP(B7,'Chart of Accounts'!B:F,4,0) -> Income | E7: Others | F7: =VLOOKUP(B7,'Chart of Accounts'!B:F,5,0) -> Income
B8: Sales | C8: =SUMIF(GL_Transactions!E:E,'Trial Balance'!B8,GL_Transactions!F:F) -> 0 | D8: =VLOOKUP(B8,'Chart of Accounts'!B:F,4,0) -> Income | E8: Others | F8: =VLOOKUP(B8,'Chart of Accounts'!B:F,5,0) -> Income
B9: General Income | C9: =SUMIF(GL_Transactions!E:E,'Trial Balance'!B9,GL_Transactions!F:F) -> 0 | D9: =VLOOKUP(B9,'Chart of Accounts'!B:F,4,0) -> Income | E9: Others | F9: =VLOOKUP(B9,'Chart of Accounts'!B:F,5,0) -> Income
B10: Interest Income | C10: =SUMIF(GL_Transactions!E:E,'Trial Balance'!B10,GL_Transactions!F:F) -> 0 | D10: =VLOOKUP(B10,'Chart of Accounts'!B:F,4,0) -> Income | E10: Interest Income | F10: Other income
B11: Late Fee Income | C11: =SUMIF(GL_Transactions!E:E,'Trial Balance'!B11,GL_Transactions!F:F) -> 0 | D11: =VLOOKUP(B11,'Chart of Accounts'!B:F,4,0) -> Income | E11: Others | F11: =VLOOKUP(B11,'Chart of Accounts'!B:F,5,0) -> Income
B12: Shipping Charge | C12: =SUMIF(GL_Transactions!E:E,'Trial Balance'!B12,GL_Transactions!F:F) -> 0 | D12: =VLOOKUP(B12,'Chart of Accounts'!B:F,4,0) -> Income | E12: Others | F12: =VLOOKUP(B12,'Chart of Accounts'!B:F,5,0) -> Income
B13: Cost of Goods Sold | C13: =SUMIF(GL_Transactions!E:E,'Trial Balance'!B13,GL_Transactions!F:F) -> 0 | D13: =VLOOKUP(B13,'Chart of Accounts'!B:F,4,0) -> Cost Of Goods Sold | E13: COGS | F13: =VLOOKUP(B13,'Chart of Accounts'!B:F,5,0) -> Cost of sales
B14: Guest entertainment | C14: =SUMIF(GL_Transactions!E:E,'Trial Balance'!B14,GL_Transactions!F:F) -> 3000091.2 | D14: =VLOOKUP(B14,'Chart of Accounts'!B:F,4,0) -> Expense | E14: Guest entertainment | F14: Administrative expenses
B15: Lodging | C15: =SUMIF(GL_Transactions!E:E,'Trial Balance'!B15,GL_Transactions!F:F) -> 0 | D15: =VLOOKUP(B15,'Chart of Accounts'!B:F,4,0) -> Expense | E15: Other Expenses | F15: =VLOOKUP(B15,'Chart of Accounts'!B:F,5,0) -> Administrative expenses
B16: Office Supplies | C16: =SUMIF(GL_Transactions!E:E,'Trial Balance'!B16,GL_Transactions!F:F) -> 6573924.8 | D16: =VLOOKUP(B16,'Chart of Accounts'!B:F,4,0) -> Expense | E16: Office Supplies | F16: =VLOOKUP(B16,'Chart of Accounts'!B:F,5,0) -> Administrative expenses
B17: Advertising And Marketing | C17: =SUMIF(GL_Transactions!E:E,'Trial Balance'!B17,GL_Transactions!F:F) -> 4020000 | D17: =VLOOKUP(B17,'Chart of Accounts'!B:F,4,0) -> Expense | E17: Advertising And Marketing | F17: =VLOOKUP(B17,'Chart of Accounts'!B:F,5,0) -> Administrative expenses
B18: Bank Fees and Charges | C18: =SUMIF(GL_Transactions!E:E,'Trial Balance'!B18,GL_Transactions!F:F) -> 236414.82 | D18: =VLOOKUP(B18,'Chart of Accounts'!B:F,4,0) -> Expense | E18: Bank Fees and Charges | F18: =VLOOKUP(B18,'Chart of Accounts'!B:F,5,0) -> Administrative expenses
B19: Credit Card Charges | C19: =SUMIF(GL_Transactions!E:E,'Trial Balance'!B19,GL_Transactions!F:F) -> 0 | D19: =VLOOKUP(B19,'Chart of Accounts'!B:F,4,0) -> Expense | E19: Other Expenses | F19: =VLOOKUP(B19,'Chart of Accounts'!B:F,5,0) -> Administrative expenses
B20: Telephone and Data expense | C20: =SUMIF(GL_Transactions!E:E,'Trial Balance'!B20,GL_Transactions!F:F) -> 6354175.8 | D20: =VLOOKUP(B20,'Chart of Accounts'!B:F,4,0) -> Expense | E20: Telephone and Data expense | F20: =VLOOKUP(B20,'Chart of Accounts'!B:F,5,0) -> Administrative expenses
B21: Software expense | C21: =SUMIF(GL_Transactions!E:E,'Trial Balance'!B21,GL_Transactions!F:F) -> 1596388.2 | D21: =VLOOKUP(B21,'Chart of Accounts'!B:F,4,0) -> Expense | E21: Software expense | F21: =VLOOKUP(B21,'Chart of Accounts'!B:F,5,0) -> Administrative expenses
B22: Exchange Gain or Loss | C22: =SUMIF(GL_Transactions!E:E,'Trial Balance'!B22,GL_Transactions!F:F) -> 0 | D22: =VLOOKUP(B22,'Chart of Accounts'!B:F,4,0) -> Other Expense | E22: Other Expenses | F22: =VLOOKUP(B22,'Chart of Accounts'!B:F,5,0) -> Administrative expenses
B23: Air Travel Expense | C23: =SUMIF(GL_Transactions!E:E,'Trial Balance'!B23,GL_Transactions!F:F) -> 0 | D23: =VLOOKUP(B23,'Chart of Accounts'!B:F,4,0) -> Expense | E23: Other Expenses | F23: =VLOOKUP(B23,'Chart of Accounts'!B:F,5,0) -> Administrative expenses
B24: Telephone Expense | C24: =SUMIF(GL_Transactions!E:E,'Trial Balance'!B24,GL_Transactions!F:F) -> 0 | D24: =VLOOKUP(B24,'Chart of Accounts'!B:F,4,0) -> Expense | E24: Other Expenses | F24: =VLOOKUP(B24,'Chart of Accounts'!B:F,5,0) -> Administrative expenses
B25: Automobile Expense | C25: =SUMIF(GL_Transactions!E:E,'Trial Balance'!B25,GL_Transactions!F:F) -> 0 | D25: =VLOOKUP(B25,'Chart of Accounts'!B:F,4,0) -> Expense | E25: Other Expenses | F25: =VLOOKUP(B25,'Chart of Accounts'!B:F,5,0) -> Administrative expenses
B26: IT and Internet Expenses | C26: =SUMIF(GL_Transactions!E:E,'Trial Balance'!B26,GL_Transactions!F:F) -> 621116.76 | D26: =VLOOKUP(B26,'Chart of Accounts'!B:F,4,0) -> Expense | E26: Other Expenses | F26: =VLOOKUP(B26,'Chart of Accounts'!B:F,5,0) -> Administrative expenses
... B78: Clearing account | C78: =SUMIF(GL_Transactions!E:E,'Trial Balance'!B78,GL_Transactions!F:F) -> -742000 | D78: =VLOOKUP(B78,'Chart of Accounts'!B:F,4,0) -> Expense | E78: Other Expenses | F78: =VLOOKUP(B78,'Chart of Accounts'!B:F,5,0) -> Administrative expenses
B80: Balance check | C80: =SUM(C3:C79) -> 62403563

Sheet GL_Transactions
A1: Trans Date | B1: Period | C1: Transaction Details | D1: Category | E1: Category per Zoho | F1: Transactions | G1: Bank | H1: Description
A2: 45798 | B2: 45808 | C2: 016NIPT251410435 NIP TRSF FROM AYOBAMI JOEL ATOLAGBE IIH HALL BOOKING by | D2: Facility rentals | E2: Facility rentals | F2: -444000 | G2: Bank01 | H2: INV-000015
A3: 45798 | B3: 45808 | C3: 016EMTL251410057 ELECTRONIC MONEY TRANSFER LEVY | D3: Bank charges | E3: Bank Fees and Charges | F3: 50 | G3: Bank01
A4: 45807 | B4: 45808 | C4: 000MOBT25150A0VX Payment for 4 flags US EU UNDP NG NIP Transfer from ILORIN INNOVATION HUB LTD to LET S BR | D4: Stationery and Office Supplies | E4: Office Supplies | F4: 40000 | G4: Bank01
A5: 45807 | B5: 45808 | C5: 000MOBT25150A0VX Payment for 4 flags US EU UNDP NG NIP Transfer from ILORIN INNOVATION HUB LTD to LET S BR | D5: Bank charges | E5: Bank Fees and Charges | F5: 25 | G5: Bank01
A6: 45807 | B6: 45808 | C6: 000MOBT25150A0VX Payment for 4 flags US EU UNDP NG NIP Transfer from ILORIN INNOVATION HUB LTD to LET S BR | D6: Bank charges | E6: Bank Fees and Charges | F6: 1.88 | G6: Bank01
A7: 45807 | B7: 45808 | C7: 0168840251500001 BNG LEGAL SEARCH FEE FOR ILORIN INNOVATION HUB LTD0040117676 | D7: Bank charges | E7: Bank Fees and Charges | F7: 10750 | G7: Bank01
A8: 45807 | B8: 45808 | C8: 000MOBT25150A5H9 Purchase of cleaning supplies NIP Transfer from ILORIN INNOVATION HUB LTD to MAUREEN DANIE | D8: Cleaning expenses | E8: Janitorial Expense | F8: 12000 | G8: Bank01
A9: 45807 | B9: 45808 | C9: 000MOBT25150A5H9 Purchase of cleaning supplies NIP Transfer from ILORIN INNOVATION HUB LTD to MAUREEN DANIE | D9: Bank charges | E9: Bank Fees and Charges | F9: 25 | G9: Bank01
A10: 45807 | B10: 45808 | C10: 000MOBT25150A5H9 Purchase of cleaning supplies NIP Transfer from ILORIN INNOVATION HUB LTD to MAUREEN DANIE | D10: Bank charges | E10: Bank Fees and Charges | F10: 1.88 | G10: Bank01
A11: 45807 | B11: 45808 | C11: 000MOBT25150AA0U NIP Transfer from ILORIN INNOVATION HUB LTD to MAUREEN DANIEL OKEY | D11: Other Expenses | E11: Other Expenses | F11: 15300 | G11: Bank01
A12: 45807 | B12: 45808 | C12: 000MOBT25150AA0U NIP Transfer from ILORIN INNOVATION HUB LTD to MAUREEN DANIEL OKEY | D12: Bank charges | E12: Bank Fees and Charges | F12: 25 | G12: Bank01
A13: 45807 | B13: 45808 | C13: 000MOBT25150AA0U NIP Transfer from ILORIN INNOVATION HUB LTD to MAUREEN DANIEL OKEY | D13: Bank charges | E13: Bank Fees and Charges | F13: 1.88 | G13: Bank01
A14: 45807 | B14: 45808 | C14: 016AMFC251500023 ACCOUNT MAINTENANCE FEE | D14: Bank charges | E14: Bank Fees and Charges | F14: 67.3 | G14: Bank01
... A19: 45810 | B19: 45838 | C19: 000MOBT25150AJEP REFUND FOR PURCHASE OF SPEAKER SYSTEM NIP Transfer from ILORIN INNOVATION HUB LTD | D19: Bank charges | E19: Bank Fees and Charges | F19: 3.75 | G19: Bank01
A20: 45810 | B20: 45838 | C20: 000NEFI251530339 NEFT INWARD STP CR - ILORIN INNOVATION HUB (Q2 ONE-OFF I B/O IHS (NIGERIA) LIMITED | D20: IHS Payment | E20: Donations | F20: -44499369 | G20: Bank01 | H20: INV-000013
A21: 45810 | B21: 45838 | C21: 000MOBT25153A588 IIH SALARY MAY 2025 NIP Transfer from ILORIN INNOVATION HUB LTD to ONUCHUKWU SINACHI GOOD | D21: Salaries and Wages | E21: Salaries and Employee Wages | F21: 249491.56 | G21: Bank01
A22: 45810 | B22: 45838 | C22: 000MOBT25153A588 IIH SALARY MAY 2025 NIP Transfer from ILORIN INNOVATION HUB LTD to ONUCHUKWU SINACHI GOOD | D22: Bank charges | E22: Bank Fees and Charges | F22: 50 | G22: Bank01
A23: 45810 | B23: 45838 | C23: 000MOBT25153A588 IIH SALARY MAY 2025 NIP Transfer from ILORIN INNOVATION HUB LTD to ONUCHUKWU SINACHI GOOD | D23: Bank charges | E23: Bank Fees and Charges | F23: 3.75 | G23: Bank01
A24: 45810 | B24: 45838 | C24: 000MOBT25153A5CB IIH SALARY MAY 2025 ALLOWANCES NIP Transfer from ILORIN INNOVATION HUB LTD to ONUCHUKWU S | D24: Salaries and Wages | E24: Salaries and Employee Wages | F24: 35000 | G24: Bank01
A25: 45810 | B25: 45838 | C25: 000MOBT25153A5CB IIH SALARY MAY 2025 ALLOWANCES NIP Transfer from ILORIN INNOVATION HUB LTD to ONUCHUKWU S | D25: Bank charges | E25: Bank Fees and Charges | F25: 25 | G25: Bank01
A26: 45810 | B26: 45838 | C26: 000MOBT25153A5CB IIH SALARY MAY 2025 ALLOWANCES NIP Transfer from ILORIN INNOVATION HUB LTD to ONUCHUKWU S | D26: Bank charges | E26: Bank Fees and Charges | F26: 1.88 | G26: Bank01
A27: 45810 | B27: 45838 | C27: 000MOBT25153A5D4 IIH MAY 2025 SALARY ALLOWANCES NIP Transfer from ILORIN INNOVATION HUB LTD to OLUWADAMILA | D27: Salaries and Wages | E27: Salaries and Employee Wages | F27: 284491.56 | G27: Bank01
A28: 45810 | B28: 45838 | C28: 000MOBT25153A5D4 IIH MAY 2025 SALARY ALLOWANCES NIP Transfer from ILORIN INNOVATION HUB LTD to OLUWADAMILA | D28: Bank charges | E28: Bank Fees and Charges | F28: 50 | G28: Bank01
A29: 45810 | B29: 45838 | C29: 000MOBT25153A5D4 IIH MAY 2025 SALARY ALLOWANCES NIP Transfer from ILORIN INNOVATION HUB LTD to OLUWADAMILA | D29: Bank charges | E29: Bank Fees and Charges | F29: 3.75 | G29: Bank01
A30: 45810 | B30: 45838 | C30: 000MOBT25153A5G3 IIH SALARY MAY 2025 ALLOWANCES NIP Transfer from ILORIN INNOVATION HUB LTD to TEMILOLUWA | D30: Salaries and Wages | E30: Salaries and Employee Wages | F30: 3570659.4 | G30: Bank01
A31: 45810 | B31: 45838 | C31: 000MOBT25153A5G3 IIH SALARY MAY 2025 ALLOWANCES NIP Transfer from ILORIN INNOVATION HUB LTD to TEMILOLUWA | D31: Bank charges | E31: Bank Fees and Charges | F31: 50 | G31: Bank01
A32: 45810 | B32: 45838 | C32: 000MOBT25153A5G3 IIH SALARY MAY 2025 ALLOWANCES NIP Transfer from ILORIN INNOVATION HUB LTD to TEMILOLUWA | D32: Bank charges | E32: Bank Fees and Charges | F32: 3.75 | G32: Bank01
... A51: 45811 | B51: 45838 | C51: 000MOBT251541459 MAY SALARY ALLOWANCES NIP Transfer from ILORIN INNOVATION HUB LTD to AKANDE | D51: Bank charges | E51: Bank Fees and Charges | F51: 3.75 | G51: Bank01
A52: 45811 | B52: 45838 | C52: 000NEFI251540263 NEFT INWARD STP CR - ILORIN INNOVATION HUB OPERATIONAL C B/O IHS (NIGERIA) LIMITED | D52: IHS Payment | E52: Donations | F52: -6935800 | G52: Bank01 | H52: INV-000014
A53: 45811 | B53: 45838 | C53: 000NEFI251540264 NEFT INWARD STP CR - ILORIN INNOVATION HUB (Q2 RECURRENT B/O IHS (NIGERIA) LIMITED | D53: IHS Payment | E53: Donations | F53: -94692772 | G53: Bank01 | H53: INV-000011
A54: 45811 | B54: 45838 | C54: 000MOBT25154A0ED IIH DEPOSIT REFUND FOR BITKWA EVENT NIP Transfer from ILORIN INNOVATION HUB LTD to AYOBAMI | D54: Deposit refund | E54: Refundable security deposit | F54: 100000 | G54: Bank01 | H54: INV-000015
A55: 45811 | B55: 45838 | C55: 000MOBT25154A0ED IIH DEPOSIT REFUND FOR BITKWA EVENT NIP Transfer from ILORIN INNOVATION HUB LTD to AYOBAMI | D55: Bank charges | E55: Bank Fees and Charges | F55: 50 | G55: Bank01
A56: 45811 | B56: 45838 | C56: 000MOBT25154A0ED IIH DEPOSIT REFUND FOR BITKWA EVENT NIP Transfer from ILORIN INNOVATION HUB LTD to AYOBAMI | D56: Bank charges | E56: Bank Fees and Charges | F56: 3.75 | G56: Bank01
A57: 45811 | B57: 45838 | C57: 000MOBT25154A0F7 JUNE OFFICE SUPPLIES NIP Transfer from ILORIN INNOVATION HUB LTD to MAUREEN DANIEL OKEY | D57: Stationery and Office Supplies | E57: Office Supplies | F57: 150000 | G57: Bank01
A58: 45811 | B58: 45838 | C58: 000MOBT25154A0F7 JUNE OFFICE SUPPLIES NIP Transfer from ILORIN INNOVATION HUB LTD to MAUREEN DANIEL OKEY | D58: Bank charges | E58: Bank Fees and Charges | F58: 50 | G58: Bank01
A59: 45811 | B59: 45838 | C59: 000MOBT25154A0F7 JUNE OFFICE SUPPLIES NIP Transfer from ILORIN INNOVATION HUB LTD to MAUREEN DANIEL OKEY | D59: Bank charges | E59: Bank Fees and Charges | F59: 3.75 | G59: Bank01
A60: 45811 | B60: 45838 | C60: 000MOBT25154A15G 50 JANITORIAL CLEANING NIP Transfer from ILORIN INNOVATION HUB LTD to SIII MULTIPURPOSE | D60: Cleaning expenses | E60: Janitorial Expense | F60: 650000 | G60: Bank01
A61: 45811 | B61: 45838 | C61: 000MOBT25154A15G 50 JANITORIAL CLEANING NIP Transfer from ILORIN INNOVATION HUB LTD to SIII MULTIPURPOSE | D61: Bank charges | E61: Bank Fees and Charges | F61: 50 | G61: Bank01
A62: 45811 | B62: 45838 | C62: 000MOBT25154A15G 50 JANITORIAL CLEANING NIP Transfer from ILORIN INNOVATION HUB LTD to SIII MULTIPURPOSE | D62: Bank charges | E62: Bank Fees and Charges | F62: 3.75 | G62: Bank01
A63: 45811 | B63: 45838 | C63: 016EMTL2515400BW ELECTRONIC MONEY TRANSFER LEVY | D63: Bank charges | E63: Bank Fees and Charges | F63: 50 | G63: Bank01
A64: 45811 | B64: 45838 | C64: 016EMTL2515400CD ELECTRONIC MONEY TRANSFER LEVY | D64: Bank charges | E64: Bank Fees and Charges | F64: 50 | G64: Bank01
A65: 45812 | B65: 45838 | C65: 000MOBT25154A3ZU MARCH SALARY ALLOWANCES NIP Transfer from ILORIN INNOVATION HUB LTD to TEMILOLUWA | D65: Salaries and Wages | E65: Salaries and Employee Wages | F65: 3570659.4 | G65: Bank01
A66: 45812 | B66: 45838 | C66: 000MOBT25154A3ZU MARCH SALARY ALLOWANCES NIP Transfer from ILORIN INNOVATION HUB LTD to TEMILOLUWA | D66: Bank charges | E66: Bank Fees and Charges | F66: 50 | G66: Bank01
... A86: 45813 | B86: 45838 | C86: 000MOBT251567774 STARLINK PURCHASE INSTALLATION NIP Transfer from ILORIN INNOVATION HUB LTD to FEMTECH INF | D86: Bank charges | E86: Bank Fees and Charges | F86: 3.75 | G86: Bank01
A87: 45818 | B87: 45838 | C87: 016NIPT251560778 NIP TRSF FROM COCREATION HUB LIMITED ER-05417 IHS ILORIN INNOVATION REFUND TO | D87: Income | E87: Guest entertainment (Income) | F87: -135300 | G87: Bank01 | H87: INV-000016
A88: 45818 | B88: 45838 | C88: 000MOBT25161B18D Reimbursement for Office Equipment purchase NIP Transfer from ILORIN INNOVATION HUB LTD t | D88: Stationery and Office Supplies | E88: Office Supplies | F88: 36000 | G88: Bank01
A89: 45818 | B89: 45838 | C89: 000MOBT25161B18D Reimbursement for Office Equipment purchase NIP Transfer from ILORIN INNOVATION HUB LTD t | D89: Bank charges | E89: Bank Fees and Charges | F89: 25 | G89: Bank01
A90: 45818 | B90: 45838 | C90: 000MOBT25161B18D Reimbursement for Office Equipment purchase NIP Transfer from ILORIN INNOVATION HUB LTD t | D90: Bank charges | E90: Bank Fees and Charges | F90: 1.88 | G90: Bank01
A91: 45818 | B91: 45838 | C91: 000MOBT25161B1AA DSTV Compact Xtraview Subscription NIP Transfer from ILORIN INNOVATION HUB LTD to ISAIAH | D91: Other Expenses | E91: Other Expenses | F91: 25000 | G91: Bank01
A92: 45818 | B92: 45838 | C92: 000MOBT25161B1AA DSTV Compact Xtraview Subscription NIP Transfer from ILORIN INNOVATION HUB LTD to ISAIAH | D92: Bank charges | E92: Bank Fees and Charges | F92: 25 | G92: Bank01
A93: 45818 | B93: 45838 | C93: 000MOBT25161B1AA DSTV Compact Xtraview Subscription NIP Transfer from ILORIN INNOVATION HUB LTD to ISAIAH | D93: Bank charges | E93: Bank Fees and Charges | F93: 1.88 | G93: Bank01
A94: 45818 | B94: 45838 | C94: 000MOBT25161B2CT Electrical security light repair NIP Transfer from ILORIN INNOVATION HUB LTD to ELIJAH OD | D94: Repairs and maintenance | E94: Repairs and Maintenance | F94: 13000 | G94: Bank01
A95: 45818 | B95: 45838 | C95: 000MOBT25161B2CT Electrical security light repair NIP Transfer from ILORIN INNOVATION HUB LTD to ELIJAH OD | D95: Bank charges | E95: Bank Fees and Charges | F95: 25 | G95: Bank01
A96: 45818 | B96: 45838 | C96: 000MOBT25161B2CT Electrical security light repair NIP Transfer from ILORIN INNOVATION HUB LTD to ELIJAH OD | D96: Bank charges | E96: Bank Fees and Charges | F96: 1.88 | G96: Bank01
A97: 45818 | B97: 45838 | C97: 000MOBT25161B2EN Reimbursement for waste disposal payment NIP Transfer from ILORIN INNOVATION HUB LTD to HE | D97: Other Expenses | E97: Other Expenses | F97: 25000 | G97: Bank01
A98: 45818 | B98: 45838 | C98: 000MOBT25161B2EN Reimbursement for waste disposal payment NIP Transfer from ILORIN INNOVATION HUB LTD to HE | D98: Bank charges | E98: Bank Fees and Charges | F98: 25 | G98: Bank01
A99: 45818 | B99: 45838 | C99: 000MOBT25161B2EN Reimbursement for waste disposal payment NIP Transfer from ILORIN INNOVATION HUB LTD to HE | D99: Bank charges | E99: Bank Fees and Charges | F99: 1.88 | G99: Bank01
... A142: 45825 | B142: 45838 | C142: 000MOBT251684004 20 STAFF CUG LINES NIP Transfer from ILORIN INNOVATION HUB LTD to MUHAMMED NASIRU MAHMOOD | D142: Bank charges | E142: Bank Fees and Charges | F142: 3.75 | G142: Bank01
A143: 45825 | B143: 45838 | C143: 000MOBT251686079 NIP Transfer from ILORIN INNOVATION HUB LTD to PRECIOUS UCHECHUKWU OSELE | D143: Unallocated expense | E143: Other Expenses | F143: 162100 | G143: Bank01 | H143: Bidet for toilet
A144: 45825 | B144: 45838 | C144: 000MOBT251686079 NIP Transfer from ILORIN INNOVATION HUB LTD to PRECIOUS UCHECHUKWU OSELE | D144: Bank charges | E144: Bank Fees and Charges | F144: 50 | G144: Bank01
A145: 45825 | B145: 45838 | C145: 000MOBT251686079 NIP Transfer from ILORIN INNOVATION HUB LTD to PRECIOUS UCHECHUKWU OSELE | D145: Bank charges | E145: Bank Fees and Charges | F145: 3.75 | G145: Bank01
A146: 45825 | B146: 45838 | C146: 000MOBT251688231 PURCHASE OF 2 WASTE BINS NIP Transfer from ILORIN INNOVATION HUB LTD to Halimat Damilola A | D146: Stationery and Office Supplies | E146: Office Supplies | F146: 164000 | G146: Bank01
A147: 45825 | B147: 45838 | C147: 000MOBT251688231 PURCHASE OF 2 WASTE BINS NIP Transfer from ILORIN INNOVATION HUB LTD to Halimat Damilola A | D147: Bank charges | E147: Bank Fees and Charges | F147: 50 | G147: Bank01
A148: 45825 | B148: 45838 | C148: 000MOBT251688231 PURCHASE OF 2 WASTE BINS NIP Transfer from ILORIN INNOVATION HUB LTD to Halimat Damilola A | D148: Bank charges | E148: Bank Fees and Charges | F148: 3.75 | G148: Bank01
A149: 45826 | B149: 45838 | C149: 000MOBT251690018 ZOHO CREATOR 1 USER ANNUAL NIP Transfer from ILORIN INNOVATION HUB LTD to PAYSTACK | D149: Software expense - Zoho | E149: Software expense | F149: 198660 | G149: Bank01
A150: 45826 | B150: 45838 | C150: 000MOBT251690018 ZOHO CREATOR 1 USER ANNUAL NIP Transfer from ILORIN INNOVATION HUB LTD to PAYSTACK | D150: Bank charges | E150: Bank Fees and Charges | F150: 50 | G150: Bank01
A151: 45826 | B151: 45838 | C151: 000MOBT251690018 ZOHO CREATOR 1 USER ANNUAL NIP Transfer from ILORIN INNOVATION HUB LTD to PAYSTACK | D151: Bank charges | E151: Bank Fees and Charges | F151: 3.75 | G151: Bank01
A152: 45826 | B152: 45838 | C152: 016NIPT251690179 NIP TRSF FROM KWSG INT REV SERV EXP ACCT GT20250649 BEING PAYMENT TO RENT INNOVATION HUB TO | D152: Income | E152: Facility rentals | F152: -420000 | G152: Bank01 | H152: INV-000018
A153: 45826 | B153: 45838 | C153: 016EMTL2516900BW ELECTRONIC MONEY TRANSFER LEVY | D153: Bank charges | E153: Bank Fees and Charges | F153: 50 | G153: Bank01
A154: 45827 | B154: 45838 | C154: 016NIPT251700200 NIP TRSF FROM DADZIE OMOTOLA VANESSA NIP Transfer to ILORIN INNOVATION HUB LTD. | D154: Income | E154: Guest entertainment (Income) | F154: -18000 | G154: Bank01 | H154: INV-000019
A155: 45827 | B155: 45838 | C155: 000MOBT251709749 MTN CUG 16 LINES NIP Transfer from ILORIN INNOVATION HUB LTD to POSTPAID CUSTOMERSCOLLECTI | D155: Data and telephone expenses | E155: Telephone and Data expense | F155: 12000 | G155: Bank01
A156: 45827 | B156: 45838 | C156: 000MOBT251709749 MTN CUG 16 LINES NIP Transfer from ILORIN INNOVATION HUB LTD to POSTPAID CUSTOMERSCOLLECTI | D156: Bank charges | E156: Bank Fees and Charges | F156: 25 | G156: Bank01
A157: 45827 | B157: 45838 | C157: 000MOBT251709749 MTN CUG 16 LINES NIP Transfer from ILORIN INNOVATION HUB LTD to POSTPAID CUSTOMERSCOLLECTI | D157: Bank charges | E157: Bank Fees and Charges | F157: 1.88 | G157: Bank01
A158: 45827 | B158: 45838 | C158: 000MOBT25170A05E PURCHASE OF POWER BANKS NIP Transfer from ILORIN INNOVATION HUB LTD to FEMTECH PHONES | D158: Stationery and Office Supplies | E158: Office Supplies | F158: 304000 | G158: Bank01
A159: 45827 | B159: 45838 | C159: 000MOBT25170A05E PURCHASE OF POWER BANKS NIP Transfer from ILORIN INNOVATION HUB LTD to FEMTECH PHONES | D159: Bank charges | E159: Bank Fees and Charges | F159: 50 | G159: Bank01
A160: 45827 | B160: 45838 | C160: 000MOBT25170A05E PURCHASE OF POWER BANKS NIP Transfer from ILORIN INNOVATION HUB LTD to FEMTECH PHONES | D160: Bank charges | E160: Bank Fees and Charges | F160: 3.75 | G160: Bank01
A161: 45827 | B161: 45838 | C161: 000MOBT25170A07Q ZOZO MAIL 1 ONE ADDITIONAL USER NIP Transfer from ILORIN INNOVATION HUB LTD to PAYSTACK CH | D161: Software expense - Zoho | E161: Software expense | F161: 9470.36 | G161: Bank01
A162: 45827 | B162: 45838 | C162: 000MOBT25170A07Q ZOZO MAIL 1 ONE ADDITIONAL USER NIP Transfer from ILORIN INNOVATION HUB LTD to PAYSTACK CH | D162: Bank charges | E162: Bank Fees and Charges | F162: 25 | G162: Bank01
A163: 45827 | B163: 45838 | C163: 000MOBT25170A07Q ZOZO MAIL 1 ONE ADDITIONAL USER NIP Transfer from ILORIN INNOVATION HUB LTD to PAYSTACK CH | D163: Bank charges | E163: Bank Fees and Charges | F163: 1.88 | G163: Bank01
A164: 45827 | B164: 45838 | C164: 000MOBT25170A0C0 PURCHASE OF SAMSUNG GALAXY A06 FOR COMM MGR NIP Transfer from ILORIN INNOVATION HUB LTD | D164: Stationery and Office Supplies | E164: Office Supplies | F164: 150000 | G164: Bank01
A165: 45827 | B165: 45838 | C165: 000MOBT25170A0C0 PURCHASE OF SAMSUNG GALAXY A06 FOR COMM MGR NIP Transfer from ILORIN INNOVATION HUB LTD | D165: Bank charges | E165: Bank Fees and Charges | F165: 50 | G165: Bank01
A166: 45827 | B166: 45838 | C166: 000MOBT25170A0C0 PURCHASE OF SAMSUNG GALAXY A06 FOR COMM MGR NIP Transfer from ILORIN INNOVATION HUB LTD | D166: Bank charges | E166: Bank Fees and Charges | F166: 3.75 | G166: Bank01
A167: 45827 | B167: 45838 | C167: 000MOBT25170A15P NIP Transfer from ILORIN INNOVATION HUB LTD to BENETTON CONSULTING LIMITED | D167: Unallocated expense | E167: Repairs and Maintenance | F167: 720000 | G167: Bank01 | H167: Landscaping
A168: 45827 | B168: 45838 | C168: 000MOBT25170A15P NIP Transfer from ILORIN INNOVATION HUB LTD to BENETTON CONSULTING LIMITED | D168: Bank charges | E168: Bank Fees and Charges | F168: 50 | G168: Bank01
A169: 45827 | B169: 45838 | C169: 000MOBT25170A15P NIP Transfer from ILORIN INNOVATION HUB LTD to BENETTON CONSULTING LIMITED | D169: Bank charges | E169: Bank Fees and Charges | F169: 3.75 | G169: Bank01
A170: 45827 | B170: 45838 | C170: 016EMTL25170006K ELECTRONIC MONEY TRANSFER LEVY | D170: Bank charges | E170: Bank Fees and Charges | F170: 50 | G170: Bank01
A171: 45828 | B171: 45838 | C171: 0166678251710001 REMITTA PAYMENT IFO E- payment till –Olaoluwa Ishola B/O ILORIN INNOVATION HUB LTD | D171: Unallocated expense | E171: Employee related costs | F171: 320161.25 | G171: Bank01 | H171: ITF contribution
A172: 45828 | B172: 45838 | C172: 016NIPT251710467 NIP TRSF FROM MICHELLE CHIDINMA UBA Transfer from MICHELLE CHIDINMA UBA | D172: Income | E172: Guest entertainment (Income) | F172: -48000 | G172: Bank01 | H172: INV-000017
A173: 45828 | B173: 45838 | C173: 000MOBT25171A1LE PURCHASE OF SNACKS FOR ILORIN DEV BOX EVENT NIP Transfer from ILORIN INNOVATION HUB LTD to | D173: Guest and entertainment | E173: Guest entertainment | F173: 48000 | G173: Bank01
A174: 45828 | B174: 45838 | C174: 000MOBT25171A1LE PURCHASE OF SNACKS FOR ILORIN DEV BOX EVENT NIP Transfer from ILORIN INNOVATION HUB LTD to | D174: Bank charges | E174: Bank Fees and Charges | F174: 25 | G174: Bank01
A175: 45828 | B175: 45838 | C175: 000MOBT25171A1LE PURCHASE OF SNACKS FOR ILORIN DEV BOX EVENT NIP Transfer from ILORIN INNOVATION HUB LTD to | D175: Bank charges | E175: Bank Fees and Charges | F175: 1.88 | G175: Bank01
A176: 45828 | B176: 45838 | C176: 016EMTL251710057 ELECTRONIC MONEY TRANSFER LEVY | D176: Bank charges | E176: Bank Fees and Charges | F176: 50 | G176: Bank01
A177: 45831 | B177: 45838 | C177: 000MOBT251740051 BREAKFAST FOR MASTERCLASS WITH PRINCE DAPO ADELEGAN NIP Transfer from ILORIN | D177: Guest and entertainment | E177: Guest entertainment | F177: 142500 | G177: Bank01
A178: 45831 | B178: 45838 | C178: 000MOBT251740051 BREAKFAST FOR MASTERCLASS WITH PRINCE DAPO ADELEGAN NIP Transfer from ILORIN | D178: Bank charges | E178: Bank Fees and Charges | F178: 50 | G178: Bank01
A179: 45831 | B179: 45838 | C179: 000MOBT251740051 BREAKFAST FOR MASTERCLASS WITH PRINCE DAPO ADELEGAN NIP Transfer from ILORIN | D179: Bank charges | E179: Bank Fees and Charges | F179: 3.75 | G179: Bank01
A180: 45831 | B180: 45838 | C180: 000MOBT251743898 AIRTEL WIFI MONTHLY RENEWAL NIP Transfer from ILORIN INNOVATION HUB LTD to PAYSTACK CHECK | D180: Data and telephone expenses | E180: Telephone and Data expense | F180: 30000 | G180: Bank01
A181: 45831 | B181: 45838 | C181: 000MOBT251743898 AIRTEL WIFI MONTHLY RENEWAL NIP Transfer from ILORIN INNOVATION HUB LTD to PAYSTACK CHECK | D181: Bank charges | E181: Bank Fees and Charges | F181: 25 | G181: Bank01
A182: 45831 | B182: 45838 | C182: 000MOBT251743898 AIRTEL WIFI MONTHLY RENEWAL NIP Transfer from ILORIN INNOVATION HUB LTD to PAYSTACK CHECK | D182: Bank charges | E182: Bank Fees and Charges | F182: 1.88 | G182: Bank01
A183: 45831 | B183: 45838 | C183: 000MOBT25174AIVI PURCHASE OF UTENCILS MICROWAVE FOR VIP LOUNGE NIP Transfer from ILORIN INNOVATION HUB LTD | D183: Stationery and Office Supplies | E183: Office Supplies | F183: 149000 | G183: Bank01
...

Sheet FAR
B2: FIXED ASSET REGISTER
B3: DATE | C3: TRANSACTION DETAILS | E3: ASSET CATEGORY | F3: AMOUNT
B4: 45824 | C4: 000MOBT25167AD55 FIRMAN GENERATOR PURCHASE 3 ITEL EXTENSIONS NIP Transfer from ILORIN INNOVATION HUB LTD t | D4: Generator | E4: Furniture and Equipment | F4: 902000
B5: 45831 | C5: 000MOBT25174ALT1 1HP AC FOR MAINTENANCE OFFICE NIP Transfer from ILORIN INNOVATION HUB LTD to CYCLE | D5: AC | E5: Furniture and Equipment | F5: 465000

Sheet MoM Transactions
A3: Sum of Transactions | B3: Column Labels
A4: Row Labels | B4: 45808 | C4: 45838 | D4: 45869 | E4: 45900 | F4: Grand Total
A5: Advertising And Marketing | C5: 1770000 | D5: 2250000 | F5: 4020000
A6: Bank Fees and Charges | B6: 10952.99 | C6: 64623.7 | D6: 47728.38 | E6: 42842.84 | F6: 166147.91
A7: Clearing account | C7: -201300 | D7: -187000 | E7: -640000 | F7: -1028300
A8: Donation income | C8: -1.4612794e+08 | F8: -1.4612794e+08
A9: Employee related costs | C9: 320161.25 | F9: 320161.25
A10: Facility rentals | B10: -444000 | C10: -420000 | D10: -3557950 | E10: -694000 | F10: -5115950
A11: Fuel/Diesel Expenses | D11: 120000 | E11: 240100 | F11: 360100
A12: Furniture and Equipment | C12: 1737000 | F12: 1737000
A13: Guest and entertainment | C13: 422400 | D13: 1787600 | E13: 826800 | F13: 3036800
A14: Guest and entertainment (Income) | D14: -1613250 | E14: -168000 | F14: -1781250
A15: IT and Internet Expenses | E15: 36116.76 | F15: 36116.76
A16: Janitorial Expense | B16: 12000 | C16: 1690000 | D16: 650000 | E16: 1300000 | F16: 3652000
A17: Meals and Entertainment | C17: 244400 | D17: 381876 | E17: 88500 | F17: 714776
A18: Office Supplies | B18: 40000 | C18: 1622500 | D18: 755164 | E18: 693500 | F18: 3111164
A19: Other Expenses | B19: 15300 | C19: 232261.25 | D19: 8062.5 | F19: 255623.75
A20: Premium Trust bank | B20: 365747.01 | C20: 1.0133034e+08 | D20: -22153745 | E20: -23416247 | F20: 56126092
A21: Refundable security deposit | C21: 200000 | E21: 180000 | F21: 380000
A22: Rental expense | D22: 120000 | E22: 560000 | F22: 680000
A23: Repairs and Maintenance | C23: 2969025 | D23: 1719000 | E23: 720000 | F23: 5408025
A24: Salaries and Employee Wages | C24: 24602438 | D24: 10105872 | E24: 20027057 | F24: 54735368
A25: Security expense | C25: 1344300 | D25: 950000 | F25: 2294300
A26: Software expense | C26: 1241019.2 | E26: 236336.25 | F26: 1477355.5
A27: Staff allowances | E27: -8806742.3 | F27: -8806742.3
A28: Staff training | D28: 500000 | E28: 2218342 | F28: 2718342
A29: Staff welfare | D29: 2220851 | F29: 2220851
A30: sterling bank | D30: 1693592.5 | E30: 734000 | F30: 2427592.5
A31: Telephone and Data expense | C31: 6123175.8 | D31: 87000 | E31: 30000 | F31: 6240175.8
A32: Travel expense - International | E32: 5147471.8 | F32: 5147471.8
A33: Travel expense - Local | C33: 835600 | D33: 1607958 | E33: 1143300 | F33: 3586858
A34: zenith bank | D34: 2276688.8 | E34: -268826.07 | F34: 2007862.7
A35: Grand Total | B35: 0 | C35: -7.4505806e-09 | D35: -230551.76 | E35: 230551.76 | F35: 1.5133992e-08

Sheet Chart of Accounts
A1: Account ID | B1: Account Name | C1: Account Code | D1: Description | E1: Account Type | F1: FSLI - Added | G1: Mileage Rate | H1: Mileage Unit | I1: IsMileage | J1: Account # | K1: Account Status | L1: Currency | M1: Parent Account
A2: 6104627000000010001 | B2: Other Charges | D2: Miscellaneous charges like adjustments made to the invoice can be recorded in this account. | E2: Income | F2: Income | G2: 0.000 | I2: false | K2: Active | L2: NGN
A3: 6104627000000032023 | B3: Lodging | D3: Any expense related to putting up at motels etc while on business travel can be entered here. | E3: Expense | F3: Administrative expenses | G3: 0.000 | I3: false | K3: Active | L3: NGN
A4: 6104627000000000358 | B4: Undeposited Funds | D4: Record funds received by your company yet to be deposited in a bank as undeposited funds and group them as a current asset in your balance sheet. | E4: Cash | F4: Current Asset | G4: 0.000 | I4: false | K4: Active | L4: NGN
A5: 6104627000000000361 | B5: Petty Cash | D5: It is a small amount of cash that is used to pay your minor or casual expenses rather than writing a check. | E5: Cash | F5: Current Asset | G5: 0.000 | I5: false | K5: Active | L5: NGN
A6: 6104627000000000364 | B6: Accounts Receivable | D6: The money that customers owe you becomes the accounts receivable. A good example of this is a payment expected from an invoice sent to your customer. | E6: Accounts Receivable | F6: Current Asset | G6: 0.000 | I6: false | K6: Active | L6: NGN
A7: 6104627000000000367 | B7: Furniture and Equipment | D7: Purchases of furniture and equipment for your office that can be used for a long period of time usually exceeding one year can be tracked with this account. | E7: Fixed Asset | F7: Non-current asset | G7: 0.000 | I7: false | K7: Active | L7: NGN
A8: 6104627000000000370 | B8: Advance Tax | D8: Any tax which is paid in advance is recorded into the advance tax account. This advance tax payment could be a quarterly, half yearly or yearly payment. | E8: Other Current Asset | F8: Current Asset | G8: 0.000 | I8: false | K8: Active | L8: NGN
A9: 6104627000000000373 | B9: Accounts Payable | D9: This is an account of all the money which you owe to others like a pending bill payment to a vendor,etc. | E9: Accounts Payable | F9: Current Liabilities | G9: 0.000 | I9: false | K9: Active | L9: NGN
A10: 6104627000000000376 | B10: Tax Payable | D10: The amount of money which you owe to your tax authority is recorded under the tax payable account. This amount is a sum of your outstanding in taxes and the tax charged on sales. | E10: Other Current Liability | F10: Current Liabilities | G10: 0.000 | I10: false | K10: Active | L10: NGN
A11: 6104627000000000379 | B11: Retained Earnings | D11: The earnings of your company which are not distributed among the share holders is accounted as retained earnings. | E11: Equity | F11: Accumulated funds | G11: 0.000 | I11: false | K11: Active | L11: NGN
A12: 6104627000000000382 | B12: Owner's Equity | D12: The owners rights to the assets of a company can be quantified in the owner''s equity account. | E12: Equity | F12: Accumulated funds | G12: 0.000 | I12: false | K12: Active | L12: NGN
A13: 6104627000000000385 | B13: Opening Balance Offset | D13: This is an account where you can record the balance from your previous years earning or the amount set aside for some activities. It is like a buffer account for your funds. | E13: Equity | F13: Accumulated funds | G13: 0.000 | I13: false | K13: Active | L13: NGN
... A52: 6104627000000091204 | B52: Parking | D52: The parking fares you pay while on business trips can be recorded under this expense category. | E52: Expense | F52: Administrative expenses | G52: 0.000 | I52: false | K52: Active | L52: NGN
A53: 6104627000000114013 | B53: Ilorin Innovation Hub Ltd | E53: Bank | F53: Current Asset | G53: 0.000 | I53: false | J53: 0040117676 | K53: Active | L53: NGN
A54: ***Added*** | B54: Zenith bank | D54: Bank transactions in the stated bank account | E54: Bank | F54: Current Asset
A55: ***Added*** | B55: Premium Trust bank | D55: Bank transactions in the stated bank account | E55: Bank | F55: Current Asset
A56: ***Added*** | B56: Sterling bank | D56: Bank transactions in the stated bank account | E56: Bank | F56: Current Asset
A57: ***Added*** | B57: Donations | D57: Donation received from IHS for day to day running of the business | E57: Income | F57: Income
A58: ***Added*** | B58: Refundable security deposit | D58: Security deposit charged to the host and refunded after event | E58: Accounts Payable | F58: Current Liabilities
A59: ***Added*** | B59: Telephone and Data expense | D59: The expenses on your telephone, data, voice mobile and fax usage | E59: Expense | F59: Administrative expenses
A60: ***Added*** | B60: Software expense | D60: Software related expenses from the use of Zoho or other software related expenses | E60: Expense | F60: Administrative expenses
A61: ***Added*** | B61: Guest entertainment | D61: Expenses on food and entertainment for Guests are recorded into this account directly related to income | E61: Expense | F61: Cost of sales
A62: ***Added*** | B62: Facility rentals | D62: Income from renting facilities to Host | E62: Income | F62: Income
A63: ***Added*** | B63: Guest entertainment (Income) | D63: Income from providing food and drinks to Host | E63: Income | F63: Income
A64: ***Added*** | B64: Fuel/Diesel Expenses | D64: Relates to all fuel and diesel related expenses | E64: Expense | F64: Administrative expenses
A65: ***Added*** | B65: Employee related costs | D65: Contrubutions relating to employees | E65: Expense | F65: Administrative expenses
... A75: ***Added*** | B75: Surplus/Deficit | D75: The surplus or deficit from each year | E75: Surplus/Deficit | F75: Accumulated funds
A76: ***Added*** | B76: Accumulated funds | E76: Accumulated funds | F76: Accumulated funds
A77: ***Added*** | B77: Reserves | E77: Reserves | F77: Accumulated funds
A78: ***Added*** | B78: Pension | D78: Employee and employer monthly pension contribution | E78: Expense | F78: Administrative expenses
A79: ***Added*** | B79: National Housing Fund | E79: Expense | F79: Administrative expenses
A80: ***Added*** | B80: Kwara State Government | E80: Income | F80: Income
A81: ***Added*** | B81: Training | E81: Expense | F81: Administrative expenses

Sheet Breakdown of MD reimbu
B3: Description | C3: Amount
B4: Pebbles sim consult (Cleaning services ) | C4: 1040000
B5: Bubble drinks (drinks and snacks ) | C5: 68000
B6: Star link Invoice | C6: 57000
B7: Zoho invoice | C7: 11610 | D7: =C7+C8+C10 -> 122550
B8: Zoho invoice | C8: 11610
B10: Zoho invoice | C10: 99330
B11: Staff lunch | C11: 40000 | D11: =C11+C12 -> 70000
B12: VIP refreshment (Coffee, water) | C12: 30000
B13: TOTAL | C13: =SUM(C4:C12) -> 1357550

Sheet invoice_details
A1: Ilorin Innovation Hub Invoice Details From 01 Mar 2025 To 30 Sep 2025
A2: invoice_id | B2: status | C2: date | D2: txn_posting_date | E2: due_date | F2: invoice_number | G2: reference_number | H2: customer_name | I2: bcy_total | J2: bcy_balance | K2: salesperson_id | L2: tax_amount | M2: paid_amount | N2: project_names | O2: currency_code | P2: currency_id | Q2: customer_id | R2: price_precision | S2: is_emailed | T2: reminders_sent | U2: exchange_rate
A3: 6104627000000094051 | B3: overdue | C3: 2025-04-23 | E3: 2025-04-23 | F3: INV-000011 | H3: IHS Nigeria | I3: 95767544 | J3: 1074771.4 | L3: 4030392.6 | M3: 94692772 | O3: NGN | P3: 6104627000000091085 | Q3: 6104627000000094027 | R3: 2 | S3: false | T3: 0 | U3: 1
A4: 6104627000000094099 | B4: overdue | C4: 2025-04-23 | E4: 2025-04-23 | F4: INV-000013 | H4: IHS Nigeria | I4: 45342959 | J4: 843589.94 | L4: 3163462.3 | M4: 44499369 | O4: NGN | P4: 6104627000000091085 | Q4: 6104627000000094027 | R4: 2 | S4: false | T4: 0 | U4: 1
A5: 6104627000000100229 | B5: overdue | C5: 2025-04-23 | E5: 2025-04-23 | F5: INV-000014 | H5: IHS Nigeria | I5: 6945600 | J5: 9800 | L5: 36750 | M5: 6935800 | O5: NGN | P5: 6104627000000091085 | Q5: 6104627000000094027 | R5: 2 | S5: false | T5: 0 | U5: 1
A6: 6104627000000110074 | B6: paid | C6: 2025-05-21 | E6: 2025-05-21 | F6: INV-000015 | H6: Bitkwa Initiatives | I6: 444000 | J6: 0 | L6: 24000 | M6: 444000 | O6: NGN | P6: 6104627000000091085 | Q6: 6104627000000110056 | R6: 2 | S6: true | T6: 0 | U6: 1
A7: 6104627000000111033 | B7: paid | C7: 2025-05-30 | E7: 2025-05-30 | F7: INV-000016 | H7: Co-creation Hub | I7: 135300 | J7: 0 | L7: 0 | M7: 135300 | O7: NGN | P7: 6104627000000091085 | Q7: 6104627000000111019 | R7: 2 | S7: true | T7: 0 | U7: 1
A8: 6104627000000133019 | B8: paid | C8: 2025-06-12 | E8: 2025-06-12 | F8: INV-000017 | H8: Co-creation Hub | I8: 48000 | J8: 0 | L8: 0 | M8: 48000 | O8: NGN | P8: 6104627000000091085 | Q8: 6104627000000111019 | R8: 2 | S8: true | T8: 0 | U8: 1
A9: 6104627000000136030 | B9: paid | C9: 2025-06-16 | E9: 2025-06-16 | F9: INV-000018 | H9: Kwara State Internal Revenue Service | I9: 420000 | J9: 0 | L9: 0 | M9: 420000 | O9: NGN | P9: 6104627000000091085 | Q9: 6104627000000136005 | R9: 2 | S9: true | T9: 0 | U9: 1
A10: 6104627000000145015 | B10: paid | C10: 2025-06-18 | E10: 2025-06-18 | F10: INV-000019 | H10: kwara kre8 | I10: 18000 | J10: 0 | L10: 0 | M10: 18000 | O10: NGN | P10: 6104627000000091085 | Q10: 6104627000000145001 | R10: 2 | S10: false | T10: 0 | U10: 1
A11: 6104627000000150021 | B11: draft | C11: 2025-07-01 | E11: 2025-07-01 | F11: INV-000020 | H11: Kwara State Ease of Doing Business Council | I11: 1634000 | J11: 1634000 | L11: 114000 | M11: 0 | O11: NGN | P11: 6104627000000091085 | Q11: 6104627000000150003 | R11: 2 | S11: false | T11: 0 | U11: 1
A12: 6104627000000162001 | B12: paid | C12: 2025-07-02 | E12: 2025-07-02 | F12: INV-000029 | H12: Kwara State Ease of Doing Business Council | I12: 324200 | J12: 0 | L12: 0 | M12: 324200 | O12: NGN | P12: 6104627000000091085 | Q12: 6104627000000150003 | R12: 2 | S12: false | T12: 0 | U12: 1
A13: 6104627000000160027 | B13: paid | C13: 2025-07-03 | E13: 2025-07-03 | F13: INV-000026 | H13: Kwara State Ease of Doing Business Council | I13: 234200 | J13: 0 | L13: 0 | M13: 234200 | O13: NGN | P13: 6104627000000091085 | Q13: 6104627000000150003 | R13: 2 | S13: false | T13: 0 | U13: 1
A14: 6104627000000154035 | B14: paid | C14: 2025-07-04 | E14: 2025-07-04 | F14: INV-000021 | H14: TA Community | I14: 43000 | J14: 0 | L14: 3000 | M14: 43000 | O14: NGN | P14: 6104627000000091085 | Q14: 6104627000000154017 | R14: 2 | S14: false | T14: 0 | U14: 1
... A57: 6104627000000227058 | B57: paid | C57: 2025-09-22 | E57: 2025-09-30 | F57: INV-000067 | H57: Special Assistant on Students’ Affairs, Kwara State Government. | I57: 700000 | J57: 0 | L57: 0 | M57: 700000 | O57: NGN | P57: 6104627000000091085 | Q57: 6104627000000227031 | R57: 2 | S57: false | T57: 0 | U57: 1
H60: AR | I60: SALES | L60: DEPOSIT REFUND | M60: TAX
H61: =I6 -> 444000 | I61: =H61-M61 -> 420000 | L61: 100000 | M61: =L6 -> 24000
L64: =I11-L11 -> 1520000
