Workbook

Sheet BUDGET 
A2: Category | B2: Description | D2: 45741 | E2: 45748 | F2: 45778 | G2: 45809 | H2: 45863 | I2: 45894 | J2: 45925 | K2: 45955 | L2: 45986 | M2: 46016 | N2: FY 2025 | O2: Comment/Justification | P2: One Time
A4: Items in green have been paid for the entire year as Q2 one-time costs | E4: =#REF!/3 -> #REF!
E5: =E4*3 -> #REF!
A7: Kwara State Government Grants | B7: Public sector funding | N7: =SUM(E7:G7) -> 0
A8: IHS Operational Funds | B8: Corporate partnerships & sponsorships | D8: 6908850 | F8: 133916648 | H8: =104296540-C16 -> 85159576 | K8: =100000000+C16 -> 1.1913696e+08 | N8: =SUM(D8:M8) -> 345122038
A9: Membership Fees | B9: Fees from startups & researchers | N9: =SUM(E9:G9) -> 0
A10: Consulting & Advisory Services | B10: Consulting services revenue | N10: =SUM(E10:G10) -> 0
A11: Event Hosting & Sponsorships | B11: Revenue from events & hackathons | E11: ='[1]Rental, Hosting & Sponsorships'!F12 -> 0 | F11: ='[1]Rental, Hosting & Sponsorships'!G12 -> 0 | G11: ='[1]Rental, Hosting & Sponsorships'!H12 -> 0 | N11: =SUM(E11:G11) -> 0
A12: Facility Rentals | E12: ='[1]Rental, Hosting & Sponsorships'!F6 -> 0 | F12: ='[1]Rental, Hosting & Sponsorships'!G6 -> 0 | G12: ='[1]Rental, Hosting & Sponsorships'!H6 -> 0 | N12: =SUM(E12:G12) -> 0
A13: Other Income | B13: Miscellaneous revenue | N13: =SUM(E13:G13) -> 0
D14: =SUM(D6:D13) -> 6908850 | E14: =SUM(E6:E13) -> 0 | F14: =SUM(F6:F13) -> 133916648 | G14: =SUM(G6:G13) -> 0 | H14: =SUM(H6:H13) -> 85159576 | I14: =SUM(I6:I13) -> 0 | J14: =SUM(J6:J13) -> 0 | K14: =SUM(K6:K13) -> 1.1913696e+08 | ... N14: =SUM(N6:N13) -> 345122038
C16: 19136964
A19: Salaries & Wages | B19: Staff salaries, mentors | D19: =[1]Salaries1!E19 -> 6418849.8 | E19: =[1]Salaries1!F19 -> 6659551.8 | F19: =[1]Salaries1!G40 -> 15298345 | G19: =[1]Salaries1!H19 -> 16040687 | H19: =[1]Salaries1!I19 -> 16040687 | I19: =[1]Salaries1!J19 -> 16040687 | J19: =[1]Salaries1!K19 -> 16040687 | K19: =[1]Salaries1!L19 -> 16040687 | L19: =[1]Salaries1!M19 -> 16040687 | M19: =[1]Salaries1!N19+[1]Salaries1!N19 -> 32081374 | N19: =SUM(D19:M19) -> 1.5670224e+08
A22: Utilities & Maintenance | B22: Rent, utilities, internet, security, cleaning
A23: Internet A Subscription (MTN) 45Mbps | F23: =1201234*8 -> 9609872 | N23: =SUM(D23:M23) -> 9609872 | O23: Till 2025 year end (8 months)
A24: Internet A Setup Cost (MTN) | F24: =1982000 -> 1982000 | N24: =SUM(D24:M24) -> 1982000 | O24: Last mile fiber + installation
A25: Internet B Subscription (Starlink) | F25: =38000*8 -> 304000 | N25: =SUM(D25:M25) -> 304000 | O25: Till 2025 year end (8 months)
A26: Internet B Device (Starlink) | F26: 679000 | N26: =SUM(D26:M26) -> 679000 | O26: Device Cost (Femtech IT, Ilorin)
A27: Internet B Installation (Starlink) | F27: 200000 | N27: =SUM(D27:M27) -> 200000 | O27: Installation + any required additional materials
A28: Cleaning | D28: 240000 | E28: 240000 | F28: 1328000 | G28: 1328000 | H28: 1328000 | I28: 1328000 | J28: 1328000 | K28: 1328000 | L28: 1328000 | M28: 1328000 | N28: =SUM(D28:M28) -> 11104000 | O28: 11 man cleaning team & consumables
A29: Landscaping | F29: 300000 | G29: 300000 | H29: 300000 | I29: 300000 | J29: 300000 | K29: 300000 | L29: 300000 | M29: 300000 | N29: =SUM(D29:M29) -> 2400000
A30: Facility Maintenance & Repairs | E30: =172000+136000+300000+800000+4429000 -> 5837000 | F30: 1500000 | G30: 1500000 | H30: 1500000 | I30: 1500000 | J30: 1500000 | K30: 1500000 | L30: 1500000 | M30: 1500000 | N30: =SUM(D30:M30) -> 17837000 | O30: Conservative estimate for repairs
A31: Security | F31: 1000000 | G31: 1000000 | H31: 920000 | I31: 920000 | J31: 920000 | K31: 920000 | L31: 920000 | M31: 920000 | N31: =SUM(D31:M31) -> 7520000 | O31: 8 guards - 5 day, 3 night at N100,000/mo and 1 supervisor @N120,000/mo
A32: HVAC Maintenance (Quarterly) | G32: 2000000 | J32: 2000000 | M32: 2000000 | N32: =SUM(D32:M32) -> 6000000 | O32: As quoted by Project Manager
A33: Solar Maintenance (Biannually) | N33: =SUM(D33:M33) -> 0 | O33: As quoted by Project Manager. Not due until Q3
A34: Electrical Maintenance (Monthly) | F34: 250000 | G34: 250000 | H34: 250000 | I34: 250000 | J34: 250000 | K34: 250000 | L34: 250000 | M34: 250000 | N34: =SUM(D34:M34) -> 2000000 | O34: As quoted by Project Manager
A35: Mechanical Maintenance (Monthly) | F35: 400000 | G35: 400000 | H35: 400000 | I35: 400000 | J35: 400000 | K35: 400000 | L35: 400000 | M35: 400000 | N35: =SUM(D35:M35) -> 3200000 | O35: As quoted by Project Manager
A36: LED Screen Maintenance (Annually) | N36: =SUM(D36:M36) -> 0 | O36: Not due until next year
A37: Access Control Maintenance (Annually) | N37: =SUM(D37:M37) -> 0 | O37: Not due until next year
A38: Project Manager Professional Fee ? | E38: 3000000 | F38: 3000000 | G38: 3000000 | H38: 3000000 | I38: 3000000 | J38: 3000000 | K38: 3000000 | L38: 3000000 | M38: 3000000 | N38: =SUM(D38:M38) -> 27000000 | O38: Geniserve
A39: Provision for Spare Parts for Solar, Electrical, Mechanical, LED Screens | G39: 10735000 | N39: =SUM(D39:M39) -> 10735000 | O39: Purchase of spare parts for hardware infrastructure. As quoted by Project Manager
D40: =SUM(D23:D39) -> 240000 | E40: =SUM(E23:E39) -> 9077000 | F40: =SUM(F23:F39) -> 20552872 | G40: =SUM(G23:G39) -> 20513000 | H40: =SUM(H23:H39) -> 7698000 | I40: =SUM(I23:I39) -> 7698000 | J40: =SUM(J23:J39) -> 9698000 | K40: =SUM(K23:K39) -> 7698000 | ... N40: =SUM(N23:N39) -> 100570872
A42: Travel & Conferences | B42: 1.1 | O42: Considering 2 people
A43: International Conference Registration | F43: 2251027 | K43: =F43*B42 -> 2476129.7 | N43: =SUM(D43:M43) -> 4727156.7 | O43: Q4 Travel costs are considered at a 10% increase from Q2 costs
A44: International Travel Flights | F44: 5478430 | K44: =F44*B42 -> 6026273 | N44: =SUM(D44:M44) -> 11504703 | O44: Q4 Travel costs are considered at a 10% increase from Q2 costs
A45: International Travel Accomodation | F45: 3214346 | K45: =F45*B42 -> 3535780.6 | N45: =SUM(D45:M45) -> 6750126.6 | O45: Q4 Travel costs are considered at a 10% increase from Q2 costs
A46: International Travel Allowance | F46: 4017435 | K46: =F46 -> 4017435 | N46: =SUM(D46:M46) -> 8034870 | O46: $200 per night for 5 nights
A47: International Visa Processing | F47: 548642 | K47: =F47 -> 548642 | N47: =SUM(D47:M47) -> 1097284 | O47: €300 @ €150 visa fee per person
A48: Local Conference Registration | G48: 750000 | J48: 750000 | M48: 750000 | N48: =SUM(D48:M48) -> 2250000 | O48: Estimated to cover any local conference reg
A49: Local Conference Exhibition | G49: 2000000 | J49: 2000000 | M49: 2000000 | N49: =SUM(D49:M49) -> 6000000 | O49: Opportunity to showcase our startups at conferences
A50: Local Travel | F50: 300000 | G50: 300000 | H50: 300000 | I50: 300000 | J50: 300000 | K50: 300000 | L50: 300000 | M50: 300000 | N50: =SUM(D50:M50) -> 2400000 | O50: Assuming N150,000 per flight within Nigeria
D51: =SUM(D43:D50) -> 0 | E51: =SUM(E43:E50) -> 0 | F51: =SUM(F43:F50) -> 15809880 | G51: =SUM(G43:G50) -> 3050000 | H51: =SUM(H43:H50) -> 300000 | I51: =SUM(I43:I50) -> 300000 | J51: =SUM(J43:J50) -> 3050000 | K51: =SUM(K43:K50) -> 16904260 | ... N51: =SUM(N43:N50) -> 42764140
A53: Equipment & Software | B53: Laptops, software, lab tools
A54: Website Hosting, Cloud Servers & Services | F54: =321528*8 -> 2572224 | N54: =SUM(D54:M54) -> 2572224 | O54: For IIH Website, Digital Ocean, Sendgrid & AWS @ $200/mo. Till 2025 year end (8 months)
A55: Staff Email + Collaboration Tools (Zoho One) | F55: =499200*1.075 -> 536640 | N55: =SUM(D55:M55) -> 536640 | O55: Till 2025 year end (8 months)
A56: Software Subscriptions & Licenses | F56: =402202*8 -> 3217616 | N56: =SUM(D56:M56) -> 3217616 | O56: Open AI credits, Canva, Bolt AI software dev tool @ $200
A57: Social Media Account Verification (Instagram, Facebook, Twitter) | F57: 526622 | N57: =SUM(D57:M57) -> 526622 | O57: Till 2025 year end (8 months)
A58: Coworking Space Management & Access Control Sofware | F58: 6491523 | N58: =SUM(D58:M58) -> 6491523 | O58: Spacebring @ €3,553.20/yr for 12 months
A59: Staff Mobile Devices | F59: 1825000 | N59: =SUM(D59:M59) -> 1825000
D60: =SUM(D54:D57) -> 0 | E60: =SUM(E54:E57) -> 0 | F60: =SUM(F54:F59) -> 15169625 | G60: =SUM(G54:G58) -> 0 | H60: =SUM(H54:H58) -> 0 | I60: =SUM(I54:I58) -> 0 | J60: =SUM(J54:J58) -> 0 | K60: =SUM(K54:K58) -> 0 | L60: =SUM(L54:L58) -> 0 | M60: =SUM(M54:M58) -> 0 | N60: =SUM(N54:N59) -> 15169625
A63: Corporate Comms & PR | B63: Branding, PR
A64: Souvenirs | F64: 2500000 | N64: =SUM(D64:M64) -> 2500000 | O64: Staff welcome kits, guest souvenirs
A65: Guest Entertainment & Refreshments | F65: 350000 | G65: 350000 | H65: 350000 | I65: 350000 | J65: 350000 | K65: 350000 | L65: 350000 | M65: 350000 | N65: =SUM(D65:M65) -> 2800000 | O65: For hosting guests
A66: Banners | F66: 250000 | N66: =SUM(D66:M66) -> 250000 | O66: Roller banners for internal and mobile use
A67: Merchandise & Staff T-Shirts | F67: 250000 | N67: =SUM(D67:M67) -> 250000
A68: Online & Social Media Marketing | F68: 250000 | G68: 250000 | H68: 250000 | I68: 250000 | J68: 250000 | K68: 250000 | L68: 250000 | M68: 250000 | N68: =SUM(D68:M68) -> 2000000 | O68: Paid online ads
A69: Photography & Videography | N69: =SUM(D69:M69) -> 0
D70: =SUM(D64:D68) -> 0 | E70: =SUM(E64:E68) -> 0 | F70: =SUM(F64:F68) -> 3600000 | G70: =SUM(G64:G68) -> 600000 | H70: =SUM(H64:H68) -> 600000 | I70: =SUM(I64:I68) -> 600000 | J70: =SUM(J64:J68) -> 600000 | K70: =SUM(K64:K68) -> 600000 | ... M70: =SUM(M64:M68) -> 600000 | N70: =SUM(N64:N69) -> 7800000
A72: Administrative Costs | B72: Office admin costs & supplies
A73: Stationery & Office Supplies | F73: 150000 | G73: 150000 | H73: 150000 | I73: 150000 | J73: 150000 | K73: 150000 | L73: 150000 | M73: 150000 | N73: =SUM(D73:M73) -> 1200000 | O73: Printer toner, water, tea, coffee
A74: Association & Society Memberships | F74: 500000 | N74: =SUM(D74:M74) -> 500000 | O74: Afrilabs @ N180,000/yr, ISN etc
D75: =SUM(D73:D74) -> 0 | E75: =SUM(E73:E74) -> 0 | F75: =SUM(F73:F74) -> 650000 | G75: =SUM(G73:G74) -> 150000 | H75: =SUM(H73:H74) -> 150000 | I75: =SUM(I73:I74) -> 150000 | J75: =SUM(J73:J74) -> 150000 | K75: =SUM(K73:K74) -> 150000 | ... N75: =SUM(N73:N74) -> 1700000
A78: Total Operational Expenses | D78: =SUM(D75,D70,D60,D51,D40,D19) -> 6658849.8 | E78: =SUM(E75,E70,E60,E51,E40,E19) -> 15736552 | F78: =SUM(F75,F70,F60,F51,F40,F19) -> 71080722 | G78: =SUM(G75,G70,G60,G51,G40,G19) -> 40353687 | H78: =SUM(H75,H70,H60,H51,H40,H19) -> 24788687 | I78: =SUM(I75,I70,I60,I51,I40,I19) -> 24788687 | J78: =SUM(J75,J70,J60,J51,J40,J19) -> 29538687 | K78: =SUM(K75,K70,K60,K51,K40,K19) -> 41392947 | ... M78: =SUM(M75,M70,M60,M51,M40,M19) -> 45579374 | N78: =SUM(D78:M78) -> 3.2470688e+08
N82: =SUM(E82:G82) -> 0
A83: Staff Professional Development | N83: =SUM(D83:M83) -> 0 | O83: Sponsoring professional development training & certifications for staff
A84: Monthly Meetups | B84: Startup acceleration & support | D84: 250000 | F84: =[1]Others!G12 -> 250000 | G84: =[1]Others!H12 -> 250000 | H84: =[1]Others!I12 -> 250000 | I84: =[1]Others!J12 -> 250000 | J84: =[1]Others!K12 -> 250000 | K84: =[1]Others!L12 -> 250000 | L84: =[1]Others!M12 -> 250000 | M84: =[1]Others!N12 -> 250000 | N84: =SUM(D84:M84) -> 2250000 | O84: Networking events like Founders Match or hosted event support - tags, refreshments etc
A85: Field Events | F85: 200000 | G85: 200000 | H85: 200000 | I85: 200000 | J85: 200000 | K85: 200000 | L85: 200000 | M85: 200000 | N85: =SUM(D85:M85) -> 1600000 | O85: Campus outreach events around Ilorin (UNILORIN, KWASU, Landmark, Al-Hikmah etc
A86: Webinars | F86: 136000 | G86: 136000 | H86: 136000 | I86: 136000 | J86: 136000 | K86: 136000 | L86: 136000 | M86: 136000 | N86: =SUM(D86:M86) -> 1088000 | O86: Zoom webinar subscription @ $79/mo
A87: Training & Mentorship | F87: 333333.33 | G87: 333333.33 | H87: 333333.33 | I87: 333333.33 | J87: 333333.33 | K87: 333333.33 | L87: 333333.33 | M87: 333333.33 | N87: =SUM(D87:M87) -> 2666666.7 | O87: Special training programs for staff
A88: Total Program Support | D88: =SUM(D84:D87) -> 250000 | E88: =SUM(E84:E87) -> 0 | F88: =SUM(F84:F87) -> 919333.33 | G88: =SUM(G84:G87) -> 919333.33 | H88: =SUM(H84:H87) -> 919333.33 | I88: =SUM(I84:I87) -> 919333.33 | J88: =SUM(J84:J87) -> 919333.33 | K88: =SUM(K84:K87) -> 919333.33 | ... M88: =SUM(M84:M87) -> 919333.33 | N88: =SUM(N83:N87) -> 7604666.7
A92: Contingency & Sustainability | N92: =SUM(E92:G92) -> 0
A93: Reserve Fund - % of Inflows | B93: Emergency fund for sustainability | C93: 0.02 | E93: =E14*$C$93 -> 0 | F93: =F14*$C$93 -> 2678333 | G93: =G14*$C$93 -> 0 | H93: =H14*$C$93 -> 1703191.5 | I93: =I14*$C$93 -> 0 | J93: =J14*$C$93 -> 0 | K93: =K14*$C$93 -> 2382739.3 | L93: =L14*$C$93 -> 0 | M93: =M14*$C$93 -> 0 | N93: =SUM(D93:M93) -> 6764263.8
A94: Miscellaneous Expenses - % of Operating Exp. | B94: Unexpected costs | C94: 0.02 | F94: =F78*$C$94 -> 1421614.4 | G94: =G78*$C$94 -> 807073.74 | H94: =H78*$C$94 -> 495773.74 | I94: =I78*$C$94 -> 495773.74 | J94: =J78*$C$94 -> 590773.74 | K94: =K78*$C$94 -> 827858.94 | L94: =L78*$C$94 -> 495773.74 | M94: =M78*$C$94 -> 911587.47 | N94: =SUM(D94:M94) -> 6046229.5
A95: Total Contingency | D95: =SUM(D93:D94) -> 0 | E95: =SUM(E93:E94) -> 0 | F95: =SUM(F93:F94) -> 4099947.4 | G95: =SUM(G93:G94) -> 807073.74 | H95: =SUM(H93:H94) -> 2198965.3 | I95: =SUM(I93:I94) -> 495773.74 | J95: =SUM(J93:J94) -> 590773.74 | K95: =SUM(K93:K94) -> 3210598.2 | ... M95: =SUM(M93:M94) -> 911587.47 | N95: =SUM(D95:M95) -> 12810493
A100: Summary | N100: =SUM(E100:G100) -> 0
A101: Total Revenue | D101: =SUM(D14) -> 6908850 | E101: =SUM(E14) -> 0 | F101: =SUM(F14) -> 133916648 | G101: =SUM(G14) -> 0 | H101: =SUM(H14) -> 85159576 | I101: =SUM(I14) -> 0 | J101: =SUM(J14) -> 0 | K101: =SUM(K14) -> 1.1913696e+08 | ... M101: =SUM(M14) -> 0 | N101: =SUM(D101:M101) -> 345122038
A102: Total Expenses | D102: =SUM(D95,D88,D78) -> 6908849.8 | E102: =SUM(E95,E88,E78) -> 15736552 | F102: =SUM(F95,F88,F78) -> 76100002 | G102: =SUM(G95,G88,G78) -> 42080094 | H102: =SUM(H95,H88,H78) -> 27906985 | I102: =SUM(I95,I88,I78) -> 26203794 | J102: =SUM(J95,J88,J78) -> 31048794 | K102: =SUM(K95,K88,K78) -> 45522879 | ... M102: =SUM(M95,M88,M78) -> 47410294 | N102: =-SUM(N95,N88,N78) -> -3.4512204e+08
N104: =N102/10 -> -34512204
N105: =N104*3 -> -1.0353661e+08
F106: =E102+F102+G102 -> 1.3391665e+08 | I106: =H102+I102+J102 -> 85159573 | L106: =K102+L102+M102 -> 1.1913697e+08
I109: =H101-I106 -> 3.2699
I110: 18754228

Sheet ACTUAL SPENT 
A1: Category | B1: Description | D1: 45741 | E1: 45748 | F1: 45778 | G1: 45809 | H1: 45863 | I1: 45894 | J1: 45925 | K1: 45955 | L1: 45986 | M1: 46016 | N1: FY 2025 | O1: Comment/Justification | P1: One Time
A3: Items in green have been paid for the entire year as Q2 one-time costs | E3: =#REF!/3 -> #REF!
E4: =E3*3 -> #REF!
A6: Kwara State Government Grants | B6: Public sector funding | N6: =SUM(D6:M6) -> 0
A7: IHS Operational Funds | B7: Corporate partnerships & sponsorships | D7: 6908850 | F7: 133916648 | H7: =104296540-C15 -> 85159576 | K7: =100000000+C15 -> 1.1913696e+08 | N7: =SUM(D7:M7) -> 345122038
A8: Membership Fees | B8: Fees from startups & researchers | N8: =SUM(D8:M8) -> 0
A9: Consulting & Advisory Services | B9: Consulting services revenue | N9: =SUM(D9:M9) -> 0
A10: Event Hosting & Sponsorships | B10: Revenue from events & hackathons | E10: ='[1]Rental, Hosting & Sponsorships'!F12 -> 0 | F10: ='[1]Rental, Hosting & Sponsorships'!G12 -> 0 | G10: ='[1]Rental, Hosting & Sponsorships'!H12 -> 0 | N10: =SUM(D10:M10) -> 0
A11: Facility Rentals | E11: ='[1]Rental, Hosting & Sponsorships'!F6 -> 0 | F11: ='[1]Rental, Hosting & Sponsorships'!G6 -> 0 | G11: ='[1]Rental, Hosting & Sponsorships'!H6 -> 0 | N11: =SUM(D11:M11) -> 0
A12: Other Income | B12: Miscellaneous revenue | N12: =SUM(D12:M12) -> 0
D13: =SUM(D5:D12) -> 6908850 | E13: =SUM(E5:E12) -> 0 | F13: =SUM(F5:F12) -> 133916648 | G13: =SUM(G5:G12) -> 0 | H13: =SUM(H5:H12) -> 85159576 | I13: =SUM(I5:I12) -> 0 | J13: =SUM(J5:J12) -> 0 | K13: =SUM(K5:K12) -> 1.1913696e+08 | ... M13: =SUM(M5:M12) -> 0 | N13: =SUM(D13:M13) -> 345122038
C15: 19136964
A18: Salaries & Wages | B18: Staff salaries, mentors | D18: 3722854.4 | E18: 3722854.4 | F18: 7356317.3 | G18: 9973607.5 | N18: =SUM(D18:M18) -> 24775634
A21: Utilities & Maintenance | B21: Rent, utilities, internet, security, cleaning
A22: Internet A Subscription (MTN) 45Mbps | G22: 2999175.8 | N22: =SUM(D22:M22) -> 2999175.8
A23: Internet A Setup Cost (MTN) | N23: =SUM(D23:M23) -> 0
A24: Internet B Subscription (Starlink) | N24: =SUM(D24:M24) -> 0
A25: Internet B Device (Starlink) | N25: =SUM(D25:M25) -> 0
A26: Internet B Installation (Starlink) | G26: 725000 | N26: =SUM(D26:M26) -> 725000
A27: Cleaning | D27: 240000 | E27: 240000 | F27: 572000 | G27: 852600 | N27: =SUM(D27:M27) -> 1904600
A28: Landscaping | G28: 860000 | N28: =SUM(D28:M28) -> 860000
A29: Facility Maintenance & Repairs | G29: 1140700 | N29: =SUM(D29:M29) -> 1140700
A30: Security | G30: 250000 | N30: =SUM(D30:M30) -> 250000
A31: HVAC Maintenance (Quarterly) | N31: =SUM(D31:M31) -> 0
A32: Solar Maintenance (Biannually) | N32: =SUM(D32:M32) -> 0
A33: Electrical Maintenance (Monthly) | N33: =SUM(D33:M33) -> 0
A34: Mechanical Maintenance (Monthly) | N34: =SUM(D34:M34) -> 0
A35: LED Screen Maintenance (Annually) | N35: =SUM(D35:M35) -> 0
A36: Access Control Maintenance (Annually) | N36: =SUM(D36:M36) -> 0
A37: Project Manager Professional Fee ? | N37: =SUM(D37:M37) -> 0
A38: Provision for Spare Parts for Solar, Electrical, Mechanical, LED Screens | G38: 1581325 | N38: =SUM(D38:M38) -> 1581325
D39: =SUM(D18:D38) -> 3962854.4 | E39: =SUM(E18:E38) -> 3962854.4 | F39: =SUM(F18:F38) -> 7928317.3 | G39: =SUM(G18:G38) -> 18382408 | H39: =SUM(H18:H38) -> 0 | I39: =SUM(I18:I38) -> 0 | J39: =SUM(J18:J38) -> 0 | K39: =SUM(K18:K38) -> 0 | ... N39: =SUM(N18:N38) -> 34236434
A41: Travel & Conferences | B41: 1.1
A42: International Conference Registration | N42: =SUM(D42:M42) -> 0
A43: International Travel Flights | N43: =SUM(D43:M43) -> 0
A44: International Travel Accomodation | N44: =SUM(D44:M44) -> 0
A45: International Travel Allowance | N45: =SUM(D45:M45) -> 0
A46: International Visa Processing | N46: =SUM(D46:M46) -> 0
A47: Local Conference Registration | N47: =SUM(D47:M47) -> 0
A48: Local Conference Exhibition | N48: =SUM(D48:M48) -> 0
A49: Local Travel | N49: =SUM(D49:M49) -> 0
D50: =SUM(D42:D49) -> 0 | E50: =SUM(E42:E49) -> 0 | F50: =SUM(F42:F49) -> 0 | G50: =SUM(G42:G49) -> 0 | H50: =SUM(H42:H49) -> 0 | I50: =SUM(I42:I49) -> 0 | J50: =SUM(J42:J49) -> 0 | K50: =SUM(K42:K49) -> 0 | ... N50: =SUM(N42:N49) -> 0
A52: Equipment & Software | B52: Laptops, software, lab tools
A53: Website Hosting, Cloud Servers & Services | N53: =SUM(D53:M53) -> 0
A54: Staff Email + Collaboration Tools (Zoho One) | N54: =SUM(D54:M54) -> 0
A55: Software Subscriptions & Licenses | D55: 11610 | E55: 11610 | G55: 1274798.8 | N55: =SUM(D55:M55) -> 1298018.8
A56: Social Media Account Verification (Instagram, Facebook, Twitter) | N56: =SUM(D56:M56) -> 0
A57: Coworking Space Management & Access Control Sofware | N57: =SUM(D57:M57) -> 0
A58: Staff Mobile Devices | G58: 2818000 | N58: =SUM(D58:M58) -> 2818000
D59: =SUM(D53:D58) -> 11610 | E59: =SUM(E53:E58) -> 11610 | F59: =SUM(F53:F58) -> 0 | G59: =SUM(G53:G58) -> 4092798.8 | H59: =SUM(H53:H58) -> 0 | I59: =SUM(I53:I58) -> 0 | J59: =SUM(J53:J58) -> 0 | K59: =SUM(K53:K58) -> 0 | ... N59: =SUM(N53:N58) -> 4116018.8
A62: Corporate Comms & PR | B62: Branding, PR
A63: Souvenirs | G63: 1820000 | N63: =SUM(D63:M63) -> 1820000
A64: Guest Entertainment & Refreshments | F64: 112000 | G64: 506200 | N64: =SUM(D64:M64) -> 618200
A65: Banners | F65: 40000 | N65: =SUM(D65:M65) -> 40000
A66: Merchandise & Staff T-Shirts | N66: =SUM(D66:M66) -> 0
A67: Online & Social Media Marketing | N67: =SUM(D67:M67) -> 0
A68: Photography & Videography | N68: =SUM(D68:M68) -> 0
D69: =SUM(D63:D67) -> 0 | E69: =SUM(E63:E67) -> 0 | F69: =SUM(F63:F67) -> 152000 | G69: =SUM(G63:G67) -> 2326200 | H69: =SUM(H63:H67) -> 0 | I69: =SUM(I63:I67) -> 0 | J69: =SUM(J63:J67) -> 0 | K69: =SUM(K63:K67) -> 0 | ... N69: =SUM(N63:N67) -> 2478200
A71: Administrative Costs | B71: Office admin costs & supplies
A72: Stationery & Office Supplies | G72: 937300 | N72: =SUM(D72:M72) -> 937300
A73: Association & Society Memberships | F73: 460133.75 | N73: =SUM(D73:M73) -> 460133.75
D74: =SUM(D72:D73) -> 0 | E74: =SUM(E72:E73) -> 0 | F74: =SUM(F72:F73) -> 460133.75 | G74: =SUM(G72:G73) -> 937300 | H74: =SUM(H72:H73) -> 0 | I74: =SUM(I72:I73) -> 0 | J74: =SUM(J72:J73) -> 0 | K74: =SUM(K72:K73) -> 0 | ... N74: =SUM(N72:N73) -> 1397433.8
A77: Total Operational Expenses | D77: =SUM(D74,D69,D59,D50,D39,D18) -> 7697318.7 | E77: =SUM(E74,E69,E59,E50,E39,E18) -> 7697318.7 | F77: =SUM(F74,F69,F59,F50,F39,F18) -> 15896768 | G77: =SUM(G74,G69,G59,G50,G39,G18) -> 35712315 | H77: =SUM(H74,H69,H59,H50,H39,H18) -> 0 | I77: =SUM(I74,I69,I59,I50,I39,I18) -> 0 | J77: =SUM(J74,J69,J59,J50,J39,J18) -> 0 | K77: =SUM(K74,K69,K59,K50,K39,K18) -> 0 | ... M77: =SUM(M74,M69,M59,M50,M39,M18) -> 0 | N77: =SUM(D77:M77) -> 67003720
N81: =SUM(E81:G81) -> 0
A82: Staff Professional Development | N82: =SUM(D82:M82) -> 0
A83: Monthly Meetups | B83: Startup acceleration & support | N83: =SUM(D83:M83) -> 0
A84: Field Events | N84: =SUM(D84:M84) -> 0
A85: Webinars | N85: =SUM(D85:M85) -> 0
A86: Training & Mentorship | N86: =SUM(D86:M86) -> 0
A87: Total Program Support | D87: =SUM(D83:D86) -> 0 | E87: =SUM(E83:E86) -> 0 | F87: =SUM(F83:F86) -> 0 | G87: =SUM(G83:G86) -> 0 | H87: =SUM(H83:H86) -> 0 | I87: =SUM(I83:I86) -> 0 | J87: =SUM(J83:J86) -> 0 | K87: =SUM(K83:K86) -> 0 | ... M87: =SUM(M83:M86) -> 0 | N87: =SUM(N82:N86) -> 0
A91: Contingency & Sustainability | N91: =SUM(E91:G91) -> 0
A92: Reserve Fund - % of Inflows | B92: Emergency fund for sustainability | C92: 0.02 | E92: =E13*$C$92 -> 0 | F92: =F13*$C$92 -> 2678333 | G92: =G13*$C$92 -> 0 | H92: =H13*$C$92 -> 1703191.5 | I92: =I13*$C$92 -> 0 | J92: =J13*$C$92 -> 0 | K92: =K13*$C$92 -> 2382739.3 | L92: =L13*$C$92 -> 0 | M92: =M13*$C$92 -> 0 | N92: =SUM(D92:M92) -> 6764263.8
A93: Miscellaneous Expenses - % of Operating Exp. | B93: Unexpected costs | C93: 0.02 | F93: =F77*$C$93 -> 317935.37 | G93: =G77*$C$93 -> 714246.29 | H93: =H77*$C$93 -> 0 | I93: =I77*$C$93 -> 0 | J93: =J77*$C$93 -> 0 | K93: =K77*$C$93 -> 0 | L93: =L77*$C$93 -> 0 | M93: =M77*$C$93 -> 0 | N93: =SUM(D93:M93) -> 1032181.7
A94: Total Contingency | D94: =SUM(D92:D93) -> 0 | E94: =SUM(E92:E93) -> 0 | F94: =SUM(F92:F93) -> 2996268.3 | G94: =SUM(G92:G93) -> 714246.29 | H94: =SUM(H92:H93) -> 1703191.5 | I94: =SUM(I92:I93) -> 0 | J94: =SUM(J92:J93) -> 0 | K94: =SUM(K92:K93) -> 2382739.3 | ... M94: =SUM(M92:M93) -> 0 | N94: =SUM(D94:M94) -> 7796445.4
A99: Summary | N99: =SUM(E99:G99) -> 0
A100: Total Revenue | D100: =SUM(D13) -> 6908850 | E100: =SUM(E13) -> 0 | F100: =SUM(F13) -> 133916648 | G100: =SUM(G13) -> 0 | H100: =SUM(H13) -> 85159576 | I100: =SUM(I13) -> 0 | J100: =SUM(J13) -> 0 | K100: =SUM(K13) -> 1.1913696e+08 | ... M100: =SUM(M13) -> 0 | N100: =SUM(D100:M100) -> 345122038
A101: Total Expenses | D101: =SUM(D94,D87,D77) -> 7697318.7 | E101: =SUM(E94,E87,E77) -> 7697318.7 | F101: =SUM(F94,F87,F77) -> 18893037 | G101: =SUM(G94,G87,G77) -> 36426561 | H101: =SUM(H94,H87,H77) -> 1703191.5 | I101: =SUM(I94,I87,I77) -> 0 | J101: =SUM(J94,J87,J77) -> 0 | K101: =SUM(K94,K87,K77) -> 2382739.3 | ... M101: =SUM(M94,M87,M77) -> 0 | N101: =-SUM(N94,N87,N77) -> -74800166
N103: =N101/10 -> -7480016.6
N104: =N103*3 -> -22440050
F105: =E101+F101+G101 -> 63016916 | I105: =H101+I101+J101 -> 1703191.5 | L105: =K101+L101+M101 -> 2382739.3
I108: =H100-I105 -> 83456385
I109: 18754228

Sheet SURPLUS AND DEFICIT
A2: Category | B2: Description | D2: 45741 | E2: 45748 | F2: 45778 | G2: 45809 | H2: 45863 | I2: 45894 | J2: 45925 | K2: 45955 | L2: 45986 | M2: 46016 | N2: FY 2025 | O2: Comment/Justification | P2: One Time
A4: Items in green have been paid for the entire year as Q2 one-time costs
A7: Kwara State Government Grants | B7: Public sector funding | N7: =SUM(D7:M7) -> 0
A8: IHS Operational Funds | B8: Corporate partnerships & sponsorships | D8: 6908850 | F8: 133916648 | H8: =104296540-C16 -> 104296540 | K8: =100000000+C16 -> 100000000 | N8: =SUM(D8:M8) -> 345122038
A9: Membership Fees | B9: Fees from startups & researchers | N9: =SUM(D9:M9) -> 0
A10: Consulting & Advisory Services | B10: Consulting services revenue | N10: =SUM(D10:M10) -> 0
A11: Event Hosting & Sponsorships | B11: Revenue from events & hackathons | E11: ='[1]Rental, Hosting & Sponsorships'!F12 -> 0 | F11: ='[1]Rental, Hosting & Sponsorships'!G12 -> 0 | G11: ='[1]Rental, Hosting & Sponsorships'!H12 -> 0 | N11: =SUM(D11:M11) -> 0
A12: Facility Rentals | E12: ='[1]Rental, Hosting & Sponsorships'!F6 -> 0 | F12: ='[1]Rental, Hosting & Sponsorships'!G6 -> 0 | G12: ='[1]Rental, Hosting & Sponsorships'!H6 -> 0 | N12: =SUM(D12:M12) -> 0
A13: Other Income | B13: Miscellaneous revenue | N13: =SUM(D13:M13) -> 0
D14: =SUM(D6:D13) -> 6908850 | E14: =SUM(E6:E13) -> 0 | F14: =SUM(F6:F13) -> 133916648 | G14: =SUM(G6:G13) -> 0 | H14: =SUM(H6:H13) -> 104296540 | I14: =SUM(I6:I13) -> 0 | J14: =SUM(J6:J13) -> 0 | K14: =SUM(K6:K13) -> 100000000 | ... M14: =SUM(M6:M13) -> 0 | N14: =SUM(D14:M14) -> 345122038
C15: 19136964
A18: Salaries & Wages | B18: Staff salaries, mentors | D18: ='BUDGET '!D19-'ACTUAL SPENT '!D18 -> 2695995.4 | E18: ='BUDGET '!E19-'ACTUAL SPENT '!E18 -> 2936697.4 | F18: ='BUDGET '!F19-'ACTUAL SPENT '!F18 -> 7942027.4 | G18: ='BUDGET '!G19-'ACTUAL SPENT '!G18 -> 6067079.3 | H18: ='BUDGET '!H19-'ACTUAL SPENT '!H18 -> 16040687 | I18: ='BUDGET '!I19-'ACTUAL SPENT '!I18 -> 16040687 | J18: ='BUDGET '!J19-'ACTUAL SPENT '!J18 -> 16040687 | K18: ='BUDGET '!K19-'ACTUAL SPENT '!K18 -> 16040687 | ... M18: ='BUDGET '!M19-'ACTUAL SPENT '!M18 -> 32081374 | N18: =SUM(D18:M18) -> 1.3192661e+08
D19: ='BUDGET '!D20-'ACTUAL SPENT '!D19 -> 0 | E19: ='BUDGET '!E20-'ACTUAL SPENT '!E19 -> 0 | F19: ='BUDGET '!F20-'ACTUAL SPENT '!F19 -> 0 | G19: ='BUDGET '!G20-'ACTUAL SPENT '!G19 -> 0 | H19: ='BUDGET '!H20-'ACTUAL SPENT '!H19 -> 0 | I19: ='BUDGET '!I20-'ACTUAL SPENT '!I19 -> 0 | J19: ='BUDGET '!J20-'ACTUAL SPENT '!J19 -> 0 | K19: ='BUDGET '!K20-'ACTUAL SPENT '!K19 -> 0 | ... M19: ='BUDGET '!M20-'ACTUAL SPENT '!M19 -> 0 | N19: =SUM(D19:M19) -> 0
D20: ='BUDGET '!D21-'ACTUAL SPENT '!D20 -> 0 | E20: ='BUDGET '!E21-'ACTUAL SPENT '!E20 -> 0 | F20: ='BUDGET '!F21-'ACTUAL SPENT '!F20 -> 0 | G20: ='BUDGET '!G21-'ACTUAL SPENT '!G20 -> 0 | H20: ='BUDGET '!H21-'ACTUAL SPENT '!H20 -> 0 | I20: ='BUDGET '!I21-'ACTUAL SPENT '!I20 -> 0 | J20: ='BUDGET '!J21-'ACTUAL SPENT '!J20 -> 0 | K20: ='BUDGET '!K21-'ACTUAL SPENT '!K20 -> 0 | ... M20: ='BUDGET '!M21-'ACTUAL SPENT '!M20 -> 0 | N20: =SUM(D20:M20) -> 0
A21: Utilities & Maintenance | B21: Rent, utilities, internet, security, cleaning | D21: ='BUDGET '!D22-'ACTUAL SPENT '!D21 -> 0 | E21: ='BUDGET '!E22-'ACTUAL SPENT '!E21 -> 0 | F21: ='BUDGET '!F22-'ACTUAL SPENT '!F21 -> 0 | G21: ='BUDGET '!G22-'ACTUAL SPENT '!G21 -> 0 | H21: ='BUDGET '!H22-'ACTUAL SPENT '!H21 -> 0 | I21: ='BUDGET '!I22-'ACTUAL SPENT '!I21 -> 0 | J21: ='BUDGET '!J22-'ACTUAL SPENT '!J21 -> 0 | K21: ='BUDGET '!K22-'ACTUAL SPENT '!K21 -> 0 | ... M21: ='BUDGET '!M22-'ACTUAL SPENT '!M21 -> 0 | N21: =SUM(D21:M21) -> 0
A22: Internet A Subscription (MTN) 45Mbps | D22: ='BUDGET '!D23-'ACTUAL SPENT '!D22 -> 0 | E22: ='BUDGET '!E23-'ACTUAL SPENT '!E22 -> 0 | F22: ='BUDGET '!F23-'ACTUAL SPENT '!F22 -> 9609872 | G22: ='BUDGET '!G23-'ACTUAL SPENT '!G22 -> -2999175.8 | H22: ='BUDGET '!H23-'ACTUAL SPENT '!H22 -> 0 | I22: ='BUDGET '!I23-'ACTUAL SPENT '!I22 -> 0 | J22: ='BUDGET '!J23-'ACTUAL SPENT '!J22 -> 0 | K22: ='BUDGET '!K23-'ACTUAL SPENT '!K22 -> 0 | ... M22: ='BUDGET '!M23-'ACTUAL SPENT '!M22 -> 0 | N22: =SUM(D22:M22) -> 6610696.2
A23: Internet A Setup Cost (MTN) | D23: ='BUDGET '!D24-'ACTUAL SPENT '!D23 -> 0 | E23: ='BUDGET '!E24-'ACTUAL SPENT '!E23 -> 0 | F23: ='BUDGET '!F24-'ACTUAL SPENT '!F23 -> 1982000 | G23: ='BUDGET '!G24-'ACTUAL SPENT '!G23 -> 0 | H23: ='BUDGET '!H24-'ACTUAL SPENT '!H23 -> 0 | I23: ='BUDGET '!I24-'ACTUAL SPENT '!I23 -> 0 | J23: ='BUDGET '!J24-'ACTUAL SPENT '!J23 -> 0 | K23: ='BUDGET '!K24-'ACTUAL SPENT '!K23 -> 0 | ... M23: ='BUDGET '!M24-'ACTUAL SPENT '!M23 -> 0 | N23: =SUM(D23:M23) -> 1982000
A24: Internet B Subscription (Starlink) | D24: ='BUDGET '!D25-'ACTUAL SPENT '!D24 -> 0 | E24: ='BUDGET '!E25-'ACTUAL SPENT '!E24 -> 0 | F24: ='BUDGET '!F25-'ACTUAL SPENT '!F24 -> 304000 | G24: ='BUDGET '!G25-'ACTUAL SPENT '!G24 -> 0 | H24: ='BUDGET '!H25-'ACTUAL SPENT '!H24 -> 0 | I24: ='BUDGET '!I25-'ACTUAL SPENT '!I24 -> 0 | J24: ='BUDGET '!J25-'ACTUAL SPENT '!J24 -> 0 | K24: ='BUDGET '!K25-'ACTUAL SPENT '!K24 -> 0 | ... M24: ='BUDGET '!M25-'ACTUAL SPENT '!M24 -> 0 | N24: =SUM(D24:M24) -> 304000
A25: Internet B Device (Starlink) | D25: ='BUDGET '!D26-'ACTUAL SPENT '!D25 -> 0 | E25: ='BUDGET '!E26-'ACTUAL SPENT '!E25 -> 0 | F25: ='BUDGET '!F26-'ACTUAL SPENT '!F25 -> 679000 | G25: ='BUDGET '!G26-'ACTUAL SPENT '!G25 -> 0 | H25: ='BUDGET '!H26-'ACTUAL SPENT '!H25 -> 0 | I25: ='BUDGET '!I26-'ACTUAL SPENT '!I25 -> 0 | J25: ='BUDGET '!J26-'ACTUAL SPENT '!J25 -> 0 | K25: ='BUDGET '!K26-'ACTUAL SPENT '!K25 -> 0 | ... M25: ='BUDGET '!M26-'ACTUAL SPENT '!M25 -> 0 | N25: =SUM(D25:M25) -> 679000
A26: Internet B Installation (Starlink) | D26: ='BUDGET '!D27-'ACTUAL SPENT '!D26 -> 0 | E26: ='BUDGET '!E27-'ACTUAL SPENT '!E26 -> 0 | F26: ='BUDGET '!F27-'ACTUAL SPENT '!F26 -> 200000 | G26: ='BUDGET '!G27-'ACTUAL SPENT '!G26 -> -725000 | H26: ='BUDGET '!H27-'ACTUAL SPENT '!H26 -> 0 | I26: ='BUDGET '!I27-'ACTUAL SPENT '!I26 -> 0 | J26: ='BUDGET '!J27-'ACTUAL SPENT '!J26 -> 0 | K26: ='BUDGET '!K27-'ACTUAL SPENT '!K26 -> 0 | ... M26: ='BUDGET '!M27-'ACTUAL SPENT '!M26 -> 0 | N26: =SUM(D26:M26) -> -525000
A27: Cleaning | D27: ='BUDGET '!D28-'ACTUAL SPENT '!D27 -> 0 | E27: ='BUDGET '!E28-'ACTUAL SPENT '!E27 -> 0 | F27: ='BUDGET '!F28-'ACTUAL SPENT '!F27 -> 756000 | G27: ='BUDGET '!G28-'ACTUAL SPENT '!G27 -> 475400 | H27: ='BUDGET '!H28-'ACTUAL SPENT '!H27 -> 1328000 | I27: ='BUDGET '!I28-'ACTUAL SPENT '!I27 -> 1328000 | J27: ='BUDGET '!J28-'ACTUAL SPENT '!J27 -> 1328000 | K27: ='BUDGET '!K28-'ACTUAL SPENT '!K27 -> 1328000 | ... M27: ='BUDGET '!M28-'ACTUAL SPENT '!M27 -> 1328000 | N27: =SUM(D27:M27) -> 9199400
A28: Landscaping | D28: ='BUDGET '!D29-'ACTUAL SPENT '!D28 -> 0 | E28: ='BUDGET '!E29-'ACTUAL SPENT '!E28 -> 0 | F28: ='BUDGET '!F29-'ACTUAL SPENT '!F28 -> 300000 | G28: ='BUDGET '!G29-'ACTUAL SPENT '!G28 -> -560000 | H28: ='BUDGET '!H29-'ACTUAL SPENT '!H28 -> 300000 | I28: ='BUDGET '!I29-'ACTUAL SPENT '!I28 -> 300000 | J28: ='BUDGET '!J29-'ACTUAL SPENT '!J28 -> 300000 | K28: ='BUDGET '!K29-'ACTUAL SPENT '!K28 -> 300000 | ... M28: ='BUDGET '!M29-'ACTUAL SPENT '!M28 -> 300000 | N28: =SUM(D28:M28) -> 1540000
A29: Facility Maintenance & Repairs | D29: ='BUDGET '!D30-'ACTUAL SPENT '!D29 -> 0 | E29: ='BUDGET '!E30-'ACTUAL SPENT '!E29 -> 5837000 | F29: ='BUDGET '!F30-'ACTUAL SPENT '!F29 -> 1500000 | G29: ='BUDGET '!G30-'ACTUAL SPENT '!G29 -> 359300 | H29: ='BUDGET '!H30-'ACTUAL SPENT '!H29 -> 1500000 | I29: ='BUDGET '!I30-'ACTUAL SPENT '!I29 -> 1500000 | J29: ='BUDGET '!J30-'ACTUAL SPENT '!J29 -> 1500000 | K29: ='BUDGET '!K30-'ACTUAL SPENT '!K29 -> 1500000 | ... M29: ='BUDGET '!M30-'ACTUAL SPENT '!M29 -> 1500000 | N29: =SUM(D29:M29) -> 16696300
A30: Security | D30: ='BUDGET '!D31-'ACTUAL SPENT '!D30 -> 0 | E30: ='BUDGET '!E31-'ACTUAL SPENT '!E30 -> 0 | F30: ='BUDGET '!F31-'ACTUAL SPENT '!F30 -> 1000000 | G30: ='BUDGET '!G31-'ACTUAL SPENT '!G30 -> 750000 | H30: ='BUDGET '!H31-'ACTUAL SPENT '!H30 -> 920000 | I30: ='BUDGET '!I31-'ACTUAL SPENT '!I30 -> 920000 | J30: ='BUDGET '!J31-'ACTUAL SPENT '!J30 -> 920000 | K30: ='BUDGET '!K31-'ACTUAL SPENT '!K30 -> 920000 | ... M30: ='BUDGET '!M31-'ACTUAL SPENT '!M30 -> 920000 | N30: =SUM(D30:M30) -> 7270000
A31: HVAC Maintenance (Quarterly) | D31: ='BUDGET '!D32-'ACTUAL SPENT '!D31 -> 0 | E31: ='BUDGET '!E32-'ACTUAL SPENT '!E31 -> 0 | F31: ='BUDGET '!F32-'ACTUAL SPENT '!F31 -> 0 | G31: ='BUDGET '!G32-'ACTUAL SPENT '!G31 -> 2000000 | H31: ='BUDGET '!H32-'ACTUAL SPENT '!H31 -> 0 | I31: ='BUDGET '!I32-'ACTUAL SPENT '!I31 -> 0 | J31: ='BUDGET '!J32-'ACTUAL SPENT '!J31 -> 2000000 | K31: ='BUDGET '!K32-'ACTUAL SPENT '!K31 -> 0 | ... M31: ='BUDGET '!M32-'ACTUAL SPENT '!M31 -> 2000000 | N31: =SUM(D31:M31) -> 6000000
A32: Solar Maintenance (Biannually) | D32: ='BUDGET '!D33-'ACTUAL SPENT '!D32 -> 0 | E32: ='BUDGET '!E33-'ACTUAL SPENT '!E32 -> 0 | F32: ='BUDGET '!F33-'ACTUAL SPENT '!F32 -> 0 | G32: ='BUDGET '!G33-'ACTUAL SPENT '!G32 -> 0 | H32: ='BUDGET '!H33-'ACTUAL SPENT '!H32 -> 0 | I32: ='BUDGET '!I33-'ACTUAL SPENT '!I32 -> 0 | J32: ='BUDGET '!J33-'ACTUAL SPENT '!J32 -> 0 | K32: ='BUDGET '!K33-'ACTUAL SPENT '!K32 -> 0 | ... M32: ='BUDGET '!M33-'ACTUAL SPENT '!M32 -> 0 | N32: =SUM(D32:M32) -> 0
A33: Electrical Maintenance (Monthly) | D33: ='BUDGET '!D34-'ACTUAL SPENT '!D33 -> 0 | E33: ='BUDGET '!E34-'ACTUAL SPENT '!E33 -> 0 | F33: ='BUDGET '!F34-'ACTUAL SPENT '!F33 -> 250000 | G33: ='BUDGET '!G34-'ACTUAL SPENT '!G33 -> 250000 | H33: ='BUDGET '!H34-'ACTUAL SPENT '!H33 -> 250000 | I33: ='BUDGET '!I34-'ACTUAL SPENT '!I33 -> 250000 | J33: ='BUDGET '!J34-'ACTUAL SPENT '!J33 -> 250000 | K33: ='BUDGET '!K34-'ACTUAL SPENT '!K33 -> 250000 | ... M33: ='BUDGET '!M34-'ACTUAL SPENT '!M33 -> 250000 | N33: =SUM(D33:M33) -> 2000000
... A38: Provision for Spare Parts for Solar, Electrical, Mechanical, LED Screens | D38: ='BUDGET '!D39-'ACTUAL SPENT '!D38 -> 0 | E38: ='BUDGET '!E39-'ACTUAL SPENT '!E38 -> 0 | F38: ='BUDGET '!F39-'ACTUAL SPENT '!F38 -> 0 | G38: ='BUDGET '!G39-'ACTUAL SPENT '!G38 -> 9153675 | H38: ='BUDGET '!H39-'ACTUAL SPENT '!H38 -> 0 | I38: ='BUDGET '!I39-'ACTUAL SPENT '!I38 -> 0 | J38: ='BUDGET '!J39-'ACTUAL SPENT '!J38 -> 0 | K38: ='BUDGET '!K39-'ACTUAL SPENT '!K38 -> 0 | ... M38: ='BUDGET '!M39-'ACTUAL SPENT '!M38 -> 0 | N38: =SUM(D38:M38) -> 9153675
D39: ='BUDGET '!D40-'ACTUAL SPENT '!D39 -> -3722854.4 | E39: ='BUDGET '!E40-'ACTUAL SPENT '!E39 -> 5114145.6 | F39: ='BUDGET '!F40-'ACTUAL SPENT '!F39 -> 12624555 | G39: ='BUDGET '!G40-'ACTUAL SPENT '!G39 -> 2130591.7 | H39: ='BUDGET '!H40-'ACTUAL SPENT '!H39 -> 7698000 | I39: ='BUDGET '!I40-'ACTUAL SPENT '!I39 -> 7698000 | J39: ='BUDGET '!J40-'ACTUAL SPENT '!J39 -> 9698000 | K39: ='BUDGET '!K40-'ACTUAL SPENT '!K39 -> 7698000 | ... M39: ='BUDGET '!M40-'ACTUAL SPENT '!M39 -> 9698000 | N39: =SUM(D39:M39) -> 66334438
D40: ='BUDGET '!D41-'ACTUAL SPENT '!D40 -> 0 | E40: ='BUDGET '!E41-'ACTUAL SPENT '!E40 -> 0 | F40: ='BUDGET '!F41-'ACTUAL SPENT '!F40 -> 0 | G40: ='BUDGET '!G41-'ACTUAL SPENT '!G40 -> 0 | H40: ='BUDGET '!H41-'ACTUAL SPENT '!H40 -> 0 | I40: ='BUDGET '!I41-'ACTUAL SPENT '!I40 -> 0 | J40: ='BUDGET '!J41-'ACTUAL SPENT '!J40 -> 0 | K40: ='BUDGET '!K41-'ACTUAL SPENT '!K40 -> 0 | ... M40: ='BUDGET '!M41-'ACTUAL SPENT '!M40 -> 0 | N40: =SUM(D40:M40) -> 0
A41: Travel & Conferences | C41: 1.1 | D41: ='BUDGET '!D42-'ACTUAL SPENT '!D41 -> 0 | E41: ='BUDGET '!E42-'ACTUAL SPENT '!E41 -> 0 | F41: ='BUDGET '!F42-'ACTUAL SPENT '!F41 -> 0 | G41: ='BUDGET '!G42-'ACTUAL SPENT '!G41 -> 0 | H41: ='BUDGET '!H42-'ACTUAL SPENT '!H41 -> 0 | I41: ='BUDGET '!I42-'ACTUAL SPENT '!I41 -> 0 | J41: ='BUDGET '!J42-'ACTUAL SPENT '!J41 -> 0 | K41: ='BUDGET '!K42-'ACTUAL SPENT '!K41 -> 0 | ... M41: ='BUDGET '!M42-'ACTUAL SPENT '!M41 -> 0 | N41: =SUM(D41:M41) -> 0
A42: International Conference Registration | D42: ='BUDGET '!D43-'ACTUAL SPENT '!D42 -> 0 | E42: ='BUDGET '!E43-'ACTUAL SPENT '!E42 -> 0 | F42: ='BUDGET '!F43-'ACTUAL SPENT '!F42 -> 2251027 | G42: ='BUDGET '!G43-'ACTUAL SPENT '!G42 -> 0 | H42: ='BUDGET '!H43-'ACTUAL SPENT '!H42 -> 0 | I42: ='BUDGET '!I43-'ACTUAL SPENT '!I42 -> 0 | J42: ='BUDGET '!J43-'ACTUAL SPENT '!J42 -> 0 | K42: ='BUDGET '!K43-'ACTUAL SPENT '!K42 -> 2476129.7 | ... M42: ='BUDGET '!M43-'ACTUAL SPENT '!M42 -> 0 | N42: =SUM(D42:M42) -> 4727156.7
A43: International Travel Flights | D43: ='BUDGET '!D44-'ACTUAL SPENT '!D43 -> 0 | E43: ='BUDGET '!E44-'ACTUAL SPENT '!E43 -> 0 | F43: ='BUDGET '!F44-'ACTUAL SPENT '!F43 -> 5478430 | G43: ='BUDGET '!G44-'ACTUAL SPENT '!G43 -> 0 | H43: ='BUDGET '!H44-'ACTUAL SPENT '!H43 -> 0 | I43: ='BUDGET '!I44-'ACTUAL SPENT '!I43 -> 0 | J43: ='BUDGET '!J44-'ACTUAL SPENT '!J43 -> 0 | K43: ='BUDGET '!K44-'ACTUAL SPENT '!K43 -> 6026273 | ... M43: ='BUDGET '!M44-'ACTUAL SPENT '!M43 -> 0 | N43: =SUM(D43:M43) -> 11504703
A44: International Travel Accomodation | D44: ='BUDGET '!D45-'ACTUAL SPENT '!D44 -> 0 | E44: ='BUDGET '!E45-'ACTUAL SPENT '!E44 -> 0 | F44: ='BUDGET '!F45-'ACTUAL SPENT '!F44 -> 3214346 | G44: ='BUDGET '!G45-'ACTUAL SPENT '!G44 -> 0 | H44: ='BUDGET '!H45-'ACTUAL SPENT '!H44 -> 0 | I44: ='BUDGET '!I45-'ACTUAL SPENT '!I44 -> 0 | J44: ='BUDGET '!J45-'ACTUAL SPENT '!J44 -> 0 | K44: ='BUDGET '!K45-'ACTUAL SPENT '!K44 -> 3535780.6 | ... M44: ='BUDGET '!M45-'ACTUAL SPENT '!M44 -> 0 | N44: =SUM(D44:M44) -> 6750126.6
A45: International Travel Allowance | D45: ='BUDGET '!D46-'ACTUAL SPENT '!D45 -> 0 | E45: ='BUDGET '!E46-'ACTUAL SPENT '!E45 -> 0 | F45: ='BUDGET '!F46-'ACTUAL SPENT '!F45 -> 4017435 | G45: ='BUDGET '!G46-'ACTUAL SPENT '!G45 -> 0 | H45: ='BUDGET '!H46-'ACTUAL SPENT '!H45 -> 0 | I45: ='BUDGET '!I46-'ACTUAL SPENT '!I45 -> 0 | J45: ='BUDGET '!J46-'ACTUAL SPENT '!J45 -> 0 | K45: ='BUDGET '!K46-'ACTUAL SPENT '!K45 -> 4017435 | ... M45: ='BUDGET '!M46-'ACTUAL SPENT '!M45 -> 0 | N45: =SUM(D45:M45) -> 8034870
A46: International Visa Processing | D46: ='BUDGET '!D47-'ACTUAL SPENT '!D46 -> 0 | E46: ='BUDGET '!E47-'ACTUAL SPENT '!E46 -> 0 | F46: ='BUDGET '!F47-'ACTUAL SPENT '!F46 -> 548642 | G46: ='BUDGET '!G47-'ACTUAL SPENT '!G46 -> 0 | H46: ='BUDGET '!H47-'ACTUAL SPENT '!H46 -> 0 | I46: ='BUDGET '!I47-'ACTUAL SPENT '!I46 -> 0 | J46: ='BUDGET '!J47-'ACTUAL SPENT '!J46 -> 0 | K46: ='BUDGET '!K47-'ACTUAL SPENT '!K46 -> 548642 | ... M46: ='BUDGET '!M47-'ACTUAL SPENT '!M46 -> 0 | N46: =SUM(D46:M46) -> 1097284
A47: Local Conference Registration | D47: ='BUDGET '!D48-'ACTUAL SPENT '!D47 -> 0 | E47: ='BUDGET '!E48-'ACTUAL SPENT '!E47 -> 0 | F47: ='BUDGET '!F48-'ACTUAL SPENT '!F47 -> 0 | G47: ='BUDGET '!G48-'ACTUAL SPENT '!G47 -> 750000 | H47: ='BUDGET '!H48-'ACTUAL SPENT '!H47 -> 0 | I47: ='BUDGET '!I48-'ACTUAL SPENT '!I47 -> 0 | J47: ='BUDGET '!J48-'ACTUAL SPENT '!J47 -> 750000 | K47: ='BUDGET '!K48-'ACTUAL SPENT '!K47 -> 0 | ... M47: ='BUDGET '!M48-'ACTUAL SPENT '!M47 -> 750000 | N47: =SUM(D47:M47) -> 2250000
A48: Local Conference Exhibition | D48: ='BUDGET '!D49-'ACTUAL SPENT '!D48 -> 0 | E48: ='BUDGET '!E49-'ACTUAL SPENT '!E48 -> 0 | F48: ='BUDGET '!F49-'ACTUAL SPENT '!F48 -> 0 | G48: ='BUDGET '!G49-'ACTUAL SPENT '!G48 -> 2000000 | H48: ='BUDGET '!H49-'ACTUAL SPENT '!H48 -> 0 | I48: ='BUDGET '!I49-'ACTUAL SPENT '!I48 -> 0 | J48: ='BUDGET '!J49-'ACTUAL SPENT '!J48 -> 2000000 | K48: ='BUDGET '!K49-'ACTUAL SPENT '!K48 -> 0 | ... M48: ='BUDGET '!M49-'ACTUAL SPENT '!M48 -> 2000000 | N48: =SUM(D48:M48) -> 6000000
A49: Local Travel | D49: ='BUDGET '!D50-'ACTUAL SPENT '!D49 -> 0 | E49: ='BUDGET '!E50-'ACTUAL SPENT '!E49 -> 0 | F49: ='BUDGET '!F50-'ACTUAL SPENT '!F49 -> 300000 | G49: ='BUDGET '!G50-'ACTUAL SPENT '!G49 -> 300000 | H49: ='BUDGET '!H50-'ACTUAL SPENT '!H49 -> 300000 | I49: ='BUDGET '!I50-'ACTUAL SPENT '!I49 -> 300000 | J49: ='BUDGET '!J50-'ACTUAL SPENT '!J49 -> 300000 | K49: ='BUDGET '!K50-'ACTUAL SPENT '!K49 -> 300000 | ... M49: ='BUDGET '!M50-'ACTUAL SPENT '!M49 -> 300000 | N49: =SUM(D49:M49) -> 2400000
D50: ='BUDGET '!D51-'ACTUAL SPENT '!D50 -> 0 | E50: ='BUDGET '!E51-'ACTUAL SPENT '!E50 -> 0 | F50: ='BUDGET '!F51-'ACTUAL SPENT '!F50 -> 15809880 | G50: ='BUDGET '!G51-'ACTUAL SPENT '!G50 -> 3050000 | H50: ='BUDGET '!H51-'ACTUAL SPENT '!H50 -> 300000 | I50: ='BUDGET '!I51-'ACTUAL SPENT '!I50 -> 300000 | J50: ='BUDGET '!J51-'ACTUAL SPENT '!J50 -> 3050000 | K50: ='BUDGET '!K51-'ACTUAL SPENT '!K50 -> 16904260 | ... M50: ='BUDGET '!M51-'ACTUAL SPENT '!M50 -> 3050000 | N50: =SUM(D50:M50) -> 42764140
D51: ='BUDGET '!D52-'ACTUAL SPENT '!D51 -> 0 | E51: ='BUDGET '!E52-'ACTUAL SPENT '!E51 -> 0 | F51: ='BUDGET '!F52-'ACTUAL SPENT '!F51 -> 0 | G51: ='BUDGET '!G52-'ACTUAL SPENT '!G51 -> 0 | H51: ='BUDGET '!H52-'ACTUAL SPENT '!H51 -> 0 | I51: ='BUDGET '!I52-'ACTUAL SPENT '!I51 -> 0 | J51: ='BUDGET '!J52-'ACTUAL SPENT '!J51 -> 0 | K51: ='BUDGET '!K52-'ACTUAL SPENT '!K51 -> 0 | ... M51: ='BUDGET '!M52-'ACTUAL SPENT '!M51 -> 0 | N51: =SUM(D51:M51) -> 0
A52: Equipment & Software | B52: Laptops, software, lab tools | D52: ='BUDGET '!D53-'ACTUAL SPENT '!D52 -> 0 | E52: ='BUDGET '!E53-'ACTUAL SPENT '!E52 -> 0 | F52: ='BUDGET '!F53-'ACTUAL SPENT '!F52 -> 0 | G52: ='BUDGET '!G53-'ACTUAL SPENT '!G52 -> 0 | H52: ='BUDGET '!H53-'ACTUAL SPENT '!H52 -> 0 | I52: ='BUDGET '!I53-'ACTUAL SPENT '!I52 -> 0 | J52: ='BUDGET '!J53-'ACTUAL SPENT '!J52 -> 0 | K52: ='BUDGET '!K53-'ACTUAL SPENT '!K52 -> 0 | ... M52: ='BUDGET '!M53-'ACTUAL SPENT '!M52 -> 0 | N52: =SUM(D52:M52) -> 0
A53: Website Hosting, Cloud Servers & Services | D53: ='BUDGET '!D54-'ACTUAL SPENT '!D53 -> 0 | E53: ='BUDGET '!E54-'ACTUAL SPENT '!E53 -> 0 | F53: ='BUDGET '!F54-'ACTUAL SPENT '!F53 -> 2572224 | G53: ='BUDGET '!G54-'ACTUAL SPENT '!G53 -> 0 | H53: ='BUDGET '!H54-'ACTUAL SPENT '!H53 -> 0 | I53: ='BUDGET '!I54-'ACTUAL SPENT '!I53 -> 0 | J53: ='BUDGET '!J54-'ACTUAL SPENT '!J53 -> 0 | K53: ='BUDGET '!K54-'ACTUAL SPENT '!K53 -> 0 | ... M53: ='BUDGET '!M54-'ACTUAL SPENT '!M53 -> 0 | N53: =SUM(D53:M53) -> 2572224
A54: Staff Email + Collaboration Tools (Zoho One) | D54: ='BUDGET '!D55-'ACTUAL SPENT '!D54 -> 0 | E54: ='BUDGET '!E55-'ACTUAL SPENT '!E54 -> 0 | F54: ='BUDGET '!F55-'ACTUAL SPENT '!F54 -> 536640 | G54: ='BUDGET '!G55-'ACTUAL SPENT '!G54 -> 0 | H54: ='BUDGET '!H55-'ACTUAL SPENT '!H54 -> 0 | I54: ='BUDGET '!I55-'ACTUAL SPENT '!I54 -> 0 | J54: ='BUDGET '!J55-'ACTUAL SPENT '!J54 -> 0 | K54: ='BUDGET '!K55-'ACTUAL SPENT '!K54 -> 0 | ... M54: ='BUDGET '!M55-'ACTUAL SPENT '!M54 -> 0 | N54: =SUM(D54:M54) -> 536640
A55: Software Subscriptions & Licenses | D55: ='BUDGET '!D56-'ACTUAL SPENT '!D55 -> -11610 | E55: ='BUDGET '!E56-'ACTUAL SPENT '!E55 -> -11610 | F55: ='BUDGET '!F56-'ACTUAL SPENT '!F55 -> 3217616 | G55: ='BUDGET '!G56-'ACTUAL SPENT '!G55 -> -1274798.8 | H55: ='BUDGET '!H56-'ACTUAL SPENT '!H55 -> 0 | I55: ='BUDGET '!I56-'ACTUAL SPENT '!I55 -> 0 | J55: ='BUDGET '!J56-'ACTUAL SPENT '!J55 -> 0 | K55: ='BUDGET '!K56-'ACTUAL SPENT '!K55 -> 0 | ... M55: ='BUDGET '!M56-'ACTUAL SPENT '!M55 -> 0 | N55: =SUM(D55:M55) -> 1919597.2
A56: Social Media Account Verification (Instagram, Facebook, Twitter) | D56: ='BUDGET '!D57-'ACTUAL SPENT '!D56 -> 0 | E56: ='BUDGET '!E57-'ACTUAL SPENT '!E56 -> 0 | F56: ='BUDGET '!F57-'ACTUAL SPENT '!F56 -> 526622 | G56: ='BUDGET '!G57-'ACTUAL SPENT '!G56 -> 0 | H56: ='BUDGET '!H57-'ACTUAL SPENT '!H56 -> 0 | I56: ='BUDGET '!I57-'ACTUAL SPENT '!I56 -> 0 | J56: ='BUDGET '!J57-'ACTUAL SPENT '!J56 -> 0 | K56: ='BUDGET '!K57-'ACTUAL SPENT '!K56 -> 0 | ... M56: ='BUDGET '!M57-'ACTUAL SPENT '!M56 -> 0 | N56: =SUM(D56:M56) -> 526622
A57: Coworking Space Management & Access Control Sofware | D57: ='BUDGET '!D58-'ACTUAL SPENT '!D57 -> 0 | E57: ='BUDGET '!E58-'ACTUAL SPENT '!E57 -> 0 | F57: ='BUDGET '!F58-'ACTUAL SPENT '!F57 -> 6491523 | G57: ='BUDGET '!G58-'ACTUAL SPENT '!G57 -> 0 | H57: ='BUDGET '!H58-'ACTUAL SPENT '!H57 -> 0 | I57: ='BUDGET '!I58-'ACTUAL SPENT '!I57 -> 0 | J57: ='BUDGET '!J58-'ACTUAL SPENT '!J57 -> 0 | K57: ='BUDGET '!K58-'ACTUAL SPENT '!K57 -> 0 | ... M57: ='BUDGET '!M58-'ACTUAL SPENT '!M57 -> 0 | N57: =SUM(D57:M57) -> 6491523
A58: Staff Mobile Devices | D58: ='BUDGET '!D59-'ACTUAL SPENT '!D58 -> 0 | E58: ='BUDGET '!E59-'ACTUAL SPENT '!E58 -> 0 | F58: ='BUDGET '!F59-'ACTUAL SPENT '!F58 -> 1825000 | G58: ='BUDGET '!G59-'ACTUAL SPENT '!G58 -> -2818000 | H58: ='BUDGET '!H59-'ACTUAL SPENT '!H58 -> 0 | I58: ='BUDGET '!I59-'ACTUAL SPENT '!I58 -> 0 | J58: ='BUDGET '!J59-'ACTUAL SPENT '!J58 -> 0 | K58: ='BUDGET '!K59-'ACTUAL SPENT '!K58 -> 0 | ... M58: ='BUDGET '!M59-'ACTUAL SPENT '!M58 -> 0 | N58: =SUM(D58:M58) -> -993000
D59: ='BUDGET '!D60-'ACTUAL SPENT '!D59 -> -11610 | E59: ='BUDGET '!E60-'ACTUAL SPENT '!E59 -> -11610 | F59: ='BUDGET '!F60-'ACTUAL SPENT '!F59 -> 15169625 | G59: ='BUDGET '!G60-'ACTUAL SPENT '!G59 -> -4092798.8 | H59: ='BUDGET '!H60-'ACTUAL SPENT '!H59 -> 0 | I59: ='BUDGET '!I60-'ACTUAL SPENT '!I59 -> 0 | J59: ='BUDGET '!J60-'ACTUAL SPENT '!J59 -> 0 | K59: ='BUDGET '!K60-'ACTUAL SPENT '!K59 -> 0 | ... M59: ='BUDGET '!M60-'ACTUAL SPENT '!M59 -> 0 | N59: =SUM(D59:M59) -> 11053606
D60: ='BUDGET '!D61-'ACTUAL SPENT '!D60 -> 0 | E60: ='BUDGET '!E61-'ACTUAL SPENT '!E60 -> 0 | F60: ='BUDGET '!F61-'ACTUAL SPENT '!F60 -> 0 | G60: ='BUDGET '!G61-'ACTUAL SPENT '!G60 -> 0 | H60: ='BUDGET '!H61-'ACTUAL SPENT '!H60 -> 0 | I60: ='BUDGET '!I61-'ACTUAL SPENT '!I60 -> 0 | J60: ='BUDGET '!J61-'ACTUAL SPENT '!J60 -> 0 | K60: ='BUDGET '!K61-'ACTUAL SPENT '!K60 -> 0 | ... M60: ='BUDGET '!M61-'ACTUAL SPENT '!M60 -> 0 | N60: =SUM(D60:M60) -> 0
D61: ='BUDGET '!D62-'ACTUAL SPENT '!D61 -> 0 | E61: ='BUDGET '!E62-'ACTUAL SPENT '!E61 -> 0 | F61: ='BUDGET '!F62-'ACTUAL SPENT '!F61 -> 0 | G61: ='BUDGET '!G62-'ACTUAL SPENT '!G61 -> 0 | H61: ='BUDGET '!H62-'ACTUAL SPENT '!H61 -> 0 | I61: ='BUDGET '!I62-'ACTUAL SPENT '!I61 -> 0 | J61: ='BUDGET '!J62-'ACTUAL SPENT '!J61 -> 0 | K61: ='BUDGET '!K62-'ACTUAL SPENT '!K61 -> 0 | ... M61: ='BUDGET '!M62-'ACTUAL SPENT '!M61 -> 0 | N61: =SUM(D61:M61) -> 0
A62: Corporate Comms & PR | B62: Branding, PR | D62: ='BUDGET '!D63-'ACTUAL SPENT '!D62 -> 0 | E62: ='BUDGET '!E63-'ACTUAL SPENT '!E62 -> 0 | F62: ='BUDGET '!F63-'ACTUAL SPENT '!F62 -> 0 | G62: ='BUDGET '!G63-'ACTUAL SPENT '!G62 -> 0 | H62: ='BUDGET '!H63-'ACTUAL SPENT '!H62 -> 0 | I62: ='BUDGET '!I63-'ACTUAL SPENT '!I62 -> 0 | J62: ='BUDGET '!J63-'ACTUAL SPENT '!J62 -> 0 | K62: ='BUDGET '!K63-'ACTUAL SPENT '!K62 -> 0 | ... M62: ='BUDGET '!M63-'ACTUAL SPENT '!M62 -> 0 | N62: =SUM(D62:M62) -> 0
A63: Souvenirs | D63: ='BUDGET '!D64-'ACTUAL SPENT '!D63 -> 0 | E63: ='BUDGET '!E64-'ACTUAL SPENT '!E63 -> 0 | F63: ='BUDGET '!F64-'ACTUAL SPENT '!F63 -> 2500000 | G63: ='BUDGET '!G64-'ACTUAL SPENT '!G63 -> -1820000 | H63: ='BUDGET '!H64-'ACTUAL SPENT '!H63 -> 0 | I63: ='BUDGET '!I64-'ACTUAL SPENT '!I63 -> 0 | J63: ='BUDGET '!J64-'ACTUAL SPENT '!J63 -> 0 | K63: ='BUDGET '!K64-'ACTUAL SPENT '!K63 -> 0 | ... M63: ='BUDGET '!M64-'ACTUAL SPENT '!M63 -> 0 | N63: =SUM(D63:M63) -> 680000
A64: Guest Entertainment & Refreshments | D64: ='BUDGET '!D65-'ACTUAL SPENT '!D64 -> 0 | E64: ='BUDGET '!E65-'ACTUAL SPENT '!E64 -> 0 | F64: ='BUDGET '!F65-'ACTUAL SPENT '!F64 -> 238000 | G64: ='BUDGET '!G65-'ACTUAL SPENT '!G64 -> -156200 | H64: ='BUDGET '!H65-'ACTUAL SPENT '!H64 -> 350000 | I64: ='BUDGET '!I65-'ACTUAL SPENT '!I64 -> 350000 | J64: ='BUDGET '!J65-'ACTUAL SPENT '!J64 -> 350000 | K64: ='BUDGET '!K65-'ACTUAL SPENT '!K64 -> 350000 | ... M64: ='BUDGET '!M65-'ACTUAL SPENT '!M64 -> 350000 | N64: =SUM(D64:M64) -> 2181800
A65: Banners | D65: ='BUDGET '!D66-'ACTUAL SPENT '!D65 -> 0 | E65: ='BUDGET '!E66-'ACTUAL SPENT '!E65 -> 0 | F65: ='BUDGET '!F66-'ACTUAL SPENT '!F65 -> 210000 | G65: ='BUDGET '!G66-'ACTUAL SPENT '!G65 -> 0 | H65: ='BUDGET '!H66-'ACTUAL SPENT '!H65 -> 0 | I65: ='BUDGET '!I66-'ACTUAL SPENT '!I65 -> 0 | J65: ='BUDGET '!J66-'ACTUAL SPENT '!J65 -> 0 | K65: ='BUDGET '!K66-'ACTUAL SPENT '!K65 -> 0 | ... M65: ='BUDGET '!M66-'ACTUAL SPENT '!M65 -> 0 | N65: =SUM(D65:M65) -> 210000
A66: Merchandise & Staff T-Shirts | D66: ='BUDGET '!D67-'ACTUAL SPENT '!D66 -> 0 | E66: ='BUDGET '!E67-'ACTUAL SPENT '!E66 -> 0 | F66: ='BUDGET '!F67-'ACTUAL SPENT '!F66 -> 250000 | G66: ='BUDGET '!G67-'ACTUAL SPENT '!G66 -> 0 | H66: ='BUDGET '!H67-'ACTUAL SPENT '!H66 -> 0 | I66: ='BUDGET '!I67-'ACTUAL SPENT '!I66 -> 0 | J66: ='BUDGET '!J67-'ACTUAL SPENT '!J66 -> 0 | K66: ='BUDGET '!K67-'ACTUAL SPENT '!K66 -> 0 | ... M66: ='BUDGET '!M67-'ACTUAL SPENT '!M66 -> 0 | N66: =SUM(D66:M66) -> 250000
A67: Online & Social Media Marketing | D67: ='BUDGET '!D68-'ACTUAL SPENT '!D67 -> 0 | E67: ='BUDGET '!E68-'ACTUAL SPENT '!E67 -> 0 | F67: ='BUDGET '!F68-'ACTUAL SPENT '!F67 -> 250000 | G67: ='BUDGET '!G68-'ACTUAL SPENT '!G67 -> 250000 | H67: ='BUDGET '!H68-'ACTUAL SPENT '!H67 -> 250000 | I67: ='BUDGET '!I68-'ACTUAL SPENT '!I67 -> 250000 | J67: ='BUDGET '!J68-'ACTUAL SPENT '!J67 -> 250000 | K67: ='BUDGET '!K68-'ACTUAL SPENT '!K67 -> 250000 | ... M67: ='BUDGET '!M68-'ACTUAL SPENT '!M67 -> 250000 | N67: =SUM(D67:M67) -> 2000000
A68: Photography & Videography | D68: ='BUDGET '!D69-'ACTUAL SPENT '!D68 -> 0 | E68: ='BUDGET '!E69-'ACTUAL SPENT '!E68 -> 0 | F68: ='BUDGET '!F69-'ACTUAL SPENT '!F68 -> 0 | G68: ='BUDGET '!G69-'ACTUAL SPENT '!G68 -> 0 | H68: ='BUDGET '!H69-'ACTUAL SPENT '!H68 -> 0 | I68: ='BUDGET '!I69-'ACTUAL SPENT '!I68 -> 0 | J68: ='BUDGET '!J69-'ACTUAL SPENT '!J68 -> 0 | K68: ='BUDGET '!K69-'ACTUAL SPENT '!K68 -> 0 | ... M68: ='BUDGET '!M69-'ACTUAL SPENT '!M68 -> 0 | N68: =SUM(D68:M68) -> 0
D69: ='BUDGET '!D70-'ACTUAL SPENT '!D69 -> 0 | E69: ='BUDGET '!E70-'ACTUAL SPENT '!E69 -> 0 | F69: ='BUDGET '!F70-'ACTUAL SPENT '!F69 -> 3448000 | G69: ='BUDGET '!G70-'ACTUAL SPENT '!G69 -> -1726200 | H69: ='BUDGET '!H70-'ACTUAL SPENT '!H69 -> 600000 | I69: ='BUDGET '!I70-'ACTUAL SPENT '!I69 -> 600000 | J69: ='BUDGET '!J70-'ACTUAL SPENT '!J69 -> 600000 | K69: ='BUDGET '!K70-'ACTUAL SPENT '!K69 -> 600000 | ... M69: ='BUDGET '!M70-'ACTUAL SPENT '!M69 -> 600000 | N69: =SUM(D69:M69) -> 5321800
D70: ='BUDGET '!D71-'ACTUAL SPENT '!D70 -> 0 | E70: ='BUDGET '!E71-'ACTUAL SPENT '!E70 -> 0 | F70: ='BUDGET '!F71-'ACTUAL SPENT '!F70 -> 0 | G70: ='BUDGET '!G71-'ACTUAL SPENT '!G70 -> 0 | H70: ='BUDGET '!H71-'ACTUAL SPENT '!H70 -> 0 | I70: ='BUDGET '!I71-'ACTUAL SPENT '!I70 -> 0 | J70: ='BUDGET '!J71-'ACTUAL SPENT '!J70 -> 0 | K70: ='BUDGET '!K71-'ACTUAL SPENT '!K70 -> 0 | ... M70: ='BUDGET '!M71-'ACTUAL SPENT '!M70 -> 0 | N70: =SUM(D70:M70) -> 0
A71: Administrative Costs | B71: Office admin costs & supplies | D71: ='BUDGET '!D72-'ACTUAL SPENT '!D71 -> 0 | E71: ='BUDGET '!E72-'ACTUAL SPENT '!E71 -> 0 | F71: ='BUDGET '!F72-'ACTUAL SPENT '!F71 -> 0 | G71: ='BUDGET '!G72-'ACTUAL SPENT '!G71 -> 0 | H71: ='BUDGET '!H72-'ACTUAL SPENT '!H71 -> 0 | I71: ='BUDGET '!I72-'ACTUAL SPENT '!I71 -> 0 | J71: ='BUDGET '!J72-'ACTUAL SPENT '!J71 -> 0 | K71: ='BUDGET '!K72-'ACTUAL SPENT '!K71 -> 0 | ... M71: ='BUDGET '!M72-'ACTUAL SPENT '!M71 -> 0 | N71: =SUM(D71:M71) -> 0
A72: Stationery & Office Supplies | D72: ='BUDGET '!D73-'ACTUAL SPENT '!D72 -> 0 | E72: ='BUDGET '!E73-'ACTUAL SPENT '!E72 -> 0 | F72: ='BUDGET '!F73-'ACTUAL SPENT '!F72 -> 150000 | G72: ='BUDGET '!G73-'ACTUAL SPENT '!G72 -> -787300 | H72: ='BUDGET '!H73-'ACTUAL SPENT '!H72 -> 150000 | I72: ='BUDGET '!I73-'ACTUAL SPENT '!I72 -> 150000 | J72: ='BUDGET '!J73-'ACTUAL SPENT '!J72 -> 150000 | K72: ='BUDGET '!K73-'ACTUAL SPENT '!K72 -> 150000 | ... M72: ='BUDGET '!M73-'ACTUAL SPENT '!M72 -> 150000 | N72: =SUM(D72:M72) -> 262700
A73: Association & Society Memberships | D73: ='BUDGET '!D74-'ACTUAL SPENT '!D73 -> 0 | E73: ='BUDGET '!E74-'ACTUAL SPENT '!E73 -> 0 | F73: ='BUDGET '!F74-'ACTUAL SPENT '!F73 -> 39866.25 | G73: ='BUDGET '!G74-'ACTUAL SPENT '!G73 -> 0 | H73: ='BUDGET '!H74-'ACTUAL SPENT '!H73 -> 0 | I73: ='BUDGET '!I74-'ACTUAL SPENT '!I73 -> 0 | J73: ='BUDGET '!J74-'ACTUAL SPENT '!J73 -> 0 | K73: ='BUDGET '!K74-'ACTUAL SPENT '!K73 -> 0 | ... M73: ='BUDGET '!M74-'ACTUAL SPENT '!M73 -> 0 | N73: =SUM(D73:M73) -> 39866.25
D74: ='BUDGET '!D75-'ACTUAL SPENT '!D74 -> 0 | E74: ='BUDGET '!E75-'ACTUAL SPENT '!E74 -> 0 | F74: ='BUDGET '!F75-'ACTUAL SPENT '!F74 -> 189866.25 | G74: ='BUDGET '!G75-'ACTUAL SPENT '!G74 -> -787300 | H74: ='BUDGET '!H75-'ACTUAL SPENT '!H74 -> 150000 | I74: ='BUDGET '!I75-'ACTUAL SPENT '!I74 -> 150000 | J74: ='BUDGET '!J75-'ACTUAL SPENT '!J74 -> 150000 | K74: ='BUDGET '!K75-'ACTUAL SPENT '!K74 -> 150000 | ... M74: ='BUDGET '!M75-'ACTUAL SPENT '!M74 -> 150000 | N74: =SUM(D74:M74) -> 302566.25
D75: ='BUDGET '!D76-'ACTUAL SPENT '!D75 -> 0 | E75: ='BUDGET '!E76-'ACTUAL SPENT '!E75 -> 0 | F75: ='BUDGET '!F76-'ACTUAL SPENT '!F75 -> 0 | G75: ='BUDGET '!G76-'ACTUAL SPENT '!G75 -> 0 | H75: ='BUDGET '!H76-'ACTUAL SPENT '!H75 -> 0 | I75: ='BUDGET '!I76-'ACTUAL SPENT '!I75 -> 0 | J75: ='BUDGET '!J76-'ACTUAL SPENT '!J75 -> 0 | K75: ='BUDGET '!K76-'ACTUAL SPENT '!K75 -> 0 | ... M75: ='BUDGET '!M76-'ACTUAL SPENT '!M75 -> 0 | N75: =SUM(D75:M75) -> 0
D76: ='BUDGET '!D77-'ACTUAL SPENT '!D76 -> 0 | E76: ='BUDGET '!E77-'ACTUAL SPENT '!E76 -> 0 | F76: ='BUDGET '!F77-'ACTUAL SPENT '!F76 -> 0 | G76: ='BUDGET '!G77-'ACTUAL SPENT '!G76 -> 0 | H76: ='BUDGET '!H77-'ACTUAL SPENT '!H76 -> 0 | I76: ='BUDGET '!I77-'ACTUAL SPENT '!I76 -> 0 | J76: ='BUDGET '!J77-'ACTUAL SPENT '!J76 -> 0 | K76: ='BUDGET '!K77-'ACTUAL SPENT '!K76 -> 0 | ... M76: ='BUDGET '!M77-'ACTUAL SPENT '!M76 -> 0 | N76: =SUM(D76:M76) -> 0
A77: Total Operational Expenses | D77: ='BUDGET '!D78-'ACTUAL SPENT '!D77 -> -1038468.9 | E77: ='BUDGET '!E78-'ACTUAL SPENT '!E77 -> 8039233.1 | F77: ='BUDGET '!F78-'ACTUAL SPENT '!F77 -> 55183953 | G77: ='BUDGET '!G78-'ACTUAL SPENT '!G77 -> 4641372.2 | H77: ='BUDGET '!H78-'ACTUAL SPENT '!H77 -> 24788687 | I77: ='BUDGET '!I78-'ACTUAL SPENT '!I77 -> 24788687 | J77: ='BUDGET '!J78-'ACTUAL SPENT '!J77 -> 29538687 | K77: ='BUDGET '!K78-'ACTUAL SPENT '!K77 -> 41392947 | ... M77: ='BUDGET '!M78-'ACTUAL SPENT '!M77 -> 45579374 | N77: =SUM(D77:M77) -> 2.5770316e+08
D78: ='BUDGET '!D79-'ACTUAL SPENT '!D78 -> 0 | E78: ='BUDGET '!E79-'ACTUAL SPENT '!E78 -> 0 | F78: ='BUDGET '!F79-'ACTUAL SPENT '!F78 -> 0 | G78: ='BUDGET '!G79-'ACTUAL SPENT '!G78 -> 0 | H78: ='BUDGET '!H79-'ACTUAL SPENT '!H78 -> 0 | I78: ='BUDGET '!I79-'ACTUAL SPENT '!I78 -> 0 | J78: ='BUDGET '!J79-'ACTUAL SPENT '!J78 -> 0 | K78: ='BUDGET '!K79-'ACTUAL SPENT '!K78 -> 0 | ... M78: ='BUDGET '!M79-'ACTUAL SPENT '!M78 -> 0 | N78: =SUM(D78:M78) -> 0
D79: ='BUDGET '!D80-'ACTUAL SPENT '!D79 -> 0 | E79: ='BUDGET '!E80-'ACTUAL SPENT '!E79 -> 0 | F79: ='BUDGET '!F80-'ACTUAL SPENT '!F79 -> 0 | G79: ='BUDGET '!G80-'ACTUAL SPENT '!G79 -> 0 | H79: ='BUDGET '!H80-'ACTUAL SPENT '!H79 -> 0 | I79: ='BUDGET '!I80-'ACTUAL SPENT '!I79 -> 0 | J79: ='BUDGET '!J80-'ACTUAL SPENT '!J79 -> 0 | K79: ='BUDGET '!K80-'ACTUAL SPENT '!K79 -> 0 | ... M79: ='BUDGET '!M80-'ACTUAL SPENT '!M79 -> 0 | N79: =SUM(D79:M79) -> 0
D80: ='BUDGET '!D81-'ACTUAL SPENT '!D80 -> 0 | E80: ='BUDGET '!E81-'ACTUAL SPENT '!E80 -> 0 | F80: ='BUDGET '!F81-'ACTUAL SPENT '!F80 -> 0 | G80: ='BUDGET '!G81-'ACTUAL SPENT '!G80 -> 0 | H80: ='BUDGET '!H81-'ACTUAL SPENT '!H80 -> 0 | I80: ='BUDGET '!I81-'ACTUAL SPENT '!I80 -> 0 | J80: ='BUDGET '!J81-'ACTUAL SPENT '!J80 -> 0 | K80: ='BUDGET '!K81-'ACTUAL SPENT '!K80 -> 0 | ... M80: ='BUDGET '!M81-'ACTUAL SPENT '!M80 -> 0 | N80: =SUM(D80:M80) -> 0
D81: ='BUDGET '!D82-'ACTUAL SPENT '!D81 -> 0 | E81: ='BUDGET '!E82-'ACTUAL SPENT '!E81 -> 0 | F81: ='BUDGET '!F82-'ACTUAL SPENT '!F81 -> 0 | G81: ='BUDGET '!G82-'ACTUAL SPENT '!G81 -> 0 | H81: ='BUDGET '!H82-'ACTUAL SPENT '!H81 -> 0 | I81: ='BUDGET '!I82-'ACTUAL SPENT '!I81 -> 0 | J81: ='BUDGET '!J82-'ACTUAL SPENT '!J81 -> 0 | K81: ='BUDGET '!K82-'ACTUAL SPENT '!K81 -> 0 | ... M81: ='BUDGET '!M82-'ACTUAL SPENT '!M81 -> 0 | N81: =SUM(D81:M81) -> 0
A82: Staff Professional Development | D82: ='BUDGET '!D83-'ACTUAL SPENT '!D82 -> 0 | E82: ='BUDGET '!E83-'ACTUAL SPENT '!E82 -> 0 | F82: ='BUDGET '!F83-'ACTUAL SPENT '!F82 -> 0 | G82: ='BUDGET '!G83-'ACTUAL SPENT '!G82 -> 0 | H82: ='BUDGET '!H83-'ACTUAL SPENT '!H82 -> 0 | I82: ='BUDGET '!I83-'ACTUAL SPENT '!I82 -> 0 | J82: ='BUDGET '!J83-'ACTUAL SPENT '!J82 -> 0 | K82: ='BUDGET '!K83-'ACTUAL SPENT '!K82 -> 0 | ... M82: ='BUDGET '!M83-'ACTUAL SPENT '!M82 -> 0 | N82: =SUM(D82:M82) -> 0
A83: Monthly Meetups | B83: Startup acceleration & support | D83: ='BUDGET '!D84-'ACTUAL SPENT '!D83 -> 250000 | E83: ='BUDGET '!E84-'ACTUAL SPENT '!E83 -> 0 | F83: ='BUDGET '!F84-'ACTUAL SPENT '!F83 -> 250000 | G83: ='BUDGET '!G84-'ACTUAL SPENT '!G83 -> 250000 | H83: ='BUDGET '!H84-'ACTUAL SPENT '!H83 -> 250000 | I83: ='BUDGET '!I84-'ACTUAL SPENT '!I83 -> 250000 | J83: ='BUDGET '!J84-'ACTUAL SPENT '!J83 -> 250000 | K83: ='BUDGET '!K84-'ACTUAL SPENT '!K83 -> 250000 | ... M83: ='BUDGET '!M84-'ACTUAL SPENT '!M83 -> 250000 | N83: =SUM(D83:M83) -> 2250000
A84: Field Events | D84: ='BUDGET '!D85-'ACTUAL SPENT '!D84 -> 0 | E84: ='BUDGET '!E85-'ACTUAL SPENT '!E84 -> 0 | F84: ='BUDGET '!F85-'ACTUAL SPENT '!F84 -> 200000 | G84: ='BUDGET '!G85-'ACTUAL SPENT '!G84 -> 200000 | H84: ='BUDGET '!H85-'ACTUAL SPENT '!H84 -> 200000 | I84: ='BUDGET '!I85-'ACTUAL SPENT '!I84 -> 200000 | J84: ='BUDGET '!J85-'ACTUAL SPENT '!J84 -> 200000 | K84: ='BUDGET '!K85-'ACTUAL SPENT '!K84 -> 200000 | ... M84: ='BUDGET '!M85-'ACTUAL SPENT '!M84 -> 200000 | N84: =SUM(D84:M84) -> 1600000
A85: Webinars | D85: ='BUDGET '!D86-'ACTUAL SPENT '!D85 -> 0 | E85: ='BUDGET '!E86-'ACTUAL SPENT '!E85 -> 0 | F85: ='BUDGET '!F86-'ACTUAL SPENT '!F85 -> 136000 | G85: ='BUDGET '!G86-'ACTUAL SPENT '!G85 -> 136000 | H85: ='BUDGET '!H86-'ACTUAL SPENT '!H85 -> 136000 | I85: ='BUDGET '!I86-'ACTUAL SPENT '!I85 -> 136000 | J85: ='BUDGET '!J86-'ACTUAL SPENT '!J85 -> 136000 | K85: ='BUDGET '!K86-'ACTUAL SPENT '!K85 -> 136000 | ... M85: ='BUDGET '!M86-'ACTUAL SPENT '!M85 -> 136000 | N85: =SUM(D85:M85) -> 1088000
A86: Training & Mentorship | D86: ='BUDGET '!D87-'ACTUAL SPENT '!D86 -> 0 | E86: ='BUDGET '!E87-'ACTUAL SPENT '!E86 -> 0 | F86: ='BUDGET '!F87-'ACTUAL SPENT '!F86 -> 333333.33 | G86: ='BUDGET '!G87-'ACTUAL SPENT '!G86 -> 333333.33 | H86: ='BUDGET '!H87-'ACTUAL SPENT '!H86 -> 333333.33 | I86: ='BUDGET '!I87-'ACTUAL SPENT '!I86 -> 333333.33 | J86: ='BUDGET '!J87-'ACTUAL SPENT '!J86 -> 333333.33 | K86: ='BUDGET '!K87-'ACTUAL SPENT '!K86 -> 333333.33 | ... M86: ='BUDGET '!M87-'ACTUAL SPENT '!M86 -> 333333.33 | N86: =SUM(D86:M86) -> 2666666.7
A87: Total Program Support | D87: ='BUDGET '!D88-'ACTUAL SPENT '!D87 -> 250000 | E87: ='BUDGET '!E88-'ACTUAL SPENT '!E87 -> 0 | F87: ='BUDGET '!F88-'ACTUAL SPENT '!F87 -> 919333.33 | G87: ='BUDGET '!G88-'ACTUAL SPENT '!G87 -> 919333.33 | H87: ='BUDGET '!H88-'ACTUAL SPENT '!H87 -> 919333.33 | I87: ='BUDGET '!I88-'ACTUAL SPENT '!I87 -> 919333.33 | J87: ='BUDGET '!J88-'ACTUAL SPENT '!J87 -> 919333.33 | K87: ='BUDGET '!K88-'ACTUAL SPENT '!K87 -> 919333.33 | ... M87: ='BUDGET '!M88-'ACTUAL SPENT '!M87 -> 919333.33 | N87: =SUM(D87:M87) -> 7604666.7
D88: ='BUDGET '!D89-'ACTUAL SPENT '!D88 -> 0 | E88: ='BUDGET '!E89-'ACTUAL SPENT '!E88 -> 0 | F88: ='BUDGET '!F89-'ACTUAL SPENT '!F88 -> 0 | G88: ='BUDGET '!G89-'ACTUAL SPENT '!G88 -> 0 | H88: ='BUDGET '!H89-'ACTUAL SPENT '!H88 -> 0 | I88: ='BUDGET '!I89-'ACTUAL SPENT '!I88 -> 0 | J88: ='BUDGET '!J89-'ACTUAL SPENT '!J88 -> 0 | K88: ='BUDGET '!K89-'ACTUAL SPENT '!K88 -> 0 | ... M88: ='BUDGET '!M89-'ACTUAL SPENT '!M88 -> 0 | N88: =SUM(D88:M88) -> 0
D89: ='BUDGET '!D90-'ACTUAL SPENT '!D89 -> 0 | E89: ='BUDGET '!E90-'ACTUAL SPENT '!E89 -> 0 | F89: ='BUDGET '!F90-'ACTUAL SPENT '!F89 -> 0 | G89: ='BUDGET '!G90-'ACTUAL SPENT '!G89 -> 0 | H89: ='BUDGET '!H90-'ACTUAL SPENT '!H89 -> 0 | I89: ='BUDGET '!I90-'ACTUAL SPENT '!I89 -> 0 | J89: ='BUDGET '!J90-'ACTUAL SPENT '!J89 -> 0 | K89: ='BUDGET '!K90-'ACTUAL SPENT '!K89 -> 0 | ... M89: ='BUDGET '!M90-'ACTUAL SPENT '!M89 -> 0 | N89: =SUM(D89:M89) -> 0
D90: ='BUDGET '!D91-'ACTUAL SPENT '!D90 -> 0 | E90: ='BUDGET '!E91-'ACTUAL SPENT '!E90 -> 0 | F90: ='BUDGET '!F91-'ACTUAL SPENT '!F90 -> 0 | G90: ='BUDGET '!G91-'ACTUAL SPENT '!G90 -> 0 | H90: ='BUDGET '!H91-'ACTUAL SPENT '!H90 -> 0 | I90: ='BUDGET '!I91-'ACTUAL SPENT '!I90 -> 0 | J90: ='BUDGET '!J91-'ACTUAL SPENT '!J90 -> 0 | K90: ='BUDGET '!K91-'ACTUAL SPENT '!K90 -> 0 | ... M90: ='BUDGET '!M91-'ACTUAL SPENT '!M90 -> 0 | N90: =SUM(D90:M90) -> 0
A91: Contingency & Sustainability
A92: Reserve Fund - % of Inflows | B92: Emergency fund for sustainability | C92: 0.02 | D92: ='BUDGET '!D93-'ACTUAL SPENT '!D92 -> 0 | E92: ='BUDGET '!E93-'ACTUAL SPENT '!E92 -> 0 | F92: ='BUDGET '!F93-'ACTUAL SPENT '!F92 -> 0 | G92: ='BUDGET '!G93-'ACTUAL SPENT '!G92 -> 0 | H92: ='BUDGET '!H93-'ACTUAL SPENT '!H92 -> 0 | I92: ='BUDGET '!I93-'ACTUAL SPENT '!I92 -> 0 | J92: ='BUDGET '!J93-'ACTUAL SPENT '!J92 -> 0 | K92: ='BUDGET '!K93-'ACTUAL SPENT '!K92 -> 0 | ... M92: ='BUDGET '!M93-'ACTUAL SPENT '!M92 -> 0 | N92: =SUM(D92:M92) -> 0
A93: Miscellaneous Expenses - % of Operating Exp. | B93: Unexpected costs | C93: 0.02 | D93: ='BUDGET '!D94-'ACTUAL SPENT '!D93 -> 0 | E93: ='BUDGET '!E94-'ACTUAL SPENT '!E93 -> 0 | F93: ='BUDGET '!F94-'ACTUAL SPENT '!F93 -> 1103679.1 | G93: ='BUDGET '!G94-'ACTUAL SPENT '!G93 -> 92827.444 | H93: ='BUDGET '!H94-'ACTUAL SPENT '!H93 -> 495773.74 | I93: ='BUDGET '!I94-'ACTUAL SPENT '!I93 -> 495773.74 | J93: ='BUDGET '!J94-'ACTUAL SPENT '!J93 -> 590773.74 | K93: ='BUDGET '!K94-'ACTUAL SPENT '!K93 -> 827858.94 | ... M93: ='BUDGET '!M94-'ACTUAL SPENT '!M93 -> 911587.47 | N93: =SUM(D93:M93) -> 5014047.9
A94: Total Contingency | D94: ='BUDGET '!D95-'ACTUAL SPENT '!D94 -> 0 | E94: ='BUDGET '!E95-'ACTUAL SPENT '!E94 -> 0 | F94: ='BUDGET '!F95-'ACTUAL SPENT '!F94 -> 1103679.1 | G94: ='BUDGET '!G95-'ACTUAL SPENT '!G94 -> 92827.444 | H94: ='BUDGET '!H95-'ACTUAL SPENT '!H94 -> 495773.74 | I94: ='BUDGET '!I95-'ACTUAL SPENT '!I94 -> 495773.74 | J94: ='BUDGET '!J95-'ACTUAL SPENT '!J94 -> 590773.74 | K94: ='BUDGET '!K95-'ACTUAL SPENT '!K94 -> 827858.94 | ... M94: ='BUDGET '!M95-'ACTUAL SPENT '!M94 -> 911587.47 | N94: =SUM(D94:M94) -> 5014047.9
D95: ='BUDGET '!D96-'ACTUAL SPENT '!D95 -> 0 | E95: ='BUDGET '!E96-'ACTUAL SPENT '!E95 -> 0 | F95: ='BUDGET '!F96-'ACTUAL SPENT '!F95 -> 0 | G95: ='BUDGET '!G96-'ACTUAL SPENT '!G95 -> 0 | H95: ='BUDGET '!H96-'ACTUAL SPENT '!H95 -> 0 | I95: ='BUDGET '!I96-'ACTUAL SPENT '!I95 -> 0 | J95: ='BUDGET '!J96-'ACTUAL SPENT '!J95 -> 0 | K95: ='BUDGET '!K96-'ACTUAL SPENT '!K95 -> 0 | ... M95: ='BUDGET '!M96-'ACTUAL SPENT '!M95 -> 0 | N95: =SUM(D95:M95) -> 0
D96: ='BUDGET '!D97-'ACTUAL SPENT '!D96 -> 0 | E96: ='BUDGET '!E97-'ACTUAL SPENT '!E96 -> 0 | F96: ='BUDGET '!F97-'ACTUAL SPENT '!F96 -> 0 | G96: ='BUDGET '!G97-'ACTUAL SPENT '!G96 -> 0 | H96: ='BUDGET '!H97-'ACTUAL SPENT '!H96 -> 0 | I96: ='BUDGET '!I97-'ACTUAL SPENT '!I96 -> 0 | J96: ='BUDGET '!J97-'ACTUAL SPENT '!J96 -> 0 | K96: ='BUDGET '!K97-'ACTUAL SPENT '!K96 -> 0 | ... M96: ='BUDGET '!M97-'ACTUAL SPENT '!M96 -> 0 | N96: =SUM(D96:M96) -> 0
D97: ='BUDGET '!D98-'ACTUAL SPENT '!D97 -> 0 | E97: ='BUDGET '!E98-'ACTUAL SPENT '!E97 -> 0 | F97: ='BUDGET '!F98-'ACTUAL SPENT '!F97 -> 0 | G97: ='BUDGET '!G98-'ACTUAL SPENT '!G97 -> 0 | H97: ='BUDGET '!H98-'ACTUAL SPENT '!H97 -> 0 | I97: ='BUDGET '!I98-'ACTUAL SPENT '!I97 -> 0 | J97: ='BUDGET '!J98-'ACTUAL SPENT '!J97 -> 0 | K97: ='BUDGET '!K98-'ACTUAL SPENT '!K97 -> 0 | ... M97: ='BUDGET '!M98-'ACTUAL SPENT '!M97 -> 0 | N97: =SUM(D97:M97) -> 0
D98: ='BUDGET '!D99-'ACTUAL SPENT '!D98 -> 0 | E98: ='BUDGET '!E99-'ACTUAL SPENT '!E98 -> 0 | F98: ='BUDGET '!F99-'ACTUAL SPENT '!F98 -> 0 | G98: ='BUDGET '!G99-'ACTUAL SPENT '!G98 -> 0 | H98: ='BUDGET '!H99-'ACTUAL SPENT '!H98 -> 0 | I98: ='BUDGET '!I99-'ACTUAL SPENT '!I98 -> 0 | J98: ='BUDGET '!J99-'ACTUAL SPENT '!J98 -> 0 | K98: ='BUDGET '!K99-'ACTUAL SPENT '!K98 -> 0 | ... M98: ='BUDGET '!M99-'ACTUAL SPENT '!M98 -> 0 | N98: =SUM(D98:M98) -> 0
A99: Summary | D99: ='BUDGET '!D100-'ACTUAL SPENT '!D99 -> 0 | E99: ='BUDGET '!E100-'ACTUAL SPENT '!E99 -> 0 | F99: ='BUDGET '!F100-'ACTUAL SPENT '!F99 -> 0 | G99: ='BUDGET '!G100-'ACTUAL SPENT '!G99 -> 0 | H99: ='BUDGET '!H100-'ACTUAL SPENT '!H99 -> 0 | I99: ='BUDGET '!I100-'ACTUAL SPENT '!I99 -> 0 | J99: ='BUDGET '!J100-'ACTUAL SPENT '!J99 -> 0 | K99: ='BUDGET '!K100-'ACTUAL SPENT '!K99 -> 0 | ... M99: ='BUDGET '!M100-'ACTUAL SPENT '!M99 -> 0 | N99: =SUM(D99:M99) -> 0
A100: Total Revenue | D100: =D14 -> 6908850 | E100: =E14 -> 0 | F100: =F14 -> 133916648 | G100: =G14 -> 0 | H100: =H14 -> 104296540 | I100: =I14 -> 0 | J100: =J14 -> 0 | K100: =K14 -> 100000000 | ... M100: =M14 -> 0 | N100: =SUM(D100:M100) -> 345122038
A101: Total Expenses | D101: ='BUDGET '!D102-'ACTUAL SPENT '!D101 -> -788468.93 | E101: ='BUDGET '!E102-'ACTUAL SPENT '!E101 -> 8039233.1 | F101: ='BUDGET '!F102-'ACTUAL SPENT '!F101 -> 57206966 | G101: ='BUDGET '!G102-'ACTUAL SPENT '!G101 -> 5653533 | H101: ='BUDGET '!H102-'ACTUAL SPENT '!H101 -> 26203794 | I101: ='BUDGET '!I102-'ACTUAL SPENT '!I101 -> 26203794 | J101: ='BUDGET '!J102-'ACTUAL SPENT '!J101 -> 31048794 | K101: ='BUDGET '!K102-'ACTUAL SPENT '!K101 -> 43140139 | ... M101: ='BUDGET '!M102-'ACTUAL SPENT '!M101 -> 47410294 | N101: =SUM(D101:M101) -> 2.7032187e+08
D102: ='BUDGET '!D103-'ACTUAL SPENT '!D102 -> 0 | E102: ='BUDGET '!E103-'ACTUAL SPENT '!E102 -> 0 | F102: ='BUDGET '!F103-'ACTUAL SPENT '!F102 -> 0 | G102: ='BUDGET '!G103-'ACTUAL SPENT '!G102 -> 0 | H102: ='BUDGET '!H103-'ACTUAL SPENT '!H102 -> 0 | I102: ='BUDGET '!I103-'ACTUAL SPENT '!I102 -> 0 | J102: ='BUDGET '!J103-'ACTUAL SPENT '!J102 -> 0 | K102: ='BUDGET '!K103-'ACTUAL SPENT '!K102 -> 0 | ... M102: ='BUDGET '!M103-'ACTUAL SPENT '!M102 -> 0 | N102: =SUM(D102:M102) -> 0
