Workbook

Sheet Summary
B2: ILORIN INNOVATION HUB ONE YEAR OPERATING BUDGET ESTIMATE SUMMARY
A4: SN | B4: Budget Summary | D4: Amount (N)
B5: Capital Expenses
A6: 1 | B6: Stationery & Supplies | D6: ='Stationery & Supplies'!E24 -> 1990600
A7: 2 | B7: Computers & Equipment | D7: ='Computers & Equipment'!E16 -> 22360000
B8: Total | D8: =SUM(D6:D7) -> 24350600
B10: Operating Expenses
A11: 3 | B11: Utilities & Diesel | D11: =Utilities!E17 -> 7200000
A12: 4 | B12: Internet & Phone | D12: ='Internet & Phone'!E17 -> 12595000
A13: 5 | B13: PR & Advertising | D13: ='PR & Advertising'!E19 -> 8365000
A14: 6 | B14: Travel & Conferences | D14: ='Travel & Conferences'!E17 -> 14000000
A15: 7 | B15: Talent Training | D15: ='Talent Training'!E10 -> 5000000
A16: 8 | B16: Cleaning & Maintenance | D16: ='Cleaning & Maintenance'!E17 -> 4800000
A17: 9 | B17: Secuity | D17: =Security!E17 -> 1800000
A18: 10 | B18: Events | D18: =Events!E17 -> 13200000
A19: 11 | B19: Salaries | D19: =Salaries!E17 -> 12480000
B20: Total | D20: =SUM(D11:D19) -> 79440000
B22: GRAND TOTAL FOR 1 YEAR | D22: =D8+D20 -> 103790600
B25: ILORIN INNOVATION HUB ONE YEAR REVENUE
A27: SN | B27: Space | C27: Rate | D27: Number of Units | E27: Revenue
A28: 1 | B28: Office Plan 1 (downstairs) | C28: 1500000 | D28: 3 | E28: 4500000
A29: 2 | B29: Office Plan 2 (upstairs) | C29: 600000 | D29: 5 | E29: 3000000
A30: 3 | B30: Office Plan 3 (upstairs) | C30: 700000 | D30: 2 | E30: 1400000
A31: 4 | B31: Individual Workspace (upstairs) | C31: 20000 | D31: 100 | E31: 2000000
A32: 5 | B32: Individual Workspace | C32: 20000 | D32: 150 | E32: 3000000
B33: (in multipurpose hall downstairs)
A34: 6 | B34: Cafeteria | C34: 6000000 | D34: 1 | E34: 6000000
A35: 7 | B35: Coffee Shop | C35: 2000000 | D35: 1 | E35: 2000000
A36: 8 | B36: Retail Shops | C36: 1000000 | D36: 3 | E36: 3000000
A37: 9 | B37: Conference Hall Rentals (estimate) | C37: 10800000 | D37: 1 | E37: 10800000
A38: 10 | B38: Main Hall Rentals (estimate) | C38: 8400000 | D38: 1 | E38: 8400000
A39: 11 | B39: Printing & Other Services | C39: 300000 | D39: 1 | E39: 300000
A40: 12 | B40: Meeting Room Rentals | C40: 1200000 | D40: 3 | E40: 300000
A41: 13 | B41: Grants | C41: 50000000 | D41: 2 | E41: 100000000
B42: Total | E42: =SUM(E28:E41) -> 144700000
B45: In the first year, the Innovation Hub is expected to run at a loss because of the fact that there will be no startup investments yet, which will be brought via the startup program. By the second year, the.
B46: We also expect at least N100m in grants (or more) as the hub will attract a lot of attention in the tech space.

Sheet Stationery & Supplies
B2: STATIONERY & SUPPLIES
A4: SN | B4: Item | C4: QTY | D4: PRICE (N) | E4: TOTAL (N)
A5: 1 | B5: Letterheaded Paper | C5: 5000 | D5: 50 | E5: =C5*D5 -> 250000
A6: 2 | B6: Continuation Sheets | C6: 5000 | D6: 50 | E6: =C6*D6 -> 250000
A7: 3 | B7: Plain Paper (ream) | C7: 20 | D7: 2000 | E7: =C7*D7 -> 40000
A8: 4 | B8: Large Envelopes | C8: 1000 | D8: 80.4 | E8: =C8*D8 -> 80400
A9: 5 | B9: Small Envelopes | C9: 1000 | D9: 40 | E9: =C9*D9 -> 40000
A10: 6 | B10: Pens (pack) | C10: 10 | D10: 3000 | E10: =C10*D10 -> 30000
A11: 7 | B11: Gift Pens | C11: 500 | D11: 130 | E11: =C11*D11 -> 65000
A12: 8 | B12: Highlighter | C12: 4 | D12: 1800 | E12: =C12*D12 -> 7200
A13: 9 | B13: Stapler | C13: 5 | D13: 2500 | E13: =C13*D13 -> 12500
A14: 10 | B14: Punch | C14: 5 | D14: 1500 | E14: =C14*D14 -> 7500
A15: 11 | B15: Self-Inking Stamp Pads | C15: 10000 | D15: 3 | E15: =C15*D15 -> 30000
A16: 12 | B16: White Board | C16: 2 | D16: 15000 | E16: =C16*D16 -> 30000
... A22: 18 | B22: Dispenser Water | C22: 120 | D22: 400 | E22: =C22*D22 -> 48000
E23: =C23*D23 -> 0
B24: Grand Total | E24: =SUM(E5:E22) -> 1990600

Sheet Computers & Equipment
B2: COMPUTERS & EQUIPMENT
A4: SN | B4: Item | C4: QTY | D4: PRICE (N) | E4: TOTAL (N)
A5: 1 | B5: Macbook Pro | C5: 4 | D5: 1200000 | E5: =C5*D5 -> 4800000
A6: 2 | B6: HP Notebooks | C6: 5 | D6: 300000 | E6: =C6*D6 -> 1500000
A7: 3 | B7: HP Desktop Computers | C7: 10 | D7: 300000 | E7: =C7*D7 -> 3000000
A8: 4 | B8: HP Laserjet M479FDW Wireless Printer | C8: 4 | D8: 200000 | E8: =C8*D8 -> 800000
A9: 5 | B9: Amazon Web Service Server Space | C9: 12 | D9: 100000 | E9: =C9*D9 -> 1200000
A10: 6 | B10: SSL Certificates | C10: 3 | D10: 20000 | E10: =C10*D10 -> 60000
A11: 7 | B11: Inverter ACs | C11: 5 | D11: 200000 | E11: =C11*D11 -> 1000000
A12: 8 | B12: Mini Data Center Setup | C12: 1 | D12: 10000000 | E12: =C12*D12 -> 10000000
E13: =C13*D13 -> 0
E14: =C14*D14 -> 0
E15: =C15*D15 -> 0
B16: Grand Total | E16: =SUM(E5:E15) -> 22360000

Sheet Utilities
B2: UTILITIES & DIESEL
A4: SN | B4: Item | C4: QTY | D4: PRICE (N) | E4: TOTAL (N)
A5: 1 | B5: Electricity | C5: 12 | D5: 300000 | E5: =C5*D5 -> 3600000
A6: 2 | B6: Diesel | C6: 12 | D6: 300000 | E6: =C6*D6 -> 3600000
B17: Grand Total | E17: =SUM(E5:E16) -> 7200000

Sheet Internet & Phone
B2: INTERNET & PHONE
A4: SN | B4: Item | C4: QTY | D4: PRICE (N) | E4: TOTAL (N)
A5: 1 | B5: Internet Subscription | C5: 12 | D5: 1000000 | E5: =C5*D5 -> 12000000
A6: 2 | B6: Desk GSM Phone | C6: 5 | D6: 15000 | E6: =C6*D6 -> 75000
A7: 3 | B7: Intercom Phones | C7: 10 | D7: 10000 | E7: =C7*D7 -> 100000
A8: 4 | B8: Intercom Installation & Setup | C8: 1 | D8: 300000 | E8: =C8*D8 -> 300000
A9: 5 | B9: Desk GSM Phone Airtime | C9: 12 | D9: 10000 | E9: =C9*D9 -> 120000
E12: =C12*D12 -> 0
E13: =C13*D13 -> 0
E14: =C14*D14 -> 0
E15: =C15*D15 -> 0
E16: =C16*D16 -> 0
B17: Grand Total | E17: =SUM(E5:E16) -> 12595000

Sheet PR & Advertising
B2: PR & ADVERTISING
A4: SN | B4: Item | C4: QTY | D4: PRICE (N) | E4: TOTAL (N)
A5: 1 | B5: Corporate Mugs | C5: 10 | D5: 2000 | E5: =C5*D5 -> 20000
A6: 2 | B6: Roll-up Banners | C6: 10 | D6: 30000 | E6: =C6*D6 -> 300000
A7: 3 | B7: Small Paper Bags | C7: 500 | D7: 300 | E7: =C7*D7 -> 150000
A8: 4 | B8: Dummy Cheque (for Prizes) | C8: 25 | D8: 15000 | E8: =C8*D8 -> 375000
A9: 5 | B9: Flyers | C9: 1000 | D9: 40 | E9: =C9*D9 -> 40000
A10: 6 | B10: Brochures | C10: 300 | D10: 3500 | E10: =C10*D10 -> 1050000
A11: 7 | B11: Digital Marketing | C11: 12 | D11: 100000 | E11: =C11*D11 -> 1200000
A12: 8 | B12: Radio Jingle Production | C12: 5 | D12: 30000 | E12: =C12*D12 -> 150000
A13: 9 | B13: Radio Jingle Airtime | C13: 52 | D13: 15000 | E13: =C13*D13 -> 780000
A14: 10 | B14: Unity Roundabout LED Billboard (1 month) | C14: 6 | D14: 300000 | E14: =C14*D14 -> 1800000
A15: 11 | B15: Tanke Junction Billboard | C15: 5 | D15: 100000 | E15: =C15*D15 -> 500000
A16: 12 | B16: Mentor Honorarium | C16: 10 | D16: 200000 | E16: =C16*D16 -> 2000000
E18: =C18*D18 -> 0
B19: Grand Total | E19: =SUM(E5:E18) -> 8365000

Sheet Travel & Conferences
B2: TRAVEL & CONFERENCES
A4: SN | B4: Item | C4: QTY | D4: PRICE (N) | E4: TOTAL (N)
A5: 1 | B5: International Innovation Conference | C5: 2 | D5: 2000000 | E5: =C5*D5 -> 4000000
A6: 2 | B6: Local Travel | C6: 12 | D6: 500000 | E6: =C6*D6 -> 6000000
A7: 3 | B7: Mentor Travel & Accomodation | C7: 10 | D7: 400000 | E7: =C7*D7 -> 4000000
E9: =C9*D9 -> 0
E10: =C10*D10 -> 0
E11: =C11*D11 -> 0
E12: =C12*D12 -> 0
E13: =C13*D13 -> 0
E14: =C14*D14 -> 0
E15: =C15*D15 -> 0
E16: =C16*D16 -> 0
B17: Grand Total | E17: =SUM(E5:E16) -> 14000000

Sheet Talent Training
B2: TALENT TRAINING
A4: SN | B4: Item | C4: QTY | D4: PRICE (N) | E4: TOTAL (N)
A5: 1 | B5: Ilorin Tech Skills Training Program | C5: 1 | D5: 3000000 | E5: =C5*D5 -> 3000000
A6: 2 | B6: Kwara Jobs Portal Implementation & Operations | C6: 1 | D6: 2000000 | E6: =C6*D6 -> 2000000
E7: =C7*D7 -> 0
E8: =C8*D8 -> 0
E9: =C9*D9 -> 0
B10: Grand Total | E10: =SUM(E5:E9) -> 5000000

Sheet Cleaning & Maintenance
B2: CLEANING & MAINTENANCE
A4: SN | B4: Item | C4: QTY | D4: PRICE (N) | E4: TOTAL (N)
A5: 1 | B5: Cleaning Fee | C5: 12 | D5: 250000 | E5: =C5*D5 -> 3000000
A6: 2 | B6: Maintenance & Repairs | C6: 12 | D6: 150000 | E6: =C6*D6 -> 1800000
A7: 3 | E7: =C7*D7 -> 0
A8: 4 | E8: =C8*D8 -> 0
A9: 5 | E9: =C9*D9 -> 0
E10: =C10*D10 -> 0
E11: =C11*D11 -> 0
E12: =C12*D12 -> 0
E13: =C13*D13 -> 0
E14: =C14*D14 -> 0
E15: =C15*D15 -> 0
E16: =C16*D16 -> 0
B17: Grand Total | E17: =SUM(E5:E16) -> 4800000

Sheet Security
B2: SECURITY
A4: SN | B4: Item | C4: QTY | D4: PRICE (N) | E4: TOTAL (N)
A5: 1 | B5: Night Security Guard x3 | C5: 12 | D5: 75000 | E5: =C5*D5 -> 900000
A6: 2 | B6: Day Security Guard x 3 | C6: 12 | D6: 75000 | E6: =C6*D6 -> 900000
B17: Grand Total | E17: =SUM(E5:E16) -> 1800000

Sheet Events
B2: LAUNCH EVENT
A4: SN | B4: Item | C4: QTY | D4: PRICE (N) | E4: TOTAL (N)
A5: 1 | B5: Launch Event | C5: 1 | D5: 7000000 | E5: =C5*D5 -> 7000000
A6: 2 | B6: Campus Tours | C6: 5 | D6: 200000 | E6: =C6*D6 -> 1000000
A7: 3 | B7: Weekly Meetups | C7: 52 | D7: 100000 | E7: =C7*D7 -> 5200000
E8: =C8*D8 -> 0
E9: =C9*D9 -> 0
E10: =C10*D10 -> 0
E11: =C11*D11 -> 0
E12: =C12*D12 -> 0
E13: =C13*D13 -> 0
E14: =C14*D14 -> 0
E15: =C15*D15 -> 0
E16: =C16*D16 -> 0
B17: Grand Total | E17: =SUM(E5:E16) -> 13200000

Sheet Salaries
B2: SALARIES
A4: SN | B4: Item | C4: QTY | D4: PRICE (N) | E4: TOTAL (N)
A5: 1 | B5: Managing Director | C5: 12 | D5: 500000 | E5: =C5*D5 -> 6000000
A6: 2 | B6: Community Manager | C6: 12 | D6: 100000 | E6: =C6*D6 -> 1200000
A7: 3 | B7: Front Desk | C7: 12 | D7: 50000 | E7: =C7*D7 -> 600000
A8: 4 | B8: Accounts & Admin | C8: 12 | D8: 70000 | E8: =C8*D8 -> 840000
A9: 5 | B9: Head of Talent & Training | C9: 12 | D9: 150000 | E9: =C9*D9 -> 1800000
A10: 6 | B10: IT Support | C10: 12 | D10: 50000 | E10: =C10*D10 -> 600000
A11: 7 | B11: Junior Officers | C11: 12 | D11: 120000 | E11: =C11*D11 -> 1440000
E12: =C12*D12 -> 0
E13: =C13*D13 -> 0
E14: =C14*D14 -> 0
E15: =C15*D15 -> 0
E16: =C16*D16 -> 0
B17: Grand Total | E17: =SUM(E5:E16) -> 12480000
