Workbook

Sheet Budget
B2: Category | C2: Description | E2: 45658 | F2: 45689 | G2: 45717 | H2: 45748 | I2: 45778 | J2: 45809 | K2: 45839 | L2: 45870 | M2: 45901 | N2: 45931 | O2: 45962 | P2: 45992 | Q2: FY 2025
G4: =Q91 -> -6.1983101e+08
G5: =G4/9 -> -68870113
A6: Inflows
B7: Kwara State Government Grants | C7: Public sector funding | Q7: =SUM(E7:P7) -> 0
B8: IHS Operational Funds | C8: Corporate partnerships & sponsorships | H8: =69000000*3 -> 207000000 | K8: =H8 -> 207000000 | N8: =K8 -> 207000000 | Q8: =SUM(E8:P8) -> 621000000
B9: Membership Fees | C9: Fees from startups & researchers | E9: ='Membership Fees'!C5 -> 0 | F9: ='Membership Fees'!D5 -> 0 | Q9: =SUM(E9:P9) -> 0
B10: Consulting & Advisory Services | C10: Consulting services revenue | Q10: =SUM(E10:P10) -> 0
B11: Event Hosting & Sponsorships | C11: Revenue from events & hackathons | E11: ='Rental, Hosting & Sponsorships'!C12 -> 0 | F11: ='Rental, Hosting & Sponsorships'!D12 -> 0 | G11: ='Rental, Hosting & Sponsorships'!E12 -> 0 | H11: ='Rental, Hosting & Sponsorships'!F12 -> 0 | I11: ='Rental, Hosting & Sponsorships'!G12 -> 0 | J11: ='Rental, Hosting & Sponsorships'!H12 -> 0 | K11: ='Rental, Hosting & Sponsorships'!I12 -> 0 | L11: ='Rental, Hosting & Sponsorships'!J12 -> 0 | ... P11: ='Rental, Hosting & Sponsorships'!N12 -> 0 | Q11: =SUM(E11:P11) -> 0
B12: Facility Rentals | E12: ='Rental, Hosting & Sponsorships'!C6 -> 0 | F12: ='Rental, Hosting & Sponsorships'!D6 -> 0 | G12: ='Rental, Hosting & Sponsorships'!E6 -> 0 | H12: ='Rental, Hosting & Sponsorships'!F6 -> 0 | I12: ='Rental, Hosting & Sponsorships'!G6 -> 0 | J12: ='Rental, Hosting & Sponsorships'!H6 -> 0 | K12: ='Rental, Hosting & Sponsorships'!I6 -> 0 | L12: ='Rental, Hosting & Sponsorships'!J6 -> 0 | ... P12: ='Rental, Hosting & Sponsorships'!N6 -> 0 | Q12: =SUM(E12:P12) -> 0
B13: Other Income | C13: Miscellaneous revenue | Q13: =SUM(E13:P13) -> 0
A14: Total Revenue | E14: =SUM(E6:E13) -> 0 | F14: =SUM(F6:F13) -> 0 | G14: =SUM(G6:G13) -> 0 | H14: =SUM(H6:H13) -> 207000000 | I14: =SUM(I6:I13) -> 0 | J14: =SUM(J6:J13) -> 0 | K14: =SUM(K6:K13) -> 207000000 | L14: =SUM(L6:L13) -> 0 | ... Q14: =SUM(Q6:Q13) -> 621000000
A18: Operational Expenses
B19: Salaries & Wages | C19: Staff salaries, mentors | E19: =Salaries!F19 -> 0 | F19: =Salaries!G19 -> 0 | G19: =Salaries1!E19 -> 6418849.8 | H19: =Salaries1!F19 -> 15610314 | I19: =Salaries1!G19 -> 16040687 | J19: =Salaries1!H19 -> 16040687 | K19: =Salaries1!I19 -> 16040687 | L19: =Salaries1!J19 -> 16040687 | M19: =Salaries1!K19 -> 16040687 | N19: =Salaries1!L19 -> 16040687 | ... P19: =Salaries1!N19 -> 16040687 | Q19: =SUM(E19:P19) -> 1.5035466e+08
B23: Utilities & Maintenance | C23: Rent, utilities, internet, security
B24: Electricity | H24: 800000 | I24: 800000 | J24: 800000 | K24: 800000 | L24: 800000 | M24: 800000 | N24: 800000 | O24: 800000 | P24: 800000 | Q24: =SUM(E24:P24) -> 7200000
B25: Diesel | E25: =Diesel!C5 -> 0 | F25: =Diesel!D5 -> 0 | H25: =Diesel!F5 -> 0 | I25: =Diesel!G5 -> 921669.93 | J25: =Diesel!H5 -> 949239.34 | K25: =Diesel!I5 -> 1039804 | L25: =Diesel!J5 -> 1064298.4 | M25: =Diesel!K5 -> 1074617.7 | N25: =Diesel!L5 -> 1087452.2 | O25: =Diesel!M5 -> 1103002.1 | P25: =Diesel!N5 -> 1116730.2 | Q25: =SUM(E25:P25) -> 8356813.9
B26: Cleaning & Landscaping | G26: 500000 | H26: 1300000 | I26: 1300000 | J26: 1300000 | K26: 1300000 | L26: 1300000 | M26: 1300000 | N26: 1300000 | O26: 1300000 | P26: 1300000 | Q26: =SUM(E26:P26) -> 12200000
B27: Facility Maintenance & Repairs | H27: 833333.33 | I27: 833333.33 | J27: 833333.33 | K27: 833333.33 | L27: 833333.33 | M27: 833333.33 | N27: 833333.33 | O27: 833333.33 | P27: 833333.33 | Q27: =SUM(E27:P27) -> 7500000
B28: Security | H28: 1000000 | I28: 1000000 | J28: 1000000 | K28: 1000000 | L28: 1000000 | M28: 1000000 | N28: 1000000 | O28: 1000000 | P28: 1000000 | Q28: =SUM(E28:P28) -> 9000000
B29: HVAC, Solar, Elevator, Access Control & LED Screen Maintenance | H29: 1666666.7 | I29: 1666666.7 | J29: 1666666.7 | K29: 1666666.7 | L29: 1666666.7 | M29: 1666666.7 | N29: 1666666.7 | O29: 1666666.7 | P29: 1666666.7 | Q29: =SUM(E29:P29) -> 15000000
G30: =SUM(G24:G29) -> 500000 | H30: =SUM(H24:H29) -> 5600000 | I30: =SUM(I24:I29) -> 6521669.9 | J30: =SUM(J24:J29) -> 6549239.3 | K30: =SUM(K24:K29) -> 6639804 | L30: =SUM(L24:L29) -> 6664298.4 | M30: =SUM(M24:M29) -> 6674617.7 | N30: =SUM(N24:N29) -> 6687452.2 | ... Q30: =SUM(Q24:Q29) -> 59256814
B31: Travel & Conferences
B32: International Conference Registration | J32: 3000000 | Q32: =SUM(E32:P32) -> 3000000
B33: International Travel & Accomodation | J33: 7000000 | M33: 7000000 | P33: 7000000 | Q33: =SUM(E33:P33) -> 21000000
B34: Local Conference Registration | J34: 750000 | M34: 750000 | P34: 750000 | Q34: =SUM(E34:P34) -> 2250000
B35: Local Conference Exhibition | H35: 666666.67 | I35: 666666.67 | J35: 666666.67 | K35: 666666.67 | L35: 666666.67 | M35: 666666.67 | N35: 666666.67 | O35: 666666.67 | P35: 666666.67 | Q35: =SUM(E35:P35) -> 6000000
B36: Local Travel | G36: 1000000 | H36: 1000000 | I36: 1000000 | J36: 1000000 | K36: 1000000 | L36: 1000000 | M36: 1000000 | N36: 1000000 | O36: 1000000 | P36: 1000000 | Q36: =SUM(E36:P36) -> 10000000
G37: =SUM(G32:G36) -> 1000000 | H37: =SUM(H32:H36) -> 1666666.7 | I37: =SUM(I32:I36) -> 1666666.7 | J37: =SUM(J32:J36) -> 12416667 | K37: =SUM(K32:K36) -> 1666666.7 | L37: =SUM(L32:L36) -> 1666666.7 | M37: =SUM(M32:M36) -> 9416666.7 | N37: =SUM(N32:N36) -> 1666666.7 | ... Q37: =SUM(Q32:Q36) -> 42250000
B39: Equipment & Infrastructure | C39: Laptops, software, lab tools
B40: Cloud Servers | E40: =Others!C4 -> 0 | F40: =Others!D4 -> 0 | H40: 416666.67 | I40: 416666.67 | J40: 416666.67 | K40: 416666.67 | L40: 416666.67 | M40: 416666.67 | N40: 416666.67 | O40: 416666.67 | P40: 416666.67 | Q40: =SUM(E40:P40) -> 3750000
B41: Staff Email | E41: =Others!C5 -> 0 | F41: =Others!D5 -> 0 | G41: =Others!E5 -> 729166.67 | H41: =Others!F5 -> 0 | I41: =Others!G5 -> 0 | J41: =Others!H5 -> 729166.67 | K41: =Others!I5 -> 0 | L41: =Others!J5 -> 0 | ... P41: =Others!N5 -> 729166.67 | Q41: =SUM(E41:P41) -> 2916666.7
B42: Software Subscriptions & Licenses | E42: =Others!C6 -> 0 | F42: =Others!D6 -> 0 | G42: =Others!E6 -> 416666.67 | H42: =Others!F6 -> 0 | I42: =Others!G6 -> 0 | J42: =Others!H6 -> 416666.67 | K42: =Others!I6 -> 0 | L42: =Others!J6 -> 0 | ... P42: =Others!N6 -> 416666.67 | Q42: =SUM(E42:P42) -> 1666666.7
B43: Access Control & Hub Management Software | H43: 6500000 | Q43: =SUM(E43:P43) -> 6500000
B44: Laptops | Q44: =SUM(E44:P44) -> 0
G45: =SUM(G40:G44) -> 1145833.3 | H45: =SUM(H40:H44) -> 6916666.7 | I45: =SUM(I40:I44) -> 416666.67 | J45: =SUM(J40:J44) -> 1562500 | K45: =SUM(K40:K44) -> 416666.67 | L45: =SUM(L40:L44) -> 416666.67 | M45: =SUM(M40:M44) -> 1562500 | N45: =SUM(N40:N44) -> 416666.67 | ... Q45: =SUM(Q40:Q44) -> 14833333
B48: Corporate Comms & PR | C48: Branding, events, PR
B49: Souvenirs | H49: 833333.33 | I49: 833333.33 | J49: 833333.33 | K49: 833333.33 | L49: 833333.33 | M49: 833333.33 | N49: 833333.33 | O49: 833333.33 | P49: 833333.33 | Q49: =SUM(E49:P49) -> 7500000
B50: Guest Entertainment & Refreshments | H50: 350000 | I50: 350000 | J50: 350000 | K50: 350000 | L50: 350000 | M50: 350000 | N50: 350000 | O50: 350000 | P50: 350000 | Q50: =SUM(E50:P50) -> 3150000
B51: Banners | H51: 125000 | I51: 125000 | J51: 125000 | K51: 125000 | L51: 125000 | M51: 125000 | N51: 125000 | O51: 125000 | P51: 125000 | Q51: =SUM(E51:P51) -> 1125000
B52: Staff T-Shirts | H52: 250000 | K52: 250000 | N52: 250000 | Q52: =SUM(E52:P52) -> 750000
B53: Online & Social Media Marketing | H53: 166666.67 | I53: 166666.67 | J53: 166666.67 | K53: 166666.67 | L53: 166666.67 | M53: 166666.67 | N53: 166666.67 | O53: 166666.67 | P53: 166666.67 | Q53: =SUM(E53:P53) -> 1500000
G54: =SUM(G49:G53) -> 0 | H54: =SUM(H49:H53) -> 1725000 | I54: =SUM(I49:I53) -> 1475000 | J54: =SUM(J49:J53) -> 1475000 | K54: =SUM(K49:K53) -> 1725000 | L54: =SUM(L49:L53) -> 1475000 | M54: =SUM(M49:M53) -> 1475000 | N54: =SUM(N49:N53) -> 1725000 | ... Q54: =SUM(Q49:Q53) -> 14025000
B56: Administrative Costs | C56: Legal, compliance, insurance
B57: Legal, Regulatory, Insurance etc | H57: 1666667 | I57: 1666667 | J57: 1666667 | K57: 1666667 | L57: 1666667 | M57: 1666667 | N57: 1666667 | O57: 1666667 | P57: 1666667 | Q57: =SUM(E57:P57) -> 15000003
B58: Stationery & Office Supplies | H58: 150000 | I58: 150000 | J58: 150000 | K58: 150000 | L58: 150000 | M58: 150000 | N58: 150000 | O58: 150000 | P58: 150000 | Q58: =SUM(E58:P58) -> 1350000
B59: Association & Society Memberships | P59: 2000000 | Q59: =SUM(E59:P59) -> 2000000
H60: =SUM(H57:H59) -> 1816667 | I60: =SUM(I57:I59) -> 1816667 | J60: =SUM(J57:J59) -> 1816667 | K60: =SUM(K57:K59) -> 1816667 | L60: =SUM(L57:L59) -> 1816667 | M60: =SUM(M57:M59) -> 1816667 | N60: =SUM(N57:N59) -> 1816667 | O60: =SUM(O57:O59) -> 1816667 | ... Q60: =SUM(Q57:Q59) -> 18350003
B63: Total Operational Expenses | G63: =SUM(G60,G54,G45,G37,G30,G19) -> 9064683.1 | H63: =SUM(H60,H54,H45,H37,H30,H19) -> 33335314 | I63: =SUM(I60,I54,I45,I37,I30,I19) -> 27937357 | J63: =SUM(J60,J54,J45,J37,J30,J19) -> 39860760 | K63: =SUM(K60,K54,K45,K37,K30,K19) -> 28305491 | L63: =SUM(L60,L54,L45,L37,L30,L19) -> 28079986 | M63: =SUM(M60,M54,M45,M37,M30,M19) -> 36986138 | N63: =SUM(N60,N54,N45,N37,N30,N19) -> 28353139 | ... P63: =SUM(P60,P54,P45,P37,P30,P19) -> 39028251 | Q63: =SUM(E63:P63) -> 2.9906981e+08
A67: Innovation & Program Support | Q67: =SUM(E67:P67) -> 0
B68: Staff Professional Development (Afrilabs Capacity Building etc) | E68: =Others!C11 -> 0 | F68: =Others!D11 -> 0 | H68: 333333.33 | I68: 333333.33 | J68: 333333.33 | K68: 333333.33 | L68: 333333.33 | M68: 333333.33 | N68: 333333.33 | O68: 333333.33 | P68: 1333333 | Q68: =SUM(E68:P68) -> 3999999.7
B69: Startup Funding & Grants | C69: Seed funding for incubated startups | Q69: =SUM(E69:P69) -> 0
B70: Accelerator/Incubation Programs | C70: Workshops, training | Q70: =SUM(E70:P70) -> 0
B71: Monthly Meetups | C71: Startup acceleration & support | E71: =Others!C12 -> 0 | F71: =Others!D12 -> 0 | G71: =Others!E12 -> 250000 | H71: =Others!F12 -> 250000 | I71: =Others!G12 -> 250000 | J71: =Others!H12 -> 250000 | K71: =Others!I12 -> 250000 | L71: =Others!J12 -> 250000 | ... P71: =Others!N12 -> 250000 | Q71: =SUM(E71:P71) -> 2500000
B72: Field Events | E72: =Others!C13 -> 0 | F72: =Others!D13 -> 0 | H72: 208333.33 | I72: 208333.33 | J72: 208333.33 | K72: 208333.33 | L72: 208333.33 | M72: 208333.33 | N72: 208333.33 | O72: 208333.33 | P72: 208333.33 | Q72: =SUM(E72:P72) -> 1875000
B73: Webinars | E73: =Others!C14 -> 0 | F73: =Others!D14 -> 0 | H73: 125000 | I73: 125000 | J73: 125000 | K73: 125000 | L73: 125000 | M73: 125000 | N73: 125000 | O73: 125000 | P73: 125000 | Q73: =SUM(E73:P73) -> 1125000
B74: Training & Mentorship | Q74: =SUM(E74:P74) -> 0
B75: Total Program Support | G75: =SUM(G68:G74) -> 250000 | H75: =SUM(H68:H74) -> 916666.67 | I75: =SUM(I68:I74) -> 916666.67 | J75: =SUM(J68:J74) -> 916666.67 | K75: =SUM(K68:K74) -> 916666.67 | L75: =SUM(L68:L74) -> 916666.67 | M75: =SUM(M68:M74) -> 916666.67 | N75: =SUM(N68:N74) -> 916666.67 | ... P75: =SUM(P68:P74) -> 1916666.3 | Q75: =SUM(E75:P75) -> 9499999.7
B81: Contingency & Sustainability | Q81: =SUM(E81:P81) -> 0
B82: Reserve Fund - % of Inflows | C82: Emergency fund for sustainability | D82: 0.01 | E82: =E14*$D$82 -> 0 | F82: =F14*$D$82 -> 0 | G82: =G14*$D$82 -> 0 | H82: =H14*$D$82 -> 2070000 | I82: =I14*$D$82 -> 0 | J82: =J14*$D$82 -> 0 | K82: =K14*$D$82 -> 2070000 | L82: =L14*$D$82 -> 0 | ... P82: =P14*$D$82 -> 0 | Q82: =SUM(E82:P82) -> 6210000
B83: Miscellaneous Expenses - % of Operating Exp. | C83: Unexpected costs | D83: 0.02 | E83: =E63*$D$83 -> 0 | F83: =F63*$D$83 -> 0 | G83: =G63*$D$83 -> 181293.66 | H83: =H63*$D$83 -> 666706.29 | I83: =I63*$D$83 -> 558747.14 | J83: =J63*$D$83 -> 797215.2 | K83: =K63*$D$83 -> 566109.82 | L83: =L63*$D$83 -> 561599.71 | ... P83: =P63*$D$83 -> 780565.01 | Q83: =SUM(E83:P83) -> 5981396.2
B84: Total Contingency | E84: =SUM(E82:E83) -> 0 | F84: =SUM(F82:F83) -> 0 | G84: =SUM(G82:G83) -> 181293.66 | H84: =SUM(H82:H83) -> 2736706.3 | I84: =SUM(I82:I83) -> 558747.14 | J84: =SUM(J82:J83) -> 797215.2 | K84: =SUM(K82:K83) -> 2636109.8 | L84: =SUM(L82:L83) -> 561599.71 | ... P84: =SUM(P82:P83) -> 780565.01 | Q84: =SUM(E84:P84) -> 12191396
B89: Summary | Q89: =SUM(E89:P89) -> 0
B90: Total Revenue | E90: =SUM(E14) -> 0 | F90: =SUM(F14) -> 0 | G90: =SUM(G14) -> 0 | H90: =SUM(H14) -> 207000000 | I90: =SUM(I14) -> 0 | J90: =SUM(J14) -> 0 | K90: =SUM(K14) -> 207000000 | L90: =SUM(L14) -> 0 | ... P90: =SUM(P14) -> 0 | Q90: =SUM(G90:P90) -> 621000000
B91: Total Expenses | E91: =-SUM(E84,E75,E63,E54,E45,E37,E30,E19) -> 0 | F91: =-SUM(F84,F75,F63,F54,F45,F37,F30,F19) -> 0 | G91: =-SUM(G84,G75,G63,G54,G45,G37,G30,G19,G60) -> -18560660 | H91: =-SUM(H84,H75,H63,H54,H45,H37,H30,H19,H60) -> -70324002 | I91: =-SUM(I84,I75,I63,I54,I45,I37,I30,I19,I60) -> -57350128 | J91: =-SUM(J84,J75,J63,J54,J45,J37,J30,J19,J60) -> -81435401 | K91: =-SUM(K84,K75,K63,K54,K45,K37,K30,K19,K60) -> -60163759 | L91: =-SUM(L84,L75,L63,L54,L45,L37,L30,L19,L60) -> -57638237 | M91: =-SUM(M84,M75,M63,M54,M45,M37,M30,M19,M60) -> -75628666 | N91: =-SUM(N84,N75,N63,N54,N45,N37,N30,N19,N60) -> -60260008 | ... Q91: =-SUM(Q84,Q75,Q63,Q54,Q45,Q37,Q30,Q19,Q60) -> -6.1983101e+08
B92: Net Surplus / Deficit | E92: =E90+E91 -> 0 | F92: =F90+F91 -> 0 | G92: =G90+G91+F92 -> -18560660 | H92: =H90+H91+G92 -> 1.1811534e+08 | I92: =I90+I91+H92 -> 60765210 | J92: =J90+J91+I92 -> -20670191 | K92: =K90+K91+J92 -> 1.2616605e+08 | L92: =L90+L91+K92 -> 68527813 | M92: =M90+M91+L92 -> -7100852.9 | N92: =N90+N91+M92 -> 1.3963914e+08 | ... P92: =P90+P91+O92 -> 1168987.5 | Q92: =Q90+Q91 -> 1168987.5
Q94: =Q91/10 -> -61983101
Q95: =Q94*3 -> -1.859493e+08

Sheet Salaries1
E1: Employer Cost - aligned with the Headcount Phasing
A2: S/N | B2: Grade | C2: Jan | D2: Feb | E2: Mar | F2: Apr | G2: May | H2: Jun | I2: Jul | J2: Aug | K2: Sep | L2: Oct | M2: Nov | N2: Dec | O2: Total Cost for the year 2025
A3: 1 | B3: Managing Director | C3: =(_xlfn.XLOOKUP(B3,'[1]Annual Employer Cost per Grade'!$C$2:$C$17,'[1]Annual Employer Cost per Grade'!$U$2:$U$17,0,0))*(INDEX('[1]Headcount Phasing'!$B$3:$M$18,MATCH(B3,'[1]Headcount Phasing'!$A$3:$A$18,0),MATCH($C$2,'[1]Headcount Phasing'!$B$2:$M$2,0))) -> 0 | D3: =(_xlfn.XLOOKUP(B3,'[1]Annual Employer Cost per Grade'!$C$2:$C$17,'[1]Annual Employer Cost per Grade'!$U$2:$U$17,0,0))*(INDEX('[1]Headcount Phasing'!$B$3:$M$18,MATCH(B3,'[1]Headcount Phasing'!$A$3:$A$18,0),MATCH($D$2,'[1]Headcount Phasing'!$B$2:$M$2,0))) -> 0 | E3: =(_xlfn.XLOOKUP(B3,'[1]Annual Employer Cost per Grade'!$C$2:$C$17,'[1]Annual Employer Cost per Grade'!$U$2:$U$17,0,0))*(INDEX('[1]Headcount Phasing'!$B$3:$M$18,MATCH(B3,'[1]Headcount Phasing'!$A$3:$A$18,0),MATCH($E$2,'[1]Headcount Phasing'!$B$2:$M$2,0))) -> 6187666.7 | F3: =(_xlfn.XLOOKUP(B3,'[1]Annual Employer Cost per Grade'!$C$2:$C$17,'[1]Annual Employer Cost per Grade'!$U$2:$U$17,0,0))*(INDEX('[1]Headcount Phasing'!$B$3:$M$18,MATCH(B3,'[1]Headcount Phasing'!$A$3:$A$18,0),MATCH($F$2,'[1]Headcount Phasing'!$B$2:$M$2,0))) -> 6187666.7 | G3: =(_xlfn.XLOOKUP(B3,'[1]Annual Employer Cost per Grade'!$C$2:$C$17,'[1]Annual Employer Cost per Grade'!$U$2:$U$17,0,0))*(INDEX('[1]Headcount Phasing'!$B$3:$M$18,MATCH(B3,'[1]Headcount Phasing'!$A$3:$A$18,0),MATCH($G$2,'[1]Headcount Phasing'!$B$2:$M$2,0))) -> 6187666.7 | H3: =(_xlfn.XLOOKUP(B3,'[1]Annual Employer Cost per Grade'!$C$2:$C$17,'[1]Annual Employer Cost per Grade'!$U$2:$U$17,0,0))*(INDEX('[1]Headcount Phasing'!$B$3:$M$18,MATCH(B3,'[1]Headcount Phasing'!$A$3:$A$18,0),MATCH($H$2,'[1]Headcount Phasing'!$B$2:$M$2,0))) -> 6187666.7 | I3: =(_xlfn.XLOOKUP(B3,'[1]Annual Employer Cost per Grade'!$C$2:$C$17,'[1]Annual Employer Cost per Grade'!$U$2:$U$17,0,0))*(INDEX('[1]Headcount Phasing'!$B$3:$M$18,MATCH(B3,'[1]Headcount Phasing'!$A$3:$A$18,0),MATCH($I$2,'[1]Headcount Phasing'!$B$2:$M$2,0))) -> 6187666.7 | J3: =(_xlfn.XLOOKUP(B3,'[1]Annual Employer Cost per Grade'!$C$2:$C$17,'[1]Annual Employer Cost per Grade'!$U$2:$U$17,0,0))*(INDEX('[1]Headcount Phasing'!$B$3:$M$18,MATCH(B3,'[1]Headcount Phasing'!$A$3:$A$18,0),MATCH($J$2,'[1]Headcount Phasing'!$B$2:$M$2,0))) -> 6187666.7 | K3: =(_xlfn.XLOOKUP(B3,'[1]Annual Employer Cost per Grade'!$C$2:$C$17,'[1]Annual Employer Cost per Grade'!$U$2:$U$17,0,0))*(INDEX('[1]Headcount Phasing'!$B$3:$M$18,MATCH(B3,'[1]Headcount Phasing'!$A$3:$A$18,0),MATCH($K$2,'[1]Headcount Phasing'!$B$2:$M$2,0))) -> 6187666.7 | L3: =(_xlfn.XLOOKUP(B3,'[1]Annual Employer Cost per Grade'!$C$2:$C$17,'[1]Annual Employer Cost per Grade'!$U$2:$U$17,0,0))*(INDEX('[1]Headcount Phasing'!$B$3:$M$18,MATCH(B3,'[1]Headcount Phasing'!$A$3:$A$18,0),MATCH($L$2,'[1]Headcount Phasing'!$B$2:$M$2,0))) -> 6187666.7 | M3: =(_xlfn.XLOOKUP(B3,'[1]Annual Employer Cost per Grade'!$C$2:$C$17,'[1]Annual Employer Cost per Grade'!$U$2:$U$17,0,0))*(INDEX('[1]Headcount Phasing'!$B$3:$M$18,MATCH(B3,'[1]Headcount Phasing'!$A$3:$A$18,0),MATCH($M$2,'[1]Headcount Phasing'!$B$2:$M$2,0))) -> 6187666.7 | N3: =(_xlfn.XLOOKUP(B3,'[1]Annual Employer Cost per Grade'!$C$2:$C$17,'[1]Annual Employer Cost per Grade'!$U$2:$U$17,0,0))*(INDEX('[1]Headcount Phasing'!$B$3:$M$18,MATCH(B3,'[1]Headcount Phasing'!$A$3:$A$18,0),MATCH($N$2,'[1]Headcount Phasing'!$B$2:$M$2,0))) -> 6187666.7 | O3: =SUM(C3:N3) -> 61876667
A4: =A3+1 -> 2 | B4: Director of Programs | C4: =(_xlfn.XLOOKUP(B4,'[1]Annual Employer Cost per Grade'!$C$2:$C$17,'[1]Annual Employer Cost per Grade'!$U$2:$U$17,0,0))*(INDEX('[1]Headcount Phasing'!$B$3:$M$18,MATCH(B4,'[1]Headcount Phasing'!$A$3:$A$18,0),MATCH($C$2,'[1]Headcount Phasing'!$B$2:$M$2,0))) -> 0 | D4: =(_xlfn.XLOOKUP(B4,'[1]Annual Employer Cost per Grade'!$C$2:$C$17,'[1]Annual Employer Cost per Grade'!$U$2:$U$17,0,0))*(INDEX('[1]Headcount Phasing'!$B$3:$M$18,MATCH(B4,'[1]Headcount Phasing'!$A$3:$A$18,0),MATCH($D$2,'[1]Headcount Phasing'!$B$2:$M$2,0))) -> 0 | E4: =(_xlfn.XLOOKUP(B4,'[1]Annual Employer Cost per Grade'!$C$2:$C$17,'[1]Annual Employer Cost per Grade'!$U$2:$U$17,0,0))*(INDEX('[1]Headcount Phasing'!$B$3:$M$18,MATCH(B4,'[1]Headcount Phasing'!$A$3:$A$18,0),MATCH($E$2,'[1]Headcount Phasing'!$B$2:$M$2,0))) -> 0 | F4: =(_xlfn.XLOOKUP(B4,'[1]Annual Employer Cost per Grade'!$C$2:$C$17,'[1]Annual Employer Cost per Grade'!$U$2:$U$17,0,0))*(INDEX('[1]Headcount Phasing'!$B$3:$M$18,MATCH(B4,'[1]Headcount Phasing'!$A$3:$A$18,0),MATCH($F$2,'[1]Headcount Phasing'!$B$2:$M$2,0))) -> 3555487.9 | G4: =(_xlfn.XLOOKUP(B4,'[1]Annual Employer Cost per Grade'!$C$2:$C$17,'[1]Annual Employer Cost per Grade'!$U$2:$U$17,0,0))*(INDEX('[1]Headcount Phasing'!$B$3:$M$18,MATCH(B4,'[1]Headcount Phasing'!$A$3:$A$18,0),MATCH($G$2,'[1]Headcount Phasing'!$B$2:$M$2,0))) -> 3555487.9 | H4: =(_xlfn.XLOOKUP(B4,'[1]Annual Employer Cost per Grade'!$C$2:$C$17,'[1]Annual Employer Cost per Grade'!$U$2:$U$17,0,0))*(INDEX('[1]Headcount Phasing'!$B$3:$M$18,MATCH(B4,'[1]Headcount Phasing'!$A$3:$A$18,0),MATCH($H$2,'[1]Headcount Phasing'!$B$2:$M$2,0))) -> 3555487.9 | I4: =(_xlfn.XLOOKUP(B4,'[1]Annual Employer Cost per Grade'!$C$2:$C$17,'[1]Annual Employer Cost per Grade'!$U$2:$U$17,0,0))*(INDEX('[1]Headcount Phasing'!$B$3:$M$18,MATCH(B4,'[1]Headcount Phasing'!$A$3:$A$18,0),MATCH($I$2,'[1]Headcount Phasing'!$B$2:$M$2,0))) -> 3555487.9 | J4: =(_xlfn.XLOOKUP(B4,'[1]Annual Employer Cost per Grade'!$C$2:$C$17,'[1]Annual Employer Cost per Grade'!$U$2:$U$17,0,0))*(INDEX('[1]Headcount Phasing'!$B$3:$M$18,MATCH(B4,'[1]Headcount Phasing'!$A$3:$A$18,0),MATCH($J$2,'[1]Headcount Phasing'!$B$2:$M$2,0))) -> 3555487.9 | K4: =(_xlfn.XLOOKUP(B4,'[1]Annual Employer Cost per Grade'!$C$2:$C$17,'[1]Annual Employer Cost per Grade'!$U$2:$U$17,0,0))*(INDEX('[1]Headcount Phasing'!$B$3:$M$18,MATCH(B4,'[1]Headcount Phasing'!$A$3:$A$18,0),MATCH($K$2,'[1]Headcount Phasing'!$B$2:$M$2,0))) -> 3555487.9 | L4: =(_xlfn.XLOOKUP(B4,'[1]Annual Employer Cost per Grade'!$C$2:$C$17,'[1]Annual Employer Cost per Grade'!$U$2:$U$17,0,0))*(INDEX('[1]Headcount Phasing'!$B$3:$M$18,MATCH(B4,'[1]Headcount Phasing'!$A$3:$A$18,0),MATCH($L$2,'[1]Headcount Phasing'!$B$2:$M$2,0))) -> 3555487.9 | M4: =(_xlfn.XLOOKUP(B4,'[1]Annual Employer Cost per Grade'!$C$2:$C$17,'[1]Annual Employer Cost per Grade'!$U$2:$U$17,0,0))*(INDEX('[1]Headcount Phasing'!$B$3:$M$18,MATCH(B4,'[1]Headcount Phasing'!$A$3:$A$18,0),MATCH($M$2,'[1]Headcount Phasing'!$B$2:$M$2,0))) -> 3555487.9 | N4: =(_xlfn.XLOOKUP(B4,'[1]Annual Employer Cost per Grade'!$C$2:$C$17,'[1]Annual Employer Cost per Grade'!$U$2:$U$17,0,0))*(INDEX('[1]Headcount Phasing'!$B$3:$M$18,MATCH(B4,'[1]Headcount Phasing'!$A$3:$A$18,0),MATCH($N$2,'[1]Headcount Phasing'!$B$2:$M$2,0))) -> 3555487.9 | O4: =SUM(C4:N4) -> 31999391
A5: =A4+1 -> 3 | B5: IT Manager | C5: =(_xlfn.XLOOKUP(B5,'[1]Annual Employer Cost per Grade'!$C$2:$C$17,'[1]Annual Employer Cost per Grade'!$U$2:$U$17,0,0))*(INDEX('[1]Headcount Phasing'!$B$3:$M$18,MATCH(B5,'[1]Headcount Phasing'!$A$3:$A$18,0),MATCH($C$2,'[1]Headcount Phasing'!$B$2:$M$2,0))) -> 0 | D5: =(_xlfn.XLOOKUP(B5,'[1]Annual Employer Cost per Grade'!$C$2:$C$17,'[1]Annual Employer Cost per Grade'!$U$2:$U$17,0,0))*(INDEX('[1]Headcount Phasing'!$B$3:$M$18,MATCH(B5,'[1]Headcount Phasing'!$A$3:$A$18,0),MATCH($D$2,'[1]Headcount Phasing'!$B$2:$M$2,0))) -> 0 | E5: =(_xlfn.XLOOKUP(B5,'[1]Annual Employer Cost per Grade'!$C$2:$C$17,'[1]Annual Employer Cost per Grade'!$U$2:$U$17,0,0))*(INDEX('[1]Headcount Phasing'!$B$3:$M$18,MATCH(B5,'[1]Headcount Phasing'!$A$3:$A$18,0),MATCH($E$2,'[1]Headcount Phasing'!$B$2:$M$2,0))) -> 0 | F5: =(_xlfn.XLOOKUP(B5,'[1]Annual Employer Cost per Grade'!$C$2:$C$17,'[1]Annual Employer Cost per Grade'!$U$2:$U$17,0,0))*(INDEX('[1]Headcount Phasing'!$B$3:$M$18,MATCH(B5,'[1]Headcount Phasing'!$A$3:$A$18,0),MATCH($F$2,'[1]Headcount Phasing'!$B$2:$M$2,0))) -> 779030.5 | G5: =(_xlfn.XLOOKUP(B5,'[1]Annual Employer Cost per Grade'!$C$2:$C$17,'[1]Annual Employer Cost per Grade'!$U$2:$U$17,0,0))*(INDEX('[1]Headcount Phasing'!$B$3:$M$18,MATCH(B5,'[1]Headcount Phasing'!$A$3:$A$18,0),MATCH($G$2,'[1]Headcount Phasing'!$B$2:$M$2,0))) -> 779030.5 | H5: =(_xlfn.XLOOKUP(B5,'[1]Annual Employer Cost per Grade'!$C$2:$C$17,'[1]Annual Employer Cost per Grade'!$U$2:$U$17,0,0))*(INDEX('[1]Headcount Phasing'!$B$3:$M$18,MATCH(B5,'[1]Headcount Phasing'!$A$3:$A$18,0),MATCH($H$2,'[1]Headcount Phasing'!$B$2:$M$2,0))) -> 779030.5 | I5: =(_xlfn.XLOOKUP(B5,'[1]Annual Employer Cost per Grade'!$C$2:$C$17,'[1]Annual Employer Cost per Grade'!$U$2:$U$17,0,0))*(INDEX('[1]Headcount Phasing'!$B$3:$M$18,MATCH(B5,'[1]Headcount Phasing'!$A$3:$A$18,0),MATCH($I$2,'[1]Headcount Phasing'!$B$2:$M$2,0))) -> 779030.5 | J5: =(_xlfn.XLOOKUP(B5,'[1]Annual Employer Cost per Grade'!$C$2:$C$17,'[1]Annual Employer Cost per Grade'!$U$2:$U$17,0,0))*(INDEX('[1]Headcount Phasing'!$B$3:$M$18,MATCH(B5,'[1]Headcount Phasing'!$A$3:$A$18,0),MATCH($J$2,'[1]Headcount Phasing'!$B$2:$M$2,0))) -> 779030.5 | K5: =(_xlfn.XLOOKUP(B5,'[1]Annual Employer Cost per Grade'!$C$2:$C$17,'[1]Annual Employer Cost per Grade'!$U$2:$U$17,0,0))*(INDEX('[1]Headcount Phasing'!$B$3:$M$18,MATCH(B5,'[1]Headcount Phasing'!$A$3:$A$18,0),MATCH($K$2,'[1]Headcount Phasing'!$B$2:$M$2,0))) -> 779030.5 | L5: =(_xlfn.XLOOKUP(B5,'[1]Annual Employer Cost per Grade'!$C$2:$C$17,'[1]Annual Employer Cost per Grade'!$U$2:$U$17,0,0))*(INDEX('[1]Headcount Phasing'!$B$3:$M$18,MATCH(B5,'[1]Headcount Phasing'!$A$3:$A$18,0),MATCH($L$2,'[1]Headcount Phasing'!$B$2:$M$2,0))) -> 779030.5 | M5: =(_xlfn.XLOOKUP(B5,'[1]Annual Employer Cost per Grade'!$C$2:$C$17,'[1]Annual Employer Cost per Grade'!$U$2:$U$17,0,0))*(INDEX('[1]Headcount Phasing'!$B$3:$M$18,MATCH(B5,'[1]Headcount Phasing'!$A$3:$A$18,0),MATCH($M$2,'[1]Headcount Phasing'!$B$2:$M$2,0))) -> 779030.5 | N5: =(_xlfn.XLOOKUP(B5,'[1]Annual Employer Cost per Grade'!$C$2:$C$17,'[1]Annual Employer Cost per Grade'!$U$2:$U$17,0,0))*(INDEX('[1]Headcount Phasing'!$B$3:$M$18,MATCH(B5,'[1]Headcount Phasing'!$A$3:$A$18,0),MATCH($N$2,'[1]Headcount Phasing'!$B$2:$M$2,0))) -> 779030.5 | O5: =SUM(C5:N5) -> 7011274.5
A6: =A5+1 -> 4 | B6: Community Manager | C6: =(_xlfn.XLOOKUP(B6,'[1]Annual Employer Cost per Grade'!$C$2:$C$17,'[1]Annual Employer Cost per Grade'!$U$2:$U$17,0,0))*(INDEX('[1]Headcount Phasing'!$B$3:$M$18,MATCH(B6,'[1]Headcount Phasing'!$A$3:$A$18,0),MATCH($C$2,'[1]Headcount Phasing'!$B$2:$M$2,0))) -> 0 | D6: =(_xlfn.XLOOKUP(B6,'[1]Annual Employer Cost per Grade'!$C$2:$C$17,'[1]Annual Employer Cost per Grade'!$U$2:$U$17,0,0))*(INDEX('[1]Headcount Phasing'!$B$3:$M$18,MATCH(B6,'[1]Headcount Phasing'!$A$3:$A$18,0),MATCH($D$2,'[1]Headcount Phasing'!$B$2:$M$2,0))) -> 0 | E6: =(_xlfn.XLOOKUP(B6,'[1]Annual Employer Cost per Grade'!$C$2:$C$17,'[1]Annual Employer Cost per Grade'!$U$2:$U$17,0,0))*(INDEX('[1]Headcount Phasing'!$B$3:$M$18,MATCH(B6,'[1]Headcount Phasing'!$A$3:$A$18,0),MATCH($E$2,'[1]Headcount Phasing'!$B$2:$M$2,0))) -> 0 | F6: =(_xlfn.XLOOKUP(B6,'[1]Annual Employer Cost per Grade'!$C$2:$C$17,'[1]Annual Employer Cost per Grade'!$U$2:$U$17,0,0))*(INDEX('[1]Headcount Phasing'!$B$3:$M$18,MATCH(B6,'[1]Headcount Phasing'!$A$3:$A$18,0),MATCH($F$2,'[1]Headcount Phasing'!$B$2:$M$2,0))) -> 474470.5 | G6: =(_xlfn.XLOOKUP(B6,'[1]Annual Employer Cost per Grade'!$C$2:$C$17,'[1]Annual Employer Cost per Grade'!$U$2:$U$17,0,0))*(INDEX('[1]Headcount Phasing'!$B$3:$M$18,MATCH(B6,'[1]Headcount Phasing'!$A$3:$A$18,0),MATCH($G$2,'[1]Headcount Phasing'!$B$2:$M$2,0))) -> 474470.5 | H6: =(_xlfn.XLOOKUP(B6,'[1]Annual Employer Cost per Grade'!$C$2:$C$17,'[1]Annual Employer Cost per Grade'!$U$2:$U$17,0,0))*(INDEX('[1]Headcount Phasing'!$B$3:$M$18,MATCH(B6,'[1]Headcount Phasing'!$A$3:$A$18,0),MATCH($H$2,'[1]Headcount Phasing'!$B$2:$M$2,0))) -> 474470.5 | I6: =(_xlfn.XLOOKUP(B6,'[1]Annual Employer Cost per Grade'!$C$2:$C$17,'[1]Annual Employer Cost per Grade'!$U$2:$U$17,0,0))*(INDEX('[1]Headcount Phasing'!$B$3:$M$18,MATCH(B6,'[1]Headcount Phasing'!$A$3:$A$18,0),MATCH($I$2,'[1]Headcount Phasing'!$B$2:$M$2,0))) -> 474470.5 | J6: =(_xlfn.XLOOKUP(B6,'[1]Annual Employer Cost per Grade'!$C$2:$C$17,'[1]Annual Employer Cost per Grade'!$U$2:$U$17,0,0))*(INDEX('[1]Headcount Phasing'!$B$3:$M$18,MATCH(B6,'[1]Headcount Phasing'!$A$3:$A$18,0),MATCH($J$2,'[1]Headcount Phasing'!$B$2:$M$2,0))) -> 474470.5 | K6: =(_xlfn.XLOOKUP(B6,'[1]Annual Employer Cost per Grade'!$C$2:$C$17,'[1]Annual Employer Cost per Grade'!$U$2:$U$17,0,0))*(INDEX('[1]Headcount Phasing'!$B$3:$M$18,MATCH(B6,'[1]Headcount Phasing'!$A$3:$A$18,0),MATCH($K$2,'[1]Headcount Phasing'!$B$2:$M$2,0))) -> 474470.5 | L6: =(_xlfn.XLOOKUP(B6,'[1]Annual Employer Cost per Grade'!$C$2:$C$17,'[1]Annual Employer Cost per Grade'!$U$2:$U$17,0,0))*(INDEX('[1]Headcount Phasing'!$B$3:$M$18,MATCH(B6,'[1]Headcount Phasing'!$A$3:$A$18,0),MATCH($L$2,'[1]Headcount Phasing'!$B$2:$M$2,0))) -> 474470.5 | M6: =(_xlfn.XLOOKUP(B6,'[1]Annual Employer Cost per Grade'!$C$2:$C$17,'[1]Annual Employer Cost per Grade'!$U$2:$U$17,0,0))*(INDEX('[1]Headcount Phasing'!$B$3:$M$18,MATCH(B6,'[1]Headcount Phasing'!$A$3:$A$18,0),MATCH($M$2,'[1]Headcount Phasing'!$B$2:$M$2,0))) -> 474470.5 | N6: =(_xlfn.XLOOKUP(B6,'[1]Annual Employer Cost per Grade'!$C$2:$C$17,'[1]Annual Employer Cost per Grade'!$U$2:$U$17,0,0))*(INDEX('[1]Headcount Phasing'!$B$3:$M$18,MATCH(B6,'[1]Headcount Phasing'!$A$3:$A$18,0),MATCH($N$2,'[1]Headcount Phasing'!$B$2:$M$2,0))) -> 474470.5 | O6: =SUM(C6:N6) -> 4270234.5
A7: =A6+1 -> 5 | B7: Facility Associate | C7: =(_xlfn.XLOOKUP(B7,'[1]Annual Employer Cost per Grade'!$C$2:$C$17,'[1]Annual Employer Cost per Grade'!$U$2:$U$17,0,0))*(INDEX('[1]Headcount Phasing'!$B$3:$M$18,MATCH(B7,'[1]Headcount Phasing'!$A$3:$A$18,0),MATCH($C$2,'[1]Headcount Phasing'!$B$2:$M$2,0))) -> 0 | D7: =(_xlfn.XLOOKUP(B7,'[1]Annual Employer Cost per Grade'!$C$2:$C$17,'[1]Annual Employer Cost per Grade'!$U$2:$U$17,0,0))*(INDEX('[1]Headcount Phasing'!$B$3:$M$18,MATCH(B7,'[1]Headcount Phasing'!$A$3:$A$18,0),MATCH($D$2,'[1]Headcount Phasing'!$B$2:$M$2,0))) -> 0 | E7: =(_xlfn.XLOOKUP(B7,'[1]Annual Employer Cost per Grade'!$C$2:$C$17,'[1]Annual Employer Cost per Grade'!$U$2:$U$17,0,0))*(INDEX('[1]Headcount Phasing'!$B$3:$M$18,MATCH(B7,'[1]Headcount Phasing'!$A$3:$A$18,0),MATCH($E$2,'[1]Headcount Phasing'!$B$2:$M$2,0))) -> 0 | F7: =(_xlfn.XLOOKUP(B7,'[1]Annual Employer Cost per Grade'!$C$2:$C$17,'[1]Annual Employer Cost per Grade'!$U$2:$U$17,0,0))*(INDEX('[1]Headcount Phasing'!$B$3:$M$18,MATCH(B7,'[1]Headcount Phasing'!$A$3:$A$18,0),MATCH($F$2,'[1]Headcount Phasing'!$B$2:$M$2,0))) -> 458050.88 | G7: =(_xlfn.XLOOKUP(B7,'[1]Annual Employer Cost per Grade'!$C$2:$C$17,'[1]Annual Employer Cost per Grade'!$U$2:$U$17,0,0))*(INDEX('[1]Headcount Phasing'!$B$3:$M$18,MATCH(B7,'[1]Headcount Phasing'!$A$3:$A$18,0),MATCH($G$2,'[1]Headcount Phasing'!$B$2:$M$2,0))) -> 458050.88 | H7: =(_xlfn.XLOOKUP(B7,'[1]Annual Employer Cost per Grade'!$C$2:$C$17,'[1]Annual Employer Cost per Grade'!$U$2:$U$17,0,0))*(INDEX('[1]Headcount Phasing'!$B$3:$M$18,MATCH(B7,'[1]Headcount Phasing'!$A$3:$A$18,0),MATCH($H$2,'[1]Headcount Phasing'!$B$2:$M$2,0))) -> 458050.88 | I7: =(_xlfn.XLOOKUP(B7,'[1]Annual Employer Cost per Grade'!$C$2:$C$17,'[1]Annual Employer Cost per Grade'!$U$2:$U$17,0,0))*(INDEX('[1]Headcount Phasing'!$B$3:$M$18,MATCH(B7,'[1]Headcount Phasing'!$A$3:$A$18,0),MATCH($I$2,'[1]Headcount Phasing'!$B$2:$M$2,0))) -> 458050.88 | J7: =(_xlfn.XLOOKUP(B7,'[1]Annual Employer Cost per Grade'!$C$2:$C$17,'[1]Annual Employer Cost per Grade'!$U$2:$U$17,0,0))*(INDEX('[1]Headcount Phasing'!$B$3:$M$18,MATCH(B7,'[1]Headcount Phasing'!$A$3:$A$18,0),MATCH($J$2,'[1]Headcount Phasing'!$B$2:$M$2,0))) -> 458050.88 | K7: =(_xlfn.XLOOKUP(B7,'[1]Annual Employer Cost per Grade'!$C$2:$C$17,'[1]Annual Employer Cost per Grade'!$U$2:$U$17,0,0))*(INDEX('[1]Headcount Phasing'!$B$3:$M$18,MATCH(B7,'[1]Headcount Phasing'!$A$3:$A$18,0),MATCH($K$2,'[1]Headcount Phasing'!$B$2:$M$2,0))) -> 458050.88 | L7: =(_xlfn.XLOOKUP(B7,'[1]Annual Employer Cost per Grade'!$C$2:$C$17,'[1]Annual Employer Cost per Grade'!$U$2:$U$17,0,0))*(INDEX('[1]Headcount Phasing'!$B$3:$M$18,MATCH(B7,'[1]Headcount Phasing'!$A$3:$A$18,0),MATCH($L$2,'[1]Headcount Phasing'!$B$2:$M$2,0))) -> 458050.88 | M7: =(_xlfn.XLOOKUP(B7,'[1]Annual Employer Cost per Grade'!$C$2:$C$17,'[1]Annual Employer Cost per Grade'!$U$2:$U$17,0,0))*(INDEX('[1]Headcount Phasing'!$B$3:$M$18,MATCH(B7,'[1]Headcount Phasing'!$A$3:$A$18,0),MATCH($M$2,'[1]Headcount Phasing'!$B$2:$M$2,0))) -> 458050.88 | N7: =(_xlfn.XLOOKUP(B7,'[1]Annual Employer Cost per Grade'!$C$2:$C$17,'[1]Annual Employer Cost per Grade'!$U$2:$U$17,0,0))*(INDEX('[1]Headcount Phasing'!$B$3:$M$18,MATCH(B7,'[1]Headcount Phasing'!$A$3:$A$18,0),MATCH($N$2,'[1]Headcount Phasing'!$B$2:$M$2,0))) -> 458050.88 | O7: =SUM(C7:N7) -> 4122457.9
A8: =A7+1 -> 6 | B8: Front Desk Associate (x1) | C8: =(_xlfn.XLOOKUP(B8,'[1]Annual Employer Cost per Grade'!$C$2:$C$17,'[1]Annual Employer Cost per Grade'!$U$2:$U$17,0,0))*(INDEX('[1]Headcount Phasing'!$B$3:$M$18,MATCH(B8,'[1]Headcount Phasing'!$A$3:$A$18,0),MATCH($C$2,'[1]Headcount Phasing'!$B$2:$M$2,0))) -> 0 | D8: =(_xlfn.XLOOKUP(B8,'[1]Annual Employer Cost per Grade'!$C$2:$C$17,'[1]Annual Employer Cost per Grade'!$U$2:$U$17,0,0))*(INDEX('[1]Headcount Phasing'!$B$3:$M$18,MATCH(B8,'[1]Headcount Phasing'!$A$3:$A$18,0),MATCH($D$2,'[1]Headcount Phasing'!$B$2:$M$2,0))) -> 0 | E8: =(_xlfn.XLOOKUP(B8,'[1]Annual Employer Cost per Grade'!$C$2:$C$17,'[1]Annual Employer Cost per Grade'!$U$2:$U$17,0,0))*(INDEX('[1]Headcount Phasing'!$B$3:$M$18,MATCH(B8,'[1]Headcount Phasing'!$A$3:$A$18,0),MATCH($E$2,'[1]Headcount Phasing'!$B$2:$M$2,0))) -> 0 | F8: =(_xlfn.XLOOKUP(B8,'[1]Annual Employer Cost per Grade'!$C$2:$C$17,'[1]Annual Employer Cost per Grade'!$U$2:$U$17,0,0))*(INDEX('[1]Headcount Phasing'!$B$3:$M$18,MATCH(B8,'[1]Headcount Phasing'!$A$3:$A$18,0),MATCH($F$2,'[1]Headcount Phasing'!$B$2:$M$2,0))) -> 458050.88 | G8: =(_xlfn.XLOOKUP(B8,'[1]Annual Employer Cost per Grade'!$C$2:$C$17,'[1]Annual Employer Cost per Grade'!$U$2:$U$17,0,0))*(INDEX('[1]Headcount Phasing'!$B$3:$M$18,MATCH(B8,'[1]Headcount Phasing'!$A$3:$A$18,0),MATCH($G$2,'[1]Headcount Phasing'!$B$2:$M$2,0))) -> 458050.88 | H8: =(_xlfn.XLOOKUP(B8,'[1]Annual Employer Cost per Grade'!$C$2:$C$17,'[1]Annual Employer Cost per Grade'!$U$2:$U$17,0,0))*(INDEX('[1]Headcount Phasing'!$B$3:$M$18,MATCH(B8,'[1]Headcount Phasing'!$A$3:$A$18,0),MATCH($H$2,'[1]Headcount Phasing'!$B$2:$M$2,0))) -> 458050.88 | I8: =(_xlfn.XLOOKUP(B8,'[1]Annual Employer Cost per Grade'!$C$2:$C$17,'[1]Annual Employer Cost per Grade'!$U$2:$U$17,0,0))*(INDEX('[1]Headcount Phasing'!$B$3:$M$18,MATCH(B8,'[1]Headcount Phasing'!$A$3:$A$18,0),MATCH($I$2,'[1]Headcount Phasing'!$B$2:$M$2,0))) -> 458050.88 | J8: =(_xlfn.XLOOKUP(B8,'[1]Annual Employer Cost per Grade'!$C$2:$C$17,'[1]Annual Employer Cost per Grade'!$U$2:$U$17,0,0))*(INDEX('[1]Headcount Phasing'!$B$3:$M$18,MATCH(B8,'[1]Headcount Phasing'!$A$3:$A$18,0),MATCH($J$2,'[1]Headcount Phasing'!$B$2:$M$2,0))) -> 458050.88 | K8: =(_xlfn.XLOOKUP(B8,'[1]Annual Employer Cost per Grade'!$C$2:$C$17,'[1]Annual Employer Cost per Grade'!$U$2:$U$17,0,0))*(INDEX('[1]Headcount Phasing'!$B$3:$M$18,MATCH(B8,'[1]Headcount Phasing'!$A$3:$A$18,0),MATCH($K$2,'[1]Headcount Phasing'!$B$2:$M$2,0))) -> 458050.88 | L8: =(_xlfn.XLOOKUP(B8,'[1]Annual Employer Cost per Grade'!$C$2:$C$17,'[1]Annual Employer Cost per Grade'!$U$2:$U$17,0,0))*(INDEX('[1]Headcount Phasing'!$B$3:$M$18,MATCH(B8,'[1]Headcount Phasing'!$A$3:$A$18,0),MATCH($L$2,'[1]Headcount Phasing'!$B$2:$M$2,0))) -> 458050.88 | M8: =(_xlfn.XLOOKUP(B8,'[1]Annual Employer Cost per Grade'!$C$2:$C$17,'[1]Annual Employer Cost per Grade'!$U$2:$U$17,0,0))*(INDEX('[1]Headcount Phasing'!$B$3:$M$18,MATCH(B8,'[1]Headcount Phasing'!$A$3:$A$18,0),MATCH($M$2,'[1]Headcount Phasing'!$B$2:$M$2,0))) -> 458050.88 | N8: =(_xlfn.XLOOKUP(B8,'[1]Annual Employer Cost per Grade'!$C$2:$C$17,'[1]Annual Employer Cost per Grade'!$U$2:$U$17,0,0))*(INDEX('[1]Headcount Phasing'!$B$3:$M$18,MATCH(B8,'[1]Headcount Phasing'!$A$3:$A$18,0),MATCH($N$2,'[1]Headcount Phasing'!$B$2:$M$2,0))) -> 458050.88 | O8: =SUM(C8:N8) -> 4122457.9
A9: =A8+1 -> 7 | B9: Front Desk Support | F9: =(_xlfn.XLOOKUP(B9,'[1]Annual Employer Cost per Grade'!$C$2:$C$17,'[1]Annual Employer Cost per Grade'!$U$2:$U$17,0,0))*(INDEX('[1]Headcount Phasing'!$B$3:$M$18,MATCH(B9,'[1]Headcount Phasing'!$A$3:$A$18,0),MATCH($F$2,'[1]Headcount Phasing'!$B$2:$M$2,0))) -> 231183.15 | G9: =(_xlfn.XLOOKUP(B9,'[1]Annual Employer Cost per Grade'!$C$2:$C$17,'[1]Annual Employer Cost per Grade'!$U$2:$U$17,0,0))*(INDEX('[1]Headcount Phasing'!$B$3:$M$18,MATCH(B9,'[1]Headcount Phasing'!$A$3:$A$18,0),MATCH($G$2,'[1]Headcount Phasing'!$B$2:$M$2,0))) -> 231183.15 | H9: =(_xlfn.XLOOKUP(B9,'[1]Annual Employer Cost per Grade'!$C$2:$C$17,'[1]Annual Employer Cost per Grade'!$U$2:$U$17,0,0))*(INDEX('[1]Headcount Phasing'!$B$3:$M$18,MATCH(B9,'[1]Headcount Phasing'!$A$3:$A$18,0),MATCH($H$2,'[1]Headcount Phasing'!$B$2:$M$2,0))) -> 231183.15 | I9: =(_xlfn.XLOOKUP(B9,'[1]Annual Employer Cost per Grade'!$C$2:$C$17,'[1]Annual Employer Cost per Grade'!$U$2:$U$17,0,0))*(INDEX('[1]Headcount Phasing'!$B$3:$M$18,MATCH(B9,'[1]Headcount Phasing'!$A$3:$A$18,0),MATCH($I$2,'[1]Headcount Phasing'!$B$2:$M$2,0))) -> 231183.15 | J9: =(_xlfn.XLOOKUP(B9,'[1]Annual Employer Cost per Grade'!$C$2:$C$17,'[1]Annual Employer Cost per Grade'!$U$2:$U$17,0,0))*(INDEX('[1]Headcount Phasing'!$B$3:$M$18,MATCH(B9,'[1]Headcount Phasing'!$A$3:$A$18,0),MATCH($J$2,'[1]Headcount Phasing'!$B$2:$M$2,0))) -> 231183.15 | K9: =(_xlfn.XLOOKUP(B9,'[1]Annual Employer Cost per Grade'!$C$2:$C$17,'[1]Annual Employer Cost per Grade'!$U$2:$U$17,0,0))*(INDEX('[1]Headcount Phasing'!$B$3:$M$18,MATCH(B9,'[1]Headcount Phasing'!$A$3:$A$18,0),MATCH($K$2,'[1]Headcount Phasing'!$B$2:$M$2,0))) -> 231183.15 | L9: =(_xlfn.XLOOKUP(B9,'[1]Annual Employer Cost per Grade'!$C$2:$C$17,'[1]Annual Employer Cost per Grade'!$U$2:$U$17,0,0))*(INDEX('[1]Headcount Phasing'!$B$3:$M$18,MATCH(B9,'[1]Headcount Phasing'!$A$3:$A$18,0),MATCH($L$2,'[1]Headcount Phasing'!$B$2:$M$2,0))) -> 231183.15 | M9: =(_xlfn.XLOOKUP(B9,'[1]Annual Employer Cost per Grade'!$C$2:$C$17,'[1]Annual Employer Cost per Grade'!$U$2:$U$17,0,0))*(INDEX('[1]Headcount Phasing'!$B$3:$M$18,MATCH(B9,'[1]Headcount Phasing'!$A$3:$A$18,0),MATCH($M$2,'[1]Headcount Phasing'!$B$2:$M$2,0))) -> 231183.15 | N9: =(_xlfn.XLOOKUP(B9,'[1]Annual Employer Cost per Grade'!$C$2:$C$17,'[1]Annual Employer Cost per Grade'!$U$2:$U$17,0,0))*(INDEX('[1]Headcount Phasing'!$B$3:$M$18,MATCH(B9,'[1]Headcount Phasing'!$A$3:$A$18,0),MATCH($N$2,'[1]Headcount Phasing'!$B$2:$M$2,0))) -> 231183.15 | O9: =SUM(C9:N9) -> 2080648.3
A10: =A9+1 -> 8 | B10: Finance Associate | C10: =(_xlfn.XLOOKUP(B10,'[1]Annual Employer Cost per Grade'!$C$2:$C$17,'[1]Annual Employer Cost per Grade'!$U$2:$U$17,0,0))*(INDEX('[1]Headcount Phasing'!$B$3:$M$18,MATCH(B10,'[1]Headcount Phasing'!$A$3:$A$18,0),MATCH($C$2,'[1]Headcount Phasing'!$B$2:$M$2,0))) -> 0 | D10: =(_xlfn.XLOOKUP(B10,'[1]Annual Employer Cost per Grade'!$C$2:$C$17,'[1]Annual Employer Cost per Grade'!$U$2:$U$17,0,0))*(INDEX('[1]Headcount Phasing'!$B$3:$M$18,MATCH(B10,'[1]Headcount Phasing'!$A$3:$A$18,0),MATCH($D$2,'[1]Headcount Phasing'!$B$2:$M$2,0))) -> 0 | E10: =(_xlfn.XLOOKUP(B10,'[1]Annual Employer Cost per Grade'!$C$2:$C$17,'[1]Annual Employer Cost per Grade'!$U$2:$U$17,0,0))*(INDEX('[1]Headcount Phasing'!$B$3:$M$18,MATCH(B10,'[1]Headcount Phasing'!$A$3:$A$18,0),MATCH($E$2,'[1]Headcount Phasing'!$B$2:$M$2,0))) -> 0 | F10: =(_xlfn.XLOOKUP(B10,'[1]Annual Employer Cost per Grade'!$C$2:$C$17,'[1]Annual Employer Cost per Grade'!$U$2:$U$17,0,0))*(INDEX('[1]Headcount Phasing'!$B$3:$M$18,MATCH(B10,'[1]Headcount Phasing'!$A$3:$A$18,0),MATCH($F$2,'[1]Headcount Phasing'!$B$2:$M$2,0))) -> 458050.88 | G10: =(_xlfn.XLOOKUP(B10,'[1]Annual Employer Cost per Grade'!$C$2:$C$17,'[1]Annual Employer Cost per Grade'!$U$2:$U$17,0,0))*(INDEX('[1]Headcount Phasing'!$B$3:$M$18,MATCH(B10,'[1]Headcount Phasing'!$A$3:$A$18,0),MATCH($G$2,'[1]Headcount Phasing'!$B$2:$M$2,0))) -> 458050.88 | H10: =(_xlfn.XLOOKUP(B10,'[1]Annual Employer Cost per Grade'!$C$2:$C$17,'[1]Annual Employer Cost per Grade'!$U$2:$U$17,0,0))*(INDEX('[1]Headcount Phasing'!$B$3:$M$18,MATCH(B10,'[1]Headcount Phasing'!$A$3:$A$18,0),MATCH($H$2,'[1]Headcount Phasing'!$B$2:$M$2,0))) -> 458050.88 | I10: =(_xlfn.XLOOKUP(B10,'[1]Annual Employer Cost per Grade'!$C$2:$C$17,'[1]Annual Employer Cost per Grade'!$U$2:$U$17,0,0))*(INDEX('[1]Headcount Phasing'!$B$3:$M$18,MATCH(B10,'[1]Headcount Phasing'!$A$3:$A$18,0),MATCH($I$2,'[1]Headcount Phasing'!$B$2:$M$2,0))) -> 458050.88 | J10: =(_xlfn.XLOOKUP(B10,'[1]Annual Employer Cost per Grade'!$C$2:$C$17,'[1]Annual Employer Cost per Grade'!$U$2:$U$17,0,0))*(INDEX('[1]Headcount Phasing'!$B$3:$M$18,MATCH(B10,'[1]Headcount Phasing'!$A$3:$A$18,0),MATCH($J$2,'[1]Headcount Phasing'!$B$2:$M$2,0))) -> 458050.88 | K10: =(_xlfn.XLOOKUP(B10,'[1]Annual Employer Cost per Grade'!$C$2:$C$17,'[1]Annual Employer Cost per Grade'!$U$2:$U$17,0,0))*(INDEX('[1]Headcount Phasing'!$B$3:$M$18,MATCH(B10,'[1]Headcount Phasing'!$A$3:$A$18,0),MATCH($K$2,'[1]Headcount Phasing'!$B$2:$M$2,0))) -> 458050.88 | L10: =(_xlfn.XLOOKUP(B10,'[1]Annual Employer Cost per Grade'!$C$2:$C$17,'[1]Annual Employer Cost per Grade'!$U$2:$U$17,0,0))*(INDEX('[1]Headcount Phasing'!$B$3:$M$18,MATCH(B10,'[1]Headcount Phasing'!$A$3:$A$18,0),MATCH($L$2,'[1]Headcount Phasing'!$B$2:$M$2,0))) -> 458050.88 | M10: =(_xlfn.XLOOKUP(B10,'[1]Annual Employer Cost per Grade'!$C$2:$C$17,'[1]Annual Employer Cost per Grade'!$U$2:$U$17,0,0))*(INDEX('[1]Headcount Phasing'!$B$3:$M$18,MATCH(B10,'[1]Headcount Phasing'!$A$3:$A$18,0),MATCH($M$2,'[1]Headcount Phasing'!$B$2:$M$2,0))) -> 458050.88 | N10: =(_xlfn.XLOOKUP(B10,'[1]Annual Employer Cost per Grade'!$C$2:$C$17,'[1]Annual Employer Cost per Grade'!$U$2:$U$17,0,0))*(INDEX('[1]Headcount Phasing'!$B$3:$M$18,MATCH(B10,'[1]Headcount Phasing'!$A$3:$A$18,0),MATCH($N$2,'[1]Headcount Phasing'!$B$2:$M$2,0))) -> 458050.88 | O10: =SUM(C10:N10) -> 4122457.9
A11: =A10+1 -> 9 | B11: Admin & HR Associate | C11: =(_xlfn.XLOOKUP(B11,'[1]Annual Employer Cost per Grade'!$C$2:$C$17,'[1]Annual Employer Cost per Grade'!$U$2:$U$17,0,0))*(INDEX('[1]Headcount Phasing'!$B$3:$M$18,MATCH(B11,'[1]Headcount Phasing'!$A$3:$A$18,0),MATCH($C$2,'[1]Headcount Phasing'!$B$2:$M$2,0))) -> 0 | D11: =(_xlfn.XLOOKUP(B11,'[1]Annual Employer Cost per Grade'!$C$2:$C$17,'[1]Annual Employer Cost per Grade'!$U$2:$U$17,0,0))*(INDEX('[1]Headcount Phasing'!$B$3:$M$18,MATCH(B11,'[1]Headcount Phasing'!$A$3:$A$18,0),MATCH($D$2,'[1]Headcount Phasing'!$B$2:$M$2,0))) -> 0 | E11: =(_xlfn.XLOOKUP(B11,'[1]Annual Employer Cost per Grade'!$C$2:$C$17,'[1]Annual Employer Cost per Grade'!$U$2:$U$17,0,0))*(INDEX('[1]Headcount Phasing'!$B$3:$M$18,MATCH(B11,'[1]Headcount Phasing'!$A$3:$A$18,0),MATCH($E$2,'[1]Headcount Phasing'!$B$2:$M$2,0))) -> 0 | F11: =(_xlfn.XLOOKUP(B11,'[1]Annual Employer Cost per Grade'!$C$2:$C$17,'[1]Annual Employer Cost per Grade'!$U$2:$U$17,0,0))*(INDEX('[1]Headcount Phasing'!$B$3:$M$18,MATCH(B11,'[1]Headcount Phasing'!$A$3:$A$18,0),MATCH($F$2,'[1]Headcount Phasing'!$B$2:$M$2,0))) -> 458050.88 | G11: =(_xlfn.XLOOKUP(B11,'[1]Annual Employer Cost per Grade'!$C$2:$C$17,'[1]Annual Employer Cost per Grade'!$U$2:$U$17,0,0))*(INDEX('[1]Headcount Phasing'!$B$3:$M$18,MATCH(B11,'[1]Headcount Phasing'!$A$3:$A$18,0),MATCH($G$2,'[1]Headcount Phasing'!$B$2:$M$2,0))) -> 458050.88 | H11: =(_xlfn.XLOOKUP(B11,'[1]Annual Employer Cost per Grade'!$C$2:$C$17,'[1]Annual Employer Cost per Grade'!$U$2:$U$17,0,0))*(INDEX('[1]Headcount Phasing'!$B$3:$M$18,MATCH(B11,'[1]Headcount Phasing'!$A$3:$A$18,0),MATCH($H$2,'[1]Headcount Phasing'!$B$2:$M$2,0))) -> 458050.88 | I11: =(_xlfn.XLOOKUP(B11,'[1]Annual Employer Cost per Grade'!$C$2:$C$17,'[1]Annual Employer Cost per Grade'!$U$2:$U$17,0,0))*(INDEX('[1]Headcount Phasing'!$B$3:$M$18,MATCH(B11,'[1]Headcount Phasing'!$A$3:$A$18,0),MATCH($I$2,'[1]Headcount Phasing'!$B$2:$M$2,0))) -> 458050.88 | J11: =(_xlfn.XLOOKUP(B11,'[1]Annual Employer Cost per Grade'!$C$2:$C$17,'[1]Annual Employer Cost per Grade'!$U$2:$U$17,0,0))*(INDEX('[1]Headcount Phasing'!$B$3:$M$18,MATCH(B11,'[1]Headcount Phasing'!$A$3:$A$18,0),MATCH($J$2,'[1]Headcount Phasing'!$B$2:$M$2,0))) -> 458050.88 | K11: =(_xlfn.XLOOKUP(B11,'[1]Annual Employer Cost per Grade'!$C$2:$C$17,'[1]Annual Employer Cost per Grade'!$U$2:$U$17,0,0))*(INDEX('[1]Headcount Phasing'!$B$3:$M$18,MATCH(B11,'[1]Headcount Phasing'!$A$3:$A$18,0),MATCH($K$2,'[1]Headcount Phasing'!$B$2:$M$2,0))) -> 458050.88 | L11: =(_xlfn.XLOOKUP(B11,'[1]Annual Employer Cost per Grade'!$C$2:$C$17,'[1]Annual Employer Cost per Grade'!$U$2:$U$17,0,0))*(INDEX('[1]Headcount Phasing'!$B$3:$M$18,MATCH(B11,'[1]Headcount Phasing'!$A$3:$A$18,0),MATCH($L$2,'[1]Headcount Phasing'!$B$2:$M$2,0))) -> 458050.88 | M11: =(_xlfn.XLOOKUP(B11,'[1]Annual Employer Cost per Grade'!$C$2:$C$17,'[1]Annual Employer Cost per Grade'!$U$2:$U$17,0,0))*(INDEX('[1]Headcount Phasing'!$B$3:$M$18,MATCH(B11,'[1]Headcount Phasing'!$A$3:$A$18,0),MATCH($M$2,'[1]Headcount Phasing'!$B$2:$M$2,0))) -> 458050.88 | N11: =(_xlfn.XLOOKUP(B11,'[1]Annual Employer Cost per Grade'!$C$2:$C$17,'[1]Annual Employer Cost per Grade'!$U$2:$U$17,0,0))*(INDEX('[1]Headcount Phasing'!$B$3:$M$18,MATCH(B11,'[1]Headcount Phasing'!$A$3:$A$18,0),MATCH($N$2,'[1]Headcount Phasing'!$B$2:$M$2,0))) -> 458050.88 | O11: =SUM(C11:N11) -> 4122457.9
A12: =A11+1 -> 10 | B12: IT Support Associate (x2) | C12: =(_xlfn.XLOOKUP(B12,'[1]Annual Employer Cost per Grade'!$C$2:$C$17,'[1]Annual Employer Cost per Grade'!$U$2:$U$17,0,0))*(INDEX('[1]Headcount Phasing'!$B$3:$M$18,MATCH(B12,'[1]Headcount Phasing'!$A$3:$A$18,0),MATCH($C$2,'[1]Headcount Phasing'!$B$2:$M$2,0))) -> 0 | D12: =(_xlfn.XLOOKUP(B12,'[1]Annual Employer Cost per Grade'!$C$2:$C$17,'[1]Annual Employer Cost per Grade'!$U$2:$U$17,0,0))*(INDEX('[1]Headcount Phasing'!$B$3:$M$18,MATCH(B12,'[1]Headcount Phasing'!$A$3:$A$18,0),MATCH($D$2,'[1]Headcount Phasing'!$B$2:$M$2,0))) -> 0 | E12: =(_xlfn.XLOOKUP(B12,'[1]Annual Employer Cost per Grade'!$C$2:$C$17,'[1]Annual Employer Cost per Grade'!$U$2:$U$17,0,0))*(INDEX('[1]Headcount Phasing'!$B$3:$M$18,MATCH(B12,'[1]Headcount Phasing'!$A$3:$A$18,0),MATCH($E$2,'[1]Headcount Phasing'!$B$2:$M$2,0))) -> 0 | F12: =(_xlfn.XLOOKUP(B12,'[1]Annual Employer Cost per Grade'!$C$2:$C$17,'[1]Annual Employer Cost per Grade'!$U$2:$U$17,0,0))*(INDEX('[1]Headcount Phasing'!$B$3:$M$18,MATCH(B12,'[1]Headcount Phasing'!$A$3:$A$18,0),MATCH($F$2,'[1]Headcount Phasing'!$B$2:$M$2,0))) -> 916101.75 | G12: =(_xlfn.XLOOKUP(B12,'[1]Annual Employer Cost per Grade'!$C$2:$C$17,'[1]Annual Employer Cost per Grade'!$U$2:$U$17,0,0))*(INDEX('[1]Headcount Phasing'!$B$3:$M$18,MATCH(B12,'[1]Headcount Phasing'!$A$3:$A$18,0),MATCH($G$2,'[1]Headcount Phasing'!$B$2:$M$2,0))) -> 916101.75 | H12: =(_xlfn.XLOOKUP(B12,'[1]Annual Employer Cost per Grade'!$C$2:$C$17,'[1]Annual Employer Cost per Grade'!$U$2:$U$17,0,0))*(INDEX('[1]Headcount Phasing'!$B$3:$M$18,MATCH(B12,'[1]Headcount Phasing'!$A$3:$A$18,0),MATCH($H$2,'[1]Headcount Phasing'!$B$2:$M$2,0))) -> 916101.75 | I12: =(_xlfn.XLOOKUP(B12,'[1]Annual Employer Cost per Grade'!$C$2:$C$17,'[1]Annual Employer Cost per Grade'!$U$2:$U$17,0,0))*(INDEX('[1]Headcount Phasing'!$B$3:$M$18,MATCH(B12,'[1]Headcount Phasing'!$A$3:$A$18,0),MATCH($I$2,'[1]Headcount Phasing'!$B$2:$M$2,0))) -> 916101.75 | J12: =(_xlfn.XLOOKUP(B12,'[1]Annual Employer Cost per Grade'!$C$2:$C$17,'[1]Annual Employer Cost per Grade'!$U$2:$U$17,0,0))*(INDEX('[1]Headcount Phasing'!$B$3:$M$18,MATCH(B12,'[1]Headcount Phasing'!$A$3:$A$18,0),MATCH($J$2,'[1]Headcount Phasing'!$B$2:$M$2,0))) -> 916101.75 | K12: =(_xlfn.XLOOKUP(B12,'[1]Annual Employer Cost per Grade'!$C$2:$C$17,'[1]Annual Employer Cost per Grade'!$U$2:$U$17,0,0))*(INDEX('[1]Headcount Phasing'!$B$3:$M$18,MATCH(B12,'[1]Headcount Phasing'!$A$3:$A$18,0),MATCH($K$2,'[1]Headcount Phasing'!$B$2:$M$2,0))) -> 916101.75 | L12: =(_xlfn.XLOOKUP(B12,'[1]Annual Employer Cost per Grade'!$C$2:$C$17,'[1]Annual Employer Cost per Grade'!$U$2:$U$17,0,0))*(INDEX('[1]Headcount Phasing'!$B$3:$M$18,MATCH(B12,'[1]Headcount Phasing'!$A$3:$A$18,0),MATCH($L$2,'[1]Headcount Phasing'!$B$2:$M$2,0))) -> 916101.75 | M12: =(_xlfn.XLOOKUP(B12,'[1]Annual Employer Cost per Grade'!$C$2:$C$17,'[1]Annual Employer Cost per Grade'!$U$2:$U$17,0,0))*(INDEX('[1]Headcount Phasing'!$B$3:$M$18,MATCH(B12,'[1]Headcount Phasing'!$A$3:$A$18,0),MATCH($M$2,'[1]Headcount Phasing'!$B$2:$M$2,0))) -> 916101.75 | N12: =(_xlfn.XLOOKUP(B12,'[1]Annual Employer Cost per Grade'!$C$2:$C$17,'[1]Annual Employer Cost per Grade'!$U$2:$U$17,0,0))*(INDEX('[1]Headcount Phasing'!$B$3:$M$18,MATCH(B12,'[1]Headcount Phasing'!$A$3:$A$18,0),MATCH($N$2,'[1]Headcount Phasing'!$B$2:$M$2,0))) -> 916101.75 | O12: =SUM(C12:N12) -> 8244915.8
A13: =A12+1 -> 11 | B13: Content & Digital Marketing Lead | C13: =(_xlfn.XLOOKUP(B13,'[1]Annual Employer Cost per Grade'!$C$2:$C$17,'[1]Annual Employer Cost per Grade'!$U$2:$U$17,0,0))*(INDEX('[1]Headcount Phasing'!$B$3:$M$18,MATCH(B13,'[1]Headcount Phasing'!$A$3:$A$18,0),MATCH($C$2,'[1]Headcount Phasing'!$B$2:$M$2,0))) -> 0 | D13: =(_xlfn.XLOOKUP(B13,'[1]Annual Employer Cost per Grade'!$C$2:$C$17,'[1]Annual Employer Cost per Grade'!$U$2:$U$17,0,0))*(INDEX('[1]Headcount Phasing'!$B$3:$M$18,MATCH(B13,'[1]Headcount Phasing'!$A$3:$A$18,0),MATCH($D$2,'[1]Headcount Phasing'!$B$2:$M$2,0))) -> 0 | E13: =(_xlfn.XLOOKUP(B13,'[1]Annual Employer Cost per Grade'!$C$2:$C$17,'[1]Annual Employer Cost per Grade'!$U$2:$U$17,0,0))*(INDEX('[1]Headcount Phasing'!$B$3:$M$18,MATCH(B13,'[1]Headcount Phasing'!$A$3:$A$18,0),MATCH($E$2,'[1]Headcount Phasing'!$B$2:$M$2,0))) -> 0 | F13: =(_xlfn.XLOOKUP(B13,'[1]Annual Employer Cost per Grade'!$C$2:$C$17,'[1]Annual Employer Cost per Grade'!$U$2:$U$17,0,0))*(INDEX('[1]Headcount Phasing'!$B$3:$M$18,MATCH(B13,'[1]Headcount Phasing'!$A$3:$A$18,0),MATCH($F$2,'[1]Headcount Phasing'!$B$2:$M$2,0))) -> 465550.88 | G13: =(_xlfn.XLOOKUP(B13,'[1]Annual Employer Cost per Grade'!$C$2:$C$17,'[1]Annual Employer Cost per Grade'!$U$2:$U$17,0,0))*(INDEX('[1]Headcount Phasing'!$B$3:$M$18,MATCH(B13,'[1]Headcount Phasing'!$A$3:$A$18,0),MATCH($G$2,'[1]Headcount Phasing'!$B$2:$M$2,0))) -> 465550.88 | H13: =(_xlfn.XLOOKUP(B13,'[1]Annual Employer Cost per Grade'!$C$2:$C$17,'[1]Annual Employer Cost per Grade'!$U$2:$U$17,0,0))*(INDEX('[1]Headcount Phasing'!$B$3:$M$18,MATCH(B13,'[1]Headcount Phasing'!$A$3:$A$18,0),MATCH($H$2,'[1]Headcount Phasing'!$B$2:$M$2,0))) -> 465550.88 | I13: =(_xlfn.XLOOKUP(B13,'[1]Annual Employer Cost per Grade'!$C$2:$C$17,'[1]Annual Employer Cost per Grade'!$U$2:$U$17,0,0))*(INDEX('[1]Headcount Phasing'!$B$3:$M$18,MATCH(B13,'[1]Headcount Phasing'!$A$3:$A$18,0),MATCH($I$2,'[1]Headcount Phasing'!$B$2:$M$2,0))) -> 465550.88 | J13: =(_xlfn.XLOOKUP(B13,'[1]Annual Employer Cost per Grade'!$C$2:$C$17,'[1]Annual Employer Cost per Grade'!$U$2:$U$17,0,0))*(INDEX('[1]Headcount Phasing'!$B$3:$M$18,MATCH(B13,'[1]Headcount Phasing'!$A$3:$A$18,0),MATCH($J$2,'[1]Headcount Phasing'!$B$2:$M$2,0))) -> 465550.88 | K13: =(_xlfn.XLOOKUP(B13,'[1]Annual Employer Cost per Grade'!$C$2:$C$17,'[1]Annual Employer Cost per Grade'!$U$2:$U$17,0,0))*(INDEX('[1]Headcount Phasing'!$B$3:$M$18,MATCH(B13,'[1]Headcount Phasing'!$A$3:$A$18,0),MATCH($K$2,'[1]Headcount Phasing'!$B$2:$M$2,0))) -> 465550.88 | L13: =(_xlfn.XLOOKUP(B13,'[1]Annual Employer Cost per Grade'!$C$2:$C$17,'[1]Annual Employer Cost per Grade'!$U$2:$U$17,0,0))*(INDEX('[1]Headcount Phasing'!$B$3:$M$18,MATCH(B13,'[1]Headcount Phasing'!$A$3:$A$18,0),MATCH($L$2,'[1]Headcount Phasing'!$B$2:$M$2,0))) -> 465550.88 | M13: =(_xlfn.XLOOKUP(B13,'[1]Annual Employer Cost per Grade'!$C$2:$C$17,'[1]Annual Employer Cost per Grade'!$U$2:$U$17,0,0))*(INDEX('[1]Headcount Phasing'!$B$3:$M$18,MATCH(B13,'[1]Headcount Phasing'!$A$3:$A$18,0),MATCH($M$2,'[1]Headcount Phasing'!$B$2:$M$2,0))) -> 465550.88 | N13: =(_xlfn.XLOOKUP(B13,'[1]Annual Employer Cost per Grade'!$C$2:$C$17,'[1]Annual Employer Cost per Grade'!$U$2:$U$17,0,0))*(INDEX('[1]Headcount Phasing'!$B$3:$M$18,MATCH(B13,'[1]Headcount Phasing'!$A$3:$A$18,0),MATCH($N$2,'[1]Headcount Phasing'!$B$2:$M$2,0))) -> 465550.88 | O13: =SUM(C13:N13) -> 4189957.9
A14: =A13+1 -> 12 | B14: Graphic & Multimedia Associate | C14: =(_xlfn.XLOOKUP(B14,'[1]Annual Employer Cost per Grade'!$C$2:$C$17,'[1]Annual Employer Cost per Grade'!$U$2:$U$17,0,0))*(INDEX('[1]Headcount Phasing'!$B$3:$M$18,MATCH(B14,'[1]Headcount Phasing'!$A$3:$A$18,0),MATCH($C$2,'[1]Headcount Phasing'!$B$2:$M$2,0))) -> 0 | D14: =(_xlfn.XLOOKUP(B14,'[1]Annual Employer Cost per Grade'!$C$2:$C$17,'[1]Annual Employer Cost per Grade'!$U$2:$U$17,0,0))*(INDEX('[1]Headcount Phasing'!$B$3:$M$18,MATCH(B14,'[1]Headcount Phasing'!$A$3:$A$18,0),MATCH($D$2,'[1]Headcount Phasing'!$B$2:$M$2,0))) -> 0 | E14: =(_xlfn.XLOOKUP(B14,'[1]Annual Employer Cost per Grade'!$C$2:$C$17,'[1]Annual Employer Cost per Grade'!$U$2:$U$17,0,0))*(INDEX('[1]Headcount Phasing'!$B$3:$M$18,MATCH(B14,'[1]Headcount Phasing'!$A$3:$A$18,0),MATCH($E$2,'[1]Headcount Phasing'!$B$2:$M$2,0))) -> 0 | F14: =(_xlfn.XLOOKUP(B14,'[1]Annual Employer Cost per Grade'!$C$2:$C$17,'[1]Annual Employer Cost per Grade'!$U$2:$U$17,0,0))*(INDEX('[1]Headcount Phasing'!$B$3:$M$18,MATCH(B14,'[1]Headcount Phasing'!$A$3:$A$18,0),MATCH($F$2,'[1]Headcount Phasing'!$B$2:$M$2,0))) -> 465550.88 | G14: =(_xlfn.XLOOKUP(B14,'[1]Annual Employer Cost per Grade'!$C$2:$C$17,'[1]Annual Employer Cost per Grade'!$U$2:$U$17,0,0))*(INDEX('[1]Headcount Phasing'!$B$3:$M$18,MATCH(B14,'[1]Headcount Phasing'!$A$3:$A$18,0),MATCH($G$2,'[1]Headcount Phasing'!$B$2:$M$2,0))) -> 465550.88 | H14: =(_xlfn.XLOOKUP(B14,'[1]Annual Employer Cost per Grade'!$C$2:$C$17,'[1]Annual Employer Cost per Grade'!$U$2:$U$17,0,0))*(INDEX('[1]Headcount Phasing'!$B$3:$M$18,MATCH(B14,'[1]Headcount Phasing'!$A$3:$A$18,0),MATCH($H$2,'[1]Headcount Phasing'!$B$2:$M$2,0))) -> 465550.88 | I14: =(_xlfn.XLOOKUP(B14,'[1]Annual Employer Cost per Grade'!$C$2:$C$17,'[1]Annual Employer Cost per Grade'!$U$2:$U$17,0,0))*(INDEX('[1]Headcount Phasing'!$B$3:$M$18,MATCH(B14,'[1]Headcount Phasing'!$A$3:$A$18,0),MATCH($I$2,'[1]Headcount Phasing'!$B$2:$M$2,0))) -> 465550.88 | J14: =(_xlfn.XLOOKUP(B14,'[1]Annual Employer Cost per Grade'!$C$2:$C$17,'[1]Annual Employer Cost per Grade'!$U$2:$U$17,0,0))*(INDEX('[1]Headcount Phasing'!$B$3:$M$18,MATCH(B14,'[1]Headcount Phasing'!$A$3:$A$18,0),MATCH($J$2,'[1]Headcount Phasing'!$B$2:$M$2,0))) -> 465550.88 | K14: =(_xlfn.XLOOKUP(B14,'[1]Annual Employer Cost per Grade'!$C$2:$C$17,'[1]Annual Employer Cost per Grade'!$U$2:$U$17,0,0))*(INDEX('[1]Headcount Phasing'!$B$3:$M$18,MATCH(B14,'[1]Headcount Phasing'!$A$3:$A$18,0),MATCH($K$2,'[1]Headcount Phasing'!$B$2:$M$2,0))) -> 465550.88 | L14: =(_xlfn.XLOOKUP(B14,'[1]Annual Employer Cost per Grade'!$C$2:$C$17,'[1]Annual Employer Cost per Grade'!$U$2:$U$17,0,0))*(INDEX('[1]Headcount Phasing'!$B$3:$M$18,MATCH(B14,'[1]Headcount Phasing'!$A$3:$A$18,0),MATCH($L$2,'[1]Headcount Phasing'!$B$2:$M$2,0))) -> 465550.88 | M14: =(_xlfn.XLOOKUP(B14,'[1]Annual Employer Cost per Grade'!$C$2:$C$17,'[1]Annual Employer Cost per Grade'!$U$2:$U$17,0,0))*(INDEX('[1]Headcount Phasing'!$B$3:$M$18,MATCH(B14,'[1]Headcount Phasing'!$A$3:$A$18,0),MATCH($M$2,'[1]Headcount Phasing'!$B$2:$M$2,0))) -> 465550.88 | N14: =(_xlfn.XLOOKUP(B14,'[1]Annual Employer Cost per Grade'!$C$2:$C$17,'[1]Annual Employer Cost per Grade'!$U$2:$U$17,0,0))*(INDEX('[1]Headcount Phasing'!$B$3:$M$18,MATCH(B14,'[1]Headcount Phasing'!$A$3:$A$18,0),MATCH($N$2,'[1]Headcount Phasing'!$B$2:$M$2,0))) -> 465550.88 | O14: =SUM(C14:N14) -> 4189957.9
A15: =A14+1 -> 13 | B15: Facility Technician (x3) | C15: =(_xlfn.XLOOKUP(B15,'[1]Annual Employer Cost per Grade'!$C$2:$C$17,'[1]Annual Employer Cost per Grade'!$U$2:$U$17,0,0))*(INDEX('[1]Headcount Phasing'!$B$3:$M$18,MATCH(B15,'[1]Headcount Phasing'!$A$3:$A$18,0),MATCH($C$2,'[1]Headcount Phasing'!$B$2:$M$2,0))) -> 0 | D15: =(_xlfn.XLOOKUP(B15,'[1]Annual Employer Cost per Grade'!$C$2:$C$17,'[1]Annual Employer Cost per Grade'!$U$2:$U$17,0,0))*(INDEX('[1]Headcount Phasing'!$B$3:$M$18,MATCH(B15,'[1]Headcount Phasing'!$A$3:$A$18,0),MATCH($D$2,'[1]Headcount Phasing'!$B$2:$M$2,0))) -> 0 | E15: =(_xlfn.XLOOKUP(B15,'[1]Annual Employer Cost per Grade'!$C$2:$C$17,'[1]Annual Employer Cost per Grade'!$U$2:$U$17,0,0))*(INDEX('[1]Headcount Phasing'!$B$3:$M$18,MATCH(B15,'[1]Headcount Phasing'!$A$3:$A$18,0),MATCH($E$2,'[1]Headcount Phasing'!$B$2:$M$2,0))) -> 0 | F15: =(_xlfn.XLOOKUP(B15,'[1]Annual Employer Cost per Grade'!$C$2:$C$17,'[1]Annual Employer Cost per Grade'!$U$2:$U$17,0,0))*(INDEX('[1]Headcount Phasing'!$B$3:$M$18,MATCH(B15,'[1]Headcount Phasing'!$A$3:$A$18,0),MATCH($F$2,'[1]Headcount Phasing'!$B$2:$M$2,0))) -> 231183.15 | G15: =(_xlfn.XLOOKUP(B15,'[1]Annual Employer Cost per Grade'!$C$2:$C$17,'[1]Annual Employer Cost per Grade'!$U$2:$U$17,0,0))*(INDEX('[1]Headcount Phasing'!$B$3:$M$18,MATCH(B15,'[1]Headcount Phasing'!$A$3:$A$18,0),MATCH($G$2,'[1]Headcount Phasing'!$B$2:$M$2,0))) -> 231183.15 | H15: =(_xlfn.XLOOKUP(B15,'[1]Annual Employer Cost per Grade'!$C$2:$C$17,'[1]Annual Employer Cost per Grade'!$U$2:$U$17,0,0))*(INDEX('[1]Headcount Phasing'!$B$3:$M$18,MATCH(B15,'[1]Headcount Phasing'!$A$3:$A$18,0),MATCH($H$2,'[1]Headcount Phasing'!$B$2:$M$2,0))) -> 231183.15 | I15: =(_xlfn.XLOOKUP(B15,'[1]Annual Employer Cost per Grade'!$C$2:$C$17,'[1]Annual Employer Cost per Grade'!$U$2:$U$17,0,0))*(INDEX('[1]Headcount Phasing'!$B$3:$M$18,MATCH(B15,'[1]Headcount Phasing'!$A$3:$A$18,0),MATCH($I$2,'[1]Headcount Phasing'!$B$2:$M$2,0))) -> 231183.15 | J15: =(_xlfn.XLOOKUP(B15,'[1]Annual Employer Cost per Grade'!$C$2:$C$17,'[1]Annual Employer Cost per Grade'!$U$2:$U$17,0,0))*(INDEX('[1]Headcount Phasing'!$B$3:$M$18,MATCH(B15,'[1]Headcount Phasing'!$A$3:$A$18,0),MATCH($J$2,'[1]Headcount Phasing'!$B$2:$M$2,0))) -> 231183.15 | K15: =(_xlfn.XLOOKUP(B15,'[1]Annual Employer Cost per Grade'!$C$2:$C$17,'[1]Annual Employer Cost per Grade'!$U$2:$U$17,0,0))*(INDEX('[1]Headcount Phasing'!$B$3:$M$18,MATCH(B15,'[1]Headcount Phasing'!$A$3:$A$18,0),MATCH($K$2,'[1]Headcount Phasing'!$B$2:$M$2,0))) -> 231183.15 | L15: =(_xlfn.XLOOKUP(B15,'[1]Annual Employer Cost per Grade'!$C$2:$C$17,'[1]Annual Employer Cost per Grade'!$U$2:$U$17,0,0))*(INDEX('[1]Headcount Phasing'!$B$3:$M$18,MATCH(B15,'[1]Headcount Phasing'!$A$3:$A$18,0),MATCH($L$2,'[1]Headcount Phasing'!$B$2:$M$2,0))) -> 231183.15 | M15: =(_xlfn.XLOOKUP(B15,'[1]Annual Employer Cost per Grade'!$C$2:$C$17,'[1]Annual Employer Cost per Grade'!$U$2:$U$17,0,0))*(INDEX('[1]Headcount Phasing'!$B$3:$M$18,MATCH(B15,'[1]Headcount Phasing'!$A$3:$A$18,0),MATCH($M$2,'[1]Headcount Phasing'!$B$2:$M$2,0))) -> 231183.15 | N15: =(_xlfn.XLOOKUP(B15,'[1]Annual Employer Cost per Grade'!$C$2:$C$17,'[1]Annual Employer Cost per Grade'!$U$2:$U$17,0,0))*(INDEX('[1]Headcount Phasing'!$B$3:$M$18,MATCH(B15,'[1]Headcount Phasing'!$A$3:$A$18,0),MATCH($N$2,'[1]Headcount Phasing'!$B$2:$M$2,0))) -> 231183.15 | O15: =SUM(C15:N15) -> 2080648.3
A16: =A15+1 -> 14 | B16: Driver | C16: =(_xlfn.XLOOKUP(B16,'[1]Annual Employer Cost per Grade'!$C$2:$C$17,'[1]Annual Employer Cost per Grade'!$U$2:$U$17,0,0))*(INDEX('[1]Headcount Phasing'!$B$3:$M$18,MATCH(B16,'[1]Headcount Phasing'!$A$3:$A$18,0),MATCH($C$2,'[1]Headcount Phasing'!$B$2:$M$2,0))) -> 0 | D16: =(_xlfn.XLOOKUP(B16,'[1]Annual Employer Cost per Grade'!$C$2:$C$17,'[1]Annual Employer Cost per Grade'!$U$2:$U$17,0,0))*(INDEX('[1]Headcount Phasing'!$B$3:$M$18,MATCH(B16,'[1]Headcount Phasing'!$A$3:$A$18,0),MATCH($D$2,'[1]Headcount Phasing'!$B$2:$M$2,0))) -> 0 | E16: =(_xlfn.XLOOKUP(B16,'[1]Annual Employer Cost per Grade'!$C$2:$C$17,'[1]Annual Employer Cost per Grade'!$U$2:$U$17,0,0))*(INDEX('[1]Headcount Phasing'!$B$3:$M$18,MATCH(B16,'[1]Headcount Phasing'!$A$3:$A$18,0),MATCH($E$2,'[1]Headcount Phasing'!$B$2:$M$2,0))) -> 231183.15 | F16: =(_xlfn.XLOOKUP(B16,'[1]Annual Employer Cost per Grade'!$C$2:$C$17,'[1]Annual Employer Cost per Grade'!$U$2:$U$17,0,0))*(INDEX('[1]Headcount Phasing'!$B$3:$M$18,MATCH(B16,'[1]Headcount Phasing'!$A$3:$A$18,0),MATCH($F$2,'[1]Headcount Phasing'!$B$2:$M$2,0))) -> 231183.15 | G16: =(_xlfn.XLOOKUP(B16,'[1]Annual Employer Cost per Grade'!$C$2:$C$17,'[1]Annual Employer Cost per Grade'!$U$2:$U$17,0,0))*(INDEX('[1]Headcount Phasing'!$B$3:$M$18,MATCH(B16,'[1]Headcount Phasing'!$A$3:$A$18,0),MATCH($G$2,'[1]Headcount Phasing'!$B$2:$M$2,0))) -> 462366.29 | H16: =(_xlfn.XLOOKUP(B16,'[1]Annual Employer Cost per Grade'!$C$2:$C$17,'[1]Annual Employer Cost per Grade'!$U$2:$U$17,0,0))*(INDEX('[1]Headcount Phasing'!$B$3:$M$18,MATCH(B16,'[1]Headcount Phasing'!$A$3:$A$18,0),MATCH($H$2,'[1]Headcount Phasing'!$B$2:$M$2,0))) -> 462366.29 | I16: =(_xlfn.XLOOKUP(B16,'[1]Annual Employer Cost per Grade'!$C$2:$C$17,'[1]Annual Employer Cost per Grade'!$U$2:$U$17,0,0))*(INDEX('[1]Headcount Phasing'!$B$3:$M$18,MATCH(B16,'[1]Headcount Phasing'!$A$3:$A$18,0),MATCH($I$2,'[1]Headcount Phasing'!$B$2:$M$2,0))) -> 462366.29 | J16: =(_xlfn.XLOOKUP(B16,'[1]Annual Employer Cost per Grade'!$C$2:$C$17,'[1]Annual Employer Cost per Grade'!$U$2:$U$17,0,0))*(INDEX('[1]Headcount Phasing'!$B$3:$M$18,MATCH(B16,'[1]Headcount Phasing'!$A$3:$A$18,0),MATCH($J$2,'[1]Headcount Phasing'!$B$2:$M$2,0))) -> 462366.29 | K16: =(_xlfn.XLOOKUP(B16,'[1]Annual Employer Cost per Grade'!$C$2:$C$17,'[1]Annual Employer Cost per Grade'!$U$2:$U$17,0,0))*(INDEX('[1]Headcount Phasing'!$B$3:$M$18,MATCH(B16,'[1]Headcount Phasing'!$A$3:$A$18,0),MATCH($K$2,'[1]Headcount Phasing'!$B$2:$M$2,0))) -> 462366.29 | L16: =(_xlfn.XLOOKUP(B16,'[1]Annual Employer Cost per Grade'!$C$2:$C$17,'[1]Annual Employer Cost per Grade'!$U$2:$U$17,0,0))*(INDEX('[1]Headcount Phasing'!$B$3:$M$18,MATCH(B16,'[1]Headcount Phasing'!$A$3:$A$18,0),MATCH($L$2,'[1]Headcount Phasing'!$B$2:$M$2,0))) -> 462366.29 | M16: =(_xlfn.XLOOKUP(B16,'[1]Annual Employer Cost per Grade'!$C$2:$C$17,'[1]Annual Employer Cost per Grade'!$U$2:$U$17,0,0))*(INDEX('[1]Headcount Phasing'!$B$3:$M$18,MATCH(B16,'[1]Headcount Phasing'!$A$3:$A$18,0),MATCH($M$2,'[1]Headcount Phasing'!$B$2:$M$2,0))) -> 462366.29 | N16: =(_xlfn.XLOOKUP(B16,'[1]Annual Employer Cost per Grade'!$C$2:$C$17,'[1]Annual Employer Cost per Grade'!$U$2:$U$17,0,0))*(INDEX('[1]Headcount Phasing'!$B$3:$M$18,MATCH(B16,'[1]Headcount Phasing'!$A$3:$A$18,0),MATCH($N$2,'[1]Headcount Phasing'!$B$2:$M$2,0))) -> 462366.29 | O16: =SUM(C16:N16) -> 4161296.6
A17: =A16+1 -> 15 | B17: NYSC Intern (x3) | C17: =(_xlfn.XLOOKUP(B17,'[1]Annual Employer Cost per Grade'!$C$2:$C$17,'[1]Annual Employer Cost per Grade'!$U$2:$U$17,0,0))*(INDEX('[1]Headcount Phasing'!$B$3:$M$18,MATCH(B17,'[1]Headcount Phasing'!$A$3:$A$18,0),MATCH($C$2,'[1]Headcount Phasing'!$B$2:$M$2,0))) -> 0 | D17: =(_xlfn.XLOOKUP(B17,'[1]Annual Employer Cost per Grade'!$C$2:$C$17,'[1]Annual Employer Cost per Grade'!$U$2:$U$17,0,0))*(INDEX('[1]Headcount Phasing'!$B$3:$M$18,MATCH(B17,'[1]Headcount Phasing'!$A$3:$A$18,0),MATCH($D$2,'[1]Headcount Phasing'!$B$2:$M$2,0))) -> 0 | E17: =(_xlfn.XLOOKUP(B17,'[1]Annual Employer Cost per Grade'!$C$2:$C$17,'[1]Annual Employer Cost per Grade'!$U$2:$U$17,0,0))*(INDEX('[1]Headcount Phasing'!$B$3:$M$18,MATCH(B17,'[1]Headcount Phasing'!$A$3:$A$18,0),MATCH($E$2,'[1]Headcount Phasing'!$B$2:$M$2,0))) -> 0 | F17: =(_xlfn.XLOOKUP(B17,'[1]Annual Employer Cost per Grade'!$C$2:$C$17,'[1]Annual Employer Cost per Grade'!$U$2:$U$17,0,0))*(INDEX('[1]Headcount Phasing'!$B$3:$M$18,MATCH(B17,'[1]Headcount Phasing'!$A$3:$A$18,0),MATCH($F$2,'[1]Headcount Phasing'!$B$2:$M$2,0))) -> 0 | G17: =(_xlfn.XLOOKUP(B17,'[1]Annual Employer Cost per Grade'!$C$2:$C$17,'[1]Annual Employer Cost per Grade'!$U$2:$U$17,0,0))*(INDEX('[1]Headcount Phasing'!$B$3:$M$18,MATCH(B17,'[1]Headcount Phasing'!$A$3:$A$18,0),MATCH($G$2,'[1]Headcount Phasing'!$B$2:$M$2,0))) -> 199189.62 | H17: =(_xlfn.XLOOKUP(B17,'[1]Annual Employer Cost per Grade'!$C$2:$C$17,'[1]Annual Employer Cost per Grade'!$U$2:$U$17,0,0))*(INDEX('[1]Headcount Phasing'!$B$3:$M$18,MATCH(B17,'[1]Headcount Phasing'!$A$3:$A$18,0),MATCH($H$2,'[1]Headcount Phasing'!$B$2:$M$2,0))) -> 199189.62 | I17: =(_xlfn.XLOOKUP(B17,'[1]Annual Employer Cost per Grade'!$C$2:$C$17,'[1]Annual Employer Cost per Grade'!$U$2:$U$17,0,0))*(INDEX('[1]Headcount Phasing'!$B$3:$M$18,MATCH(B17,'[1]Headcount Phasing'!$A$3:$A$18,0),MATCH($I$2,'[1]Headcount Phasing'!$B$2:$M$2,0))) -> 199189.62 | J17: =(_xlfn.XLOOKUP(B17,'[1]Annual Employer Cost per Grade'!$C$2:$C$17,'[1]Annual Employer Cost per Grade'!$U$2:$U$17,0,0))*(INDEX('[1]Headcount Phasing'!$B$3:$M$18,MATCH(B17,'[1]Headcount Phasing'!$A$3:$A$18,0),MATCH($J$2,'[1]Headcount Phasing'!$B$2:$M$2,0))) -> 199189.62 | K17: =(_xlfn.XLOOKUP(B17,'[1]Annual Employer Cost per Grade'!$C$2:$C$17,'[1]Annual Employer Cost per Grade'!$U$2:$U$17,0,0))*(INDEX('[1]Headcount Phasing'!$B$3:$M$18,MATCH(B17,'[1]Headcount Phasing'!$A$3:$A$18,0),MATCH($K$2,'[1]Headcount Phasing'!$B$2:$M$2,0))) -> 199189.62 | L17: =(_xlfn.XLOOKUP(B17,'[1]Annual Employer Cost per Grade'!$C$2:$C$17,'[1]Annual Employer Cost per Grade'!$U$2:$U$17,0,0))*(INDEX('[1]Headcount Phasing'!$B$3:$M$18,MATCH(B17,'[1]Headcount Phasing'!$A$3:$A$18,0),MATCH($L$2,'[1]Headcount Phasing'!$B$2:$M$2,0))) -> 199189.62 | M17: =(_xlfn.XLOOKUP(B17,'[1]Annual Employer Cost per Grade'!$C$2:$C$17,'[1]Annual Employer Cost per Grade'!$U$2:$U$17,0,0))*(INDEX('[1]Headcount Phasing'!$B$3:$M$18,MATCH(B17,'[1]Headcount Phasing'!$A$3:$A$18,0),MATCH($M$2,'[1]Headcount Phasing'!$B$2:$M$2,0))) -> 199189.62 | N17: =(_xlfn.XLOOKUP(B17,'[1]Annual Employer Cost per Grade'!$C$2:$C$17,'[1]Annual Employer Cost per Grade'!$U$2:$U$17,0,0))*(INDEX('[1]Headcount Phasing'!$B$3:$M$18,MATCH(B17,'[1]Headcount Phasing'!$A$3:$A$18,0),MATCH($N$2,'[1]Headcount Phasing'!$B$2:$M$2,0))) -> 199189.62 | O17: =SUM(C17:N17) -> 1593517
A18: =A17+1 -> 16 | B18: Student Intern (x3) | C18: =(_xlfn.XLOOKUP(B18,'[1]Annual Employer Cost per Grade'!$C$2:$C$17,'[1]Annual Employer Cost per Grade'!$U$2:$U$17,0,0))*(INDEX('[1]Headcount Phasing'!$B$3:$M$18,MATCH(B18,'[1]Headcount Phasing'!$A$3:$A$18,0),MATCH($C$2,'[1]Headcount Phasing'!$B$2:$M$2,0))) -> 0 | D18: =(_xlfn.XLOOKUP(B18,'[1]Annual Employer Cost per Grade'!$C$2:$C$17,'[1]Annual Employer Cost per Grade'!$U$2:$U$17,0,0))*(INDEX('[1]Headcount Phasing'!$B$3:$M$18,MATCH(B18,'[1]Headcount Phasing'!$A$3:$A$18,0),MATCH($D$2,'[1]Headcount Phasing'!$B$2:$M$2,0))) -> 0 | E18: =(_xlfn.XLOOKUP(B18,'[1]Annual Employer Cost per Grade'!$C$2:$C$17,'[1]Annual Employer Cost per Grade'!$U$2:$U$17,0,0))*(INDEX('[1]Headcount Phasing'!$B$3:$M$18,MATCH(B18,'[1]Headcount Phasing'!$A$3:$A$18,0),MATCH($E$2,'[1]Headcount Phasing'!$B$2:$M$2,0))) -> 0 | F18: =(_xlfn.XLOOKUP(B18,'[1]Annual Employer Cost per Grade'!$C$2:$C$17,'[1]Annual Employer Cost per Grade'!$U$2:$U$17,0,0))*(INDEX('[1]Headcount Phasing'!$B$3:$M$18,MATCH(B18,'[1]Headcount Phasing'!$A$3:$A$18,0),MATCH($F$2,'[1]Headcount Phasing'!$B$2:$M$2,0))) -> 240702 | G18: =(_xlfn.XLOOKUP(B18,'[1]Annual Employer Cost per Grade'!$C$2:$C$17,'[1]Annual Employer Cost per Grade'!$U$2:$U$17,0,0))*(INDEX('[1]Headcount Phasing'!$B$3:$M$18,MATCH(B18,'[1]Headcount Phasing'!$A$3:$A$18,0),MATCH($G$2,'[1]Headcount Phasing'!$B$2:$M$2,0))) -> 240702 | H18: =(_xlfn.XLOOKUP(B18,'[1]Annual Employer Cost per Grade'!$C$2:$C$17,'[1]Annual Employer Cost per Grade'!$U$2:$U$17,0,0))*(INDEX('[1]Headcount Phasing'!$B$3:$M$18,MATCH(B18,'[1]Headcount Phasing'!$A$3:$A$18,0),MATCH($H$2,'[1]Headcount Phasing'!$B$2:$M$2,0))) -> 240702 | I18: =(_xlfn.XLOOKUP(B18,'[1]Annual Employer Cost per Grade'!$C$2:$C$17,'[1]Annual Employer Cost per Grade'!$U$2:$U$17,0,0))*(INDEX('[1]Headcount Phasing'!$B$3:$M$18,MATCH(B18,'[1]Headcount Phasing'!$A$3:$A$18,0),MATCH($I$2,'[1]Headcount Phasing'!$B$2:$M$2,0))) -> 240702 | J18: =(_xlfn.XLOOKUP(B18,'[1]Annual Employer Cost per Grade'!$C$2:$C$17,'[1]Annual Employer Cost per Grade'!$U$2:$U$17,0,0))*(INDEX('[1]Headcount Phasing'!$B$3:$M$18,MATCH(B18,'[1]Headcount Phasing'!$A$3:$A$18,0),MATCH($J$2,'[1]Headcount Phasing'!$B$2:$M$2,0))) -> 240702 | K18: =(_xlfn.XLOOKUP(B18,'[1]Annual Employer Cost per Grade'!$C$2:$C$17,'[1]Annual Employer Cost per Grade'!$U$2:$U$17,0,0))*(INDEX('[1]Headcount Phasing'!$B$3:$M$18,MATCH(B18,'[1]Headcount Phasing'!$A$3:$A$18,0),MATCH($K$2,'[1]Headcount Phasing'!$B$2:$M$2,0))) -> 240702 | L18: =(_xlfn.XLOOKUP(B18,'[1]Annual Employer Cost per Grade'!$C$2:$C$17,'[1]Annual Employer Cost per Grade'!$U$2:$U$17,0,0))*(INDEX('[1]Headcount Phasing'!$B$3:$M$18,MATCH(B18,'[1]Headcount Phasing'!$A$3:$A$18,0),MATCH($L$2,'[1]Headcount Phasing'!$B$2:$M$2,0))) -> 240702 | M18: =(_xlfn.XLOOKUP(B18,'[1]Annual Employer Cost per Grade'!$C$2:$C$17,'[1]Annual Employer Cost per Grade'!$U$2:$U$17,0,0))*(INDEX('[1]Headcount Phasing'!$B$3:$M$18,MATCH(B18,'[1]Headcount Phasing'!$A$3:$A$18,0),MATCH($M$2,'[1]Headcount Phasing'!$B$2:$M$2,0))) -> 240702 | N18: =(_xlfn.XLOOKUP(B18,'[1]Annual Employer Cost per Grade'!$C$2:$C$17,'[1]Annual Employer Cost per Grade'!$U$2:$U$17,0,0))*(INDEX('[1]Headcount Phasing'!$B$3:$M$18,MATCH(B18,'[1]Headcount Phasing'!$A$3:$A$18,0),MATCH($N$2,'[1]Headcount Phasing'!$B$2:$M$2,0))) -> 240702 | O18: =SUM(C18:N18) -> 2166318
B19: Total | C19: =SUM(C3:C18) -> 0 | D19: =SUM(D3:D18) -> 0 | E19: =SUM(E3:E18) -> 6418849.8 | F19: =SUM(F3:F18) -> 15610314 | G19: =SUM(G3:G18) -> 16040687 | H19: =SUM(H3:H18) -> 16040687 | I19: =SUM(I3:I18) -> 16040687 | J19: =SUM(J3:J18) -> 16040687 | ... O19: =SUM(O3:O18) -> 1.5035466e+08
M29: reduction
L30: 2.3501734e+08 | M30: =L30-O19 -> 84662677
M31: =(L30-O19)/L30 -> 0.36024014

Sheet Others
B2: Equipment & Infrastructure
C3: Jan | D3: Feb | E3: Mar | F3: Apr | G3: May | H3: Jun | I3: Jul | J3: Aug | K3: Sep | L3: Oct | M3: Nov | N3: Dec | O3: Total
B4: Cloud Servers | E4: =$O$4/4 -> 1041666.7 | H4: =$O$4/4 -> 1041666.7 | K4: =$O$4/4 -> 1041666.7 | N4: =$O$4/4 -> 1041666.7 | O4: 4166666.7
B5: Staff Email | E5: =$O$5/4 -> 729166.67 | H5: =$O$5/4 -> 729166.67 | K5: =$O$5/4 -> 729166.67 | N5: =$O$5/4 -> 729166.67 | O5: 2916666.7
B6: Miscellaneous Software Subscriptions & Licenses | E6: =$O$6/4 -> 416666.67 | H6: =$O$6/4 -> 416666.67 | K6: =$O$6/4 -> 416666.67 | N6: =$O$6/4 -> 416666.67 | O6: 1666666.7
B9: Innovation & Program Support
C10: Jan | D10: Feb | E10: Mar | F10: Apr | G10: May | H10: Jun | I10: Jul | J10: Aug | K10: Sep | L10: Oct | M10: Nov | N10: Dec | O10: Total
B11: Staff Professional Development (Afrilabs Capacity Building etc) | E11: =$O11/4 -> 1000000 | H11: =$O11/4 -> 1000000 | K11: =$O11/4 -> 1000000 | N11: =$O11/4 -> 1000000 | O11: 4000000
B12: Monthly Meetups | E12: =$O12/10 -> 250000 | F12: =$O12/10 -> 250000 | G12: =$O12/10 -> 250000 | H12: =$O12/10 -> 250000 | I12: =$O12/10 -> 250000 | J12: =$O12/10 -> 250000 | K12: =$O12/10 -> 250000 | L12: =$O12/10 -> 250000 | ... N12: =$O12/10 -> 250000 | O12: 2500000
B13: Field Events | E13: =$O13/4 -> 520833.33 | H13: =$O13/4 -> 520833.33 | K13: =$O13/4 -> 520833.33 | N13: =$O13/4 -> 520833.33 | O13: 2083333.3
B14: Webinars | E14: =$O14/4 -> 312500 | H14: =$O14/4 -> 312500 | K14: =$O14/4 -> 312500 | N14: =$O14/4 -> 312500 | O14: 1250000

Sheet Membership Fees
C2: Jan | D2: Feb | E2: Mar | F2: Apr | G2: May | H2: Jun | I2: Jul | J2: Aug | K2: Sep | L2: Oct | M2: Nov | N2: Dec
B3: Fees/Member | C3: 5000 | D3: 5000 | E3: 5000 | F3: 5000 | G3: 5000 | H3: 5000 | I3: 5000 | J3: 5000 | K3: 5000 | L3: 5000 | M3: 5000 | N3: 5000
B4: No of members | C4: 0 | D4: 0 | E4: 5 | F4: =E4+10 -> 15 | G4: =F4+10 -> 25 | H4: =G4+10 -> 35 | I4: =H4+10 -> 45 | J4: =I4+10 -> 55 | K4: =J4+10 -> 65 | L4: =K4+10 -> 75 | M4: =L4+10 -> 85 | N4: =M4+10 -> 95
B5: Total | C5: =C3*C4 -> 0 | D5: =D3*D4 -> 0 | E5: =E3*E4 -> 25000 | F5: =F3*F4 -> 75000 | G5: =G3*G4 -> 125000 | H5: =H3*H4 -> 175000 | I5: =I3*I4 -> 225000 | J5: =J3*J4 -> 275000 | ... N5: =N3*N4 -> 475000

Sheet Diesel
C2: Jan | D2: Feb | E2: Mar | F2: Apr | G2: May | H2: Jun | I2: Jul | J2: Aug | K2: Sep | L2: Oct | M2: Nov | N2: Dec
B3: Price | C3: 1193.9812 | D3: 1182.3158 | E3: 1100 | F3: 1149.5997 | G3: 1152.0874 | H3: 1186.5492 | I3: 1299.7549 | J3: 1330.373 | K3: 1343.2722 | L3: 1359.3153 | M3: 1378.7526 | N3: 1395.9128
B4: Consumption | G4: 800 | H4: =G4 -> 800 | I4: =H4 -> 800 | J4: =I4 -> 800 | K4: =J4 -> 800 | L4: =K4 -> 800 | M4: =L4 -> 800 | N4: =M4 -> 800
B5: Total | C5: =C3*C4 -> 0 | D5: =D3*D4 -> 0 | E5: =E3*E4 -> 0 | F5: =F3*F4 -> 0 | G5: =G3*G4 -> 921669.93 | H5: =H3*H4 -> 949239.34 | I5: =I3*I4 -> 1039804 | J5: =J3*J4 -> 1064298.4 | ... N5: =N3*N4 -> 1116730.2

Sheet Salaries
B2: Grade | C2: Annual Package (₦) | D2: Monhly Salary Amount (₦) | F2: Jan | G2: Feb | H2: Mar | I2: Apr | J2: May | K2: Jun | L2: Jul | M2: Aug | N2: Sep | O2: Oct | P2: Nov | Q2: Dec
B3: Managing Director | C3: 92560384 | D3: =C3/12 -> 7713365.3 | H3: 1 | I3: 1 | J3: 1 | K3: 1 | L3: 1 | M3: 1 | N3: 1 | O3: 1 | P3: 1 | Q3: 1
B4: Director of Programs | C4: 51528999 | D4: =C4/12 -> 4294083.2 | I4: 1 | J4: 1 | K4: 1 | L4: 1 | M4: 1 | N4: 1 | O4: 1 | P4: 1 | Q4: 1
B5: IT Manager | C5: 10365498 | D5: =C5/12 -> 863791.5 | I5: 1 | J5: 1 | K5: 1 | L5: 1 | M5: 1 | N5: 1 | O5: 1 | P5: 1 | Q5: 1
B6: Community Manager | C6: 10365498 | D6: =C6/12 -> 863791.5 | I6: 1 | J6: 1 | K6: 1 | L6: 1 | M6: 1 | N6: 1 | O6: 1 | P6: 1 | Q6: 1
B7: Facility Associate | C7: 5939986.5 | D7: =C7/12 -> 494998.88 | I7: 1 | J7: 1 | K7: 1 | L7: 1 | M7: 1 | N7: 1 | O7: 1 | P7: 1 | Q7: 1
B8: Front Desk Associate (x2) | C8: 11879973 | D8: =C8/12 -> 989997.75 | I8: 1 | J8: 1 | K8: 2 | L8: 2 | M8: 2 | N8: 2 | O8: 2 | P8: 2 | Q8: 2
B9: Finance Associate | C9: 5939986.5 | D9: =C9/12 -> 494998.88 | I9: 1 | J9: 1 | K9: 1 | L9: 1 | M9: 1 | N9: 1 | O9: 1 | P9: 1 | Q9: 1
B10: Admin & HR Associate | C10: 5939986.5 | D10: =C10/12 -> 494998.88 | I10: 1 | J10: 1 | K10: 1 | L10: 1 | M10: 1 | N10: 1 | O10: 1 | P10: 1 | Q10: 1
B11: IT Support Associate (x2) | C11: 11879973 | D11: =C11/12 -> 989997.75 | I11: 1 | J11: 1 | K11: 1 | L11: 1 | M11: 1 | N11: 1 | O11: 1 | P11: 1 | Q11: 1
B12: Content & Digital Marketing Lead | C12: 5939986.5 | D12: =C12/12 -> 494998.88 | I12: 1 | J12: 1 | K12: 1 | L12: 1 | M12: 1 | N12: 1 | O12: 1 | P12: 1 | Q12: 1
B13: Graphic & Multimedia Associate | C13: 5939986.5 | D13: =C13/12 -> 494998.88 | I13: 1 | J13: 1 | K13: 1 | L13: 1 | M13: 1 | N13: 1 | O13: 1 | P13: 1 | Q13: 1
B14: Facility Technician (x3) | C14: 8840273.2 | D14: =C14/12 -> 736689.44 | I14: 1 | J14: 1 | K14: 1 | L14: 1 | M14: 1 | N14: 1 | O14: 1 | P14: 1 | Q14: 1
B15: Driver | C15: 2946757.8 | D15: =C15/12 -> 245563.15 | I15: 1 | J15: 2 | K15: 2 | L15: 2 | M15: 2 | N15: 2 | O15: 2 | P15: 2 | Q15: 2
... B17: Intern (x3) | C17: 2689867.2 | D17: =C17/12 -> 224155.6 | I17: 3 | J17: 3 | K17: 3 | L17: 3 | M17: 3 | N17: 3 | O17: 3 | P17: 3 | Q17: 3
B19: Total Monthly Employee Cost | F19: =SUM(F3:F18) -> 0 | G19: =SUM(G3:G18) -> 0 | H19: =SUMPRODUCT(H3:H18,$D$3:$D$18) -> 7713365.3 | I19: =SUMPRODUCT(I3:I18,$D$3:$D$18) -> 20221437 | J19: =SUMPRODUCT(J3:J18,$D$3:$D$18) -> 20467001 | K19: =SUMPRODUCT(K3:K18,$D$3:$D$18) -> 21456998 | L19: =SUMPRODUCT(L3:L18,$D$3:$D$18) -> 21456998 | M19: =SUMPRODUCT(M3:M18,$D$3:$D$18) -> 21456998 | N19: =SUMPRODUCT(N3:N18,$D$3:$D$18) -> 21456998 | O19: =SUMPRODUCT(O3:O18,$D$3:$D$18) -> 21456998 | ... Q19: =SUMPRODUCT(Q3:Q18,$D$3:$D$18) -> 21456998
H22: 6418849.8 | I22: 15610314 | J22: 16040687 | K22: 16040687 | L22: 16040687 | M22: 16040687 | N22: 16040687 | O22: 16040687 | P22: 16040687 | Q22: 16040687

Sheet Rental, Hosting & Sponsorships
B2: Facility Rentals
C3: Jan | D3: Feb | E3: Mar | F3: Apr | G3: May | H3: Jun | I3: Jul | J3: Aug | K3: Sep | L3: Oct | M3: Nov | N3: Dec
B4: Rate | C4: 500000 | D4: 500000 | E4: 500000 | F4: 500000 | G4: 500000 | H4: 500000 | I4: 500000 | J4: 500000 | K4: 500000 | L4: 500000 | M4: 500000 | N4: 500000
B5: No of rentals | C5: 0 | D5: 0 | E5: 0 | F5: 0 | G5: 0 | H5: 0 | I5: 0 | J5: 0 | K5: 0 | L5: 0 | M5: 0 | N5: 0
B6: Total | C6: =C4*C5 -> 0 | D6: =D4*D5 -> 0 | E6: =E4*E5 -> 0 | F6: =F4*F5 -> 0 | G6: =G4*G5 -> 0 | H6: =H4*H5 -> 0 | I6: =I4*I5 -> 0 | J6: =J4*J5 -> 0 | ... N6: =N4*N5 -> 0
B8: Event Hosting & Sponsorships
C9: Jan | D9: Feb | E9: Mar | F9: Apr | G9: May | H9: Jun | I9: Jul | J9: Aug | K9: Sep | L9: Oct | M9: Nov | N9: Dec
B10: Rate | C10: 1000000 | D10: 1000000 | E10: 1000000 | F10: 1000000 | G10: 1000000 | H10: 1000000 | I10: 1000000 | J10: 1000000 | K10: 1000000 | L10: 1000000 | M10: 1000000 | N10: 1000000
B11: No of events | C11: 0 | D11: 0 | E11: 0 | F11: 0 | G11: 0 | H11: 0 | I11: 0 | J11: 0 | K11: 0 | L11: 0 | M11: 0 | N11: 0
B12: Total | C12: =C10*C11 -> 0 | D12: =D10*D11 -> 0 | E12: =E10*E11 -> 0 | F12: =F10*F11 -> 0 | G12: =G10*G11 -> 0 | H12: =H10*H11 -> 0 | I12: =I10*I11 -> 0 | J12: =J10*J11 -> 0 | ... N12: =N10*N11 -> 0
